Workbook

Sheet HAHA合集
A1: ID | B1: 品级 | C1: 丹药名称 | D1: 耐药性 | E1: 效果/丹毒 | F1: 主需求 | G1: 药力↓ | H1: 辅需求 | I1: 辅药力↓ | J1: 辅需求2 | K1: 辅药力2 | L1: 寒热 | M1: 药引药力 | N1: 丹药价值
A2: 5315 | B2: 4 | C2: 九转再造丹 | D2: 5 | E2: 资质+3/丹毒+2 | F2: 聚元 | G2: 252 | H2: 洗髓 | I2: 36 | L2: =IF(IFERROR(IF(AND(#REF!>0,#REF!<>""),VLOOKUP(#REF!,药材与丹炉!$B:$D,3,0),0),0)+IFERROR(IF(AND(#REF!>0,#REF!<>""),VLOOKUP(#REF!,药材与丹炉!$B:$D,3,0),0),0)+IFERROR(IF(AND(#REF!>0,#REF!<>""),VLOOKUP(#REF!,药材与丹炉!$B:$D,3,0),0),0)+IFERROR(IF(AND(#REF!>0,#REF!<>""),VLOOKUP(#REF!,药材与丹炉!$B:$D,3,0),0),0)>0,1,IF(IFERROR(IF(AND(#REF!>0,#REF!<>""),VLOOKUP(#REF!,药材与丹炉!$B:$D,3,0),0),0)+IFERROR(IF(AND(#REF!>0,#REF!<>""),VLOOKUP(#REF!,药材与丹炉!$B:$D,3,0),0),0)+IFERROR(IF(AND(#REF!>0,#REF!<>""),VLOOKUP(#REF!,药材与丹炉!$B:$D,3,0),0),0)+IFERROR(IF(AND(#REF!>0,#REF!<>""),VLOOKUP(#REF!,药材与丹炉!$B:$D,3,0),0),0)<0,2,0)) -> 0 | M2: 36 | N2: 31250
A3: 5321 | B3: 4 | C3: 蚀月强魂丹 | D3: 30 | E3: 下次战斗神识加10/丹毒+5 | F3: 振气 | G3: 36 | H3: 凝神 | I3: 36 | L3: =IF(IFERROR(IF(AND(#REF!>0,#REF!<>""),VLOOKUP(#REF!,药材与丹炉!$B:$D,3,0),0),0)+IFERROR(IF(AND(#REF!>0,#REF!<>""),VLOOKUP(#REF!,药材与丹炉!$B:$D,3,0),0),0)+IFERROR(IF(AND(#REF!>0,#REF!<>""),VLOOKUP(#REF!,药材与丹炉!$B:$D,3,0),0),0)+IFERROR(IF(AND(#REF!>0,#REF!<>""),VLOOKUP(#REF!,药材与丹炉!$B:$D,3,0),0),0)>0,1,IF(IFERROR(IF(AND(#REF!>0,#REF!<>""),VLOOKUP(#REF!,药材与丹炉!$B:$D,3,0),0),0)+IFERROR(IF(AND(#REF!>0,#REF!<>""),VLOOKUP(#REF!,药材与丹炉!$B:$D,3,0),0),0)+IFERROR(IF(AND(#REF!>0,#REF!<>""),VLOOKUP(#REF!,药材与丹炉!$B:$D,3,0),0),0)+IFERROR(IF(AND(#REF!>0,#REF!<>""),VLOOKUP(#REF!,药材与丹炉!$B:$D,3,0),0),0)<0,2,0)) -> 0 | M3: 36 | N3: 8000
A4: 5402 | B4: 5 | C4: 天尘丹 | D4: 100 | E4: 修为+118800，境界不足元婴期时服用，额外获得30丹毒。 | F4: 生息 | G4: 360 | H4: 炼气 | I4: 180 | L4: =IF(IFERROR(IF(AND(#REF!>0,#REF!<>""),VLOOKUP(#REF!,药材与丹炉!$B:$D,3,0),0),0)+IFERROR(IF(AND(#REF!>0,#REF!<>""),VLOOKUP(#REF!,药材与丹炉!$B:$D,3,0),0),0)+IFERROR(IF(AND(#REF!>0,#REF!<>""),VLOOKUP(#REF!,药材与丹炉!$B:$D,3,0),0),0)+IFERROR(IF(AND(#REF!>0,#REF!<>""),VLOOKUP(#REF!,药材与丹炉!$B:$D,3,0),0),0)>0,1,IF(IFERROR(IF(AND(#REF!>0,#REF!<>""),VLOOKUP(#REF!,药材与丹炉!$B:$D,3,0),0),0)+IFERROR(IF(AND(#REF!>0,#REF!<>""),VLOOKUP(#REF!,药材与丹炉!$B:$D,3,0),0),0)+IFERROR(IF(AND(#REF!>0,#REF!<>""),VLOOKUP(#REF!,药材与丹炉!$B:$D,3,0),0),0)+IFERROR(IF(AND(#REF!>0,#REF!<>""),VLOOKUP(#REF!,药材与丹炉!$B:$D,3,0),0),0)<0,2,0)) -> 0 | M4: 36 | N4: 118800
A5: 5404 | B5: 5 | C5: 长生丹 | D5: 5 | E5: 寿元+30 | F5: 聚元 | G5: 288 | H5: 益寿 | I5: 360 | L5: =IF(IFERROR(IF(AND(#REF!>0,#REF!<>""),VLOOKUP(#REF!,药材与丹炉!$B:$D,3,0),0),0)+IFERROR(IF(AND(#REF!>0,#REF!<>""),VLOOKUP(#REF!,药材与丹炉!$B:$D,3,0),0),0)+IFERROR(IF(AND(#REF!>0,#REF!<>""),VLOOKUP(#REF!,药材与丹炉!$B:$D,3,0),0),0)+IFERROR(IF(AND(#REF!>0,#REF!<>""),VLOOKUP(#REF!,药材与丹炉!$B:$D,3,0),0),0)>0,1,IF(IFERROR(IF(AND(#REF!>0,#REF!<>""),VLOOKUP(#REF!,药材与丹炉!$B:$D,3,0),0),0)+IFERROR(IF(AND(#REF!>0,#REF!<>""),VLOOKUP(#REF!,药材与丹炉!$B:$D,3,0),0),0)+IFERROR(IF(AND(#REF!>0,#REF!<>""),VLOOKUP(#REF!,药材与丹炉!$B:$D,3,0),0),0)+IFERROR(IF(AND(#REF!>0,#REF!<>""),VLOOKUP(#REF!,药材与丹炉!$B:$D,3,0),0),0)<0,2,0)) -> 0 | M5: 36 | N5: 100000
A6: 5405 | B6: 5 | C6: 厉魄丹 | D6: 2 | E6: 神识+4/丹毒+2 | F6: 聚元 | G6: 216 | H6: 养魂 | I6: 180 | L6: =IF(IFERROR(IF(AND(#REF!>0,#REF!<>""),VLOOKUP(#REF!,药材与丹炉!$B:$D,3,0),0),0)+IFERROR(IF(AND(#REF!>0,#REF!<>""),VLOOKUP(#REF!,药材与丹炉!$B:$D,3,0),0),0)+IFERROR(IF(AND(#REF!>0,#REF!<>""),VLOOKUP(#REF!,药材与丹炉!$B:$D,3,0),0),0)+IFERROR(IF(AND(#REF!>0,#REF!<>""),VLOOKUP(#REF!,药材与丹炉!$B:$D,3,0),0),0)>0,1,IF(IFERROR(IF(AND(#REF!>0,#REF!<>""),VLOOKUP(#REF!,药材与丹炉!$B:$D,3,0),0),0)+IFERROR(IF(AND(#REF!>0,#REF!<>""),VLOOKUP(#REF!,药材与丹炉!$B:$D,3,0),0),0)+IFERROR(IF(AND(#REF!>0,#REF!<>""),VLOOKUP(#REF!,药材与丹炉!$B:$D,3,0),0),0)+IFERROR(IF(AND(#REF!>0,#REF!<>""),VLOOKUP(#REF!,药材与丹炉!$B:$D,3,0),0),0)<0,2,0)) -> 0 | M6: 9 | N6: 57500
A7: 5406 | B7: 5 | C7: 朝元丹 | D7: 1 | E7: 在五气朝元阶段，每回合抽牌数+1/丹毒+6 | F7: 振气 | G7: 18 | H7: 凝液 | I7: 72 | J7: 聚灵 | K7: 36 | L7: =IF(IFERROR(IF(AND(#REF!>0,#REF!<>""),VLOOKUP(#REF!,药材与丹炉!$B:$D,3,0),0),0)+IFERROR(IF(AND(#REF!>0,#REF!<>""),VLOOKUP(#REF!,药材与丹炉!$B:$D,3,0),0),0)+IFERROR(IF(AND(#REF!>0,#REF!<>""),VLOOKUP(#REF!,药材与丹炉!$B:$D,3,0),0),0)+IFERROR(IF(AND(#REF!>0,#REF!<>""),VLOOKUP(#REF!,药材与丹炉!$B:$D,3,0),0),0)>0,1,IF(IFERROR(IF(AND(#REF!>0,#REF!<>""),VLOOKUP(#REF!,药材与丹炉!$B:$D,3,0),0),0)+IFERROR(IF(AND(#REF!>0,#REF!<>""),VLOOKUP(#REF!,药材与丹炉!$B:$D,3,0),0),0)+IFERROR(IF(AND(#REF!>0,#REF!<>""),VLOOKUP(#REF!,药材与丹炉!$B:$D,3,0),0),0)+IFERROR(IF(AND(#REF!>0,#REF!<>""),VLOOKUP(#REF!,药材与丹炉!$B:$D,3,0),0),0)<0,2,0)) -> 0 | M7: 9 | N7: 12500
A8: 5407 | B8: 5 | C8: 鐾金元丹 | D8: 10 | E8: 提升金之道悟道经验600点/丹毒+2 | F8: 聚元 | G8: 180 | H8: 强金 | I8: 540 | J8: 道蕴 | K8: 180 | L8: =IF(IFERROR(IF(AND(#REF!>0,#REF!<>""),VLOOKUP(#REF!,药材与丹炉!$B:$D,3,0),0),0)+IFERROR(IF(AND(#REF!>0,#REF!<>""),VLOOKUP(#REF!,药材与丹炉!$B:$D,3,0),0),0)+IFERROR(IF(AND(#REF!>0,#REF!<>""),VLOOKUP(#REF!,药材与丹炉!$B:$D,3,0),0),0)+IFERROR(IF(AND(#REF!>0,#REF!<>""),VLOOKUP(#REF!,药材与丹炉!$B:$D,3,0),0),0)>0,1,IF(IFERROR(IF(AND(#REF!>0,#REF!<>""),VLOOKUP(#REF!,药材与丹炉!$B:$D,3,0),0),0)+IFERROR(IF(AND(#REF!>0,#REF!<>""),VLOOKUP(#REF!,药材与丹炉!$B:$D,3,0),0),0)+IFERROR(IF(AND(#REF!>0,#REF!<>""),VLOOKUP(#REF!,药材与丹炉!$B:$D,3,0),0),0)+IFERROR(IF(AND(#REF!>0,#REF!<>""),VLOOKUP(#REF!,药材与丹炉!$B:$D,3,0),0),0)<0,2,0)) -> 0 | M8: 180 | N8: 180000
A9: 5408 | B9: 5 | C9: 森檀元丹 | D9: 10 | E9: 提升木之道悟道经验600点/丹毒+2 | F9: 聚元 | G9: 180 | H9: 强木 | I9: 540 | J9: 道蕴 | K9: 180 | L9: =IF(IFERROR(IF(AND(#REF!>0,#REF!<>""),VLOOKUP(#REF!,药材与丹炉!$B:$D,3,0),0),0)+IFERROR(IF(AND(#REF!>0,#REF!<>""),VLOOKUP(#REF!,药材与丹炉!$B:$D,3,0),0),0)+IFERROR(IF(AND(#REF!>0,#REF!<>""),VLOOKUP(#REF!,药材与丹炉!$B:$D,3,0),0),0)+IFERROR(IF(AND(#REF!>0,#REF!<>""),VLOOKUP(#REF!,药材与丹炉!$B:$D,3,0),0),0)>0,1,IF(IFERROR(IF(AND(#REF!>0,#REF!<>""),VLOOKUP(#REF!,药材与丹炉!$B:$D,3,0),0),0)+IFERROR(IF(AND(#REF!>0,#REF!<>""),VLOOKUP(#REF!,药材与丹炉!$B:$D,3,0),0),0)+IFERROR(IF(AND(#REF!>0,#REF!<>""),VLOOKUP(#REF!,药材与丹炉!$B:$D,3,0),0),0)+IFERROR(IF(AND(#REF!>0,#REF!<>""),VLOOKUP(#REF!,药材与丹炉!$B:$D,3,0),0),0)<0,2,0)) -> 0 | M9: 180 | N9: 180000
A10: 5409 | B10: 5 | C10: 浩淼元丹 | D10: 10 | E10: 提升水之道悟道经验600点/丹毒+2 | F10: 聚元 | G10: 180 | H10: 强水 | I10: 540 | J10: 道蕴 | K10: 180 | L10: =IF(IFERROR(IF(AND(#REF!>0,#REF!<>""),VLOOKUP(#REF!,药材与丹炉!$B:$D,3,0),0),0)+IFERROR(IF(AND(#REF!>0,#REF!<>""),VLOOKUP(#REF!,药材与丹炉!$B:$D,3,0),0),0)+IFERROR(IF(AND(#REF!>0,#REF!<>""),VLOOKUP(#REF!,药材与丹炉!$B:$D,3,0),0),0)+IFERROR(IF(AND(#REF!>0,#REF!<>""),VLOOKUP(#REF!,药材与丹炉!$B:$D,3,0),0),0)>0,1,IF(IFERROR(IF(AND(#REF!>0,#REF!<>""),VLOOKUP(#REF!,药材与丹炉!$B:$D,3,0),0),0)+IFERROR(IF(AND(#REF!>0,#REF!<>""),VLOOKUP(#REF!,药材与丹炉!$B:$D,3,0),0),0)+IFERROR(IF(AND(#REF!>0,#REF!<>""),VLOOKUP(#REF!,药材与丹炉!$B:$D,3,0),0),0)+IFERROR(IF(AND(#REF!>0,#REF!<>""),VLOOKUP(#REF!,药材与丹炉!$B:$D,3,0),0),0)<0,2,0)) -> 0 | M10: 180 | N10: 180000
A11: 5410 | B11: 5 | C11: 芒焰元丹 | D11: 10 | E11: 提升火之道悟道经验600点/丹毒+2 | F11: 聚元 | G11: 180 | H11: 强火 | I11: 540 | J11: 道蕴 | K11: 180 | L11: =IF(IFERROR(IF(AND(#REF!>0,#REF!<>""),VLOOKUP(#REF!,药材与丹炉!$B:$D,3,0),0),0)+IFERROR(IF(AND(#REF!>0,#REF!<>""),VLOOKUP(#REF!,药材与丹炉!$B:$D,3,0),0),0)+IFERROR(IF(AND(#REF!>0,#REF!<>""),VLOOKUP(#REF!,药材与丹炉!$B:$D,3,0),0),0)+IFERROR(IF(AND(#REF!>0,#REF!<>""),VLOOKUP(#REF!,药材与丹炉!$B:$D,3,0),0),0)>0,1,IF(IFERROR(IF(AND(#REF!>0,#REF!<>""),VLOOKUP(#REF!,药材与丹炉!$B:$D,3,0),0),0)+IFERROR(IF(AND(#REF!>0,#REF!<>""),VLOOKUP(#REF!,药材与丹炉!$B:$D,3,0),0),0)+IFERROR(IF(AND(#REF!>0,#REF!<>""),VLOOKUP(#REF!,药材与丹炉!$B:$D,3,0),0),0)+IFERROR(IF(AND(#REF!>0,#REF!<>""),VLOOKUP(#REF!,药材与丹炉!$B:$D,3,0),0),0)<0,2,0)) -> 0 | M11: 180 | N11: 180000
A12: 5411 | B12: 5 | C12: 无垠元丹 | D12: 10 | E12: 提升土之道悟道经验600点/丹毒+2 | F12: 聚元 | G12: 180 | H12: 强土 | I12: 540 | J12: 道蕴 | K12: 180 | L12: =IF(IFERROR(IF(AND(#REF!>0,#REF!<>""),VLOOKUP(#REF!,药材与丹炉!$B:$D,3,0),0),0)+IFERROR(IF(AND(#REF!>0,#REF!<>""),VLOOKUP(#REF!,药材与丹炉!$B:$D,3,0),0),0)+IFERROR(IF(AND(#REF!>0,#REF!<>""),VLOOKUP(#REF!,药材与丹炉!$B:$D,3,0),0),0)+IFERROR(IF(AND(#REF!>0,#REF!<>""),VLOOKUP(#REF!,药材与丹炉!$B:$D,3,0),0),0)>0,1,IF(IFERROR(IF(AND(#REF!>0,#REF!<>""),VLOOKUP(#REF!,药材与丹炉!$B:$D,3,0),0),0)+IFERROR(IF(AND(#REF!>0,#REF!<>""),VLOOKUP(#REF!,药材与丹炉!$B:$D,3,0),0),0)+IFERROR(IF(AND(#REF!>0,#REF!<>""),VLOOKUP(#REF!,药材与丹炉!$B:$D,3,0),0),0)+IFERROR(IF(AND(#REF!>0,#REF!<>""),VLOOKUP(#REF!,药材与丹炉!$B:$D,3,0),0),0)<0,2,0)) -> 0 | M12: 180 | N12: 180000
A13: 5412 | B13: 5 | C13: 天剑元丹 | D13: 10 | E13: 提升剑之道悟道经验600点/丹毒+2 | F13: 聚元 | G13: 180 | H13: 剑意 | I13: 540 | J13: 道蕴 | K13: 180 | L13: =IF(IFERROR(IF(AND(#REF!>0,#REF!<>""),VLOOKUP(#REF!,药材与丹炉!$B:$D,3,0),0),0)+IFERROR(IF(AND(#REF!>0,#REF!<>""),VLOOKUP(#REF!,药材与丹炉!$B:$D,3,0),0),0)+IFERROR(IF(AND(#REF!>0,#REF!<>""),VLOOKUP(#REF!,药材与丹炉!$B:$D,3,0),0),0)+IFERROR(IF(AND(#REF!>0,#REF!<>""),VLOOKUP(#REF!,药材与丹炉!$B:$D,3,0),0),0)>0,1,IF(IFERROR(IF(AND(#REF!>0,#REF!<>""),VLOOKUP(#REF!,药材与丹炉!$B:$D,3,0),0),0)+IFERROR(IF(AND(#REF!>0,#REF!<>""),VLOOKUP(#REF!,药材与丹炉!$B:$D,3,0),0),0)+IFERROR(IF(AND(#REF!>0,#REF!<>""),VLOOKUP(#REF!,药材与丹炉!$B:$D,3,0),0),0)+IFERROR(IF(AND(#REF!>0,#REF!<>""),VLOOKUP(#REF!,药材与丹炉!$B:$D,3,0),0),0)<0,2,0)) -> 0 | M13: 180 | N13: 180000
A14: 5413 | B14: 5 | C14: 炼魂元丹 | D14: 10 | E14: 提升神之道悟道经验600点/丹毒+2 | F14: 聚元 | G14: 180 | H14: 凝神 | I14: 540 | J14: 道蕴 | K14: 180 | L14: =IF(IFERROR(IF(AND(#REF!>0,#REF!<>""),VLOOKUP(#REF!,药材与丹炉!$B:$D,3,0),0),0)+IFERROR(IF(AND(#REF!>0,#REF!<>""),VLOOKUP(#REF!,药材与丹炉!$B:$D,3,0),0),0)+IFERROR(IF(AND(#REF!>0,#REF!<>""),VLOOKUP(#REF!,药材与丹炉!$B:$D,3,0),0),0)+IFERROR(IF(AND(#REF!>0,#REF!<>""),VLOOKUP(#REF!,药材与丹炉!$B:$D,3,0),0),0)>0,1,IF(IFERROR(IF(AND(#REF!>0,#REF!<>""),VLOOKUP(#REF!,药材与丹炉!$B:$D,3,0),0),0)+IFERROR(IF(AND(#REF!>0,#REF!<>""),VLOOKUP(#REF!,药材与丹炉!$B:$D,3,0),0),0)+IFERROR(IF(AND(#REF!>0,#REF!<>""),VLOOKUP(#REF!,药材与丹炉!$B:$D,3,0),0),0)+IFERROR(IF(AND(#REF!>0,#REF!<>""),VLOOKUP(#REF!,药材与丹炉!$B:$D,3,0),0),0)<0,2,0)) -> 0 | M14: 180 | N14: 180000
A15: 5414 | B15: 5 | C15: 道源丹 | D15: 3 | E15: 增加悟道点1点/丹毒+2 | F15: 聚元 | G15: 360 | H15: 开悟 | I15: 1260 | L15: =IF(IFERROR(IF(AND(#REF!>0,#REF!<>""),VLOOKUP(#REF!,药材与丹炉!$B:$D,3,0),0),0)+IFERROR(IF(AND(#REF!>0,#REF!<>""),VLOOKUP(#REF!,药材与丹炉!$B:$D,3,0),0),0)+IFERROR(IF(AND(#REF!>0,#REF!<>""),VLOOKUP(#REF!,药材与丹炉!$B:$D,3,0),0),0)+IFERROR(IF(AND(#REF!>0,#REF!<>""),VLOOKUP(#REF!,药材与丹炉!$B:$D,3,0),0),0)>0,1,IF(IFERROR(IF(AND(#REF!>0,#REF!<>""),VLOOKUP(#REF!,药材与丹炉!$B:$D,3,0),0),0)+IFERROR(IF(AND(#REF!>0,#REF!<>""),VLOOKUP(#REF!,药材与丹炉!$B:$D,3,0),0),0)+IFERROR(IF(AND(#REF!>0,#REF!<>""),VLOOKUP(#REF!,药材与丹炉!$B:$D,3,0),0),0)+IFERROR(IF(AND(#REF!>0,#REF!<>""),VLOOKUP(#REF!,药材与丹炉!$B:$D,3,0),0),0)<0,2,0)) -> 0 | M15: 180 | N15: 270000
A16: 5415 | B16: 5 | C16: 玉清昊元丹 | D16: 3 | E16: 悟性+4/丹毒+2 | F16: 聚元 | G16: 180 | H16: 开窍 | I16: 180 | J16: 调和 | K16: 180 | L16: =IF(IFERROR(IF(AND(#REF!>0,#REF!<>""),VLOOKUP(#REF!,药材与丹炉!$B:$D,3,0),0),0)+IFERROR(IF(AND(#REF!>0,#REF!<>""),VLOOKUP(#REF!,药材与丹炉!$B:$D,3,0),0),0)+IFERROR(IF(AND(#REF!>0,#REF!<>""),VLOOKUP(#REF!,药材与丹炉!$B:$D,3,0),0),0)+IFERROR(IF(AND(#REF!>0,#REF!<>""),VLOOKUP(#REF!,药材与丹炉!$B:$D,3,0),0),0)>0,1,IF(IFERROR(IF(AND(#REF!>0,#REF!<>""),VLOOKUP(#REF!,药材与丹炉!$B:$D,3,0),0),0)+IFERROR(IF(AND(#REF!>0,#REF!<>""),VLOOKUP(#REF!,药材与丹炉!$B:$D,3,0),0),0)+IFERROR(IF(AND(#REF!>0,#REF!<>""),VLOOKUP(#REF!,药材与丹炉!$B:$D,3,0),0),0)+IFERROR(IF(AND(#REF!>0,#REF!<>""),VLOOKUP(#REF!,药材与丹炉!$B:$D,3,0),0),0)<0,2,0)) -> 0 | M16: 36 | N16: 57500
A17: 5416 | B17: 5 | C17: 修髓丹 | D17: 1 | E17: 资质+9/丹毒+2 | F17: 聚元 | G17: 180 | H17: 洗髓 | I17: 180 | L17: =IF(IFERROR(IF(AND(#REF!>0,#REF!<>""),VLOOKUP(#REF!,药材与丹炉!$B:$D,3,0),0),0)+IFERROR(IF(AND(#REF!>0,#REF!<>""),VLOOKUP(#REF!,药材与丹炉!$B:$D,3,0),0),0)+IFERROR(IF(AND(#REF!>0,#REF!<>""),VLOOKUP(#REF!,药材与丹炉!$B:$D,3,0),0),0)+IFERROR(IF(AND(#REF!>0,#REF!<>""),VLOOKUP(#REF!,药材与丹炉!$B:$D,3,0),0),0)>0,1,IF(IFERROR(IF(AND(#REF!>0,#REF!<>""),VLOOKUP(#REF!,药材与丹炉!$B:$D,3,0),0),0)+IFERROR(IF(AND(#REF!>0,#REF!<>""),VLOOKUP(#REF!,药材与丹炉!$B:$D,3,0),0),0)+IFERROR(IF(AND(#REF!>0,#REF!<>""),VLOOKUP(#REF!,药材与丹炉!$B:$D,3,0),0),0)+IFERROR(IF(AND(#REF!>0,#REF!<>""),VLOOKUP(#REF!,药材与丹炉!$B:$D,3,0),0),0)<0,2,0)) -> 0 | M17: 180 | N17: 82000
A18: 5417 | B18: 5 | C18: 赤阳丹 | D18: 5 | E18: 生命值上限+20/丹毒+3 | F18: 聚元 | G18: 180 | H18: 煅体 | I18: 180 | L18: =IF(IFERROR(IF(AND(#REF!>0,#REF!<>""),VLOOKUP(#REF!,药材与丹炉!$B:$D,3,0),0),0)+IFERROR(IF(AND(#REF!>0,#REF!<>""),VLOOKUP(#REF!,药材与丹炉!$B:$D,3,0),0),0)+IFERROR(IF(AND(#REF!>0,#REF!<>""),VLOOKUP(#REF!,药材与丹炉!$B:$D,3,0),0),0)+IFERROR(IF(AND(#REF!>0,#REF!<>""),VLOOKUP(#REF!,药材与丹炉!$B:$D,3,0),0),0)>0,1,IF(IFERROR(IF(AND(#REF!>0,#REF!<>""),VLOOKUP(#REF!,药材与丹炉!$B:$D,3,0),0),0)+IFERROR(IF(AND(#REF!>0,#REF!<>""),VLOOKUP(#REF!,药材与丹炉!$B:$D,3,0),0),0)+IFERROR(IF(AND(#REF!>0,#REF!<>""),VLOOKUP(#REF!,药材与丹炉!$B:$D,3,0),0),0)+IFERROR(IF(AND(#REF!>0,#REF!<>""),VLOOKUP(#REF!,药材与丹炉!$B:$D,3,0),0),0)<0,2,0)) -> 0 | M18: 180 | N18: 82000
A19: 5418 | B19: 5 | C19: 青灵丹 | D19: 2 | E19: 遁速+9/丹毒+2 | F19: 聚元 | G19: 108 | H19: 神行 | I19: 72 | L19: =IF(IFERROR(IF(AND(#REF!>0,#REF!<>""),VLOOKUP(#REF!,药材与丹炉!$B:$D,3,0),0),0)+IFERROR(IF(AND(#REF!>0,#REF!<>""),VLOOKUP(#REF!,药材与丹炉!$B:$D,3,0),0),0)+IFERROR(IF(AND(#REF!>0,#REF!<>""),VLOOKUP(#REF!,药材与丹炉!$B:$D,3,0),0),0)+IFERROR(IF(AND(#REF!>0,#REF!<>""),VLOOKUP(#REF!,药材与丹炉!$B:$D,3,0),0),0)>0,1,IF(IFERROR(IF(AND(#REF!>0,#REF!<>""),VLOOKUP(#REF!,药材与丹炉!$B:$D,3,0),0),0)+IFERROR(IF(AND(#REF!>0,#REF!<>""),VLOOKUP(#REF!,药材与丹炉!$B:$D,3,0),0),0)+IFERROR(IF(AND(#REF!>0,#REF!<>""),VLOOKUP(#REF!,药材与丹炉!$B:$D,3,0),0),0)+IFERROR(IF(AND(#REF!>0,#REF!<>""),VLOOKUP(#REF!,药材与丹炉!$B:$D,3,0),0),0)<0,2,0)) -> 0 | M19: 36 | N19: 26250
A20: 5419 | B20: 5 | C20: 少阴清灵丹 | D20: 50 | E20: 心境+9 | F20: 聚元 | G20: 108 | H20: 清心 | I20: 72 | L20: =IF(IFERROR(IF(AND(#REF!>0,#REF!<>""),VLOOKUP(#REF!,药材与丹炉!$B:$D,3,0),0),0)+IFERROR(IF(AND(#REF!>0,#REF!<>""),VLOOKUP(#REF!,药材与丹炉!$B:$D,3,0),0),0)+IFERROR(IF(AND(#REF!>0,#REF!<>""),VLOOKUP(#REF!,药材与丹炉!$B:$D,3,0),0),0)+IFERROR(IF(AND(#REF!>0,#REF!<>""),VLOOKUP(#REF!,药材与丹炉!$B:$D,3,0),0),0)>0,1,IF(IFERROR(IF(AND(#REF!>0,#REF!<>""),VLOOKUP(#REF!,药材与丹炉!$B:$D,3,0),0),0)+IFERROR(IF(AND(#REF!>0,#REF!<>""),VLOOKUP(#REF!,药材与丹炉!$B:$D,3,0),0),0)+IFERROR(IF(AND(#REF!>0,#REF!<>""),VLOOKUP(#REF!,药材与丹炉!$B:$D,3,0),0),0)+IFERROR(IF(AND(#REF!>0,#REF!<>""),VLOOKUP(#REF!,药材与丹炉!$B:$D,3,0),0),0)<0,2,0)) -> 0 | M20: 36 | N20: 26250
A21: 5420 | B21: 5 | C21: 太乙降尘丹 | D21: 10 | E21: 丹毒-30 | F21: 净血 | G21: 108 | H21: 解毒 | I21: 72 | L21: =IF(IFERROR(IF(AND(#REF!>0,#REF!<>""),VLOOKUP(#REF!,药材与丹炉!$B:$D,3,0),0),0)+IFERROR(IF(AND(#REF!>0,#REF!<>""),VLOOKUP(#REF!,药材与丹炉!$B:$D,3,0),0),0)+IFERROR(IF(AND(#REF!>0,#REF!<>""),VLOOKUP(#REF!,药材与丹炉!$B:$D,3,0),0),0)+IFERROR(IF(AND(#REF!>0,#REF!<>""),VLOOKUP(#REF!,药材与丹炉!$B:$D,3,0),0),0)>0,1,IF(IFERROR(IF(AND(#REF!>0,#REF!<>""),VLOOKUP(#REF!,药材与丹炉!$B:$D,3,0),0),0)+IFERROR(IF(AND(#REF!>0,#REF!<>""),VLOOKUP(#REF!,药材与丹炉!$B:$D,3,0),0),0)+IFERROR(IF(AND(#REF!>0,#REF!<>""),VLOOKUP(#REF!,药材与丹炉!$B:$D,3,0),0),0)+IFERROR(IF(AND(#REF!>0,#REF!<>""),VLOOKUP(#REF!,药材与丹炉!$B:$D,3,0),0),0)<0,2,0)) -> 0 | M21: 36 | N21: 26250
A22: 5501 | B22: 5 | C22: 九转灵蛇丹 | D22: 100 | E22: 恢复全部生命值/丹毒+1 | F22: 活血 | G22: 9 | H22: 固元 | I22: 9 | J22: 培元 | K22: 9 | L22: =IF(IFERROR(IF(AND(#REF!>0,#REF!<>""),VLOOKUP(#REF!,药材与丹炉!$B:$D,3,0),0),0)+IFERROR(IF(AND(#REF!>0,#REF!<>""),VLOOKUP(#REF!,药材与丹炉!$B:$D,3,0),0),0)+IFERROR(IF(AND(#REF!>0,#REF!<>""),VLOOKUP(#REF!,药材与丹炉!$B:$D,3,0),0),0)+IFERROR(IF(AND(#REF!>0,#REF!<>""),VLOOKUP(#REF!,药材与丹炉!$B:$D,3,0),0),0)>0,1,IF(IFERROR(IF(AND(#REF!>0,#REF!<>""),VLOOKUP(#REF!,药材与丹炉!$B:$D,3,0),0),0)+IFERROR(IF(AND(#REF!>0,#REF!<>""),VLOOKUP(#REF!,药材与丹炉!$B:$D,3,0),0),0)+IFERROR(IF(AND(#REF!>0,#REF!<>""),VLOOKUP(#REF!,药材与丹炉!$B:$D,3,0),0),0)+IFERROR(IF(AND(#REF!>0,#REF!<>""),VLOOKUP(#REF!,药材与丹炉!$B:$D,3,0),0),0)<0,2,0)) -> 0 | M22: 9 | N22: 3500
A23: 5502 | B23: 6 | C23: 天元神丹 | D23: 100 | E23: 修为+594000，境界不足化神期时服用，额外获得30丹毒。 | F23: 生息 | G23: 81 | H23: 炼气 | I23: 2160 | L23: =IF(IFERROR(IF(AND(#REF!>0,#REF!<>""),VLOOKUP(#REF!,药材与丹炉!$B:$D,3,0),0),0)+IFERROR(IF(AND(#REF!>0,#REF!<>""),VLOOKUP(#REF!,药材与丹炉!$B:$D,3,0),0),0)+IFERROR(IF(AND(#REF!>0,#REF!<>""),VLOOKUP(#REF!,药材与丹炉!$B:$D,3,0),0),0)+IFERROR(IF(AND(#REF!>0,#REF!<>""),VLOOKUP(#REF!,药材与丹炉!$B:$D,3,0),0),0)>0,1,IF(IFERROR(IF(AND(#REF!>0,#REF!<>""),VLOOKUP(#REF!,药材与丹炉!$B:$D,3,0),0),0)+IFERROR(IF(AND(#REF!>0,#REF!<>""),VLOOKUP(#REF!,药材与丹炉!$B:$D,3,0),0),0)+IFERROR(IF(AND(#REF!>0,#REF!<>""),VLOOKUP(#REF!,药材与丹炉!$B:$D,3,0),0),0)+IFERROR(IF(AND(#REF!>0,#REF!<>""),VLOOKUP(#REF!,药材与丹炉!$B:$D,3,0),0),0)<0,2,0)) -> 0 | M23: 36 | N23: 594000
A24: 5512 | B24: 6 | C24: 天道源丹 | D24: 1 | E24: 增加悟道点3点/丹毒+2 | F24: 聚元 | G24: 2160 | H24: 开悟 | I24: 7560 | L24: =IF(IFERROR(IF(AND(#REF!>0,#REF!<>""),VLOOKUP(#REF!,药材与丹炉!$B:$D,3,0),0),0)+IFERROR(IF(AND(#REF!>0,#REF!<>""),VLOOKUP(#REF!,药材与丹炉!$B:$D,3,0),0),0)+IFERROR(IF(AND(#REF!>0,#REF!<>""),VLOOKUP(#REF!,药材与丹炉!$B:$D,3,0),0),0)+IFERROR(IF(AND(#REF!>0,#REF!<>""),VLOOKUP(#REF!,药材与丹炉!$B:$D,3,0),0),0)>0,1,IF(IFERROR(IF(AND(#REF!>0,#REF!<>""),VLOOKUP(#REF!,药材与丹炉!$B:$D,3,0),0),0)+IFERROR(IF(AND(#REF!>0,#REF!<>""),VLOOKUP(#REF!,药材与丹炉!$B:$D,3,0),0),0)+IFERROR(IF(AND(#REF!>0,#REF!<>""),VLOOKUP(#REF!,药材与丹炉!$B:$D,3,0),0),0)+IFERROR(IF(AND(#REF!>0,#REF!<>""),VLOOKUP(#REF!,药材与丹炉!$B:$D,3,0),0),0)<0,2,0)) -> 0 | M24: 1080 | N24: 1782000
A25: 5517 | B25: 6 | C25: 六阳长生丹 | D25: 5 | E25: 寿元+50 | F25: 聚元 | G25: 180 | H25: 益寿 | I25: 720 | L25: =IF(IFERROR(IF(AND(#REF!>0,#REF!<>""),VLOOKUP(#REF!,药材与丹炉!$B:$D,3,0),0),0)+IFERROR(IF(AND(#REF!>0,#REF!<>""),VLOOKUP(#REF!,药材与丹炉!$B:$D,3,0),0),0)+IFERROR(IF(AND(#REF!>0,#REF!<>""),VLOOKUP(#REF!,药材与丹炉!$B:$D,3,0),0),0)+IFERROR(IF(AND(#REF!>0,#REF!<>""),VLOOKUP(#REF!,药材与丹炉!$B:$D,3,0),0),0)>0,1,IF(IFERROR(IF(AND(#REF!>0,#REF!<>""),VLOOKUP(#REF!,药材与丹炉!$B:$D,3,0),0),0)+IFERROR(IF(AND(#REF!>0,#REF!<>""),VLOOKUP(#REF!,药材与丹炉!$B:$D,3,0),0),0)+IFERROR(IF(AND(#REF!>0,#REF!<>""),VLOOKUP(#REF!,药材与丹炉!$B:$D,3,0),0),0)+IFERROR(IF(AND(#REF!>0,#REF!<>""),VLOOKUP(#REF!,药材与丹炉!$B:$D,3,0),0),0)<0,2,0)) -> 0 | M25: 180 | N25: 220000

Sheet 记事本
B1: 默认适应X100%
B2: 部分数据源 | D2: 版本 | F2: 一仙道人 | I2: 属性 | J2: 一品 | K2: 二品 | L2: 三品 | M2: 四品 | N2: 五品 | O2: 六品 | Q2: 竹山丹圣-整合
B3: 丹普传承 | D3: 1.0 | F3: 武陵城 | G3: 44223 | I3: 心境 | J3: 冰心丹 | K3: 明心丹 | L3: 幻心玄丹 | M3: 鬼面炼心丹 | N3: 少阴清灵丹 | O3: 天命炼心丹
B4: 炼器传承 | D4: 2.0 | F4: 逸风城 | G4: 44267 | I4: 寿元 | K4: 续命丹 | L4: 延寿丹 | M4: 青冥丹 | N4: 长生丹 | O4: 六阳长生丹
B5: 流派传承 | D5: 2.0 | F5: 云汐城 | G5: 44372 | I5: 神识 | J5: 《23年1月18日》 =V1.7= 仙录传承更新 | L5: 养魂丹 | M5: 灵魂丹 | N5: 厉魂丹 | O5: 三阳锻魄丹
B6: 功法神通 | D6: 2.0 | F6: 天星城 | G6: 44421 | I6: 资质 | L6: 草还丹 | M6: 九转再造丹 | N6: 修髓丹 | O6: 太乙炼髓丹
B7: 复杂任务 | D7: 2.0 | F7: 广陵城 | G7: 44513 | I7: 遁速 | L7: 御风丹 | M7: 神行丹 | N7: 青灵丹 | O7: 太乙碧莹丹
B8: 境界突破 | D8: 2.0 | F8: 跑`商 | I8: 悟性 | L8: 启灵丹 | M8: 玄元丹 | N8: 玉清昊元丹 | O8: 太上玄门丹
B9: 年历游记 | D9: 2.0 | F9: 炼丹 | I9: 气血 | L9: 锻体丹 | M9: 金刚铁骨丹 | N9: 赤阳丹 | O9: 天命血凝丹
B10: 灵石笔记 | D10: 2.0 | F10: 炼器 | I10: 悟道 | N10: 道源丹 | O10: 天道源丹
B11: 桃花笔记 | D11: 1.3 | F11: 挖矿 | I11: 灵根 | K11: 金元丹 | L11: 水元丹 | M11: 木元丹 | N11: 火元丹 | O11: 土元丹
B13: 证道长生
B14: 相较于V1.6 更新了：炼丹模拟器->丹普传承，炼器表->炼器传承，，渡劫，功法神通检查，字体界面调整，流派->流派传承 修正了：炼器-天阳剑效果，练气期小境界提升血量调整，年历大量更新，化神领域效果 添加了：境界晋升修为需求，星官，龙宫，岫络谷，九州游记，灵石笔记，桃花笔记 删除了：流派评分，之前是看名字填的【狗头保命】，洞府，炼丹赚钱，灵石 额外的： 1.快捷键CTRL+F查找表内容 2.任何道友都可随意转载修改和使用，但不得用于商业目的 3.等待1.8的升级更新，计划年历，化神和渡劫整完，灵石攻略点名方向不做具体操作，合并表白攻略，剑灵剧情，合并龙宫与龙族剧情 4.攻略多来自各方道友，我主要制作页面，填充更新数据。同步数据于觅长生1.0.009 2023/1/18，如果版本更新或者表格错误，数据不对了可以来QQ频道传音符找我ID：竹山丹圣

Sheet 丹普传承
A1: ID | B1: 品级 | C1: 丹药名称 | D1: 耐药性 | E1: 效果/丹毒 | F1: 总主药需求 | G1: 主需求 | H1: 药力↓ | I1: 主药↓ | J1: 数量 | K1: 主需求2 | L1: 药力2 | M1: 主药2↓ | N1: 数量2 | O1: 总辅需求 | P1: 辅需求 | Q1: 辅药力↓ | R1: 辅药↓ | S1: 数量3 | T1: 辅需求2 | U1: 辅药力2 | V1: 辅药2↓ | W1: 数量4 | X1: 寒热 | Y1: 药引药力 | Z1: 药引↓ | AA1: 数量5 | AB1: 丹炉↓ | AC1: 丹炉耐久消耗 | AD1: 药材总数 | AE1: 炼丹理论消耗灵石 | AF1: 丹药价值 | AG1: 价值差 | AH1: 价格 | AI1: 价格差 | AJ1: 药引容量 | AK1: 是否出错 | AL1: 价格倍率→ | AM1: 2 | AN1: 控火悟道→ | AO1: 否
A2: 5001 | B2: 1 | C2: 化淤丹 | D2: 999 | E2: 生命值+20/丹毒+1 | F2: 1 | G2: 活血 | H2: 1 | I2: 天青花 | J2: =IFERROR(CEILING($H2/VLOOKUP($I2,药材与丹炉!$B:$H,COLUMN(药材与丹炉!$H2)-1,0),1),"") -> 1 | K2: 活血 | L2: =IFERROR(IF($F2-$H2=0,"",$F2-$H2),"") | N2: =IFERROR(CEILING($L2/VLOOKUP($M2,药材与丹炉!$B:$H,COLUMN(药材与丹炉!$H2)-1,0),1),"") | O2: 1 | P2: 培元 | Q2: 1 | R2: 流莹草 | S2: =IFERROR(CEILING($Q2/VLOOKUP($R2,药材与丹炉!$B:$H,COLUMN(药材与丹炉!$H2)-1,0),1),"") -> 1 | T2: =P2 -> 培元 | U2: =IFERROR(IF($O2-$Q2=0,"",$O2-$Q2),"") | W2: =IFERROR(CEILING($U2/VLOOKUP($V2,药材与丹炉!$B:$H,COLUMN(药材与丹炉!$H2)-1,0),1),"") | X2: =IF(IFERROR(IF(AND($J2>0,$J2<>""),VLOOKUP($I2,药材与丹炉!$B:$D,3,0),0),0)+IFERROR(IF(AND($N2>0,$N2<>""),VLOOKUP($M2,药材与丹炉!$B:$D,3,0),0),0)+IFERROR(IF(AND($S2>0,$S2<>""),VLOOKUP($R2,药材与丹炉!$B:$D,3,0),0),0)+IFERROR(IF(AND($W2>0,$W2<>""),VLOOKUP($V2,药材与丹炉!$B:$D,3,0),0),0)>0,1,IF(IFERROR(IF(AND($J2>0,$J2<>""),VLOOKUP($I2,药材与丹炉!$B:$D,3,0),0),0)+IFERROR(IF(AND($N2>0,$N2<>""),VLOOKUP($M2,药材与丹炉!$B:$D,3,0),0),0)+IFERROR(IF(AND($S2>0,$S2<>""),VLOOKUP($R2,药材与丹炉!$B:$D,3,0),0),0)+IFERROR(IF(AND($W2>0,$W2<>""),VLOOKUP($V2,药材与丹炉!$B:$D,3,0),0),0)<0,2,0)) -> 1 | Y2: 1 | Z2: 银月花 | AA2: =IFERROR($Y2/VLOOKUP($Z2,药材与丹炉!$B:$H,COLUMN(药材与丹炉!$H2)-1,0),"") -> 1 | AB2: 普通丹炉 | AC2: =IFERROR(IF($B2-VLOOKUP($AB2,药材与丹炉!$N:$P,2,0)<0,IF($AO$1="是",0,1),IF($B2-VLOOKUP($AB2,药材与丹炉!$N:$P,2,0)=0,2,IF($B2-VLOOKUP($AB2,药材与丹炉!$N:$P,2,0)=1,40,IF($B2-VLOOKUP($AB2,药材与丹炉!$N:$P,2,0)=2,80,"爆炸")))),"") -> 2 | AD2: =IFERROR($J2+IFERROR(IF($N2="",0,$N2),0)+IFERROR(IF($S2="",0,$S2),0)+IFERROR(IF($W2="",0,$W2),0)+IFERROR(IF($AA2="",0,$AA2),0),"") -> 3 | AE2: =IFERROR($J2*VLOOKUP($I2,药材与丹炉!$B:$K,10,0),0)+IFERROR($N2*VLOOKUP($M2,药材与丹炉!$B:$K,10,0),0)+IFERROR($S2*VLOOKUP($R2,药材与丹炉!$B:$K,10,0),0)+IFERROR($W2*VLOOKUP($V2,药材与丹炉!$B:$K,10,0),0)+IFERROR($AA2*VLOOKUP($Z2,药材与丹炉!$B:$K,10,0),0)+IFERROR($AC2*VLOOKUP($AB2,药材与丹炉!$N:$P,3,0)/100,0) -> 39 | AF2: 68 | AG2: =$AF2-$AE2 -> 29 | AH2: =$AF2*$AM$1*$AM$21 -> 136 | AI2: =$AH2-$AE2 -> 97 | AJ2: =IFERROR(IF($Y2/VLOOKUP($Y2,药材与丹炉!$T:$U,2,0)<=(VLOOKUP($AB2,药材与丹炉!$N:$O,2,0)+8)-($J2+IFERROR(IF($N2="",0,$N2),0)+IFERROR(IF($S2="",0,$S2),0)+IFERROR(IF($W2="",0,$W2),0)),1,2),1) -> 1 | AK2: =OR(NOT(IFERROR(OR($L2="",AND($L2<>"",$L2>0,VLOOKUP($AB2,药材与丹炉!$N:$O,2,0)=6)),0)),AND($L2<>"",$L2>0,OR(VLOOKUP($AB2,药材与丹炉!$N:$Q,4,0)-2<$N2,$N2="")),AND($U2<>"",$U2>0,OR(VLOOKUP($AB2,药材与丹炉!$N:$Q,4,0)-3<$W2,$W2="")),NOT(OR(AND($Q2<>"",$S2<>"",VLOOKUP($AB2,药材与丹炉!$N:$Q,4,0)-3>=$S2),$P2="")),NOT(OR(AND($H2<>"",$J2<>"",VLOOKUP($AB2,药材与丹炉!$N:$Q,4,0)-1>=$J2),$G2="")),NOT(OR($U2="",AND($U2<>"",$U2>0))),NOT(OR($Y2="",IF($Z2<>"",IFERROR(IF(VLOOKUP($Z2,药材与丹炉!$B:$D,3,0)=-1,$X2=1,IF(VLOOKUP($Z2,药材与丹炉!$B:$D,3,0)=1,$X2=2,$X2=0)),0),0))),$AC2="爆炸",(VLOOKUP($AB2,药材与丹炉!$N:$O,2,0)+8)<$AD2) -> FALSE | AL2: 控火悟道涵义： | AM2: 为"是"表示领悟了丹道融汇贯通中的控火，在计算炼丹消耗灵石价时减少丹炉所带的价格消耗；为"否"则正常计算丹炉损耗
A3: 5002 | B3: 1 | C3: 洗髓丹 | D3: 100 | E3: 修为+180 | F3: 15 | G3: 生息 | H3: 15 | I3: 何首乌 | J3: =IFERROR(CEILING($H3/VLOOKUP($I3,药材与丹炉!$B:$H,COLUMN(药材与丹炉!$H3)-1,0),1),"") -> 5 | K3: 生息 | L3: =IFERROR(IF($F3-$H3=0,"",$F3-$H3),"") | N3: =IFERROR(CEILING($L3/VLOOKUP($M3,药材与丹炉!$B:$H,COLUMN(药材与丹炉!$H3)-1,0),1),"") | S3: =IFERROR(CEILING($Q3/VLOOKUP($R3,药材与丹炉!$B:$H,COLUMN(药材与丹炉!$H3)-1,0),1),"") | U3: =IFERROR(IF($O3-$Q3=0,"",$O3-$Q3),"") | W3: =IFERROR(CEILING($U3/VLOOKUP($V3,药材与丹炉!$B:$H,COLUMN(药材与丹炉!$H3)-1,0),1),"") | X3: =IF(IFERROR(IF(AND($J3>0,$J3<>""),VLOOKUP($I3,药材与丹炉!$B:$D,3,0),0),0)+IFERROR(IF(AND($N3>0,$N3<>""),VLOOKUP($M3,药材与丹炉!$B:$D,3,0),0),0)+IFERROR(IF(AND($S3>0,$S3<>""),VLOOKUP($R3,药材与丹炉!$B:$D,3,0),0),0)+IFERROR(IF(AND($W3>0,$W3<>""),VLOOKUP($V3,药材与丹炉!$B:$D,3,0),0),0)>0,1,IF(IFERROR(IF(AND($J3>0,$J3<>""),VLOOKUP($I3,药材与丹炉!$B:$D,3,0),0),0)+IFERROR(IF(AND($N3>0,$N3<>""),VLOOKUP($M3,药材与丹炉!$B:$D,3,0),0),0)+IFERROR(IF(AND($S3>0,$S3<>""),VLOOKUP($R3,药材与丹炉!$B:$D,3,0),0),0)+IFERROR(IF(AND($W3>0,$W3<>""),VLOOKUP($V3,药材与丹炉!$B:$D,3,0),0),0)<0,2,0)) -> 1 | Y3: 1 | Z3: 宁心草 | AA3: =IFERROR($Y3/VLOOKUP($Z3,药材与丹炉!$B:$H,COLUMN(药材与丹炉!$H3)-1,0),"") -> 1 | AB3: 普通丹炉 | AC3: =IFERROR(IF($B3-VLOOKUP($AB3,药材与丹炉!$N:$P,2,0)<0,IF($AO$1="是",0,1),IF($B3-VLOOKUP($AB3,药材与丹炉!$N:$P,2,0)=0,2,IF($B3-VLOOKUP($AB3,药材与丹炉!$N:$P,2,0)=1,40,IF($B3-VLOOKUP($AB3,药材与丹炉!$N:$P,2,0)=2,80,"爆炸")))),"") -> 2 | AD3: =IFERROR($J3+IFERROR(IF($N3="",0,$N3),0)+IFERROR(IF($S3="",0,$S3),0)+IFERROR(IF($W3="",0,$W3),0)+IFERROR(IF($AA3="",0,$AA3),0),"") -> 6 | AE3: =IFERROR($J3*VLOOKUP($I3,药材与丹炉!$B:$K,10,0),0)+IFERROR($N3*VLOOKUP($M3,药材与丹炉!$B:$K,10,0),0)+IFERROR($S3*VLOOKUP($R3,药材与丹炉!$B:$K,10,0),0)+IFERROR($W3*VLOOKUP($V3,药材与丹炉!$B:$K,10,0),0)+IFERROR($AA3*VLOOKUP($Z3,药材与丹炉!$B:$K,10,0),0)+IFERROR($AC3*VLOOKUP($AB3,药材与丹炉!$N:$P,3,0)/100,0) -> 201 | AF3: 225 | AG3: =$AF3-$AE3 -> 24 | AH3: =$AF3*$AM$1*$AM$21 -> 450 | AI3: =$AH3-$AE3 -> 249 | AJ3: =IFERROR(IF($Y3/VLOOKUP($Y3,药材与丹炉!$T:$U,2,0)<=(VLOOKUP($AB3,药材与丹炉!$N:$O,2,0)+8)-($J3+IFERROR(IF($N3="",0,$N3),0)+IFERROR(IF($S3="",0,$S3),0)+IFERROR(IF($W3="",0,$W3),0)),1,2),1) -> 1 | AK3: =OR(NOT(IFERROR(OR($L3="",AND($L3<>"",$L3>0,VLOOKUP($AB3,药材与丹炉!$N:$O,2,0)=6)),0)),AND($L3<>"",$L3>0,OR(VLOOKUP($AB3,药材与丹炉!$N:$Q,4,0)-2<$N3,$N3="")),AND($U3<>"",$U3>0,OR(VLOOKUP($AB3,药材与丹炉!$N:$Q,4,0)-3<$W3,$W3="")),NOT(OR(AND($Q3<>"",$S3<>"",VLOOKUP($AB3,药材与丹炉!$N:$Q,4,0)-3>=$S3),$P3="")),NOT(OR(AND($H3<>"",$J3<>"",VLOOKUP($AB3,药材与丹炉!$N:$Q,4,0)-1>=$J3),$G3="")),NOT(OR($U3="",AND($U3<>"",$U3>0))),NOT(OR($Y3="",IF($Z3<>"",IFERROR(IF(VLOOKUP($Z3,药材与丹炉!$B:$D,3,0)=-1,$X3=1,IF(VLOOKUP($Z3,药材与丹炉!$B:$D,3,0)=1,$X3=2,$X3=0)),0),0))),$AC3="爆炸",(VLOOKUP($AB3,药材与丹炉!$N:$O,2,0)+8)<$AD3) -> FALSE
A4: 5003 | B4: 1 | C4: 生骨丹 | D4: 999 | E4: 生命值+35/丹毒+1 | F4: 1 | G4: 活血 | H4: 1 | I4: 天青花 | J4: =IFERROR(CEILING($H4/VLOOKUP($I4,药材与丹炉!$B:$H,COLUMN(药材与丹炉!$H4)-1,0),1),"") -> 1 | K4: 活血 | L4: =IFERROR(IF($F4-$H4=0,"",$F4-$H4),"") | N4: =IFERROR(CEILING($L4/VLOOKUP($M4,药材与丹炉!$B:$H,COLUMN(药材与丹炉!$H4)-1,0),1),"") | O4: 3 | P4: 固元 | Q4: 3 | R4: 银月花 | S4: =IFERROR(CEILING($Q4/VLOOKUP($R4,药材与丹炉!$B:$H,COLUMN(药材与丹炉!$H4)-1,0),1),"") -> 3 | T4: =P4 -> 固元 | U4: =IFERROR(IF($O4-$Q4=0,"",$O4-$Q4),"") | W4: =IFERROR(CEILING($U4/VLOOKUP($V4,药材与丹炉!$B:$H,COLUMN(药材与丹炉!$H4)-1,0),1),"") | X4: =IF(IFERROR(IF(AND($J4>0,$J4<>""),VLOOKUP($I4,药材与丹炉!$B:$D,3,0),0),0)+IFERROR(IF(AND($N4>0,$N4<>""),VLOOKUP($M4,药材与丹炉!$B:$D,3,0),0),0)+IFERROR(IF(AND($S4>0,$S4<>""),VLOOKUP($R4,药材与丹炉!$B:$D,3,0),0),0)+IFERROR(IF(AND($W4>0,$W4<>""),VLOOKUP($V4,药材与丹炉!$B:$D,3,0),0),0)>0,1,IF(IFERROR(IF(AND($J4>0,$J4<>""),VLOOKUP($I4,药材与丹炉!$B:$D,3,0),0),0)+IFERROR(IF(AND($N4>0,$N4<>""),VLOOKUP($M4,药材与丹炉!$B:$D,3,0),0),0)+IFERROR(IF(AND($S4>0,$S4<>""),VLOOKUP($R4,药材与丹炉!$B:$D,3,0),0),0)+IFERROR(IF(AND($W4>0,$W4<>""),VLOOKUP($V4,药材与丹炉!$B:$D,3,0),0),0)<0,2,0)) -> 0 | Y4: 1 | Z4: 凝血草 | AA4: =IFERROR($Y4/VLOOKUP($Z4,药材与丹炉!$B:$H,COLUMN(药材与丹炉!$H4)-1,0),"") -> 1 | AB4: 普通丹炉 | AC4: =IFERROR(IF($B4-VLOOKUP($AB4,药材与丹炉!$N:$P,2,0)<0,IF($AO$1="是",0,1),IF($B4-VLOOKUP($AB4,药材与丹炉!$N:$P,2,0)=0,2,IF($B4-VLOOKUP($AB4,药材与丹炉!$N:$P,2,0)=1,40,IF($B4-VLOOKUP($AB4,药材与丹炉!$N:$P,2,0)=2,80,"爆炸")))),"") -> 2 | AD4: =IFERROR($J4+IFERROR(IF($N4="",0,$N4),0)+IFERROR(IF($S4="",0,$S4),0)+IFERROR(IF($W4="",0,$W4),0)+IFERROR(IF($AA4="",0,$AA4),0),"") -> 5 | AE4: =IFERROR($J4*VLOOKUP($I4,药材与丹炉!$B:$K,10,0),0)+IFERROR($N4*VLOOKUP($M4,药材与丹炉!$B:$K,10,0),0)+IFERROR($S4*VLOOKUP($R4,药材与丹炉!$B:$K,10,0),0)+IFERROR($W4*VLOOKUP($V4,药材与丹炉!$B:$K,10,0),0)+IFERROR($AA4*VLOOKUP($Z4,药材与丹炉!$B:$K,10,0),0)+IFERROR($AC4*VLOOKUP($AB4,药材与丹炉!$N:$P,3,0)/100,0) -> 57 | AF4: 106 | AG4: =$AF4-$AE4 -> 49 | AH4: =$AF4*$AM$1*$AM$21 -> 212 | AI4: =$AH4-$AE4 -> 155 | AJ4: =IFERROR(IF($Y4/VLOOKUP($Y4,药材与丹炉!$T:$U,2,0)<=(VLOOKUP($AB4,药材与丹炉!$N:$O,2,0)+8)-($J4+IFERROR(IF($N4="",0,$N4),0)+IFERROR(IF($S4="",0,$S4),0)+IFERROR(IF($W4="",0,$W4),0)),1,2),1) -> 1 | AK4: =OR(NOT(IFERROR(OR($L4="",AND($L4<>"",$L4>0,VLOOKUP($AB4,药材与丹炉!$N:$O,2,0)=6)),0)),AND($L4<>"",$L4>0,OR(VLOOKUP($AB4,药材与丹炉!$N:$Q,4,0)-2<$N4,$N4="")),AND($U4<>"",$U4>0,OR(VLOOKUP($AB4,药材与丹炉!$N:$Q,4,0)-3<$W4,$W4="")),NOT(OR(AND($Q4<>"",$S4<>"",VLOOKUP($AB4,药材与丹炉!$N:$Q,4,0)-3>=$S4),$P4="")),NOT(OR(AND($H4<>"",$J4<>"",VLOOKUP($AB4,药材与丹炉!$N:$Q,4,0)-1>=$J4),$G4="")),NOT(OR($U4="",AND($U4<>"",$U4>0))),NOT(OR($Y4="",IF($Z4<>"",IFERROR(IF(VLOOKUP($Z4,药材与丹炉!$B:$D,3,0)=-1,$X4=1,IF(VLOOKUP($Z4,药材与丹炉!$B:$D,3,0)=1,$X4=2,$X4=0)),0),0))),$AC4="爆炸",(VLOOKUP($AB4,药材与丹炉!$N:$O,2,0)+8)<$AD4) -> FALSE | AL4: 价值与价格： | AM4: 丹药价格是丹药价值的货币表现 | AP4: 草药价格可以去药材与丹炉页面单独调整
A5: 5004 | B5: 1 | C5: 冰心丹 | D5: 30 | E5: 心境+1 | F5: 6 | G5: 聚元 | H5: 6 | I5: 恒心草 | J5: =IFERROR(CEILING($H5/VLOOKUP($I5,药材与丹炉!$B:$H,COLUMN(药材与丹炉!$H5)-1,0),1),"") -> 6 | K5: 聚元 | L5: =IFERROR(IF($F5-$H5=0,"",$F5-$H5),"") | N5: =IFERROR(CEILING($L5/VLOOKUP($M5,药材与丹炉!$B:$H,COLUMN(药材与丹炉!$H5)-1,0),1),"") | O5: 3 | P5: 清心 | Q5: 3 | R5: 宁心草 | S5: =IFERROR(CEILING($Q5/VLOOKUP($R5,药材与丹炉!$B:$H,COLUMN(药材与丹炉!$H5)-1,0),1),"") -> 3 | T5: =P5 -> 清心 | U5: =IFERROR(IF($O5-$Q5=0,"",$O5-$Q5),"") | W5: =IFERROR(CEILING($U5/VLOOKUP($V5,药材与丹炉!$B:$H,COLUMN(药材与丹炉!$H5)-1,0),1),"") | X5: =IF(IFERROR(IF(AND($J5>0,$J5<>""),VLOOKUP($I5,药材与丹炉!$B:$D,3,0),0),0)+IFERROR(IF(AND($N5>0,$N5<>""),VLOOKUP($M5,药材与丹炉!$B:$D,3,0),0),0)+IFERROR(IF(AND($S5>0,$S5<>""),VLOOKUP($R5,药材与丹炉!$B:$D,3,0),0),0)+IFERROR(IF(AND($W5>0,$W5<>""),VLOOKUP($V5,药材与丹炉!$B:$D,3,0),0),0)>0,1,IF(IFERROR(IF(AND($J5>0,$J5<>""),VLOOKUP($I5,药材与丹炉!$B:$D,3,0),0),0)+IFERROR(IF(AND($N5>0,$N5<>""),VLOOKUP($M5,药材与丹炉!$B:$D,3,0),0),0)+IFERROR(IF(AND($S5>0,$S5<>""),VLOOKUP($R5,药材与丹炉!$B:$D,3,0),0),0)+IFERROR(IF(AND($W5>0,$W5<>""),VLOOKUP($V5,药材与丹炉!$B:$D,3,0),0),0)<0,2,0)) -> 2 | Y5: 3 | Z5: 天元果 | AA5: =IFERROR($Y5/VLOOKUP($Z5,药材与丹炉!$B:$H,COLUMN(药材与丹炉!$H5)-1,0),"") -> 1 | AB5: 陨铁炉 | AC5: =IFERROR(IF($B5-VLOOKUP($AB5,药材与丹炉!$N:$P,2,0)<0,IF($AO$1="是",0,1),IF($B5-VLOOKUP($AB5,药材与丹炉!$N:$P,2,0)=0,2,IF($B5-VLOOKUP($AB5,药材与丹炉!$N:$P,2,0)=1,40,IF($B5-VLOOKUP($AB5,药材与丹炉!$N:$P,2,0)=2,80,"爆炸")))),"") -> 1 | AD5: =IFERROR($J5+IFERROR(IF($N5="",0,$N5),0)+IFERROR(IF($S5="",0,$S5),0)+IFERROR(IF($W5="",0,$W5),0)+IFERROR(IF($AA5="",0,$AA5),0),"") -> 10 | AE5: =IFERROR($J5*VLOOKUP($I5,药材与丹炉!$B:$K,10,0),0)+IFERROR($N5*VLOOKUP($M5,药材与丹炉!$B:$K,10,0),0)+IFERROR($S5*VLOOKUP($R5,药材与丹炉!$B:$K,10,0),0)+IFERROR($W5*VLOOKUP($V5,药材与丹炉!$B:$K,10,0),0)+IFERROR($AA5*VLOOKUP($Z5,药材与丹炉!$B:$K,10,0),0)+IFERROR($AC5*VLOOKUP($AB5,药材与丹炉!$N:$P,3,0)/100,0) -> 129 | AF5: 168 | AG5: =$AF5-$AE5 -> 39 | AH5: =$AF5*$AM$1*$AM$21 -> 336 | AI5: =$AH5-$AE5 -> 207 | AJ5: =IFERROR(IF($Y5/VLOOKUP($Y5,药材与丹炉!$T:$U,2,0)<=(VLOOKUP($AB5,药材与丹炉!$N:$O,2,0)+8)-($J5+IFERROR(IF($N5="",0,$N5),0)+IFERROR(IF($S5="",0,$S5),0)+IFERROR(IF($W5="",0,$W5),0)),1,2),1) -> 2 | AK5: =OR(NOT(IFERROR(OR($L5="",AND($L5<>"",$L5>0,VLOOKUP($AB5,药材与丹炉!$N:$O,2,0)=6)),0)),AND($L5<>"",$L5>0,OR(VLOOKUP($AB5,药材与丹炉!$N:$Q,4,0)-2<$N5,$N5="")),AND($U5<>"",$U5>0,OR(VLOOKUP($AB5,药材与丹炉!$N:$Q,4,0)-3<$W5,$W5="")),NOT(OR(AND($Q5<>"",$S5<>"",VLOOKUP($AB5,药材与丹炉!$N:$Q,4,0)-3>=$S5),$P5="")),NOT(OR(AND($H5<>"",$J5<>"",VLOOKUP($AB5,药材与丹炉!$N:$Q,4,0)-1>=$J5),$G5="")),NOT(OR($U5="",AND($U5<>"",$U5>0))),NOT(OR($Y5="",IF($Z5<>"",IFERROR(IF(VLOOKUP($Z5,药材与丹炉!$B:$D,3,0)=-1,$X5=1,IF(VLOOKUP($Z5,药材与丹炉!$B:$D,3,0)=1,$X5=2,$X5=0)),0),0))),$AC5="爆炸",(VLOOKUP($AB5,药材与丹炉!$N:$O,2,0)+8)<$AD5) -> FALSE | AL5: 价值差： | AM5: 丹药原价-炼制成本 (中草阁购买草药价)
A6: 5005 | B6: 1 | C6: 凝神丹 | D6: 50 | E6: 下场战斗中神识+1/丹毒+5 | F6: 3 | G6: 振气 | H6: 3 | I6: 宁心草 | J6: =IFERROR(CEILING($H6/VLOOKUP($I6,药材与丹炉!$B:$H,COLUMN(药材与丹炉!$H6)-1,0),1),"") -> 3 | K6: 振气 | L6: =IFERROR(IF($F6-$H6=0,"",$F6-$H6),"") | N6: =IFERROR(CEILING($L6/VLOOKUP($M6,药材与丹炉!$B:$H,COLUMN(药材与丹炉!$H6)-1,0),1),"") | O6: 1 | P6: 凝神 | Q6: 1 | R6: 宁神花 | S6: =IFERROR(CEILING($Q6/VLOOKUP($R6,药材与丹炉!$B:$H,COLUMN(药材与丹炉!$H6)-1,0),1),"") -> 1 | T6: =P6 -> 凝神 | U6: =IFERROR(IF($O6-$Q6=0,"",$O6-$Q6),"") | W6: =IFERROR(CEILING($U6/VLOOKUP($V6,药材与丹炉!$B:$H,COLUMN(药材与丹炉!$H6)-1,0),1),"") | X6: =IF(IFERROR(IF(AND($J6>0,$J6<>""),VLOOKUP($I6,药材与丹炉!$B:$D,3,0),0),0)+IFERROR(IF(AND($N6>0,$N6<>""),VLOOKUP($M6,药材与丹炉!$B:$D,3,0),0),0)+IFERROR(IF(AND($S6>0,$S6<>""),VLOOKUP($R6,药材与丹炉!$B:$D,3,0),0),0)+IFERROR(IF(AND($W6>0,$W6<>""),VLOOKUP($V6,药材与丹炉!$B:$D,3,0),0),0)>0,1,IF(IFERROR(IF(AND($J6>0,$J6<>""),VLOOKUP($I6,药材与丹炉!$B:$D,3,0),0),0)+IFERROR(IF(AND($N6>0,$N6<>""),VLOOKUP($M6,药材与丹炉!$B:$D,3,0),0),0)+IFERROR(IF(AND($S6>0,$S6<>""),VLOOKUP($R6,药材与丹炉!$B:$D,3,0),0),0)+IFERROR(IF(AND($W6>0,$W6<>""),VLOOKUP($V6,药材与丹炉!$B:$D,3,0),0),0)<0,2,0)) -> 2 | Y6: 3 | Z6: 流莹草 | AA6: =IFERROR($Y6/VLOOKUP($Z6,药材与丹炉!$B:$H,COLUMN(药材与丹炉!$H6)-1,0),"") -> 3 | AB6: 普通丹炉 | AC6: =IFERROR(IF($B6-VLOOKUP($AB6,药材与丹炉!$N:$P,2,0)<0,IF($AO$1="是",0,1),IF($B6-VLOOKUP($AB6,药材与丹炉!$N:$P,2,0)=0,2,IF($B6-VLOOKUP($AB6,药材与丹炉!$N:$P,2,0)=1,40,IF($B6-VLOOKUP($AB6,药材与丹炉!$N:$P,2,0)=2,80,"爆炸")))),"") -> 2 | AD6: =IFERROR($J6+IFERROR(IF($N6="",0,$N6),0)+IFERROR(IF($S6="",0,$S6),0)+IFERROR(IF($W6="",0,$W6),0)+IFERROR(IF($AA6="",0,$AA6),0),"") -> 7 | AE6: =IFERROR($J6*VLOOKUP($I6,药材与丹炉!$B:$K,10,0),0)+IFERROR($N6*VLOOKUP($M6,药材与丹炉!$B:$K,10,0),0)+IFERROR($S6*VLOOKUP($R6,药材与丹炉!$B:$K,10,0),0)+IFERROR($W6*VLOOKUP($V6,药材与丹炉!$B:$K,10,0),0)+IFERROR($AA6*VLOOKUP($Z6,药材与丹炉!$B:$K,10,0),0)+IFERROR($AC6*VLOOKUP($AB6,药材与丹炉!$N:$P,3,0)/100,0) -> 75 | AF6: 118 | AG6: =$AF6-$AE6 -> 43 | AH6: =$AF6*$AM$1*$AM$21 -> 236 | AI6: =$AH6-$AE6 -> 161 | AJ6: =IFERROR(IF($Y6/VLOOKUP($Y6,药材与丹炉!$T:$U,2,0)<=(VLOOKUP($AB6,药材与丹炉!$N:$O,2,0)+8)-($J6+IFERROR(IF($N6="",0,$N6),0)+IFERROR(IF($S6="",0,$S6),0)+IFERROR(IF($W6="",0,$W6),0)),1,2),1) -> 1 | AK6: =OR(NOT(IFERROR(OR($L6="",AND($L6<>"",$L6>0,VLOOKUP($AB6,药材与丹炉!$N:$O,2,0)=6)),0)),AND($L6<>"",$L6>0,OR(VLOOKUP($AB6,药材与丹炉!$N:$Q,4,0)-2<$N6,$N6="")),AND($U6<>"",$U6>0,OR(VLOOKUP($AB6,药材与丹炉!$N:$Q,4,0)-3<$W6,$W6="")),NOT(OR(AND($Q6<>"",$S6<>"",VLOOKUP($AB6,药材与丹炉!$N:$Q,4,0)-3>=$S6),$P6="")),NOT(OR(AND($H6<>"",$J6<>"",VLOOKUP($AB6,药材与丹炉!$N:$Q,4,0)-1>=$J6),$G6="")),NOT(OR($U6="",AND($U6<>"",$U6>0))),NOT(OR($Y6="",IF($Z6<>"",IFERROR(IF(VLOOKUP($Z6,药材与丹炉!$B:$D,3,0)=-1,$X6=1,IF(VLOOKUP($Z6,药材与丹炉!$B:$D,3,0)=1,$X6=2,$X6=0)),0),0))),$AC6="爆炸",(VLOOKUP($AB6,药材与丹炉!$N:$O,2,0)+8)<$AD6) -> FALSE | AL6: 价格差： | AM6: 交易价格-炼制成本 (中草阁购买草药价)
A7: 5006 | B7: 1 | C7: 龙虎丹 | D7: 50 | E7: 下场战斗第一回合造成的伤害+1/丹毒+5 | F7: 6 | G7: 振气 | H7: 6 | I7: 宁心草 | J7: =IFERROR(CEILING($H7/VLOOKUP($I7,药材与丹炉!$B:$H,COLUMN(药材与丹炉!$H7)-1,0),1),"") -> 6 | K7: 振气 | L7: =IFERROR(IF($F7-$H7=0,"",$F7-$H7),"") | N7: =IFERROR(CEILING($L7/VLOOKUP($M7,药材与丹炉!$B:$H,COLUMN(药材与丹炉!$H7)-1,0),1),"") | O7: 3 | P7: 混元 | Q7: 3 | R7: 凝血草 | S7: =IFERROR(CEILING($Q7/VLOOKUP($R7,药材与丹炉!$B:$H,COLUMN(药材与丹炉!$H7)-1,0),1),"") -> 3 | T7: =P7 -> 混元 | U7: =IFERROR(IF($O7-$Q7=0,"",$O7-$Q7),"") | W7: =IFERROR(CEILING($U7/VLOOKUP($V7,药材与丹炉!$B:$H,COLUMN(药材与丹炉!$H7)-1,0),1),"") | X7: =IF(IFERROR(IF(AND($J7>0,$J7<>""),VLOOKUP($I7,药材与丹炉!$B:$D,3,0),0),0)+IFERROR(IF(AND($N7>0,$N7<>""),VLOOKUP($M7,药材与丹炉!$B:$D,3,0),0),0)+IFERROR(IF(AND($S7>0,$S7<>""),VLOOKUP($R7,药材与丹炉!$B:$D,3,0),0),0)+IFERROR(IF(AND($W7>0,$W7<>""),VLOOKUP($V7,药材与丹炉!$B:$D,3,0),0),0)>0,1,IF(IFERROR(IF(AND($J7>0,$J7<>""),VLOOKUP($I7,药材与丹炉!$B:$D,3,0),0),0)+IFERROR(IF(AND($N7>0,$N7<>""),VLOOKUP($M7,药材与丹炉!$B:$D,3,0),0),0)+IFERROR(IF(AND($S7>0,$S7<>""),VLOOKUP($R7,药材与丹炉!$B:$D,3,0),0),0)+IFERROR(IF(AND($W7>0,$W7<>""),VLOOKUP($V7,药材与丹炉!$B:$D,3,0),0),0)<0,2,0)) -> 2 | Y7: 1 | Z7: 流莹草 | AA7: =IFERROR($Y7/VLOOKUP($Z7,药材与丹炉!$B:$H,COLUMN(药材与丹炉!$H7)-1,0),"") -> 1 | AB7: 陨铁炉 | AC7: =IFERROR(IF($B7-VLOOKUP($AB7,药材与丹炉!$N:$P,2,0)<0,IF($AO$1="是",0,1),IF($B7-VLOOKUP($AB7,药材与丹炉!$N:$P,2,0)=0,2,IF($B7-VLOOKUP($AB7,药材与丹炉!$N:$P,2,0)=1,40,IF($B7-VLOOKUP($AB7,药材与丹炉!$N:$P,2,0)=2,80,"爆炸")))),"") -> 1 | AD7: =IFERROR($J7+IFERROR(IF($N7="",0,$N7),0)+IFERROR(IF($S7="",0,$S7),0)+IFERROR(IF($W7="",0,$W7),0)+IFERROR(IF($AA7="",0,$AA7),0),"") -> 10 | AE7: =IFERROR($J7*VLOOKUP($I7,药材与丹炉!$B:$K,10,0),0)+IFERROR($N7*VLOOKUP($M7,药材与丹炉!$B:$K,10,0),0)+IFERROR($S7*VLOOKUP($R7,药材与丹炉!$B:$K,10,0),0)+IFERROR($W7*VLOOKUP($V7,药材与丹炉!$B:$K,10,0),0)+IFERROR($AA7*VLOOKUP($Z7,药材与丹炉!$B:$K,10,0),0)+IFERROR($AC7*VLOOKUP($AB7,药材与丹炉!$N:$P,3,0)/100,0) -> 102 | AF7: 143 | AG7: =$AF7-$AE7 -> 41 | AH7: =$AF7*$AM$1*$AM$21 -> 286 | AI7: =$AH7-$AE7 -> 184 | AJ7: =IFERROR(IF($Y7/VLOOKUP($Y7,药材与丹炉!$T:$U,2,0)<=(VLOOKUP($AB7,药材与丹炉!$N:$O,2,0)+8)-($J7+IFERROR(IF($N7="",0,$N7),0)+IFERROR(IF($S7="",0,$S7),0)+IFERROR(IF($W7="",0,$W7),0)),1,2),1) -> 1 | AK7: =OR(NOT(IFERROR(OR($L7="",AND($L7<>"",$L7>0,VLOOKUP($AB7,药材与丹炉!$N:$O,2,0)=6)),0)),AND($L7<>"",$L7>0,OR(VLOOKUP($AB7,药材与丹炉!$N:$Q,4,0)-2<$N7,$N7="")),AND($U7<>"",$U7>0,OR(VLOOKUP($AB7,药材与丹炉!$N:$Q,4,0)-3<$W7,$W7="")),NOT(OR(AND($Q7<>"",$S7<>"",VLOOKUP($AB7,药材与丹炉!$N:$Q,4,0)-3>=$S7),$P7="")),NOT(OR(AND($H7<>"",$J7<>"",VLOOKUP($AB7,药材与丹炉!$N:$Q,4,0)-1>=$J7),$G7="")),NOT(OR($U7="",AND($U7<>"",$U7>0))),NOT(OR($Y7="",IF($Z7<>"",IFERROR(IF(VLOOKUP($Z7,药材与丹炉!$B:$D,3,0)=-1,$X7=1,IF(VLOOKUP($Z7,药材与丹炉!$B:$D,3,0)=1,$X7=2,$X7=0)),0),0))),$AC7="爆炸",(VLOOKUP($AB7,药材与丹炉!$N:$O,2,0)+8)<$AD7) -> FALSE | AL7: 倍率说明
A8: 5007 | B8: 1 | C8: 引灵丹 | D8: 50 | E8: 下场战斗开始时，额外抽1张灵气牌/丹毒+5 | F8: 3 | G8: 振气 | H8: 3 | I8: 宁心草 | J8: =IFERROR(CEILING($H8/VLOOKUP($I8,药材与丹炉!$B:$H,COLUMN(药材与丹炉!$H8)-1,0),1),"") -> 3 | K8: 振气 | L8: =IFERROR(IF($F8-$H8=0,"",$F8-$H8),"") | N8: =IFERROR(CEILING($L8/VLOOKUP($M8,药材与丹炉!$B:$H,COLUMN(药材与丹炉!$H8)-1,0),1),"") | O8: 3 | P8: 聚灵 | Q8: 3 | R8: 蛇涎果 | S8: =IFERROR(CEILING($Q8/VLOOKUP($R8,药材与丹炉!$B:$H,COLUMN(药材与丹炉!$H8)-1,0),1),"") -> 1 | T8: =P8 -> 聚灵 | U8: =IFERROR(IF($O8-$Q8=0,"",$O8-$Q8),"") | W8: =IFERROR(CEILING($U8/VLOOKUP($V8,药材与丹炉!$B:$H,COLUMN(药材与丹炉!$H8)-1,0),1),"") | X8: =IF(IFERROR(IF(AND($J8>0,$J8<>""),VLOOKUP($I8,药材与丹炉!$B:$D,3,0),0),0)+IFERROR(IF(AND($N8>0,$N8<>""),VLOOKUP($M8,药材与丹炉!$B:$D,3,0),0),0)+IFERROR(IF(AND($S8>0,$S8<>""),VLOOKUP($R8,药材与丹炉!$B:$D,3,0),0),0)+IFERROR(IF(AND($W8>0,$W8<>""),VLOOKUP($V8,药材与丹炉!$B:$D,3,0),0),0)>0,1,IF(IFERROR(IF(AND($J8>0,$J8<>""),VLOOKUP($I8,药材与丹炉!$B:$D,3,0),0),0)+IFERROR(IF(AND($N8>0,$N8<>""),VLOOKUP($M8,药材与丹炉!$B:$D,3,0),0),0)+IFERROR(IF(AND($S8>0,$S8<>""),VLOOKUP($R8,药材与丹炉!$B:$D,3,0),0),0)+IFERROR(IF(AND($W8>0,$W8<>""),VLOOKUP($V8,药材与丹炉!$B:$D,3,0),0),0)<0,2,0)) -> 0 | Y8: 1 | Z8: 恒心草 | AA8: =IFERROR($Y8/VLOOKUP($Z8,药材与丹炉!$B:$H,COLUMN(药材与丹炉!$H8)-1,0),"") -> 1 | AB8: 普通丹炉 | AC8: =IFERROR(IF($B8-VLOOKUP($AB8,药材与丹炉!$N:$P,2,0)<0,IF($AO$1="是",0,1),IF($B8-VLOOKUP($AB8,药材与丹炉!$N:$P,2,0)=0,2,IF($B8-VLOOKUP($AB8,药材与丹炉!$N:$P,2,0)=1,40,IF($B8-VLOOKUP($AB8,药材与丹炉!$N:$P,2,0)=2,80,"爆炸")))),"") -> 2 | AD8: =IFERROR($J8+IFERROR(IF($N8="",0,$N8),0)+IFERROR(IF($S8="",0,$S8),0)+IFERROR(IF($W8="",0,$W8),0)+IFERROR(IF($AA8="",0,$AA8),0),"") -> 5 | AE8: =IFERROR($J8*VLOOKUP($I8,药材与丹炉!$B:$K,10,0),0)+IFERROR($N8*VLOOKUP($M8,药材与丹炉!$B:$K,10,0),0)+IFERROR($S8*VLOOKUP($R8,药材与丹炉!$B:$K,10,0),0)+IFERROR($W8*VLOOKUP($V8,药材与丹炉!$B:$K,10,0),0)+IFERROR($AA8*VLOOKUP($Z8,药材与丹炉!$B:$K,10,0),0)+IFERROR($AC8*VLOOKUP($AB8,药材与丹炉!$N:$P,3,0)/100,0) -> 84 | AF8: 143 | AG8: =$AF8-$AE8 -> 59 | AH8: =$AF8*$AM$1*$AM$21 -> 286 | AI8: =$AH8-$AE8 -> 202 | AJ8: =IFERROR(IF($Y8/VLOOKUP($Y8,药材与丹炉!$T:$U,2,0)<=(VLOOKUP($AB8,药材与丹炉!$N:$O,2,0)+8)-($J8+IFERROR(IF($N8="",0,$N8),0)+IFERROR(IF($S8="",0,$S8),0)+IFERROR(IF($W8="",0,$W8),0)),1,2),1) -> 1 | AK8: =OR(NOT(IFERROR(OR($L8="",AND($L8<>"",$L8>0,VLOOKUP($AB8,药材与丹炉!$N:$O,2,0)=6)),0)),AND($L8<>"",$L8>0,OR(VLOOKUP($AB8,药材与丹炉!$N:$Q,4,0)-2<$N8,$N8="")),AND($U8<>"",$U8>0,OR(VLOOKUP($AB8,药材与丹炉!$N:$Q,4,0)-3<$W8,$W8="")),NOT(OR(AND($Q8<>"",$S8<>"",VLOOKUP($AB8,药材与丹炉!$N:$Q,4,0)-3>=$S8),$P8="")),NOT(OR(AND($H8<>"",$J8<>"",VLOOKUP($AB8,药材与丹炉!$N:$Q,4,0)-1>=$J8),$G8="")),NOT(OR($U8="",AND($U8<>"",$U8>0))),NOT(OR($Y8="",IF($Z8<>"",IFERROR(IF(VLOOKUP($Z8,药材与丹炉!$B:$D,3,0)=-1,$X8=1,IF(VLOOKUP($Z8,药材与丹炉!$B:$D,3,0)=1,$X8=2,$X8=0)),0),0))),$AC8="爆炸",(VLOOKUP($AB8,药材与丹炉!$N:$O,2,0)+8)<$AD8) -> FALSE | AL8: 0.475 | AM8: 在坊市将物品卖给不感兴趣的NPC【坊市95折】
A9: 5008 | B9: 1 | C9: 聚甲丹 | D9: 50 | E9: 下场战斗开始时，获得【护罩】*1/丹毒+5 | F9: 6 | G9: 御气 | H9: 6 | I9: 地黄参 | J9: =IFERROR(CEILING($H9/VLOOKUP($I9,药材与丹炉!$B:$H,COLUMN(药材与丹炉!$H9)-1,0),1),"") -> 2 | K9: 御气 | L9: =IFERROR(IF($F9-$H9=0,"",$F9-$H9),"") | N9: =IFERROR(CEILING($L9/VLOOKUP($M9,药材与丹炉!$B:$H,COLUMN(药材与丹炉!$H9)-1,0),1),"") | O9: 3 | P9: 固元 | Q9: 3 | R9: 银月花 | S9: =IFERROR(CEILING($Q9/VLOOKUP($R9,药材与丹炉!$B:$H,COLUMN(药材与丹炉!$H9)-1,0),1),"") -> 3 | T9: =P9 -> 固元 | U9: =IFERROR(IF($O9-$Q9=0,"",$O9-$Q9),"") | W9: =IFERROR(CEILING($U9/VLOOKUP($V9,药材与丹炉!$B:$H,COLUMN(药材与丹炉!$H9)-1,0),1),"") | X9: =IF(IFERROR(IF(AND($J9>0,$J9<>""),VLOOKUP($I9,药材与丹炉!$B:$D,3,0),0),0)+IFERROR(IF(AND($N9>0,$N9<>""),VLOOKUP($M9,药材与丹炉!$B:$D,3,0),0),0)+IFERROR(IF(AND($S9>0,$S9<>""),VLOOKUP($R9,药材与丹炉!$B:$D,3,0),0),0)+IFERROR(IF(AND($W9>0,$W9<>""),VLOOKUP($V9,药材与丹炉!$B:$D,3,0),0),0)>0,1,IF(IFERROR(IF(AND($J9>0,$J9<>""),VLOOKUP($I9,药材与丹炉!$B:$D,3,0),0),0)+IFERROR(IF(AND($N9>0,$N9<>""),VLOOKUP($M9,药材与丹炉!$B:$D,3,0),0),0)+IFERROR(IF(AND($S9>0,$S9<>""),VLOOKUP($R9,药材与丹炉!$B:$D,3,0),0),0)+IFERROR(IF(AND($W9>0,$W9<>""),VLOOKUP($V9,药材与丹炉!$B:$D,3,0),0),0)<0,2,0)) -> 0 | Y9: 1 | Z9: 恒心草 | AA9: =IFERROR($Y9/VLOOKUP($Z9,药材与丹炉!$B:$H,COLUMN(药材与丹炉!$H9)-1,0),"") -> 1 | AB9: 普通丹炉 | AC9: =IFERROR(IF($B9-VLOOKUP($AB9,药材与丹炉!$N:$P,2,0)<0,IF($AO$1="是",0,1),IF($B9-VLOOKUP($AB9,药材与丹炉!$N:$P,2,0)=0,2,IF($B9-VLOOKUP($AB9,药材与丹炉!$N:$P,2,0)=1,40,IF($B9-VLOOKUP($AB9,药材与丹炉!$N:$P,2,0)=2,80,"爆炸")))),"") -> 2 | AD9: =IFERROR($J9+IFERROR(IF($N9="",0,$N9),0)+IFERROR(IF($S9="",0,$S9),0)+IFERROR(IF($W9="",0,$W9),0)+IFERROR(IF($AA9="",0,$AA9),0),"") -> 6 | AE9: =IFERROR($J9*VLOOKUP($I9,药材与丹炉!$B:$K,10,0),0)+IFERROR($N9*VLOOKUP($M9,药材与丹炉!$B:$K,10,0),0)+IFERROR($S9*VLOOKUP($R9,药材与丹炉!$B:$K,10,0),0)+IFERROR($W9*VLOOKUP($V9,药材与丹炉!$B:$K,10,0),0)+IFERROR($AA9*VLOOKUP($Z9,药材与丹炉!$B:$K,10,0),0)+IFERROR($AC9*VLOOKUP($AB9,药材与丹炉!$N:$P,3,0)/100,0) -> 120 | AF9: 187 | AG9: =$AF9-$AE9 -> 67 | AH9: =$AF9*$AM$1*$AM$21 -> 374 | AI9: =$AH9-$AE9 -> 254 | AJ9: =IFERROR(IF($Y9/VLOOKUP($Y9,药材与丹炉!$T:$U,2,0)<=(VLOOKUP($AB9,药材与丹炉!$N:$O,2,0)+8)-($J9+IFERROR(IF($N9="",0,$N9),0)+IFERROR(IF($S9="",0,$S9),0)+IFERROR(IF($W9="",0,$W9),0)),1,2),1) -> 1 | AK9: =OR(NOT(IFERROR(OR($L9="",AND($L9<>"",$L9>0,VLOOKUP($AB9,药材与丹炉!$N:$O,2,0)=6)),0)),AND($L9<>"",$L9>0,OR(VLOOKUP($AB9,药材与丹炉!$N:$Q,4,0)-2<$N9,$N9="")),AND($U9<>"",$U9>0,OR(VLOOKUP($AB9,药材与丹炉!$N:$Q,4,0)-3<$W9,$W9="")),NOT(OR(AND($Q9<>"",$S9<>"",VLOOKUP($AB9,药材与丹炉!$N:$Q,4,0)-3>=$S9),$P9="")),NOT(OR(AND($H9<>"",$J9<>"",VLOOKUP($AB9,药材与丹炉!$N:$Q,4,0)-1>=$J9),$G9="")),NOT(OR($U9="",AND($U9<>"",$U9>0))),NOT(OR($Y9="",IF($Z9<>"",IFERROR(IF(VLOOKUP($Z9,药材与丹炉!$B:$D,3,0)=-1,$X9=1,IF(VLOOKUP($Z9,药材与丹炉!$B:$D,3,0)=1,$X9=2,$X9=0)),0),0))),$AC9="爆炸",(VLOOKUP($AB9,药材与丹炉!$N:$O,2,0)+8)<$AD9) -> FALSE | AL9: 0.5 | AM9: 在非坊市地区将物品卖给不感兴趣NPC的标价
A10: 5009 | B10: 1 | C10: 龟灵丹 | D10: 50 | E10: 下场战斗开始时，获得【减伤】*1/丹毒+5 | F10: 3 | G10: 御气 | H10: 3 | I10: 地黄参 | J10: =IFERROR(CEILING($H10/VLOOKUP($I10,药材与丹炉!$B:$H,COLUMN(药材与丹炉!$H10)-1,0),1),"") -> 1 | K10: 御气 | L10: =IFERROR(IF($F10-$H10=0,"",$F10-$H10),"") | N10: =IFERROR(CEILING($L10/VLOOKUP($M10,药材与丹炉!$B:$H,COLUMN(药材与丹炉!$H10)-1,0),1),"") | O10: 4 | P10: 混元 | Q10: 4 | R10: 凝血草 | S10: =IFERROR(CEILING($Q10/VLOOKUP($R10,药材与丹炉!$B:$H,COLUMN(药材与丹炉!$H10)-1,0),1),"") -> 4 | T10: =P10 -> 混元 | U10: =IFERROR(IF($O10-$Q10=0,"",$O10-$Q10),"") | W10: =IFERROR(CEILING($U10/VLOOKUP($V10,药材与丹炉!$B:$H,COLUMN(药材与丹炉!$H10)-1,0),1),"") | X10: =IF(IFERROR(IF(AND($J10>0,$J10<>""),VLOOKUP($I10,药材与丹炉!$B:$D,3,0),0),0)+IFERROR(IF(AND($N10>0,$N10<>""),VLOOKUP($M10,药材与丹炉!$B:$D,3,0),0),0)+IFERROR(IF(AND($S10>0,$S10<>""),VLOOKUP($R10,药材与丹炉!$B:$D,3,0),0),0)+IFERROR(IF(AND($W10>0,$W10<>""),VLOOKUP($V10,药材与丹炉!$B:$D,3,0),0),0)>0,1,IF(IFERROR(IF(AND($J10>0,$J10<>""),VLOOKUP($I10,药材与丹炉!$B:$D,3,0),0),0)+IFERROR(IF(AND($N10>0,$N10<>""),VLOOKUP($M10,药材与丹炉!$B:$D,3,0),0),0)+IFERROR(IF(AND($S10>0,$S10<>""),VLOOKUP($R10,药材与丹炉!$B:$D,3,0),0),0)+IFERROR(IF(AND($W10>0,$W10<>""),VLOOKUP($V10,药材与丹炉!$B:$D,3,0),0),0)<0,2,0)) -> 1 | Y10: 3 | Z10: 宁神花 | AA10: =IFERROR($Y10/VLOOKUP($Z10,药材与丹炉!$B:$H,COLUMN(药材与丹炉!$H10)-1,0),"") -> 3 | AB10: 普通丹炉 | AC10: =IFERROR(IF($B10-VLOOKUP($AB10,药材与丹炉!$N:$P,2,0)<0,IF($AO$1="是",0,1),IF($B10-VLOOKUP($AB10,药材与丹炉!$N:$P,2,0)=0,2,IF($B10-VLOOKUP($AB10,药材与丹炉!$N:$P,2,0)=1,40,IF($B10-VLOOKUP($AB10,药材与丹炉!$N:$P,2,0)=2,80,"爆炸")))),"") -> 2 | AD10: =IFERROR($J10+IFERROR(IF($N10="",0,$N10),0)+IFERROR(IF($S10="",0,$S10),0)+IFERROR(IF($W10="",0,$W10),0)+IFERROR(IF($AA10="",0,$AA10),0),"") -> 8 | AE10: =IFERROR($J10*VLOOKUP($I10,药材与丹炉!$B:$K,10,0),0)+IFERROR($N10*VLOOKUP($M10,药材与丹炉!$B:$K,10,0),0)+IFERROR($S10*VLOOKUP($R10,药材与丹炉!$B:$K,10,0),0)+IFERROR($W10*VLOOKUP($V10,药材与丹炉!$B:$K,10,0),0)+IFERROR($AA10*VLOOKUP($Z10,药材与丹炉!$B:$K,10,0),0)+IFERROR($AC10*VLOOKUP($AB10,药材与丹炉!$N:$P,3,0)/100,0) -> 111 | AF10: 150 | AG10: =$AF10-$AE10 -> 39 | AH10: =$AF10*$AM$1*$AM$21 -> 300 | AI10: =$AH10-$AE10 -> 189 | AJ10: =IFERROR(IF($Y10/VLOOKUP($Y10,药材与丹炉!$T:$U,2,0)<=(VLOOKUP($AB10,药材与丹炉!$N:$O,2,0)+8)-($J10+IFERROR(IF($N10="",0,$N10),0)+IFERROR(IF($S10="",0,$S10),0)+IFERROR(IF($W10="",0,$W10),0)),1,2),1) -> 1 | AK10: =OR(NOT(IFERROR(OR($L10="",AND($L10<>"",$L10>0,VLOOKUP($AB10,药材与丹炉!$N:$O,2,0)=6)),0)),AND($L10<>"",$L10>0,OR(VLOOKUP($AB10,药材与丹炉!$N:$Q,4,0)-2<$N10,$N10="")),AND($U10<>"",$U10>0,OR(VLOOKUP($AB10,药材与丹炉!$N:$Q,4,0)-3<$W10,$W10="")),NOT(OR(AND($Q10<>"",$S10<>"",VLOOKUP($AB10,药材与丹炉!$N:$Q,4,0)-3>=$S10),$P10="")),NOT(OR(AND($H10<>"",$J10<>"",VLOOKUP($AB10,药材与丹炉!$N:$Q,4,0)-1>=$J10),$G10="")),NOT(OR($U10="",AND($U10<>"",$U10>0))),NOT(OR($Y10="",IF($Z10<>"",IFERROR(IF(VLOOKUP($Z10,药材与丹炉!$B:$D,3,0)=-1,$X10=1,IF(VLOOKUP($Z10,药材与丹炉!$B:$D,3,0)=1,$X10=2,$X10=0)),0),0))),$AC10="爆炸",(VLOOKUP($AB10,药材与丹炉!$N:$O,2,0)+8)<$AD10) -> FALSE | AL10: 0.9 | AM10: 灵药堂的收购价【灵药堂9折】
B11: 1 | C11: 一阶废丹 | D11: 999 | E11: 修为+132（需神秘贝壳）/丹毒+10 | F11: 1 | G11: 活血 | H11: 1 | I11: 银月花 | J11: =IFERROR(CEILING($H11/VLOOKUP($I11,药材与丹炉!$B:$H,COLUMN(药材与丹炉!$H11)-1,0),1),"") -> 1 | K11: 活血 | L11: =IFERROR(IF($F11-$H11=0,"",$F11-$H11),"") | N11: =IFERROR(CEILING($L11/VLOOKUP($M11,药材与丹炉!$B:$H,COLUMN(药材与丹炉!$H11)-1,0),1),"") | O11: 1 | P11: 培元 | Q11: 1 | R11: 流莹草 | S11: =IFERROR(CEILING($Q11/VLOOKUP($R11,药材与丹炉!$B:$H,COLUMN(药材与丹炉!$H11)-1,0),1),"") -> 1 | T11: =P11 -> 培元 | U11: =IFERROR(IF($O11-$Q11=0,"",$O11-$Q11),"") | W11: =IFERROR(CEILING($U11/VLOOKUP($V11,药材与丹炉!$B:$H,COLUMN(药材与丹炉!$H11)-1,0),1),"") | X11: =IF(IFERROR(IF(AND($J11>0,$J11<>""),VLOOKUP($I11,药材与丹炉!$B:$D,3,0),0),0)+IFERROR(IF(AND($N11>0,$N11<>""),VLOOKUP($M11,药材与丹炉!$B:$D,3,0),0),0)+IFERROR(IF(AND($S11>0,$S11<>""),VLOOKUP($R11,药材与丹炉!$B:$D,3,0),0),0)+IFERROR(IF(AND($W11>0,$W11<>""),VLOOKUP($V11,药材与丹炉!$B:$D,3,0),0),0)>0,1,IF(IFERROR(IF(AND($J11>0,$J11<>""),VLOOKUP($I11,药材与丹炉!$B:$D,3,0),0),0)+IFERROR(IF(AND($N11>0,$N11<>""),VLOOKUP($M11,药材与丹炉!$B:$D,3,0),0),0)+IFERROR(IF(AND($S11>0,$S11<>""),VLOOKUP($R11,药材与丹炉!$B:$D,3,0),0),0)+IFERROR(IF(AND($W11>0,$W11<>""),VLOOKUP($V11,药材与丹炉!$B:$D,3,0),0),0)<0,2,0)) -> 0 | AA11: =IFERROR($Y11/VLOOKUP($Z11,药材与丹炉!$B:$H,COLUMN(药材与丹炉!$H11)-1,0),"") | AB11: 普通丹炉 | AC11: =IFERROR(IF($B11-VLOOKUP($AB11,药材与丹炉!$N:$P,2,0)<0,IF($AO$1="是",0,1),IF($B11-VLOOKUP($AB11,药材与丹炉!$N:$P,2,0)=0,2,IF($B11-VLOOKUP($AB11,药材与丹炉!$N:$P,2,0)=1,40,IF($B11-VLOOKUP($AB11,药材与丹炉!$N:$P,2,0)=2,80,"爆炸")))),"") -> 2 | AD11: =IFERROR($J11+IFERROR(IF($N11="",0,$N11),0)+IFERROR(IF($S11="",0,$S11),0)+IFERROR(IF($W11="",0,$W11),0)+IFERROR(IF($AA11="",0,$AA11),0),"") -> 2 | AE11: =IFERROR($J11*VLOOKUP($I11,药材与丹炉!$B:$K,10,0),0)+IFERROR($N11*VLOOKUP($M11,药材与丹炉!$B:$K,10,0),0)+IFERROR($S11*VLOOKUP($R11,药材与丹炉!$B:$K,10,0),0)+IFERROR($W11*VLOOKUP($V11,药材与丹炉!$B:$K,10,0),0)+IFERROR($AA11*VLOOKUP($Z11,药材与丹炉!$B:$K,10,0),0)+IFERROR($AC11*VLOOKUP($AB11,药材与丹炉!$N:$P,3,0)/100,0) -> 30 | AF11: 1 | AG11: =$AF11-$AE11 -> -29 | AH11: =$AF11*$AM$1*$AM$21 -> 2 | AI11: =$AH11-$AE11 -> -28 | AJ11: =IFERROR(IF($Y11/VLOOKUP($Y11,药材与丹炉!$T:$U,2,0)<=(VLOOKUP($AB11,药材与丹炉!$N:$O,2,0)+8)-($J11+IFERROR(IF($N11="",0,$N11),0)+IFERROR(IF($S11="",0,$S11),0)+IFERROR(IF($W11="",0,$W11),0)),1,2),1) -> 1 | AK11: =OR(NOT(IFERROR(OR($L11="",AND($L11<>"",$L11>0,VLOOKUP($AB11,药材与丹炉!$N:$O,2,0)=6)),0)),AND($L11<>"",$L11>0,OR(VLOOKUP($AB11,药材与丹炉!$N:$Q,4,0)-2<$N11,$N11="")),AND($U11<>"",$U11>0,OR(VLOOKUP($AB11,药材与丹炉!$N:$Q,4,0)-3<$W11,$W11="")),NOT(OR(AND($Q11<>"",$S11<>"",VLOOKUP($AB11,药材与丹炉!$N:$Q,4,0)-3>=$S11),$P11="")),NOT(OR(AND($H11<>"",$J11<>"",VLOOKUP($AB11,药材与丹炉!$N:$Q,4,0)-1>=$J11),$G11="")),NOT(OR($U11="",AND($U11<>"",$U11>0))),NOT(OR($Y11="",IF($Z11<>"",IFERROR(IF(VLOOKUP($Z11,药材与丹炉!$B:$D,3,0)=-1,$X11=1,IF(VLOOKUP($Z11,药材与丹炉!$B:$D,3,0)=1,$X11=2,$X11=0)),0),0))),$AC11="爆炸",(VLOOKUP($AB11,药材与丹炉!$N:$O,2,0)+8)<$AD11) -> FALSE | AL11: 0.95 | AM11: 在坊市从不感兴趣的NPC收购该丹药【坊市95折】
A12: 5101 | B12: 2 | C12: 培元丹 | D12: 999 | E12: 生命值+170/丹毒+1 | F12: 6 | G12: 活血 | H12: 6 | I12: 银月花 | J12: =IFERROR(CEILING($H12/VLOOKUP($I12,药材与丹炉!$B:$H,COLUMN(药材与丹炉!$H12)-1,0),1),"") -> 6 | K12: 活血 | L12: =IFERROR(IF($F12-$H12=0,"",$F12-$H12),"") | N12: =IFERROR(CEILING($L12/VLOOKUP($M12,药材与丹炉!$B:$H,COLUMN(药材与丹炉!$H12)-1,0),1),"") | O12: 3 | P12: 固元 | Q12: 3 | R12: 何首乌 | S12: =IFERROR(CEILING($Q12/VLOOKUP($R12,药材与丹炉!$B:$H,COLUMN(药材与丹炉!$H12)-1,0),1),"") -> 1 | T12: =P12 -> 固元 | U12: =IFERROR(IF($O12-$Q12=0,"",$O12-$Q12),"") | W12: =IFERROR(CEILING($U12/VLOOKUP($V12,药材与丹炉!$B:$H,COLUMN(药材与丹炉!$H12)-1,0),1),"") | X12: =IF(IFERROR(IF(AND($J12>0,$J12<>""),VLOOKUP($I12,药材与丹炉!$B:$D,3,0),0),0)+IFERROR(IF(AND($N12>0,$N12<>""),VLOOKUP($M12,药材与丹炉!$B:$D,3,0),0),0)+IFERROR(IF(AND($S12>0,$S12<>""),VLOOKUP($R12,药材与丹炉!$B:$D,3,0),0),0)+IFERROR(IF(AND($W12>0,$W12<>""),VLOOKUP($V12,药材与丹炉!$B:$D,3,0),0),0)>0,1,IF(IFERROR(IF(AND($J12>0,$J12<>""),VLOOKUP($I12,药材与丹炉!$B:$D,3,0),0),0)+IFERROR(IF(AND($N12>0,$N12<>""),VLOOKUP($M12,药材与丹炉!$B:$D,3,0),0),0)+IFERROR(IF(AND($S12>0,$S12<>""),VLOOKUP($R12,药材与丹炉!$B:$D,3,0),0),0)+IFERROR(IF(AND($W12>0,$W12<>""),VLOOKUP($V12,药材与丹炉!$B:$D,3,0),0),0)<0,2,0)) -> 0 | Y12: 3 | Z12: 恒心草 | AA12: =IFERROR($Y12/VLOOKUP($Z12,药材与丹炉!$B:$H,COLUMN(药材与丹炉!$H12)-1,0),"") -> 3 | AB12: 陨铁炉 | AC12: =IFERROR(IF($B12-VLOOKUP($AB12,药材与丹炉!$N:$P,2,0)<0,IF($AO$1="是",0,1),IF($B12-VLOOKUP($AB12,药材与丹炉!$N:$P,2,0)=0,2,IF($B12-VLOOKUP($AB12,药材与丹炉!$N:$P,2,0)=1,40,IF($B12-VLOOKUP($AB12,药材与丹炉!$N:$P,2,0)=2,80,"爆炸")))),"") -> 2 | AD12: =IFERROR($J12+IFERROR(IF($N12="",0,$N12),0)+IFERROR(IF($S12="",0,$S12),0)+IFERROR(IF($W12="",0,$W12),0)+IFERROR(IF($AA12="",0,$AA12),0),"") -> 10 | AE12: =IFERROR($J12*VLOOKUP($I12,药材与丹炉!$B:$K,10,0),0)+IFERROR($N12*VLOOKUP($M12,药材与丹炉!$B:$K,10,0),0)+IFERROR($S12*VLOOKUP($R12,药材与丹炉!$B:$K,10,0),0)+IFERROR($W12*VLOOKUP($V12,药材与丹炉!$B:$K,10,0),0)+IFERROR($AA12*VLOOKUP($Z12,药材与丹炉!$B:$K,10,0),0)+IFERROR($AC12*VLOOKUP($AB12,药材与丹炉!$N:$P,3,0)/100,0) -> 141 | AF12: 206 | AG12: =$AF12-$AE12 -> 65 | AH12: =$AF12*$AM$1*$AM$21 -> 412 | AI12: =$AH12-$AE12 -> 271 | AJ12: =IFERROR(IF($Y12/VLOOKUP($Y12,药材与丹炉!$T:$U,2,0)<=(VLOOKUP($AB12,药材与丹炉!$N:$O,2,0)+8)-($J12+IFERROR(IF($N12="",0,$N12),0)+IFERROR(IF($S12="",0,$S12),0)+IFERROR(IF($W12="",0,$W12),0)),1,2),1) -> 1 | AK12: =OR(NOT(IFERROR(OR($L12="",AND($L12<>"",$L12>0,VLOOKUP($AB12,药材与丹炉!$N:$O,2,0)=6)),0)),AND($L12<>"",$L12>0,OR(VLOOKUP($AB12,药材与丹炉!$N:$Q,4,0)-2<$N12,$N12="")),AND($U12<>"",$U12>0,OR(VLOOKUP($AB12,药材与丹炉!$N:$Q,4,0)-3<$W12,$W12="")),NOT(OR(AND($Q12<>"",$S12<>"",VLOOKUP($AB12,药材与丹炉!$N:$Q,4,0)-3>=$S12),$P12="")),NOT(OR(AND($H12<>"",$J12<>"",VLOOKUP($AB12,药材与丹炉!$N:$Q,4,0)-1>=$J12),$G12="")),NOT(OR($U12="",AND($U12<>"",$U12>0))),NOT(OR($Y12="",IF($Z12<>"",IFERROR(IF(VLOOKUP($Z12,药材与丹炉!$B:$D,3,0)=-1,$X12=1,IF(VLOOKUP($Z12,药材与丹炉!$B:$D,3,0)=1,$X12=2,$X12=0)),0),0))),$AC12="爆炸",(VLOOKUP($AB12,药材与丹炉!$N:$O,2,0)+8)<$AD12) -> FALSE | AL12: 0.975 | AM12: 在坊市将物品卖给感兴趣NPC【坊市95折】
A13: 5102 | B13: 2 | C13: 养气丹 | D13: 100 | E13: 修为+553 | F13: 9 | G13: 生息 | H13: 9 | I13: 风灵花 | J13: =IFERROR(CEILING($H13/VLOOKUP($I13,药材与丹炉!$B:$H,COLUMN(药材与丹炉!$H13)-1,0),1),"") -> 3 | K13: 生息 | L13: =IFERROR(IF($F13-$H13=0,"",$F13-$H13),"") | N13: =IFERROR(CEILING($L13/VLOOKUP($M13,药材与丹炉!$B:$H,COLUMN(药材与丹炉!$H13)-1,0),1),"") | O13: 21 | P13: 养气 | Q13: 21 | R13: 轻灵草 | S13: =IFERROR(CEILING($Q13/VLOOKUP($R13,药材与丹炉!$B:$H,COLUMN(药材与丹炉!$H13)-1,0),1),"") -> 7 | T13: =P13 -> 养气 | U13: =IFERROR(IF($O13-$Q13=0,"",$O13-$Q13),"") | W13: =IFERROR(CEILING($U13/VLOOKUP($V13,药材与丹炉!$B:$H,COLUMN(药材与丹炉!$H13)-1,0),1),"") | X13: =IF(IFERROR(IF(AND($J13>0,$J13<>""),VLOOKUP($I13,药材与丹炉!$B:$D,3,0),0),0)+IFERROR(IF(AND($N13>0,$N13<>""),VLOOKUP($M13,药材与丹炉!$B:$D,3,0),0),0)+IFERROR(IF(AND($S13>0,$S13<>""),VLOOKUP($R13,药材与丹炉!$B:$D,3,0),0),0)+IFERROR(IF(AND($W13>0,$W13<>""),VLOOKUP($V13,药材与丹炉!$B:$D,3,0),0),0)>0,1,IF(IFERROR(IF(AND($J13>0,$J13<>""),VLOOKUP($I13,药材与丹炉!$B:$D,3,0),0),0)+IFERROR(IF(AND($N13>0,$N13<>""),VLOOKUP($M13,药材与丹炉!$B:$D,3,0),0),0)+IFERROR(IF(AND($S13>0,$S13<>""),VLOOKUP($R13,药材与丹炉!$B:$D,3,0),0),0)+IFERROR(IF(AND($W13>0,$W13<>""),VLOOKUP($V13,药材与丹炉!$B:$D,3,0),0),0)<0,2,0)) -> 2 | Y13: 3 | Z13: 地黄参 | AA13: =IFERROR($Y13/VLOOKUP($Z13,药材与丹炉!$B:$H,COLUMN(药材与丹炉!$H13)-1,0),"") -> 1 | AB13: 雕花紫铜炉 | AC13: =IFERROR(IF($B13-VLOOKUP($AB13,药材与丹炉!$N:$P,2,0)<0,IF($AO$1="是",0,1),IF($B13-VLOOKUP($AB13,药材与丹炉!$N:$P,2,0)=0,2,IF($B13-VLOOKUP($AB13,药材与丹炉!$N:$P,2,0)=1,40,IF($B13-VLOOKUP($AB13,药材与丹炉!$N:$P,2,0)=2,80,"爆炸")))),"") -> 1 | AD13: =IFERROR($J13+IFERROR(IF($N13="",0,$N13),0)+IFERROR(IF($S13="",0,$S13),0)+IFERROR(IF($W13="",0,$W13),0)+IFERROR(IF($AA13="",0,$AA13),0),"") -> 11 | AE13: =IFERROR($J13*VLOOKUP($I13,药材与丹炉!$B:$K,10,0),0)+IFERROR($N13*VLOOKUP($M13,药材与丹炉!$B:$K,10,0),0)+IFERROR($S13*VLOOKUP($R13,药材与丹炉!$B:$K,10,0),0)+IFERROR($W13*VLOOKUP($V13,药材与丹炉!$B:$K,10,0),0)+IFERROR($AA13*VLOOKUP($Z13,药材与丹炉!$B:$K,10,0),0)+IFERROR($AC13*VLOOKUP($AB13,药材与丹炉!$N:$P,3,0)/100,0) -> 436 | AF13: 608 | AG13: =$AF13-$AE13 -> 172 | AH13: =$AF13*$AM$1*$AM$21 -> 1216 | AI13: =$AH13-$AE13 -> 780 | AJ13: =IFERROR(IF($Y13/VLOOKUP($Y13,药材与丹炉!$T:$U,2,0)<=(VLOOKUP($AB13,药材与丹炉!$N:$O,2,0)+8)-($J13+IFERROR(IF($N13="",0,$N13),0)+IFERROR(IF($S13="",0,$S13),0)+IFERROR(IF($W13="",0,$W13),0)),1,2),1) -> 2 | AK13: =OR(NOT(IFERROR(OR($L13="",AND($L13<>"",$L13>0,VLOOKUP($AB13,药材与丹炉!$N:$O,2,0)=6)),0)),AND($L13<>"",$L13>0,OR(VLOOKUP($AB13,药材与丹炉!$N:$Q,4,0)-2<$N13,$N13="")),AND($U13<>"",$U13>0,OR(VLOOKUP($AB13,药材与丹炉!$N:$Q,4,0)-3<$W13,$W13="")),NOT(OR(AND($Q13<>"",$S13<>"",VLOOKUP($AB13,药材与丹炉!$N:$Q,4,0)-3>=$S13),$P13="")),NOT(OR(AND($H13<>"",$J13<>"",VLOOKUP($AB13,药材与丹炉!$N:$Q,4,0)-1>=$J13),$G13="")),NOT(OR($U13="",AND($U13<>"",$U13>0))),NOT(OR($Y13="",IF($Z13<>"",IFERROR(IF(VLOOKUP($Z13,药材与丹炉!$B:$D,3,0)=-1,$X13=1,IF(VLOOKUP($Z13,药材与丹炉!$B:$D,3,0)=1,$X13=2,$X13=0)),0),0))),$AC13="爆炸",(VLOOKUP($AB13,药材与丹炉!$N:$O,2,0)+8)<$AD13) -> FALSE | AL13: 1 | AM13: 在非坊市地区将物品卖给感兴趣的NPC或者从不感兴趣NPC收购
A14: 5103 | B14: 2 | C14: 疾行丹 | D14: 100 | E14: 本场战斗中遁速+5/丹毒+3 | F14: 3 | G14: 振气 | H14: 3 | I14: 宁心草 | J14: =IFERROR(CEILING($H14/VLOOKUP($I14,药材与丹炉!$B:$H,COLUMN(药材与丹炉!$H14)-1,0),1),"") -> 3 | K14: 振气 | L14: =IFERROR(IF($F14-$H14=0,"",$F14-$H14),"") | N14: =IFERROR(CEILING($L14/VLOOKUP($M14,药材与丹炉!$B:$H,COLUMN(药材与丹炉!$H14)-1,0),1),"") | O14: 3 | P14: 神行 | Q14: 3 | R14: 夏枯草 | S14: =IFERROR(CEILING($Q14/VLOOKUP($R14,药材与丹炉!$B:$H,COLUMN(药材与丹炉!$H14)-1,0),1),"") -> 1 | T14: =P14 -> 神行 | U14: =IFERROR(IF($O14-$Q14=0,"",$O14-$Q14),"") | W14: =IFERROR(CEILING($U14/VLOOKUP($V14,药材与丹炉!$B:$H,COLUMN(药材与丹炉!$H14)-1,0),1),"") | X14: =IF(IFERROR(IF(AND($J14>0,$J14<>""),VLOOKUP($I14,药材与丹炉!$B:$D,3,0),0),0)+IFERROR(IF(AND($N14>0,$N14<>""),VLOOKUP($M14,药材与丹炉!$B:$D,3,0),0),0)+IFERROR(IF(AND($S14>0,$S14<>""),VLOOKUP($R14,药材与丹炉!$B:$D,3,0),0),0)+IFERROR(IF(AND($W14>0,$W14<>""),VLOOKUP($V14,药材与丹炉!$B:$D,3,0),0),0)>0,1,IF(IFERROR(IF(AND($J14>0,$J14<>""),VLOOKUP($I14,药材与丹炉!$B:$D,3,0),0),0)+IFERROR(IF(AND($N14>0,$N14<>""),VLOOKUP($M14,药材与丹炉!$B:$D,3,0),0),0)+IFERROR(IF(AND($S14>0,$S14<>""),VLOOKUP($R14,药材与丹炉!$B:$D,3,0),0),0)+IFERROR(IF(AND($W14>0,$W14<>""),VLOOKUP($V14,药材与丹炉!$B:$D,3,0),0),0)<0,2,0)) -> 0 | Y14: 1 | Z14: 恒心草 | AA14: =IFERROR($Y14/VLOOKUP($Z14,药材与丹炉!$B:$H,COLUMN(药材与丹炉!$H14)-1,0),"") -> 1 | AB14: 陨铁炉 | AC14: =IFERROR(IF($B14-VLOOKUP($AB14,药材与丹炉!$N:$P,2,0)<0,IF($AO$1="是",0,1),IF($B14-VLOOKUP($AB14,药材与丹炉!$N:$P,2,0)=0,2,IF($B14-VLOOKUP($AB14,药材与丹炉!$N:$P,2,0)=1,40,IF($B14-VLOOKUP($AB14,药材与丹炉!$N:$P,2,0)=2,80,"爆炸")))),"") -> 2 | AD14: =IFERROR($J14+IFERROR(IF($N14="",0,$N14),0)+IFERROR(IF($S14="",0,$S14),0)+IFERROR(IF($W14="",0,$W14),0)+IFERROR(IF($AA14="",0,$AA14),0),"") -> 5 | AE14: =IFERROR($J14*VLOOKUP($I14,药材与丹炉!$B:$K,10,0),0)+IFERROR($N14*VLOOKUP($M14,药材与丹炉!$B:$K,10,0),0)+IFERROR($S14*VLOOKUP($R14,药材与丹炉!$B:$K,10,0),0)+IFERROR($W14*VLOOKUP($V14,药材与丹炉!$B:$K,10,0),0)+IFERROR($AA14*VLOOKUP($Z14,药材与丹炉!$B:$K,10,0),0)+IFERROR($AC14*VLOOKUP($AB14,药材与丹炉!$N:$P,3,0)/100,0) -> 96 | AF14: 143 | AG14: =$AF14-$AE14 -> 47 | AH14: =$AF14*$AM$1*$AM$21 -> 286 | AI14: =$AH14-$AE14 -> 190 | AJ14: =IFERROR(IF($Y14/VLOOKUP($Y14,药材与丹炉!$T:$U,2,0)<=(VLOOKUP($AB14,药材与丹炉!$N:$O,2,0)+8)-($J14+IFERROR(IF($N14="",0,$N14),0)+IFERROR(IF($S14="",0,$S14),0)+IFERROR(IF($W14="",0,$W14),0)),1,2),1) -> 1 | AK14: =OR(NOT(IFERROR(OR($L14="",AND($L14<>"",$L14>0,VLOOKUP($AB14,药材与丹炉!$N:$O,2,0)=6)),0)),AND($L14<>"",$L14>0,OR(VLOOKUP($AB14,药材与丹炉!$N:$Q,4,0)-2<$N14,$N14="")),AND($U14<>"",$U14>0,OR(VLOOKUP($AB14,药材与丹炉!$N:$Q,4,0)-3<$W14,$W14="")),NOT(OR(AND($Q14<>"",$S14<>"",VLOOKUP($AB14,药材与丹炉!$N:$Q,4,0)-3>=$S14),$P14="")),NOT(OR(AND($H14<>"",$J14<>"",VLOOKUP($AB14,药材与丹炉!$N:$Q,4,0)-1>=$J14),$G14="")),NOT(OR($U14="",AND($U14<>"",$U14>0))),NOT(OR($Y14="",IF($Z14<>"",IFERROR(IF(VLOOKUP($Z14,药材与丹炉!$B:$D,3,0)=-1,$X14=1,IF(VLOOKUP($Z14,药材与丹炉!$B:$D,3,0)=1,$X14=2,$X14=0)),0),0))),$AC14="爆炸",(VLOOKUP($AB14,药材与丹炉!$N:$O,2,0)+8)<$AD14) -> FALSE | AL14: 1.5 | AM14: 在灵药堂的购买丹药的价格
A15: 5104 | B15: 2 | C15: 黄龙丹 | D15: 999 | E15: 生命值+320/丹毒+2 | F15: 3 | G15: 活血 | H15: 3 | I15: 银月花 | J15: =IFERROR(CEILING($H15/VLOOKUP($I15,药材与丹炉!$B:$H,COLUMN(药材与丹炉!$H15)-1,0),1),"") -> 3 | K15: 活血 | L15: =IFERROR(IF($F15-$H15=0,"",$F15-$H15),"") | N15: =IFERROR(CEILING($L15/VLOOKUP($M15,药材与丹炉!$B:$H,COLUMN(药材与丹炉!$H15)-1,0),1),"") | O15: 18 | P15: 培元 | Q15: 18 | R15: 红绫草 | S15: =IFERROR(CEILING($Q15/VLOOKUP($R15,药材与丹炉!$B:$H,COLUMN(药材与丹炉!$H15)-1,0),1),"") -> 6 | T15: =P15 -> 培元 | U15: =IFERROR(IF($O15-$Q15=0,"",$O15-$Q15),"") | W15: =IFERROR(CEILING($U15/VLOOKUP($V15,药材与丹炉!$B:$H,COLUMN(药材与丹炉!$H15)-1,0),1),"") | X15: =IF(IFERROR(IF(AND($J15>0,$J15<>""),VLOOKUP($I15,药材与丹炉!$B:$D,3,0),0),0)+IFERROR(IF(AND($N15>0,$N15<>""),VLOOKUP($M15,药材与丹炉!$B:$D,3,0),0),0)+IFERROR(IF(AND($S15>0,$S15<>""),VLOOKUP($R15,药材与丹炉!$B:$D,3,0),0),0)+IFERROR(IF(AND($W15>0,$W15<>""),VLOOKUP($V15,药材与丹炉!$B:$D,3,0),0),0)>0,1,IF(IFERROR(IF(AND($J15>0,$J15<>""),VLOOKUP($I15,药材与丹炉!$B:$D,3,0),0),0)+IFERROR(IF(AND($N15>0,$N15<>""),VLOOKUP($M15,药材与丹炉!$B:$D,3,0),0),0)+IFERROR(IF(AND($S15>0,$S15<>""),VLOOKUP($R15,药材与丹炉!$B:$D,3,0),0),0)+IFERROR(IF(AND($W15>0,$W15<>""),VLOOKUP($V15,药材与丹炉!$B:$D,3,0),0),0)<0,2,0)) -> 2 | Y15: 3 | Z15: 地黄参 | AA15: =IFERROR($Y15/VLOOKUP($Z15,药材与丹炉!$B:$H,COLUMN(药材与丹炉!$H15)-1,0),"") -> 1 | AB15: 陨铁炉 | AC15: =IFERROR(IF($B15-VLOOKUP($AB15,药材与丹炉!$N:$P,2,0)<0,IF($AO$1="是",0,1),IF($B15-VLOOKUP($AB15,药材与丹炉!$N:$P,2,0)=0,2,IF($B15-VLOOKUP($AB15,药材与丹炉!$N:$P,2,0)=1,40,IF($B15-VLOOKUP($AB15,药材与丹炉!$N:$P,2,0)=2,80,"爆炸")))),"") -> 2 | AD15: =IFERROR($J15+IFERROR(IF($N15="",0,$N15),0)+IFERROR(IF($S15="",0,$S15),0)+IFERROR(IF($W15="",0,$W15),0)+IFERROR(IF($AA15="",0,$AA15),0),"") -> 10 | AE15: =IFERROR($J15*VLOOKUP($I15,药材与丹炉!$B:$K,10,0),0)+IFERROR($N15*VLOOKUP($M15,药材与丹炉!$B:$K,10,0),0)+IFERROR($S15*VLOOKUP($R15,药材与丹炉!$B:$K,10,0),0)+IFERROR($W15*VLOOKUP($V15,药材与丹炉!$B:$K,10,0),0)+IFERROR($AA15*VLOOKUP($Z15,药材与丹炉!$B:$K,10,0),0)+IFERROR($AC15*VLOOKUP($AB15,药材与丹炉!$N:$P,3,0)/100,0) -> 303 | AF15: 356 | AG15: =$AF15-$AE15 -> 53 | AH15: =$AF15*$AM$1*$AM$21 -> 712 | AI15: =$AH15-$AE15 -> 409 | AJ15: =IFERROR(IF($Y15/VLOOKUP($Y15,药材与丹炉!$T:$U,2,0)<=(VLOOKUP($AB15,药材与丹炉!$N:$O,2,0)+8)-($J15+IFERROR(IF($N15="",0,$N15),0)+IFERROR(IF($S15="",0,$S15),0)+IFERROR(IF($W15="",0,$W15),0)),1,2),1) -> 2 | AK15: =OR(NOT(IFERROR(OR($L15="",AND($L15<>"",$L15>0,VLOOKUP($AB15,药材与丹炉!$N:$O,2,0)=6)),0)),AND($L15<>"",$L15>0,OR(VLOOKUP($AB15,药材与丹炉!$N:$Q,4,0)-2<$N15,$N15="")),AND($U15<>"",$U15>0,OR(VLOOKUP($AB15,药材与丹炉!$N:$Q,4,0)-3<$W15,$W15="")),NOT(OR(AND($Q15<>"",$S15<>"",VLOOKUP($AB15,药材与丹炉!$N:$Q,4,0)-3>=$S15),$P15="")),NOT(OR(AND($H15<>"",$J15<>"",VLOOKUP($AB15,药材与丹炉!$N:$Q,4,0)-1>=$J15),$G15="")),NOT(OR($U15="",AND($U15<>"",$U15>0))),NOT(OR($Y15="",IF($Z15<>"",IFERROR(IF(VLOOKUP($Z15,药材与丹炉!$B:$D,3,0)=-1,$X15=1,IF(VLOOKUP($Z15,药材与丹炉!$B:$D,3,0)=1,$X15=2,$X15=0)),0),0))),$AC15="爆炸",(VLOOKUP($AB15,药材与丹炉!$N:$O,2,0)+8)<$AD15) -> FALSE | AL15: 2 | AM15: 领悟丹圣后出双倍丹，且在非坊市地区将物品卖给感兴趣NPC的双倍价
A16: 5105 | B16: 2 | C16: 炼血丹 | D16: 100 | E16: 修为+2000/丹毒+6 | F16: 9 | G16: 炼魔 | H16: 9 | I16: 炼血珠 | J16: =IFERROR(CEILING($H16/VLOOKUP($I16,药材与丹炉!$B:$H,COLUMN(药材与丹炉!$H16)-1,0),1),"") -> 1 | K16: 炼魔 | L16: =IFERROR(IF($F16-$H16=0,"",$F16-$H16),"") | N16: =IFERROR(CEILING($L16/VLOOKUP($M16,药材与丹炉!$B:$H,COLUMN(药材与丹炉!$H16)-1,0),1),"") | S16: =IFERROR(CEILING($Q16/VLOOKUP($R16,药材与丹炉!$B:$H,COLUMN(药材与丹炉!$H16)-1,0),1),"") | U16: =IFERROR(IF($O16-$Q16=0,"",$O16-$Q16),"") | W16: =IFERROR(CEILING($U16/VLOOKUP($V16,药材与丹炉!$B:$H,COLUMN(药材与丹炉!$H16)-1,0),1),"") | X16: =IF(IFERROR(IF(AND($J16>0,$J16<>""),VLOOKUP($I16,药材与丹炉!$B:$D,3,0),0),0)+IFERROR(IF(AND($N16>0,$N16<>""),VLOOKUP($M16,药材与丹炉!$B:$D,3,0),0),0)+IFERROR(IF(AND($S16>0,$S16<>""),VLOOKUP($R16,药材与丹炉!$B:$D,3,0),0),0)+IFERROR(IF(AND($W16>0,$W16<>""),VLOOKUP($V16,药材与丹炉!$B:$D,3,0),0),0)>0,1,IF(IFERROR(IF(AND($J16>0,$J16<>""),VLOOKUP($I16,药材与丹炉!$B:$D,3,0),0),0)+IFERROR(IF(AND($N16>0,$N16<>""),VLOOKUP($M16,药材与丹炉!$B:$D,3,0),0),0)+IFERROR(IF(AND($S16>0,$S16<>""),VLOOKUP($R16,药材与丹炉!$B:$D,3,0),0),0)+IFERROR(IF(AND($W16>0,$W16<>""),VLOOKUP($V16,药材与丹炉!$B:$D,3,0),0),0)<0,2,0)) -> 2 | Y16: 3 | Z16: 天青花 | AA16: =IFERROR($Y16/VLOOKUP($Z16,药材与丹炉!$B:$H,COLUMN(药材与丹炉!$H16)-1,0),"") -> 3 | AB16: 陨铁炉 | AC16: =IFERROR(IF($B16-VLOOKUP($AB16,药材与丹炉!$N:$P,2,0)<0,IF($AO$1="是",0,1),IF($B16-VLOOKUP($AB16,药材与丹炉!$N:$P,2,0)=0,2,IF($B16-VLOOKUP($AB16,药材与丹炉!$N:$P,2,0)=1,40,IF($B16-VLOOKUP($AB16,药材与丹炉!$N:$P,2,0)=2,80,"爆炸")))),"") -> 2 | AD16: =IFERROR($J16+IFERROR(IF($N16="",0,$N16),0)+IFERROR(IF($S16="",0,$S16),0)+IFERROR(IF($W16="",0,$W16),0)+IFERROR(IF($AA16="",0,$AA16),0),"") -> 4 | AE16: =IFERROR($J16*VLOOKUP($I16,药材与丹炉!$B:$K,10,0),0)+IFERROR($N16*VLOOKUP($M16,药材与丹炉!$B:$K,10,0),0)+IFERROR($S16*VLOOKUP($R16,药材与丹炉!$B:$K,10,0),0)+IFERROR($W16*VLOOKUP($V16,药材与丹炉!$B:$K,10,0),0)+IFERROR($AA16*VLOOKUP($Z16,药材与丹炉!$B:$K,10,0),0)+IFERROR($AC16*VLOOKUP($AB16,药材与丹炉!$N:$P,3,0)/100,0) -> 456 | AF16: 281 | AG16: =$AF16-$AE16 -> -175 | AH16: =$AF16*$AM$1*$AM$21 -> 562 | AI16: =$AH16-$AE16 -> 106 | AJ16: =IFERROR(IF($Y16/VLOOKUP($Y16,药材与丹炉!$T:$U,2,0)<=(VLOOKUP($AB16,药材与丹炉!$N:$O,2,0)+8)-($J16+IFERROR(IF($N16="",0,$N16),0)+IFERROR(IF($S16="",0,$S16),0)+IFERROR(IF($W16="",0,$W16),0)),1,2),1) -> 1 | AK16: =OR(NOT(IFERROR(OR($L16="",AND($L16<>"",$L16>0,VLOOKUP($AB16,药材与丹炉!$N:$O,2,0)=6)),0)),AND($L16<>"",$L16>0,OR(VLOOKUP($AB16,药材与丹炉!$N:$Q,4,0)-2<$N16,$N16="")),AND($U16<>"",$U16>0,OR(VLOOKUP($AB16,药材与丹炉!$N:$Q,4,0)-3<$W16,$W16="")),NOT(OR(AND($Q16<>"",$S16<>"",VLOOKUP($AB16,药材与丹炉!$N:$Q,4,0)-3>=$S16),$P16="")),NOT(OR(AND($H16<>"",$J16<>"",VLOOKUP($AB16,药材与丹炉!$N:$Q,4,0)-1>=$J16),$G16="")),NOT(OR($U16="",AND($U16<>"",$U16>0))),NOT(OR($Y16="",IF($Z16<>"",IFERROR(IF(VLOOKUP($Z16,药材与丹炉!$B:$D,3,0)=-1,$X16=1,IF(VLOOKUP($Z16,药材与丹炉!$B:$D,3,0)=1,$X16=2,$X16=0)),0),0))),$AC16="爆炸",(VLOOKUP($AB16,药材与丹炉!$N:$O,2,0)+8)<$AD16) -> FALSE | AL16: 4
A17: 5106 | B17: 2 | C17: 三阳丹 | D17: 50 | E17: 本场战斗中造成的火系伤害+1/丹毒+4 | F17: 3 | G17: 振气 | H17: 3 | I17: 宁心草 | J17: =IFERROR(CEILING($H17/VLOOKUP($I17,药材与丹炉!$B:$H,COLUMN(药材与丹炉!$H17)-1,0),1),"") -> 3 | K17: 振气 | L17: =IFERROR(IF($F17-$H17=0,"",$F17-$H17),"") | N17: =IFERROR(CEILING($L17/VLOOKUP($M17,药材与丹炉!$B:$H,COLUMN(药材与丹炉!$H17)-1,0),1),"") | P17: 强火 | Q17: 3 | R17: 火精枣 | S17: =IFERROR(CEILING($Q17/VLOOKUP($R17,药材与丹炉!$B:$H,COLUMN(药材与丹炉!$H17)-1,0),1),"") -> 1 | T17: 混元 | U17: 3 | V17: 凝血草 | W17: =IFERROR(CEILING($U17/VLOOKUP($V17,药材与丹炉!$B:$H,COLUMN(药材与丹炉!$H17)-1,0),1),"") -> 3 | X17: =IF(IFERROR(IF(AND($J17>0,$J17<>""),VLOOKUP($I17,药材与丹炉!$B:$D,3,0),0),0)+IFERROR(IF(AND($N17>0,$N17<>""),VLOOKUP($M17,药材与丹炉!$B:$D,3,0),0),0)+IFERROR(IF(AND($S17>0,$S17<>""),VLOOKUP($R17,药材与丹炉!$B:$D,3,0),0),0)+IFERROR(IF(AND($W17>0,$W17<>""),VLOOKUP($V17,药材与丹炉!$B:$D,3,0),0),0)>0,1,IF(IFERROR(IF(AND($J17>0,$J17<>""),VLOOKUP($I17,药材与丹炉!$B:$D,3,0),0),0)+IFERROR(IF(AND($N17>0,$N17<>""),VLOOKUP($M17,药材与丹炉!$B:$D,3,0),0),0)+IFERROR(IF(AND($S17>0,$S17<>""),VLOOKUP($R17,药材与丹炉!$B:$D,3,0),0),0)+IFERROR(IF(AND($W17>0,$W17<>""),VLOOKUP($V17,药材与丹炉!$B:$D,3,0),0),0)<0,2,0)) -> 0 | Y17: 3 | Z17: 恒心草 | AA17: =IFERROR($Y17/VLOOKUP($Z17,药材与丹炉!$B:$H,COLUMN(药材与丹炉!$H17)-1,0),"") -> 3 | AB17: 陨铁炉 | AC17: =IFERROR(IF($B17-VLOOKUP($AB17,药材与丹炉!$N:$P,2,0)<0,IF($AO$1="是",0,1),IF($B17-VLOOKUP($AB17,药材与丹炉!$N:$P,2,0)=0,2,IF($B17-VLOOKUP($AB17,药材与丹炉!$N:$P,2,0)=1,40,IF($B17-VLOOKUP($AB17,药材与丹炉!$N:$P,2,0)=2,80,"爆炸")))),"") -> 2 | AD17: =IFERROR($J17+IFERROR(IF($N17="",0,$N17),0)+IFERROR(IF($S17="",0,$S17),0)+IFERROR(IF($W17="",0,$W17),0)+IFERROR(IF($AA17="",0,$AA17),0),"") -> 10 | AE17: =IFERROR($J17*VLOOKUP($I17,药材与丹炉!$B:$K,10,0),0)+IFERROR($N17*VLOOKUP($M17,药材与丹炉!$B:$K,10,0),0)+IFERROR($S17*VLOOKUP($R17,药材与丹炉!$B:$K,10,0),0)+IFERROR($W17*VLOOKUP($V17,药材与丹炉!$B:$K,10,0),0)+IFERROR($AA17*VLOOKUP($Z17,药材与丹炉!$B:$K,10,0),0)+IFERROR($AC17*VLOOKUP($AB17,药材与丹炉!$N:$P,3,0)/100,0) -> 141 | AF17: 231 | AG17: =$AF17-$AE17 -> 90 | AH17: =$AF17*$AM$1*$AM$21 -> 462 | AI17: =$AH17-$AE17 -> 321 | AJ17: =IFERROR(IF($Y17/VLOOKUP($Y17,药材与丹炉!$T:$U,2,0)<=(VLOOKUP($AB17,药材与丹炉!$N:$O,2,0)+8)-($J17+IFERROR(IF($N17="",0,$N17),0)+IFERROR(IF($S17="",0,$S17),0)+IFERROR(IF($W17="",0,$W17),0)),1,2),1) -> 1 | AK17: =OR(NOT(IFERROR(OR($L17="",AND($L17<>"",$L17>0,VLOOKUP($AB17,药材与丹炉!$N:$O,2,0)=6)),0)),AND($L17<>"",$L17>0,OR(VLOOKUP($AB17,药材与丹炉!$N:$Q,4,0)-2<$N17,$N17="")),AND($U17<>"",$U17>0,OR(VLOOKUP($AB17,药材与丹炉!$N:$Q,4,0)-3<$W17,$W17="")),NOT(OR(AND($Q17<>"",$S17<>"",VLOOKUP($AB17,药材与丹炉!$N:$Q,4,0)-3>=$S17),$P17="")),NOT(OR(AND($H17<>"",$J17<>"",VLOOKUP($AB17,药材与丹炉!$N:$Q,4,0)-1>=$J17),$G17="")),NOT(OR($U17="",AND($U17<>"",$U17>0))),NOT(OR($Y17="",IF($Z17<>"",IFERROR(IF(VLOOKUP($Z17,药材与丹炉!$B:$D,3,0)=-1,$X17=1,IF(VLOOKUP($Z17,药材与丹炉!$B:$D,3,0)=1,$X17=2,$X17=0)),0),0))),$AC17="爆炸",(VLOOKUP($AB17,药材与丹炉!$N:$O,2,0)+8)<$AD17) -> FALSE | AL17: 6
A18: 5107 | B18: 2 | C18: 葵水丹 | D18: 50 | E18: 本场战斗中造成的水系伤害+1/丹毒+4 | F18: 3 | G18: 振气 | H18: 3 | I18: 宁心草 | J18: =IFERROR(CEILING($H18/VLOOKUP($I18,药材与丹炉!$B:$H,COLUMN(药材与丹炉!$H18)-1,0),1),"") -> 3 | K18: 振气 | L18: =IFERROR(IF($F18-$H18=0,"",$F18-$H18),"") | N18: =IFERROR(CEILING($L18/VLOOKUP($M18,药材与丹炉!$B:$H,COLUMN(药材与丹炉!$H18)-1,0),1),"") | P18: 强水 | Q18: 3 | R18: 弗兰草 | S18: =IFERROR(CEILING($Q18/VLOOKUP($R18,药材与丹炉!$B:$H,COLUMN(药材与丹炉!$H18)-1,0),1),"") -> 1 | T18: 混元 | U18: 3 | V18: 凝血草 | W18: =IFERROR(CEILING($U18/VLOOKUP($V18,药材与丹炉!$B:$H,COLUMN(药材与丹炉!$H18)-1,0),1),"") -> 3 | X18: =IF(IFERROR(IF(AND($J18>0,$J18<>""),VLOOKUP($I18,药材与丹炉!$B:$D,3,0),0),0)+IFERROR(IF(AND($N18>0,$N18<>""),VLOOKUP($M18,药材与丹炉!$B:$D,3,0),0),0)+IFERROR(IF(AND($S18>0,$S18<>""),VLOOKUP($R18,药材与丹炉!$B:$D,3,0),0),0)+IFERROR(IF(AND($W18>0,$W18<>""),VLOOKUP($V18,药材与丹炉!$B:$D,3,0),0),0)>0,1,IF(IFERROR(IF(AND($J18>0,$J18<>""),VLOOKUP($I18,药材与丹炉!$B:$D,3,0),0),0)+IFERROR(IF(AND($N18>0,$N18<>""),VLOOKUP($M18,药材与丹炉!$B:$D,3,0),0),0)+IFERROR(IF(AND($S18>0,$S18<>""),VLOOKUP($R18,药材与丹炉!$B:$D,3,0),0),0)+IFERROR(IF(AND($W18>0,$W18<>""),VLOOKUP($V18,药材与丹炉!$B:$D,3,0),0),0)<0,2,0)) -> 2 | Y18: 3 | Z18: 流莹草 | AA18: =IFERROR($Y18/VLOOKUP($Z18,药材与丹炉!$B:$H,COLUMN(药材与丹炉!$H18)-1,0),"") -> 3 | AB18: 陨铁炉 | AC18: =IFERROR(IF($B18-VLOOKUP($AB18,药材与丹炉!$N:$P,2,0)<0,IF($AO$1="是",0,1),IF($B18-VLOOKUP($AB18,药材与丹炉!$N:$P,2,0)=0,2,IF($B18-VLOOKUP($AB18,药材与丹炉!$N:$P,2,0)=1,40,IF($B18-VLOOKUP($AB18,药材与丹炉!$N:$P,2,0)=2,80,"爆炸")))),"") -> 2 | AD18: =IFERROR($J18+IFERROR(IF($N18="",0,$N18),0)+IFERROR(IF($S18="",0,$S18),0)+IFERROR(IF($W18="",0,$W18),0)+IFERROR(IF($AA18="",0,$AA18),0),"") -> 10 | AE18: =IFERROR($J18*VLOOKUP($I18,药材与丹炉!$B:$K,10,0),0)+IFERROR($N18*VLOOKUP($M18,药材与丹炉!$B:$K,10,0),0)+IFERROR($S18*VLOOKUP($R18,药材与丹炉!$B:$K,10,0),0)+IFERROR($W18*VLOOKUP($V18,药材与丹炉!$B:$K,10,0),0)+IFERROR($AA18*VLOOKUP($Z18,药材与丹炉!$B:$K,10,0),0)+IFERROR($AC18*VLOOKUP($AB18,药材与丹炉!$N:$P,3,0)/100,0) -> 141 | AF18: 231 | AG18: =$AF18-$AE18 -> 90 | AH18: =$AF18*$AM$1*$AM$21 -> 462 | AI18: =$AH18-$AE18 -> 321 | AJ18: =IFERROR(IF($Y18/VLOOKUP($Y18,药材与丹炉!$T:$U,2,0)<=(VLOOKUP($AB18,药材与丹炉!$N:$O,2,0)+8)-($J18+IFERROR(IF($N18="",0,$N18),0)+IFERROR(IF($S18="",0,$S18),0)+IFERROR(IF($W18="",0,$W18),0)),1,2),1) -> 1 | AK18: =OR(NOT(IFERROR(OR($L18="",AND($L18<>"",$L18>0,VLOOKUP($AB18,药材与丹炉!$N:$O,2,0)=6)),0)),AND($L18<>"",$L18>0,OR(VLOOKUP($AB18,药材与丹炉!$N:$Q,4,0)-2<$N18,$N18="")),AND($U18<>"",$U18>0,OR(VLOOKUP($AB18,药材与丹炉!$N:$Q,4,0)-3<$W18,$W18="")),NOT(OR(AND($Q18<>"",$S18<>"",VLOOKUP($AB18,药材与丹炉!$N:$Q,4,0)-3>=$S18),$P18="")),NOT(OR(AND($H18<>"",$J18<>"",VLOOKUP($AB18,药材与丹炉!$N:$Q,4,0)-1>=$J18),$G18="")),NOT(OR($U18="",AND($U18<>"",$U18>0))),NOT(OR($Y18="",IF($Z18<>"",IFERROR(IF(VLOOKUP($Z18,药材与丹炉!$B:$D,3,0)=-1,$X18=1,IF(VLOOKUP($Z18,药材与丹炉!$B:$D,3,0)=1,$X18=2,$X18=0)),0),0))),$AC18="爆炸",(VLOOKUP($AB18,药材与丹炉!$N:$O,2,0)+8)<$AD18) -> FALSE | AL18: 8
A19: 5108 | B19: 2 | C19: 锐金丹 | D19: 50 | E19: 本场战斗中造成的金系伤害+1/丹毒+4 | F19: 3 | G19: 振气 | H19: 3 | I19: 宁心草 | J19: =IFERROR(CEILING($H19/VLOOKUP($I19,药材与丹炉!$B:$H,COLUMN(药材与丹炉!$H19)-1,0),1),"") -> 3 | K19: 振气 | L19: =IFERROR(IF($F19-$H19=0,"",$F19-$H19),"") | N19: =IFERROR(CEILING($L19/VLOOKUP($M19,药材与丹炉!$B:$H,COLUMN(药材与丹炉!$H19)-1,0),1),"") | P19: 强金 | Q19: 3 | R19: 罗犀草 | S19: =IFERROR(CEILING($Q19/VLOOKUP($R19,药材与丹炉!$B:$H,COLUMN(药材与丹炉!$H19)-1,0),1),"") -> 1 | T19: 混元 | U19: 3 | V19: 凝血草 | W19: =IFERROR(CEILING($U19/VLOOKUP($V19,药材与丹炉!$B:$H,COLUMN(药材与丹炉!$H19)-1,0),1),"") -> 3 | X19: =IF(IFERROR(IF(AND($J19>0,$J19<>""),VLOOKUP($I19,药材与丹炉!$B:$D,3,0),0),0)+IFERROR(IF(AND($N19>0,$N19<>""),VLOOKUP($M19,药材与丹炉!$B:$D,3,0),0),0)+IFERROR(IF(AND($S19>0,$S19<>""),VLOOKUP($R19,药材与丹炉!$B:$D,3,0),0),0)+IFERROR(IF(AND($W19>0,$W19<>""),VLOOKUP($V19,药材与丹炉!$B:$D,3,0),0),0)>0,1,IF(IFERROR(IF(AND($J19>0,$J19<>""),VLOOKUP($I19,药材与丹炉!$B:$D,3,0),0),0)+IFERROR(IF(AND($N19>0,$N19<>""),VLOOKUP($M19,药材与丹炉!$B:$D,3,0),0),0)+IFERROR(IF(AND($S19>0,$S19<>""),VLOOKUP($R19,药材与丹炉!$B:$D,3,0),0),0)+IFERROR(IF(AND($W19>0,$W19<>""),VLOOKUP($V19,药材与丹炉!$B:$D,3,0),0),0)<0,2,0)) -> 2 | Y19: 3 | Z19: 流莹草 | AA19: =IFERROR($Y19/VLOOKUP($Z19,药材与丹炉!$B:$H,COLUMN(药材与丹炉!$H19)-1,0),"") -> 3 | AB19: 陨铁炉 | AC19: =IFERROR(IF($B19-VLOOKUP($AB19,药材与丹炉!$N:$P,2,0)<0,IF($AO$1="是",0,1),IF($B19-VLOOKUP($AB19,药材与丹炉!$N:$P,2,0)=0,2,IF($B19-VLOOKUP($AB19,药材与丹炉!$N:$P,2,0)=1,40,IF($B19-VLOOKUP($AB19,药材与丹炉!$N:$P,2,0)=2,80,"爆炸")))),"") -> 2 | AD19: =IFERROR($J19+IFERROR(IF($N19="",0,$N19),0)+IFERROR(IF($S19="",0,$S19),0)+IFERROR(IF($W19="",0,$W19),0)+IFERROR(IF($AA19="",0,$AA19),0),"") -> 10 | AE19: =IFERROR($J19*VLOOKUP($I19,药材与丹炉!$B:$K,10,0),0)+IFERROR($N19*VLOOKUP($M19,药材与丹炉!$B:$K,10,0),0)+IFERROR($S19*VLOOKUP($R19,药材与丹炉!$B:$K,10,0),0)+IFERROR($W19*VLOOKUP($V19,药材与丹炉!$B:$K,10,0),0)+IFERROR($AA19*VLOOKUP($Z19,药材与丹炉!$B:$K,10,0),0)+IFERROR($AC19*VLOOKUP($AB19,药材与丹炉!$N:$P,3,0)/100,0) -> 141 | AF19: 231 | AG19: =$AF19-$AE19 -> 90 | AH19: =$AF19*$AM$1*$AM$21 -> 462 | AI19: =$AH19-$AE19 -> 321 | AJ19: =IFERROR(IF($Y19/VLOOKUP($Y19,药材与丹炉!$T:$U,2,0)<=(VLOOKUP($AB19,药材与丹炉!$N:$O,2,0)+8)-($J19+IFERROR(IF($N19="",0,$N19),0)+IFERROR(IF($S19="",0,$S19),0)+IFERROR(IF($W19="",0,$W19),0)),1,2),1) -> 1 | AK19: =OR(NOT(IFERROR(OR($L19="",AND($L19<>"",$L19>0,VLOOKUP($AB19,药材与丹炉!$N:$O,2,0)=6)),0)),AND($L19<>"",$L19>0,OR(VLOOKUP($AB19,药材与丹炉!$N:$Q,4,0)-2<$N19,$N19="")),AND($U19<>"",$U19>0,OR(VLOOKUP($AB19,药材与丹炉!$N:$Q,4,0)-3<$W19,$W19="")),NOT(OR(AND($Q19<>"",$S19<>"",VLOOKUP($AB19,药材与丹炉!$N:$Q,4,0)-3>=$S19),$P19="")),NOT(OR(AND($H19<>"",$J19<>"",VLOOKUP($AB19,药材与丹炉!$N:$Q,4,0)-1>=$J19),$G19="")),NOT(OR($U19="",AND($U19<>"",$U19>0))),NOT(OR($Y19="",IF($Z19<>"",IFERROR(IF(VLOOKUP($Z19,药材与丹炉!$B:$D,3,0)=-1,$X19=1,IF(VLOOKUP($Z19,药材与丹炉!$B:$D,3,0)=1,$X19=2,$X19=0)),0),0))),$AC19="爆炸",(VLOOKUP($AB19,药材与丹炉!$N:$O,2,0)+8)<$AD19) -> FALSE | AL19: 10
A20: 5109 | B20: 2 | C20: 乙木丹 | D20: 50 | E20: 本场战斗中造成的木系伤害+1/丹毒+4 | F20: 3 | G20: 振气 | H20: 3 | I20: 宁心草 | J20: =IFERROR(CEILING($H20/VLOOKUP($I20,药材与丹炉!$B:$H,COLUMN(药材与丹炉!$H20)-1,0),1),"") -> 3 | K20: 振气 | L20: =IFERROR(IF($F20-$H20=0,"",$F20-$H20),"") | N20: =IFERROR(CEILING($L20/VLOOKUP($M20,药材与丹炉!$B:$H,COLUMN(药材与丹炉!$H20)-1,0),1),"") | P20: 强木 | Q20: 3 | R20: 风灵花 | S20: =IFERROR(CEILING($Q20/VLOOKUP($R20,药材与丹炉!$B:$H,COLUMN(药材与丹炉!$H20)-1,0),1),"") -> 1 | T20: 混元 | U20: 3 | V20: 凝血草 | W20: =IFERROR(CEILING($U20/VLOOKUP($V20,药材与丹炉!$B:$H,COLUMN(药材与丹炉!$H20)-1,0),1),"") -> 3 | X20: =IF(IFERROR(IF(AND($J20>0,$J20<>""),VLOOKUP($I20,药材与丹炉!$B:$D,3,0),0),0)+IFERROR(IF(AND($N20>0,$N20<>""),VLOOKUP($M20,药材与丹炉!$B:$D,3,0),0),0)+IFERROR(IF(AND($S20>0,$S20<>""),VLOOKUP($R20,药材与丹炉!$B:$D,3,0),0),0)+IFERROR(IF(AND($W20>0,$W20<>""),VLOOKUP($V20,药材与丹炉!$B:$D,3,0),0),0)>0,1,IF(IFERROR(IF(AND($J20>0,$J20<>""),VLOOKUP($I20,药材与丹炉!$B:$D,3,0),0),0)+IFERROR(IF(AND($N20>0,$N20<>""),VLOOKUP($M20,药材与丹炉!$B:$D,3,0),0),0)+IFERROR(IF(AND($S20>0,$S20<>""),VLOOKUP($R20,药材与丹炉!$B:$D,3,0),0),0)+IFERROR(IF(AND($W20>0,$W20<>""),VLOOKUP($V20,药材与丹炉!$B:$D,3,0),0),0)<0,2,0)) -> 2 | Y20: 3 | Z20: 流莹草 | AA20: =IFERROR($Y20/VLOOKUP($Z20,药材与丹炉!$B:$H,COLUMN(药材与丹炉!$H20)-1,0),"") -> 3 | AB20: 陨铁炉 | AC20: =IFERROR(IF($B20-VLOOKUP($AB20,药材与丹炉!$N:$P,2,0)<0,IF($AO$1="是",0,1),IF($B20-VLOOKUP($AB20,药材与丹炉!$N:$P,2,0)=0,2,IF($B20-VLOOKUP($AB20,药材与丹炉!$N:$P,2,0)=1,40,IF($B20-VLOOKUP($AB20,药材与丹炉!$N:$P,2,0)=2,80,"爆炸")))),"") -> 2 | AD20: =IFERROR($J20+IFERROR(IF($N20="",0,$N20),0)+IFERROR(IF($S20="",0,$S20),0)+IFERROR(IF($W20="",0,$W20),0)+IFERROR(IF($AA20="",0,$AA20),0),"") -> 10 | AE20: =IFERROR($J20*VLOOKUP($I20,药材与丹炉!$B:$K,10,0),0)+IFERROR($N20*VLOOKUP($M20,药材与丹炉!$B:$K,10,0),0)+IFERROR($S20*VLOOKUP($R20,药材与丹炉!$B:$K,10,0),0)+IFERROR($W20*VLOOKUP($V20,药材与丹炉!$B:$K,10,0),0)+IFERROR($AA20*VLOOKUP($Z20,药材与丹炉!$B:$K,10,0),0)+IFERROR($AC20*VLOOKUP($AB20,药材与丹炉!$N:$P,3,0)/100,0) -> 141 | AF20: 231 | AG20: =$AF20-$AE20 -> 90 | AH20: =$AF20*$AM$1*$AM$21 -> 462 | AI20: =$AH20-$AE20 -> 321 | AJ20: =IFERROR(IF($Y20/VLOOKUP($Y20,药材与丹炉!$T:$U,2,0)<=(VLOOKUP($AB20,药材与丹炉!$N:$O,2,0)+8)-($J20+IFERROR(IF($N20="",0,$N20),0)+IFERROR(IF($S20="",0,$S20),0)+IFERROR(IF($W20="",0,$W20),0)),1,2),1) -> 1 | AK20: =OR(NOT(IFERROR(OR($L20="",AND($L20<>"",$L20>0,VLOOKUP($AB20,药材与丹炉!$N:$O,2,0)=6)),0)),AND($L20<>"",$L20>0,OR(VLOOKUP($AB20,药材与丹炉!$N:$Q,4,0)-2<$N20,$N20="")),AND($U20<>"",$U20>0,OR(VLOOKUP($AB20,药材与丹炉!$N:$Q,4,0)-3<$W20,$W20="")),NOT(OR(AND($Q20<>"",$S20<>"",VLOOKUP($AB20,药材与丹炉!$N:$Q,4,0)-3>=$S20),$P20="")),NOT(OR(AND($H20<>"",$J20<>"",VLOOKUP($AB20,药材与丹炉!$N:$Q,4,0)-1>=$J20),$G20="")),NOT(OR($U20="",AND($U20<>"",$U20>0))),NOT(OR($Y20="",IF($Z20<>"",IFERROR(IF(VLOOKUP($Z20,药材与丹炉!$B:$D,3,0)=-1,$X20=1,IF(VLOOKUP($Z20,药材与丹炉!$B:$D,3,0)=1,$X20=2,$X20=0)),0),0))),$AC20="爆炸",(VLOOKUP($AB20,药材与丹炉!$N:$O,2,0)+8)<$AD20) -> FALSE | AL20: 境界等级→ | AM20: 凡人 | AO20: 这是我自己玩的自定义成丹数 不用管 默认凡人就行
A21: 5110 | B21: 2 | C21: 厚土丹 | D21: 50 | E21: 本场战斗中造成的土系伤害+1/丹毒+4 | F21: 3 | G21: 振气 | H21: 3 | I21: 宁心草 | J21: =IFERROR(CEILING($H21/VLOOKUP($I21,药材与丹炉!$B:$H,COLUMN(药材与丹炉!$H21)-1,0),1),"") -> 3 | K21: 振气 | L21: =IFERROR(IF($F21-$H21=0,"",$F21-$H21),"") | N21: =IFERROR(CEILING($L21/VLOOKUP($M21,药材与丹炉!$B:$H,COLUMN(药材与丹炉!$H21)-1,0),1),"") | P21: 强土 | Q21: 3 | R21: 地黄参 | S21: =IFERROR(CEILING($Q21/VLOOKUP($R21,药材与丹炉!$B:$H,COLUMN(药材与丹炉!$H21)-1,0),1),"") -> 1 | T21: 混元 | U21: 3 | V21: 凝血草 | W21: =IFERROR(CEILING($U21/VLOOKUP($V21,药材与丹炉!$B:$H,COLUMN(药材与丹炉!$H21)-1,0),1),"") -> 3 | X21: =IF(IFERROR(IF(AND($J21>0,$J21<>""),VLOOKUP($I21,药材与丹炉!$B:$D,3,0),0),0)+IFERROR(IF(AND($N21>0,$N21<>""),VLOOKUP($M21,药材与丹炉!$B:$D,3,0),0),0)+IFERROR(IF(AND($S21>0,$S21<>""),VLOOKUP($R21,药材与丹炉!$B:$D,3,0),0),0)+IFERROR(IF(AND($W21>0,$W21<>""),VLOOKUP($V21,药材与丹炉!$B:$D,3,0),0),0)>0,1,IF(IFERROR(IF(AND($J21>0,$J21<>""),VLOOKUP($I21,药材与丹炉!$B:$D,3,0),0),0)+IFERROR(IF(AND($N21>0,$N21<>""),VLOOKUP($M21,药材与丹炉!$B:$D,3,0),0),0)+IFERROR(IF(AND($S21>0,$S21<>""),VLOOKUP($R21,药材与丹炉!$B:$D,3,0),0),0)+IFERROR(IF(AND($W21>0,$W21<>""),VLOOKUP($V21,药材与丹炉!$B:$D,3,0),0),0)<0,2,0)) -> 0 | Y21: 3 | Z21: 恒心草 | AA21: =IFERROR($Y21/VLOOKUP($Z21,药材与丹炉!$B:$H,COLUMN(药材与丹炉!$H21)-1,0),"") -> 3 | AB21: 陨铁炉 | AC21: =IFERROR(IF($B21-VLOOKUP($AB21,药材与丹炉!$N:$P,2,0)<0,IF($AO$1="是",0,1),IF($B21-VLOOKUP($AB21,药材与丹炉!$N:$P,2,0)=0,2,IF($B21-VLOOKUP($AB21,药材与丹炉!$N:$P,2,0)=1,40,IF($B21-VLOOKUP($AB21,药材与丹炉!$N:$P,2,0)=2,80,"爆炸")))),"") -> 2 | AD21: =IFERROR($J21+IFERROR(IF($N21="",0,$N21),0)+IFERROR(IF($S21="",0,$S21),0)+IFERROR(IF($W21="",0,$W21),0)+IFERROR(IF($AA21="",0,$AA21),0),"") -> 10 | AE21: =IFERROR($J21*VLOOKUP($I21,药材与丹炉!$B:$K,10,0),0)+IFERROR($N21*VLOOKUP($M21,药材与丹炉!$B:$K,10,0),0)+IFERROR($S21*VLOOKUP($R21,药材与丹炉!$B:$K,10,0),0)+IFERROR($W21*VLOOKUP($V21,药材与丹炉!$B:$K,10,0),0)+IFERROR($AA21*VLOOKUP($Z21,药材与丹炉!$B:$K,10,0),0)+IFERROR($AC21*VLOOKUP($AB21,药材与丹炉!$N:$P,3,0)/100,0) -> 141 | AF21: 231 | AG21: =$AF21-$AE21 -> 90 | AH21: =$AF21*$AM$1*$AM$21 -> 462 | AI21: =$AH21-$AE21 -> 321 | AJ21: =IFERROR(IF($Y21/VLOOKUP($Y21,药材与丹炉!$T:$U,2,0)<=(VLOOKUP($AB21,药材与丹炉!$N:$O,2,0)+8)-($J21+IFERROR(IF($N21="",0,$N21),0)+IFERROR(IF($S21="",0,$S21),0)+IFERROR(IF($W21="",0,$W21),0)),1,2),1) -> 1 | AK21: =OR(NOT(IFERROR(OR($L21="",AND($L21<>"",$L21>0,VLOOKUP($AB21,药材与丹炉!$N:$O,2,0)=6)),0)),AND($L21<>"",$L21>0,OR(VLOOKUP($AB21,药材与丹炉!$N:$Q,4,0)-2<$N21,$N21="")),AND($U21<>"",$U21>0,OR(VLOOKUP($AB21,药材与丹炉!$N:$Q,4,0)-3<$W21,$W21="")),NOT(OR(AND($Q21<>"",$S21<>"",VLOOKUP($AB21,药材与丹炉!$N:$Q,4,0)-3>=$S21),$P21="")),NOT(OR(AND($H21<>"",$J21<>"",VLOOKUP($AB21,药材与丹炉!$N:$Q,4,0)-1>=$J21),$G21="")),NOT(OR($U21="",AND($U21<>"",$U21>0))),NOT(OR($Y21="",IF($Z21<>"",IFERROR(IF(VLOOKUP($Z21,药材与丹炉!$B:$D,3,0)=-1,$X21=1,IF(VLOOKUP($Z21,药材与丹炉!$B:$D,3,0)=1,$X21=2,$X21=0)),0),0))),$AC21="爆炸",(VLOOKUP($AB21,药材与丹炉!$N:$O,2,0)+8)<$AD21) -> FALSE | AL21: 境界倍率→ | AM21: =VLOOKUP(AM20,AL22:AM27,2,FALSE) -> 1
A22: 5111 | B22: 2 | C22: 净血丹 | D22: 20 | E22: 丹毒-2 | F22: 9 | G22: 净血 | H22: 9 | I22: 玄参 | J22: =IFERROR(CEILING($H22/VLOOKUP($I22,药材与丹炉!$B:$H,COLUMN(药材与丹炉!$H22)-1,0),1),"") -> 3 | K22: 净血 | L22: =IFERROR(IF($F22-$H22=0,"",$F22-$H22),"") | N22: =IFERROR(CEILING($L22/VLOOKUP($M22,药材与丹炉!$B:$H,COLUMN(药材与丹炉!$H22)-1,0),1),"") | O22: 6 | P22: 解毒 | Q22: 6 | R22: 龙葵 | S22: =IFERROR(CEILING($Q22/VLOOKUP($R22,药材与丹炉!$B:$H,COLUMN(药材与丹炉!$H22)-1,0),1),"") -> 2 | T22: =P22 -> 解毒 | U22: =IFERROR(IF($O22-$Q22=0,"",$O22-$Q22),"") | W22: =IFERROR(CEILING($U22/VLOOKUP($V22,药材与丹炉!$B:$H,COLUMN(药材与丹炉!$H22)-1,0),1),"") | X22: =IF(IFERROR(IF(AND($J22>0,$J22<>""),VLOOKUP($I22,药材与丹炉!$B:$D,3,0),0),0)+IFERROR(IF(AND($N22>0,$N22<>""),VLOOKUP($M22,药材与丹炉!$B:$D,3,0),0),0)+IFERROR(IF(AND($S22>0,$S22<>""),VLOOKUP($R22,药材与丹炉!$B:$D,3,0),0),0)+IFERROR(IF(AND($W22>0,$W22<>""),VLOOKUP($V22,药材与丹炉!$B:$D,3,0),0),0)>0,1,IF(IFERROR(IF(AND($J22>0,$J22<>""),VLOOKUP($I22,药材与丹炉!$B:$D,3,0),0),0)+IFERROR(IF(AND($N22>0,$N22<>""),VLOOKUP($M22,药材与丹炉!$B:$D,3,0),0),0)+IFERROR(IF(AND($S22>0,$S22<>""),VLOOKUP($R22,药材与丹炉!$B:$D,3,0),0),0)+IFERROR(IF(AND($W22>0,$W22<>""),VLOOKUP($V22,药材与丹炉!$B:$D,3,0),0),0)<0,2,0)) -> 2 | Y22: 3 | Z22: 流莹草 | AA22: =IFERROR($Y22/VLOOKUP($Z22,药材与丹炉!$B:$H,COLUMN(药材与丹炉!$H22)-1,0),"") -> 3 | AB22: 陨铁炉 | AC22: =IFERROR(IF($B22-VLOOKUP($AB22,药材与丹炉!$N:$P,2,0)<0,IF($AO$1="是",0,1),IF($B22-VLOOKUP($AB22,药材与丹炉!$N:$P,2,0)=0,2,IF($B22-VLOOKUP($AB22,药材与丹炉!$N:$P,2,0)=1,40,IF($B22-VLOOKUP($AB22,药材与丹炉!$N:$P,2,0)=2,80,"爆炸")))),"") -> 2 | AD22: =IFERROR($J22+IFERROR(IF($N22="",0,$N22),0)+IFERROR(IF($S22="",0,$S22),0)+IFERROR(IF($W22="",0,$W22),0)+IFERROR(IF($AA22="",0,$AA22),0),"") -> 8 | AE22: =IFERROR($J22*VLOOKUP($I22,药材与丹炉!$B:$K,10,0),0)+IFERROR($N22*VLOOKUP($M22,药材与丹炉!$B:$K,10,0),0)+IFERROR($S22*VLOOKUP($R22,药材与丹炉!$B:$K,10,0),0)+IFERROR($W22*VLOOKUP($V22,药材与丹炉!$B:$K,10,0),0)+IFERROR($AA22*VLOOKUP($Z22,药材与丹炉!$B:$K,10,0),0)+IFERROR($AC22*VLOOKUP($AB22,药材与丹炉!$N:$P,3,0)/100,0) -> 231 | AF22: 281 | AG22: =$AF22-$AE22 -> 50 | AH22: =$AF22*$AM$1*$AM$21 -> 562 | AI22: =$AH22-$AE22 -> 331 | AJ22: =IFERROR(IF($Y22/VLOOKUP($Y22,药材与丹炉!$T:$U,2,0)<=(VLOOKUP($AB22,药材与丹炉!$N:$O,2,0)+8)-($J22+IFERROR(IF($N22="",0,$N22),0)+IFERROR(IF($S22="",0,$S22),0)+IFERROR(IF($W22="",0,$W22),0)),1,2),1) -> 1 | AK22: =OR(NOT(IFERROR(OR($L22="",AND($L22<>"",$L22>0,VLOOKUP($AB22,药材与丹炉!$N:$O,2,0)=6)),0)),AND($L22<>"",$L22>0,OR(VLOOKUP($AB22,药材与丹炉!$N:$Q,4,0)-2<$N22,$N22="")),AND($U22<>"",$U22>0,OR(VLOOKUP($AB22,药材与丹炉!$N:$Q,4,0)-3<$W22,$W22="")),NOT(OR(AND($Q22<>"",$S22<>"",VLOOKUP($AB22,药材与丹炉!$N:$Q,4,0)-3>=$S22),$P22="")),NOT(OR(AND($H22<>"",$J22<>"",VLOOKUP($AB22,药材与丹炉!$N:$Q,4,0)-1>=$J22),$G22="")),NOT(OR($U22="",AND($U22<>"",$U22>0))),NOT(OR($Y22="",IF($Z22<>"",IFERROR(IF(VLOOKUP($Z22,药材与丹炉!$B:$D,3,0)=-1,$X22=1,IF(VLOOKUP($Z22,药材与丹炉!$B:$D,3,0)=1,$X22=2,$X22=0)),0),0))),$AC22="爆炸",(VLOOKUP($AB22,药材与丹炉!$N:$O,2,0)+8)<$AD22) -> FALSE | AL22: 凡人 | AM22: 1
A23: 5112 | B23: 2 | C23: 明心丹 | D23: 40 | E23: 心境+4 | F23: 9 | G23: 聚元 | H23: 9 | I23: 夜交藤 | J23: =IFERROR(CEILING($H23/VLOOKUP($I23,药材与丹炉!$B:$H,COLUMN(药材与丹炉!$H23)-1,0),1),"") -> 3 | K23: 聚元 | L23: =IFERROR(IF($F23-$H23=0,"",$F23-$H23),"") | N23: =IFERROR(CEILING($L23/VLOOKUP($M23,药材与丹炉!$B:$H,COLUMN(药材与丹炉!$H23)-1,0),1),"") | P23: 清心 | Q23: 12 | R23: 七星草 | S23: =IFERROR(CEILING($Q23/VLOOKUP($R23,药材与丹炉!$B:$H,COLUMN(药材与丹炉!$H23)-1,0),1),"") -> 4 | T23: 调和 | U23: 6 | V23: 百草露 | W23: =IFERROR(CEILING($U23/VLOOKUP($V23,药材与丹炉!$B:$H,COLUMN(药材与丹炉!$H23)-1,0),1),"") -> 2 | X23: =IF(IFERROR(IF(AND($J23>0,$J23<>""),VLOOKUP($I23,药材与丹炉!$B:$D,3,0),0),0)+IFERROR(IF(AND($N23>0,$N23<>""),VLOOKUP($M23,药材与丹炉!$B:$D,3,0),0),0)+IFERROR(IF(AND($S23>0,$S23<>""),VLOOKUP($R23,药材与丹炉!$B:$D,3,0),0),0)+IFERROR(IF(AND($W23>0,$W23<>""),VLOOKUP($V23,药材与丹炉!$B:$D,3,0),0),0)>0,1,IF(IFERROR(IF(AND($J23>0,$J23<>""),VLOOKUP($I23,药材与丹炉!$B:$D,3,0),0),0)+IFERROR(IF(AND($N23>0,$N23<>""),VLOOKUP($M23,药材与丹炉!$B:$D,3,0),0),0)+IFERROR(IF(AND($S23>0,$S23<>""),VLOOKUP($R23,药材与丹炉!$B:$D,3,0),0),0)+IFERROR(IF(AND($W23>0,$W23<>""),VLOOKUP($V23,药材与丹炉!$B:$D,3,0),0),0)<0,2,0)) -> 0 | Y23: 3 | Z23: 红绫草 | AA23: =IFERROR($Y23/VLOOKUP($Z23,药材与丹炉!$B:$H,COLUMN(药材与丹炉!$H23)-1,0),"") -> 1 | AB23: 陨铁炉 | AC23: =IFERROR(IF($B23-VLOOKUP($AB23,药材与丹炉!$N:$P,2,0)<0,IF($AO$1="是",0,1),IF($B23-VLOOKUP($AB23,药材与丹炉!$N:$P,2,0)=0,2,IF($B23-VLOOKUP($AB23,药材与丹炉!$N:$P,2,0)=1,40,IF($B23-VLOOKUP($AB23,药材与丹炉!$N:$P,2,0)=2,80,"爆炸")))),"") -> 2 | AD23: =IFERROR($J23+IFERROR(IF($N23="",0,$N23),0)+IFERROR(IF($S23="",0,$S23),0)+IFERROR(IF($W23="",0,$W23),0)+IFERROR(IF($AA23="",0,$AA23),0),"") -> 10 | AE23: =IFERROR($J23*VLOOKUP($I23,药材与丹炉!$B:$K,10,0),0)+IFERROR($N23*VLOOKUP($M23,药材与丹炉!$B:$K,10,0),0)+IFERROR($S23*VLOOKUP($R23,药材与丹炉!$B:$K,10,0),0)+IFERROR($W23*VLOOKUP($V23,药材与丹炉!$B:$K,10,0),0)+IFERROR($AA23*VLOOKUP($Z23,药材与丹炉!$B:$K,10,0),0)+IFERROR($AC23*VLOOKUP($AB23,药材与丹炉!$N:$P,3,0)/100,0) -> 384 | AF23: 525 | AG23: =$AF23-$AE23 -> 141 | AH23: =$AF23*$AM$1*$AM$21 -> 1050 | AI23: =$AH23-$AE23 -> 666 | AJ23: =IFERROR(IF($Y23/VLOOKUP($Y23,药材与丹炉!$T:$U,2,0)<=(VLOOKUP($AB23,药材与丹炉!$N:$O,2,0)+8)-($J23+IFERROR(IF($N23="",0,$N23),0)+IFERROR(IF($S23="",0,$S23),0)+IFERROR(IF($W23="",0,$W23),0)),1,2),1) -> 2 | AK23: =OR(NOT(IFERROR(OR($L23="",AND($L23<>"",$L23>0,VLOOKUP($AB23,药材与丹炉!$N:$O,2,0)=6)),0)),AND($L23<>"",$L23>0,OR(VLOOKUP($AB23,药材与丹炉!$N:$Q,4,0)-2<$N23,$N23="")),AND($U23<>"",$U23>0,OR(VLOOKUP($AB23,药材与丹炉!$N:$Q,4,0)-3<$W23,$W23="")),NOT(OR(AND($Q23<>"",$S23<>"",VLOOKUP($AB23,药材与丹炉!$N:$Q,4,0)-3>=$S23),$P23="")),NOT(OR(AND($H23<>"",$J23<>"",VLOOKUP($AB23,药材与丹炉!$N:$Q,4,0)-1>=$J23),$G23="")),NOT(OR($U23="",AND($U23<>"",$U23>0))),NOT(OR($Y23="",IF($Z23<>"",IFERROR(IF(VLOOKUP($Z23,药材与丹炉!$B:$D,3,0)=-1,$X23=1,IF(VLOOKUP($Z23,药材与丹炉!$B:$D,3,0)=1,$X23=2,$X23=0)),0),0))),$AC23="爆炸",(VLOOKUP($AB23,药材与丹炉!$N:$O,2,0)+8)<$AD23) -> FALSE | AL23: 练气 | AM23: 2
A24: 5113 | B24: 2 | C24: 御剑丹 | D24: 50 | E24: 下场战斗开始时，获得【剑气】*1/丹毒+4 | F24: 6 | G24: 振气 | H24: 6 | I24: 火精枣 | J24: =IFERROR(CEILING($H24/VLOOKUP($I24,药材与丹炉!$B:$H,COLUMN(药材与丹炉!$H24)-1,0),1),"") -> 2 | K24: 振气 | L24: =IFERROR(IF($F24-$H24=0,"",$F24-$H24),"") | N24: =IFERROR(CEILING($L24/VLOOKUP($M24,药材与丹炉!$B:$H,COLUMN(药材与丹炉!$H24)-1,0),1),"") | O24: 12 | P24: 剑意 | Q24: 12 | R24: 剑芦 | S24: =IFERROR(CEILING($Q24/VLOOKUP($R24,药材与丹炉!$B:$H,COLUMN(药材与丹炉!$H24)-1,0),1),"") -> 4 | T24: =P24 -> 剑意 | U24: =IFERROR(IF($O24-$Q24=0,"",$O24-$Q24),"") | W24: =IFERROR(CEILING($U24/VLOOKUP($V24,药材与丹炉!$B:$H,COLUMN(药材与丹炉!$H24)-1,0),1),"") | X24: =IF(IFERROR(IF(AND($J24>0,$J24<>""),VLOOKUP($I24,药材与丹炉!$B:$D,3,0),0),0)+IFERROR(IF(AND($N24>0,$N24<>""),VLOOKUP($M24,药材与丹炉!$B:$D,3,0),0),0)+IFERROR(IF(AND($S24>0,$S24<>""),VLOOKUP($R24,药材与丹炉!$B:$D,3,0),0),0)+IFERROR(IF(AND($W24>0,$W24<>""),VLOOKUP($V24,药材与丹炉!$B:$D,3,0),0),0)>0,1,IF(IFERROR(IF(AND($J24>0,$J24<>""),VLOOKUP($I24,药材与丹炉!$B:$D,3,0),0),0)+IFERROR(IF(AND($N24>0,$N24<>""),VLOOKUP($M24,药材与丹炉!$B:$D,3,0),0),0)+IFERROR(IF(AND($S24>0,$S24<>""),VLOOKUP($R24,药材与丹炉!$B:$D,3,0),0),0)+IFERROR(IF(AND($W24>0,$W24<>""),VLOOKUP($V24,药材与丹炉!$B:$D,3,0),0),0)<0,2,0)) -> 1 | Y24: 3 | Z24: 宁神花 | AA24: =IFERROR($Y24/VLOOKUP($Z24,药材与丹炉!$B:$H,COLUMN(药材与丹炉!$H24)-1,0),"") -> 3 | AB24: 陨铁炉 | AC24: =IFERROR(IF($B24-VLOOKUP($AB24,药材与丹炉!$N:$P,2,0)<0,IF($AO$1="是",0,1),IF($B24-VLOOKUP($AB24,药材与丹炉!$N:$P,2,0)=0,2,IF($B24-VLOOKUP($AB24,药材与丹炉!$N:$P,2,0)=1,40,IF($B24-VLOOKUP($AB24,药材与丹炉!$N:$P,2,0)=2,80,"爆炸")))),"") -> 2 | AD24: =IFERROR($J24+IFERROR(IF($N24="",0,$N24),0)+IFERROR(IF($S24="",0,$S24),0)+IFERROR(IF($W24="",0,$W24),0)+IFERROR(IF($AA24="",0,$AA24),0),"") -> 9 | AE24: =IFERROR($J24*VLOOKUP($I24,药材与丹炉!$B:$K,10,0),0)+IFERROR($N24*VLOOKUP($M24,药材与丹炉!$B:$K,10,0),0)+IFERROR($S24*VLOOKUP($R24,药材与丹炉!$B:$K,10,0),0)+IFERROR($W24*VLOOKUP($V24,药材与丹炉!$B:$K,10,0),0)+IFERROR($AA24*VLOOKUP($Z24,药材与丹炉!$B:$K,10,0),0)+IFERROR($AC24*VLOOKUP($AB24,药材与丹炉!$N:$P,3,0)/100,0) -> 267 | AF24: 281 | AG24: =$AF24-$AE24 -> 14 | AH24: =$AF24*$AM$1*$AM$21 -> 562 | AI24: =$AH24-$AE24 -> 295 | AJ24: =IFERROR(IF($Y24/VLOOKUP($Y24,药材与丹炉!$T:$U,2,0)<=(VLOOKUP($AB24,药材与丹炉!$N:$O,2,0)+8)-($J24+IFERROR(IF($N24="",0,$N24),0)+IFERROR(IF($S24="",0,$S24),0)+IFERROR(IF($W24="",0,$W24),0)),1,2),1) -> 1 | AK24: =OR(NOT(IFERROR(OR($L24="",AND($L24<>"",$L24>0,VLOOKUP($AB24,药材与丹炉!$N:$O,2,0)=6)),0)),AND($L24<>"",$L24>0,OR(VLOOKUP($AB24,药材与丹炉!$N:$Q,4,0)-2<$N24,$N24="")),AND($U24<>"",$U24>0,OR(VLOOKUP($AB24,药材与丹炉!$N:$Q,4,0)-3<$W24,$W24="")),NOT(OR(AND($Q24<>"",$S24<>"",VLOOKUP($AB24,药材与丹炉!$N:$Q,4,0)-3>=$S24),$P24="")),NOT(OR(AND($H24<>"",$J24<>"",VLOOKUP($AB24,药材与丹炉!$N:$Q,4,0)-1>=$J24),$G24="")),NOT(OR($U24="",AND($U24<>"",$U24>0))),NOT(OR($Y24="",IF($Z24<>"",IFERROR(IF(VLOOKUP($Z24,药材与丹炉!$B:$D,3,0)=-1,$X24=1,IF(VLOOKUP($Z24,药材与丹炉!$B:$D,3,0)=1,$X24=2,$X24=0)),0),0))),$AC24="爆炸",(VLOOKUP($AB24,药材与丹炉!$N:$O,2,0)+8)<$AD24) -> FALSE | AL24: 筑基 | AM24: 3
A25: 5114 | B25: 2 | C25: 真金丹 | D25: 50 | E25: 下场战斗开始时，获得【易伤】*1，金系灵根权重+10/丹毒+4 | F25: 9 | G25: 振气 | H25: 9 | I25: 夏枯草 | J25: =IFERROR(CEILING($H25/VLOOKUP($I25,药材与丹炉!$B:$H,COLUMN(药材与丹炉!$H25)-1,0),1),"") -> 3 | K25: 振气 | L25: =IFERROR(IF($F25-$H25=0,"",$F25-$H25),"") | N25: =IFERROR(CEILING($L25/VLOOKUP($M25,药材与丹炉!$B:$H,COLUMN(药材与丹炉!$H25)-1,0),1),"") | O25: 6 | P25: 强金 | Q25: 6 | R25: 罗犀草 | S25: =IFERROR(CEILING($Q25/VLOOKUP($R25,药材与丹炉!$B:$H,COLUMN(药材与丹炉!$H25)-1,0),1),"") -> 2 | T25: =P25 -> 强金 | U25: =IFERROR(IF($O25-$Q25=0,"",$O25-$Q25),"") | W25: =IFERROR(CEILING($U25/VLOOKUP($V25,药材与丹炉!$B:$H,COLUMN(药材与丹炉!$H25)-1,0),1),"") | X25: =IF(IFERROR(IF(AND($J25>0,$J25<>""),VLOOKUP($I25,药材与丹炉!$B:$D,3,0),0),0)+IFERROR(IF(AND($N25>0,$N25<>""),VLOOKUP($M25,药材与丹炉!$B:$D,3,0),0),0)+IFERROR(IF(AND($S25>0,$S25<>""),VLOOKUP($R25,药材与丹炉!$B:$D,3,0),0),0)+IFERROR(IF(AND($W25>0,$W25<>""),VLOOKUP($V25,药材与丹炉!$B:$D,3,0),0),0)>0,1,IF(IFERROR(IF(AND($J25>0,$J25<>""),VLOOKUP($I25,药材与丹炉!$B:$D,3,0),0),0)+IFERROR(IF(AND($N25>0,$N25<>""),VLOOKUP($M25,药材与丹炉!$B:$D,3,0),0),0)+IFERROR(IF(AND($S25>0,$S25<>""),VLOOKUP($R25,药材与丹炉!$B:$D,3,0),0),0)+IFERROR(IF(AND($W25>0,$W25<>""),VLOOKUP($V25,药材与丹炉!$B:$D,3,0),0),0)<0,2,0)) -> 1 | Y25: 3 | Z25: 宁神花 | AA25: =IFERROR($Y25/VLOOKUP($Z25,药材与丹炉!$B:$H,COLUMN(药材与丹炉!$H25)-1,0),"") -> 3 | AB25: 陨铁炉 | AC25: =IFERROR(IF($B25-VLOOKUP($AB25,药材与丹炉!$N:$P,2,0)<0,IF($AO$1="是",0,1),IF($B25-VLOOKUP($AB25,药材与丹炉!$N:$P,2,0)=0,2,IF($B25-VLOOKUP($AB25,药材与丹炉!$N:$P,2,0)=1,40,IF($B25-VLOOKUP($AB25,药材与丹炉!$N:$P,2,0)=2,80,"爆炸")))),"") -> 2 | AD25: =IFERROR($J25+IFERROR(IF($N25="",0,$N25),0)+IFERROR(IF($S25="",0,$S25),0)+IFERROR(IF($W25="",0,$W25),0)+IFERROR(IF($AA25="",0,$AA25),0),"") -> 8 | AE25: =IFERROR($J25*VLOOKUP($I25,药材与丹炉!$B:$K,10,0),0)+IFERROR($N25*VLOOKUP($M25,药材与丹炉!$B:$K,10,0),0)+IFERROR($S25*VLOOKUP($R25,药材与丹炉!$B:$K,10,0),0)+IFERROR($W25*VLOOKUP($V25,药材与丹炉!$B:$K,10,0),0)+IFERROR($AA25*VLOOKUP($Z25,药材与丹炉!$B:$K,10,0),0)+IFERROR($AC25*VLOOKUP($AB25,药材与丹炉!$N:$P,3,0)/100,0) -> 231 | AF25: 281 | AG25: =$AF25-$AE25 -> 50 | AH25: =$AF25*$AM$1*$AM$21 -> 562 | AI25: =$AH25-$AE25 -> 331 | AJ25: =IFERROR(IF($Y25/VLOOKUP($Y25,药材与丹炉!$T:$U,2,0)<=(VLOOKUP($AB25,药材与丹炉!$N:$O,2,0)+8)-($J25+IFERROR(IF($N25="",0,$N25),0)+IFERROR(IF($S25="",0,$S25),0)+IFERROR(IF($W25="",0,$W25),0)),1,2),1) -> 1 | AK25: =OR(NOT(IFERROR(OR($L25="",AND($L25<>"",$L25>0,VLOOKUP($AB25,药材与丹炉!$N:$O,2,0)=6)),0)),AND($L25<>"",$L25>0,OR(VLOOKUP($AB25,药材与丹炉!$N:$Q,4,0)-2<$N25,$N25="")),AND($U25<>"",$U25>0,OR(VLOOKUP($AB25,药材与丹炉!$N:$Q,4,0)-3<$W25,$W25="")),NOT(OR(AND($Q25<>"",$S25<>"",VLOOKUP($AB25,药材与丹炉!$N:$Q,4,0)-3>=$S25),$P25="")),NOT(OR(AND($H25<>"",$J25<>"",VLOOKUP($AB25,药材与丹炉!$N:$Q,4,0)-1>=$J25),$G25="")),NOT(OR($U25="",AND($U25<>"",$U25>0))),NOT(OR($Y25="",IF($Z25<>"",IFERROR(IF(VLOOKUP($Z25,药材与丹炉!$B:$D,3,0)=-1,$X25=1,IF(VLOOKUP($Z25,药材与丹炉!$B:$D,3,0)=1,$X25=2,$X25=0)),0),0))),$AC25="爆炸",(VLOOKUP($AB25,药材与丹炉!$N:$O,2,0)+8)<$AD25) -> FALSE | AL25: 金丹 | AM25: 4
A26: 5115 | B26: 2 | C26: 森木丹 | D26: 50 | E26: 下场战斗开始时，获得【中毒】*1，木系灵根权重+10/丹毒+4 | F26: 9 | G26: 振气 | H26: 9 | I26: 夏枯草 | J26: =IFERROR(CEILING($H26/VLOOKUP($I26,药材与丹炉!$B:$H,COLUMN(药材与丹炉!$H26)-1,0),1),"") -> 3 | K26: 振气 | L26: =IFERROR(IF($F26-$H26=0,"",$F26-$H26),"") | N26: =IFERROR(CEILING($L26/VLOOKUP($M26,药材与丹炉!$B:$H,COLUMN(药材与丹炉!$H26)-1,0),1),"") | O26: 6 | P26: 强木 | Q26: 6 | R26: 风灵花 | S26: =IFERROR(CEILING($Q26/VLOOKUP($R26,药材与丹炉!$B:$H,COLUMN(药材与丹炉!$H26)-1,0),1),"") -> 2 | T26: =P26 -> 强木 | U26: =IFERROR(IF($O26-$Q26=0,"",$O26-$Q26),"") | W26: =IFERROR(CEILING($U26/VLOOKUP($V26,药材与丹炉!$B:$H,COLUMN(药材与丹炉!$H26)-1,0),1),"") | X26: =IF(IFERROR(IF(AND($J26>0,$J26<>""),VLOOKUP($I26,药材与丹炉!$B:$D,3,0),0),0)+IFERROR(IF(AND($N26>0,$N26<>""),VLOOKUP($M26,药材与丹炉!$B:$D,3,0),0),0)+IFERROR(IF(AND($S26>0,$S26<>""),VLOOKUP($R26,药材与丹炉!$B:$D,3,0),0),0)+IFERROR(IF(AND($W26>0,$W26<>""),VLOOKUP($V26,药材与丹炉!$B:$D,3,0),0),0)>0,1,IF(IFERROR(IF(AND($J26>0,$J26<>""),VLOOKUP($I26,药材与丹炉!$B:$D,3,0),0),0)+IFERROR(IF(AND($N26>0,$N26<>""),VLOOKUP($M26,药材与丹炉!$B:$D,3,0),0),0)+IFERROR(IF(AND($S26>0,$S26<>""),VLOOKUP($R26,药材与丹炉!$B:$D,3,0),0),0)+IFERROR(IF(AND($W26>0,$W26<>""),VLOOKUP($V26,药材与丹炉!$B:$D,3,0),0),0)<0,2,0)) -> 1 | Y26: 3 | Z26: 宁神花 | AA26: =IFERROR($Y26/VLOOKUP($Z26,药材与丹炉!$B:$H,COLUMN(药材与丹炉!$H26)-1,0),"") -> 3 | AB26: 陨铁炉 | AC26: =IFERROR(IF($B26-VLOOKUP($AB26,药材与丹炉!$N:$P,2,0)<0,IF($AO$1="是",0,1),IF($B26-VLOOKUP($AB26,药材与丹炉!$N:$P,2,0)=0,2,IF($B26-VLOOKUP($AB26,药材与丹炉!$N:$P,2,0)=1,40,IF($B26-VLOOKUP($AB26,药材与丹炉!$N:$P,2,0)=2,80,"爆炸")))),"") -> 2 | AD26: =IFERROR($J26+IFERROR(IF($N26="",0,$N26),0)+IFERROR(IF($S26="",0,$S26),0)+IFERROR(IF($W26="",0,$W26),0)+IFERROR(IF($AA26="",0,$AA26),0),"") -> 8 | AE26: =IFERROR($J26*VLOOKUP($I26,药材与丹炉!$B:$K,10,0),0)+IFERROR($N26*VLOOKUP($M26,药材与丹炉!$B:$K,10,0),0)+IFERROR($S26*VLOOKUP($R26,药材与丹炉!$B:$K,10,0),0)+IFERROR($W26*VLOOKUP($V26,药材与丹炉!$B:$K,10,0),0)+IFERROR($AA26*VLOOKUP($Z26,药材与丹炉!$B:$K,10,0),0)+IFERROR($AC26*VLOOKUP($AB26,药材与丹炉!$N:$P,3,0)/100,0) -> 231 | AF26: 281 | AG26: =$AF26-$AE26 -> 50 | AH26: =$AF26*$AM$1*$AM$21 -> 562 | AI26: =$AH26-$AE26 -> 331 | AJ26: =IFERROR(IF($Y26/VLOOKUP($Y26,药材与丹炉!$T:$U,2,0)<=(VLOOKUP($AB26,药材与丹炉!$N:$O,2,0)+8)-($J26+IFERROR(IF($N26="",0,$N26),0)+IFERROR(IF($S26="",0,$S26),0)+IFERROR(IF($W26="",0,$W26),0)),1,2),1) -> 1 | AK26: =OR(NOT(IFERROR(OR($L26="",AND($L26<>"",$L26>0,VLOOKUP($AB26,药材与丹炉!$N:$O,2,0)=6)),0)),AND($L26<>"",$L26>0,OR(VLOOKUP($AB26,药材与丹炉!$N:$Q,4,0)-2<$N26,$N26="")),AND($U26<>"",$U26>0,OR(VLOOKUP($AB26,药材与丹炉!$N:$Q,4,0)-3<$W26,$W26="")),NOT(OR(AND($Q26<>"",$S26<>"",VLOOKUP($AB26,药材与丹炉!$N:$Q,4,0)-3>=$S26),$P26="")),NOT(OR(AND($H26<>"",$J26<>"",VLOOKUP($AB26,药材与丹炉!$N:$Q,4,0)-1>=$J26),$G26="")),NOT(OR($U26="",AND($U26<>"",$U26>0))),NOT(OR($Y26="",IF($Z26<>"",IFERROR(IF(VLOOKUP($Z26,药材与丹炉!$B:$D,3,0)=-1,$X26=1,IF(VLOOKUP($Z26,药材与丹炉!$B:$D,3,0)=1,$X26=2,$X26=0)),0),0))),$AC26="爆炸",(VLOOKUP($AB26,药材与丹炉!$N:$O,2,0)+8)<$AD26) -> FALSE | AL26: 元婴 | AM26: 5
A27: 5116 | B27: 2 | C27: 生水丹 | D27: 50 | E27: 下场战斗开始时，获得【霜冻】*1，水系灵根权重+10/丹毒+4 | F27: 9 | G27: 振气 | H27: 9 | I27: 夏枯草 | J27: =IFERROR(CEILING($H27/VLOOKUP($I27,药材与丹炉!$B:$H,COLUMN(药材与丹炉!$H27)-1,0),1),"") -> 3 | K27: 振气 | L27: =IFERROR(IF($F27-$H27=0,"",$F27-$H27),"") | N27: =IFERROR(CEILING($L27/VLOOKUP($M27,药材与丹炉!$B:$H,COLUMN(药材与丹炉!$H27)-1,0),1),"") | O27: 6 | P27: 强水 | Q27: 6 | R27: 弗兰草 | S27: =IFERROR(CEILING($Q27/VLOOKUP($R27,药材与丹炉!$B:$H,COLUMN(药材与丹炉!$H27)-1,0),1),"") -> 2 | T27: =P27 -> 强水 | U27: =IFERROR(IF($O27-$Q27=0,"",$O27-$Q27),"") | W27: =IFERROR(CEILING($U27/VLOOKUP($V27,药材与丹炉!$B:$H,COLUMN(药材与丹炉!$H27)-1,0),1),"") | X27: =IF(IFERROR(IF(AND($J27>0,$J27<>""),VLOOKUP($I27,药材与丹炉!$B:$D,3,0),0),0)+IFERROR(IF(AND($N27>0,$N27<>""),VLOOKUP($M27,药材与丹炉!$B:$D,3,0),0),0)+IFERROR(IF(AND($S27>0,$S27<>""),VLOOKUP($R27,药材与丹炉!$B:$D,3,0),0),0)+IFERROR(IF(AND($W27>0,$W27<>""),VLOOKUP($V27,药材与丹炉!$B:$D,3,0),0),0)>0,1,IF(IFERROR(IF(AND($J27>0,$J27<>""),VLOOKUP($I27,药材与丹炉!$B:$D,3,0),0),0)+IFERROR(IF(AND($N27>0,$N27<>""),VLOOKUP($M27,药材与丹炉!$B:$D,3,0),0),0)+IFERROR(IF(AND($S27>0,$S27<>""),VLOOKUP($R27,药材与丹炉!$B:$D,3,0),0),0)+IFERROR(IF(AND($W27>0,$W27<>""),VLOOKUP($V27,药材与丹炉!$B:$D,3,0),0),0)<0,2,0)) -> 0 | Y27: 3 | Z27: 恒心草 | AA27: =IFERROR($Y27/VLOOKUP($Z27,药材与丹炉!$B:$H,COLUMN(药材与丹炉!$H27)-1,0),"") -> 3 | AB27: 陨铁炉 | AC27: =IFERROR(IF($B27-VLOOKUP($AB27,药材与丹炉!$N:$P,2,0)<0,IF($AO$1="是",0,1),IF($B27-VLOOKUP($AB27,药材与丹炉!$N:$P,2,0)=0,2,IF($B27-VLOOKUP($AB27,药材与丹炉!$N:$P,2,0)=1,40,IF($B27-VLOOKUP($AB27,药材与丹炉!$N:$P,2,0)=2,80,"爆炸")))),"") -> 2 | AD27: =IFERROR($J27+IFERROR(IF($N27="",0,$N27),0)+IFERROR(IF($S27="",0,$S27),0)+IFERROR(IF($W27="",0,$W27),0)+IFERROR(IF($AA27="",0,$AA27),0),"") -> 8 | AE27: =IFERROR($J27*VLOOKUP($I27,药材与丹炉!$B:$K,10,0),0)+IFERROR($N27*VLOOKUP($M27,药材与丹炉!$B:$K,10,0),0)+IFERROR($S27*VLOOKUP($R27,药材与丹炉!$B:$K,10,0),0)+IFERROR($W27*VLOOKUP($V27,药材与丹炉!$B:$K,10,0),0)+IFERROR($AA27*VLOOKUP($Z27,药材与丹炉!$B:$K,10,0),0)+IFERROR($AC27*VLOOKUP($AB27,药材与丹炉!$N:$P,3,0)/100,0) -> 231 | AF27: 281 | AG27: =$AF27-$AE27 -> 50 | AH27: =$AF27*$AM$1*$AM$21 -> 562 | AI27: =$AH27-$AE27 -> 331 | AJ27: =IFERROR(IF($Y27/VLOOKUP($Y27,药材与丹炉!$T:$U,2,0)<=(VLOOKUP($AB27,药材与丹炉!$N:$O,2,0)+8)-($J27+IFERROR(IF($N27="",0,$N27),0)+IFERROR(IF($S27="",0,$S27),0)+IFERROR(IF($W27="",0,$W27),0)),1,2),1) -> 1 | AK27: =OR(NOT(IFERROR(OR($L27="",AND($L27<>"",$L27>0,VLOOKUP($AB27,药材与丹炉!$N:$O,2,0)=6)),0)),AND($L27<>"",$L27>0,OR(VLOOKUP($AB27,药材与丹炉!$N:$Q,4,0)-2<$N27,$N27="")),AND($U27<>"",$U27>0,OR(VLOOKUP($AB27,药材与丹炉!$N:$Q,4,0)-3<$W27,$W27="")),NOT(OR(AND($Q27<>"",$S27<>"",VLOOKUP($AB27,药材与丹炉!$N:$Q,4,0)-3>=$S27),$P27="")),NOT(OR(AND($H27<>"",$J27<>"",VLOOKUP($AB27,药材与丹炉!$N:$Q,4,0)-1>=$J27),$G27="")),NOT(OR($U27="",AND($U27<>"",$U27>0))),NOT(OR($Y27="",IF($Z27<>"",IFERROR(IF(VLOOKUP($Z27,药材与丹炉!$B:$D,3,0)=-1,$X27=1,IF(VLOOKUP($Z27,药材与丹炉!$B:$D,3,0)=1,$X27=2,$X27=0)),0),0))),$AC27="爆炸",(VLOOKUP($AB27,药材与丹炉!$N:$O,2,0)+8)<$AD27) -> FALSE | AL27: 化神 | AM27: 6
A28: 5117 | B28: 2 | C28: 聚火丹 | D28: 50 | E28: 下场战斗开始时，获得【灼烧】*1，火系灵根权重+10/丹毒+4 | F28: 9 | G28: 振气 | H28: 9 | I28: 夏枯草 | J28: =IFERROR(CEILING($H28/VLOOKUP($I28,药材与丹炉!$B:$H,COLUMN(药材与丹炉!$H28)-1,0),1),"") -> 3 | K28: 振气 | L28: =IFERROR(IF($F28-$H28=0,"",$F28-$H28),"") | N28: =IFERROR(CEILING($L28/VLOOKUP($M28,药材与丹炉!$B:$H,COLUMN(药材与丹炉!$H28)-1,0),1),"") | O28: 6 | P28: 强火 | Q28: 6 | R28: 火精枣 | S28: =IFERROR(CEILING($Q28/VLOOKUP($R28,药材与丹炉!$B:$H,COLUMN(药材与丹炉!$H28)-1,0),1),"") -> 2 | T28: =P28 -> 强火 | U28: =IFERROR(IF($O28-$Q28=0,"",$O28-$Q28),"") | W28: =IFERROR(CEILING($U28/VLOOKUP($V28,药材与丹炉!$B:$H,COLUMN(药材与丹炉!$H28)-1,0),1),"") | X28: =IF(IFERROR(IF(AND($J28>0,$J28<>""),VLOOKUP($I28,药材与丹炉!$B:$D,3,0),0),0)+IFERROR(IF(AND($N28>0,$N28<>""),VLOOKUP($M28,药材与丹炉!$B:$D,3,0),0),0)+IFERROR(IF(AND($S28>0,$S28<>""),VLOOKUP($R28,药材与丹炉!$B:$D,3,0),0),0)+IFERROR(IF(AND($W28>0,$W28<>""),VLOOKUP($V28,药材与丹炉!$B:$D,3,0),0),0)>0,1,IF(IFERROR(IF(AND($J28>0,$J28<>""),VLOOKUP($I28,药材与丹炉!$B:$D,3,0),0),0)+IFERROR(IF(AND($N28>0,$N28<>""),VLOOKUP($M28,药材与丹炉!$B:$D,3,0),0),0)+IFERROR(IF(AND($S28>0,$S28<>""),VLOOKUP($R28,药材与丹炉!$B:$D,3,0),0),0)+IFERROR(IF(AND($W28>0,$W28<>""),VLOOKUP($V28,药材与丹炉!$B:$D,3,0),0),0)<0,2,0)) -> 1 | Y28: 3 | Z28: 宁神花 | AA28: =IFERROR($Y28/VLOOKUP($Z28,药材与丹炉!$B:$H,COLUMN(药材与丹炉!$H28)-1,0),"") -> 3 | AB28: 陨铁炉 | AC28: =IFERROR(IF($B28-VLOOKUP($AB28,药材与丹炉!$N:$P,2,0)<0,IF($AO$1="是",0,1),IF($B28-VLOOKUP($AB28,药材与丹炉!$N:$P,2,0)=0,2,IF($B28-VLOOKUP($AB28,药材与丹炉!$N:$P,2,0)=1,40,IF($B28-VLOOKUP($AB28,药材与丹炉!$N:$P,2,0)=2,80,"爆炸")))),"") -> 2 | AD28: =IFERROR($J28+IFERROR(IF($N28="",0,$N28),0)+IFERROR(IF($S28="",0,$S28),0)+IFERROR(IF($W28="",0,$W28),0)+IFERROR(IF($AA28="",0,$AA28),0),"") -> 8 | AE28: =IFERROR($J28*VLOOKUP($I28,药材与丹炉!$B:$K,10,0),0)+IFERROR($N28*VLOOKUP($M28,药材与丹炉!$B:$K,10,0),0)+IFERROR($S28*VLOOKUP($R28,药材与丹炉!$B:$K,10,0),0)+IFERROR($W28*VLOOKUP($V28,药材与丹炉!$B:$K,10,0),0)+IFERROR($AA28*VLOOKUP($Z28,药材与丹炉!$B:$K,10,0),0)+IFERROR($AC28*VLOOKUP($AB28,药材与丹炉!$N:$P,3,0)/100,0) -> 231 | AF28: 281 | AG28: =$AF28-$AE28 -> 50 | AH28: =$AF28*$AM$1*$AM$21 -> 562 | AI28: =$AH28-$AE28 -> 331 | AJ28: =IFERROR(IF($Y28/VLOOKUP($Y28,药材与丹炉!$T:$U,2,0)<=(VLOOKUP($AB28,药材与丹炉!$N:$O,2,0)+8)-($J28+IFERROR(IF($N28="",0,$N28),0)+IFERROR(IF($S28="",0,$S28),0)+IFERROR(IF($W28="",0,$W28),0)),1,2),1) -> 1 | AK28: =OR(NOT(IFERROR(OR($L28="",AND($L28<>"",$L28>0,VLOOKUP($AB28,药材与丹炉!$N:$O,2,0)=6)),0)),AND($L28<>"",$L28>0,OR(VLOOKUP($AB28,药材与丹炉!$N:$Q,4,0)-2<$N28,$N28="")),AND($U28<>"",$U28>0,OR(VLOOKUP($AB28,药材与丹炉!$N:$Q,4,0)-3<$W28,$W28="")),NOT(OR(AND($Q28<>"",$S28<>"",VLOOKUP($AB28,药材与丹炉!$N:$Q,4,0)-3>=$S28),$P28="")),NOT(OR(AND($H28<>"",$J28<>"",VLOOKUP($AB28,药材与丹炉!$N:$Q,4,0)-1>=$J28),$G28="")),NOT(OR($U28="",AND($U28<>"",$U28>0))),NOT(OR($Y28="",IF($Z28<>"",IFERROR(IF(VLOOKUP($Z28,药材与丹炉!$B:$D,3,0)=-1,$X28=1,IF(VLOOKUP($Z28,药材与丹炉!$B:$D,3,0)=1,$X28=2,$X28=0)),0),0))),$AC28="爆炸",(VLOOKUP($AB28,药材与丹炉!$N:$O,2,0)+8)<$AD28) -> FALSE
A29: 5118 | B29: 2 | C29: 玄土丹 | D29: 50 | E29: 下场战斗开始时，获得【滞气】*1，土系灵根权重+10/丹毒+4 | F29: 9 | G29: 振气 | H29: 9 | I29: 夏枯草 | J29: =IFERROR(CEILING($H29/VLOOKUP($I29,药材与丹炉!$B:$H,COLUMN(药材与丹炉!$H29)-1,0),1),"") -> 3 | K29: 振气 | L29: =IFERROR(IF($F29-$H29=0,"",$F29-$H29),"") | N29: =IFERROR(CEILING($L29/VLOOKUP($M29,药材与丹炉!$B:$H,COLUMN(药材与丹炉!$H29)-1,0),1),"") | O29: 6 | P29: 强土 | Q29: 6 | R29: 地黄参 | S29: =IFERROR(CEILING($Q29/VLOOKUP($R29,药材与丹炉!$B:$H,COLUMN(药材与丹炉!$H29)-1,0),1),"") -> 2 | T29: =P29 -> 强土 | U29: =IFERROR(IF($O29-$Q29=0,"",$O29-$Q29),"") | W29: =IFERROR(CEILING($U29/VLOOKUP($V29,药材与丹炉!$B:$H,COLUMN(药材与丹炉!$H29)-1,0),1),"") | X29: =IF(IFERROR(IF(AND($J29>0,$J29<>""),VLOOKUP($I29,药材与丹炉!$B:$D,3,0),0),0)+IFERROR(IF(AND($N29>0,$N29<>""),VLOOKUP($M29,药材与丹炉!$B:$D,3,0),0),0)+IFERROR(IF(AND($S29>0,$S29<>""),VLOOKUP($R29,药材与丹炉!$B:$D,3,0),0),0)+IFERROR(IF(AND($W29>0,$W29<>""),VLOOKUP($V29,药材与丹炉!$B:$D,3,0),0),0)>0,1,IF(IFERROR(IF(AND($J29>0,$J29<>""),VLOOKUP($I29,药材与丹炉!$B:$D,3,0),0),0)+IFERROR(IF(AND($N29>0,$N29<>""),VLOOKUP($M29,药材与丹炉!$B:$D,3,0),0),0)+IFERROR(IF(AND($S29>0,$S29<>""),VLOOKUP($R29,药材与丹炉!$B:$D,3,0),0),0)+IFERROR(IF(AND($W29>0,$W29<>""),VLOOKUP($V29,药材与丹炉!$B:$D,3,0),0),0)<0,2,0)) -> 1 | Y29: 3 | Z29: 宁神花 | AA29: =IFERROR($Y29/VLOOKUP($Z29,药材与丹炉!$B:$H,COLUMN(药材与丹炉!$H29)-1,0),"") -> 3 | AB29: 陨铁炉 | AC29: =IFERROR(IF($B29-VLOOKUP($AB29,药材与丹炉!$N:$P,2,0)<0,IF($AO$1="是",0,1),IF($B29-VLOOKUP($AB29,药材与丹炉!$N:$P,2,0)=0,2,IF($B29-VLOOKUP($AB29,药材与丹炉!$N:$P,2,0)=1,40,IF($B29-VLOOKUP($AB29,药材与丹炉!$N:$P,2,0)=2,80,"爆炸")))),"") -> 2 | AD29: =IFERROR($J29+IFERROR(IF($N29="",0,$N29),0)+IFERROR(IF($S29="",0,$S29),0)+IFERROR(IF($W29="",0,$W29),0)+IFERROR(IF($AA29="",0,$AA29),0),"") -> 8 | AE29: =IFERROR($J29*VLOOKUP($I29,药材与丹炉!$B:$K,10,0),0)+IFERROR($N29*VLOOKUP($M29,药材与丹炉!$B:$K,10,0),0)+IFERROR($S29*VLOOKUP($R29,药材与丹炉!$B:$K,10,0),0)+IFERROR($W29*VLOOKUP($V29,药材与丹炉!$B:$K,10,0),0)+IFERROR($AA29*VLOOKUP($Z29,药材与丹炉!$B:$K,10,0),0)+IFERROR($AC29*VLOOKUP($AB29,药材与丹炉!$N:$P,3,0)/100,0) -> 231 | AF29: 281 | AG29: =$AF29-$AE29 -> 50 | AH29: =$AF29*$AM$1*$AM$21 -> 562 | AI29: =$AH29-$AE29 -> 331 | AJ29: =IFERROR(IF($Y29/VLOOKUP($Y29,药材与丹炉!$T:$U,2,0)<=(VLOOKUP($AB29,药材与丹炉!$N:$O,2,0)+8)-($J29+IFERROR(IF($N29="",0,$N29),0)+IFERROR(IF($S29="",0,$S29),0)+IFERROR(IF($W29="",0,$W29),0)),1,2),1) -> 1 | AK29: =OR(NOT(IFERROR(OR($L29="",AND($L29<>"",$L29>0,VLOOKUP($AB29,药材与丹炉!$N:$O,2,0)=6)),0)),AND($L29<>"",$L29>0,OR(VLOOKUP($AB29,药材与丹炉!$N:$Q,4,0)-2<$N29,$N29="")),AND($U29<>"",$U29>0,OR(VLOOKUP($AB29,药材与丹炉!$N:$Q,4,0)-3<$W29,$W29="")),NOT(OR(AND($Q29<>"",$S29<>"",VLOOKUP($AB29,药材与丹炉!$N:$Q,4,0)-3>=$S29),$P29="")),NOT(OR(AND($H29<>"",$J29<>"",VLOOKUP($AB29,药材与丹炉!$N:$Q,4,0)-1>=$J29),$G29="")),NOT(OR($U29="",AND($U29<>"",$U29>0))),NOT(OR($Y29="",IF($Z29<>"",IFERROR(IF(VLOOKUP($Z29,药材与丹炉!$B:$D,3,0)=-1,$X29=1,IF(VLOOKUP($Z29,药材与丹炉!$B:$D,3,0)=1,$X29=2,$X29=0)),0),0))),$AC29="爆炸",(VLOOKUP($AB29,药材与丹炉!$N:$O,2,0)+8)<$AD29) -> FALSE
A30: 5119 | B30: 2 | C30: 续命丹 | D30: 2 | E30: 寿元+5/丹毒+10 | F30: 9 | G30: 聚元 | H30: 9 | I30: 夜交藤 | J30: =IFERROR(CEILING($H30/VLOOKUP($I30,药材与丹炉!$B:$H,COLUMN(药材与丹炉!$H30)-1,0),1),"") -> 3 | K30: 聚元 | L30: =IFERROR(IF($F30-$H30=0,"",$F30-$H30),"") | N30: =IFERROR(CEILING($L30/VLOOKUP($M30,药材与丹炉!$B:$H,COLUMN(药材与丹炉!$H30)-1,0),1),"") | O30: 27 | P30: 益寿 | Q30: 27 | R30: 玉龙参 | S30: =IFERROR(CEILING($Q30/VLOOKUP($R30,药材与丹炉!$B:$H,COLUMN(药材与丹炉!$H30)-1,0),1),"") -> 3 | T30: =P30 -> 益寿 | U30: =IFERROR(IF($O30-$Q30=0,"",$O30-$Q30),"") | W30: =IFERROR(CEILING($U30/VLOOKUP($V30,药材与丹炉!$B:$H,COLUMN(药材与丹炉!$H30)-1,0),1),"") | X30: =IF(IFERROR(IF(AND($J30>0,$J30<>""),VLOOKUP($I30,药材与丹炉!$B:$D,3,0),0),0)+IFERROR(IF(AND($N30>0,$N30<>""),VLOOKUP($M30,药材与丹炉!$B:$D,3,0),0),0)+IFERROR(IF(AND($S30>0,$S30<>""),VLOOKUP($R30,药材与丹炉!$B:$D,3,0),0),0)+IFERROR(IF(AND($W30>0,$W30<>""),VLOOKUP($V30,药材与丹炉!$B:$D,3,0),0),0)>0,1,IF(IFERROR(IF(AND($J30>0,$J30<>""),VLOOKUP($I30,药材与丹炉!$B:$D,3,0),0),0)+IFERROR(IF(AND($N30>0,$N30<>""),VLOOKUP($M30,药材与丹炉!$B:$D,3,0),0),0)+IFERROR(IF(AND($S30>0,$S30<>""),VLOOKUP($R30,药材与丹炉!$B:$D,3,0),0),0)+IFERROR(IF(AND($W30>0,$W30<>""),VLOOKUP($V30,药材与丹炉!$B:$D,3,0),0),0)<0,2,0)) -> 2 | Y30: 3 | Z30: 流莹草 | AA30: =IFERROR($Y30/VLOOKUP($Z30,药材与丹炉!$B:$H,COLUMN(药材与丹炉!$H30)-1,0),"") -> 3 | AB30: 陨铁炉 | AC30: =IFERROR(IF($B30-VLOOKUP($AB30,药材与丹炉!$N:$P,2,0)<0,IF($AO$1="是",0,1),IF($B30-VLOOKUP($AB30,药材与丹炉!$N:$P,2,0)=0,2,IF($B30-VLOOKUP($AB30,药材与丹炉!$N:$P,2,0)=1,40,IF($B30-VLOOKUP($AB30,药材与丹炉!$N:$P,2,0)=2,80,"爆炸")))),"") -> 2 | AD30: =IFERROR($J30+IFERROR(IF($N30="",0,$N30),0)+IFERROR(IF($S30="",0,$S30),0)+IFERROR(IF($W30="",0,$W30),0)+IFERROR(IF($AA30="",0,$AA30),0),"") -> 9 | AE30: =IFERROR($J30*VLOOKUP($I30,药材与丹炉!$B:$K,10,0),0)+IFERROR($N30*VLOOKUP($M30,药材与丹炉!$B:$K,10,0),0)+IFERROR($S30*VLOOKUP($R30,药材与丹炉!$B:$K,10,0),0)+IFERROR($W30*VLOOKUP($V30,药材与丹炉!$B:$K,10,0),0)+IFERROR($AA30*VLOOKUP($Z30,药材与丹炉!$B:$K,10,0),0)+IFERROR($AC30*VLOOKUP($AB30,药材与丹炉!$N:$P,3,0)/100,0) -> 1374 | AF30: 1281 | AG30: =$AF30-$AE30 -> -93 | AH30: =$AF30*$AM$1*$AM$21 -> 2562 | AI30: =$AH30-$AE30 -> 1188 | AJ30: =IFERROR(IF($Y30/VLOOKUP($Y30,药材与丹炉!$T:$U,2,0)<=(VLOOKUP($AB30,药材与丹炉!$N:$O,2,0)+8)-($J30+IFERROR(IF($N30="",0,$N30),0)+IFERROR(IF($S30="",0,$S30),0)+IFERROR(IF($W30="",0,$W30),0)),1,2),1) -> 1 | AK30: =OR(NOT(IFERROR(OR($L30="",AND($L30<>"",$L30>0,VLOOKUP($AB30,药材与丹炉!$N:$O,2,0)=6)),0)),AND($L30<>"",$L30>0,OR(VLOOKUP($AB30,药材与丹炉!$N:$Q,4,0)-2<$N30,$N30="")),AND($U30<>"",$U30>0,OR(VLOOKUP($AB30,药材与丹炉!$N:$Q,4,0)-3<$W30,$W30="")),NOT(OR(AND($Q30<>"",$S30<>"",VLOOKUP($AB30,药材与丹炉!$N:$Q,4,0)-3>=$S30),$P30="")),NOT(OR(AND($H30<>"",$J30<>"",VLOOKUP($AB30,药材与丹炉!$N:$Q,4,0)-1>=$J30),$G30="")),NOT(OR($U30="",AND($U30<>"",$U30>0))),NOT(OR($Y30="",IF($Z30<>"",IFERROR(IF(VLOOKUP($Z30,药材与丹炉!$B:$D,3,0)=-1,$X30=1,IF(VLOOKUP($Z30,药材与丹炉!$B:$D,3,0)=1,$X30=2,$X30=0)),0),0))),$AC30="爆炸",(VLOOKUP($AB30,药材与丹炉!$N:$O,2,0)+8)<$AD30) -> FALSE
A31: 5120 | B31: 2 | C31: 炼甲丹 | D31: 50 | E31: 下场战斗开始时，获得【护罩】*5/丹毒+5 | F31: 9 | G31: 御气 | H31: 9 | I31: 地黄参 | J31: =IFERROR(CEILING($H31/VLOOKUP($I31,药材与丹炉!$B:$H,COLUMN(药材与丹炉!$H31)-1,0),1),"") -> 3 | K31: 御气 | L31: =IFERROR(IF($F31-$H31=0,"",$F31-$H31),"") | N31: =IFERROR(CEILING($L31/VLOOKUP($M31,药材与丹炉!$B:$H,COLUMN(药材与丹炉!$H31)-1,0),1),"") | O31: 9 | P31: 固元 | Q31: 9 | R31: 何首乌 | S31: =IFERROR(CEILING($Q31/VLOOKUP($R31,药材与丹炉!$B:$H,COLUMN(药材与丹炉!$H31)-1,0),1),"") -> 3 | T31: =P31 -> 固元 | U31: =IFERROR(IF($O31-$Q31=0,"",$O31-$Q31),"") | W31: =IFERROR(CEILING($U31/VLOOKUP($V31,药材与丹炉!$B:$H,COLUMN(药材与丹炉!$H31)-1,0),1),"") | X31: =IF(IFERROR(IF(AND($J31>0,$J31<>""),VLOOKUP($I31,药材与丹炉!$B:$D,3,0),0),0)+IFERROR(IF(AND($N31>0,$N31<>""),VLOOKUP($M31,药材与丹炉!$B:$D,3,0),0),0)+IFERROR(IF(AND($S31>0,$S31<>""),VLOOKUP($R31,药材与丹炉!$B:$D,3,0),0),0)+IFERROR(IF(AND($W31>0,$W31<>""),VLOOKUP($V31,药材与丹炉!$B:$D,3,0),0),0)>0,1,IF(IFERROR(IF(AND($J31>0,$J31<>""),VLOOKUP($I31,药材与丹炉!$B:$D,3,0),0),0)+IFERROR(IF(AND($N31>0,$N31<>""),VLOOKUP($M31,药材与丹炉!$B:$D,3,0),0),0)+IFERROR(IF(AND($S31>0,$S31<>""),VLOOKUP($R31,药材与丹炉!$B:$D,3,0),0),0)+IFERROR(IF(AND($W31>0,$W31<>""),VLOOKUP($V31,药材与丹炉!$B:$D,3,0),0),0)<0,2,0)) -> 1 | Y31: 3 | Z31: 宁神花 | AA31: =IFERROR($Y31/VLOOKUP($Z31,药材与丹炉!$B:$H,COLUMN(药材与丹炉!$H31)-1,0),"") -> 3 | AB31: 陨铁炉 | AC31: =IFERROR(IF($B31-VLOOKUP($AB31,药材与丹炉!$N:$P,2,0)<0,IF($AO$1="是",0,1),IF($B31-VLOOKUP($AB31,药材与丹炉!$N:$P,2,0)=0,2,IF($B31-VLOOKUP($AB31,药材与丹炉!$N:$P,2,0)=1,40,IF($B31-VLOOKUP($AB31,药材与丹炉!$N:$P,2,0)=2,80,"爆炸")))),"") -> 2 | AD31: =IFERROR($J31+IFERROR(IF($N31="",0,$N31),0)+IFERROR(IF($S31="",0,$S31),0)+IFERROR(IF($W31="",0,$W31),0)+IFERROR(IF($AA31="",0,$AA31),0),"") -> 9 | AE31: =IFERROR($J31*VLOOKUP($I31,药材与丹炉!$B:$K,10,0),0)+IFERROR($N31*VLOOKUP($M31,药材与丹炉!$B:$K,10,0),0)+IFERROR($S31*VLOOKUP($R31,药材与丹炉!$B:$K,10,0),0)+IFERROR($W31*VLOOKUP($V31,药材与丹炉!$B:$K,10,0),0)+IFERROR($AA31*VLOOKUP($Z31,药材与丹炉!$B:$K,10,0),0)+IFERROR($AC31*VLOOKUP($AB31,药材与丹炉!$N:$P,3,0)/100,0) -> 267 | AF31: 375 | AG31: =$AF31-$AE31 -> 108 | AH31: =$AF31*$AM$1*$AM$21 -> 750 | AI31: =$AH31-$AE31 -> 483 | AJ31: =IFERROR(IF($Y31/VLOOKUP($Y31,药材与丹炉!$T:$U,2,0)<=(VLOOKUP($AB31,药材与丹炉!$N:$O,2,0)+8)-($J31+IFERROR(IF($N31="",0,$N31),0)+IFERROR(IF($S31="",0,$S31),0)+IFERROR(IF($W31="",0,$W31),0)),1,2),1) -> 1 | AK31: =OR(NOT(IFERROR(OR($L31="",AND($L31<>"",$L31>0,VLOOKUP($AB31,药材与丹炉!$N:$O,2,0)=6)),0)),AND($L31<>"",$L31>0,OR(VLOOKUP($AB31,药材与丹炉!$N:$Q,4,0)-2<$N31,$N31="")),AND($U31<>"",$U31>0,OR(VLOOKUP($AB31,药材与丹炉!$N:$Q,4,0)-3<$W31,$W31="")),NOT(OR(AND($Q31<>"",$S31<>"",VLOOKUP($AB31,药材与丹炉!$N:$Q,4,0)-3>=$S31),$P31="")),NOT(OR(AND($H31<>"",$J31<>"",VLOOKUP($AB31,药材与丹炉!$N:$Q,4,0)-1>=$J31),$G31="")),NOT(OR($U31="",AND($U31<>"",$U31>0))),NOT(OR($Y31="",IF($Z31<>"",IFERROR(IF(VLOOKUP($Z31,药材与丹炉!$B:$D,3,0)=-1,$X31=1,IF(VLOOKUP($Z31,药材与丹炉!$B:$D,3,0)=1,$X31=2,$X31=0)),0),0))),$AC31="爆炸",(VLOOKUP($AB31,药材与丹炉!$N:$O,2,0)+8)<$AD31) -> FALSE
A32: 5121 | B32: 2 | C32: 龟甲丹 | D32: 50 | E32: 下场战斗中受到的技能伤害减一/丹毒+5 | F32: 6 | G32: 御气 | H32: 6 | I32: 地黄参 | J32: =IFERROR(CEILING($H32/VLOOKUP($I32,药材与丹炉!$B:$H,COLUMN(药材与丹炉!$H32)-1,0),1),"") -> 2 | K32: 御气 | L32: =IFERROR(IF($F32-$H32=0,"",$F32-$H32),"") | N32: =IFERROR(CEILING($L32/VLOOKUP($M32,药材与丹炉!$B:$H,COLUMN(药材与丹炉!$H32)-1,0),1),"") | O32: 12 | P32: 混元 | Q32: 9 | R32: 锦地罗 | S32: =IFERROR(CEILING($Q32/VLOOKUP($R32,药材与丹炉!$B:$H,COLUMN(药材与丹炉!$H32)-1,0),1),"") -> 1 | T32: =P32 -> 混元 | U32: =IFERROR(IF($O32-$Q32=0,"",$O32-$Q32),"") -> 3 | V32: 玄参 | W32: =IFERROR(CEILING($U32/VLOOKUP($V32,药材与丹炉!$B:$H,COLUMN(药材与丹炉!$H32)-1,0),1),"") -> 1 | X32: =IF(IFERROR(IF(AND($J32>0,$J32<>""),VLOOKUP($I32,药材与丹炉!$B:$D,3,0),0),0)+IFERROR(IF(AND($N32>0,$N32<>""),VLOOKUP($M32,药材与丹炉!$B:$D,3,0),0),0)+IFERROR(IF(AND($S32>0,$S32<>""),VLOOKUP($R32,药材与丹炉!$B:$D,3,0),0),0)+IFERROR(IF(AND($W32>0,$W32<>""),VLOOKUP($V32,药材与丹炉!$B:$D,3,0),0),0)>0,1,IF(IFERROR(IF(AND($J32>0,$J32<>""),VLOOKUP($I32,药材与丹炉!$B:$D,3,0),0),0)+IFERROR(IF(AND($N32>0,$N32<>""),VLOOKUP($M32,药材与丹炉!$B:$D,3,0),0),0)+IFERROR(IF(AND($S32>0,$S32<>""),VLOOKUP($R32,药材与丹炉!$B:$D,3,0),0),0)+IFERROR(IF(AND($W32>0,$W32<>""),VLOOKUP($V32,药材与丹炉!$B:$D,3,0),0),0)<0,2,0)) -> 1 | Y32: 3 | Z32: 夜交藤 | AA32: =IFERROR($Y32/VLOOKUP($Z32,药材与丹炉!$B:$H,COLUMN(药材与丹炉!$H32)-1,0),"") -> 1 | AB32: 陨铁炉 | AC32: =IFERROR(IF($B32-VLOOKUP($AB32,药材与丹炉!$N:$P,2,0)<0,IF($AO$1="是",0,1),IF($B32-VLOOKUP($AB32,药材与丹炉!$N:$P,2,0)=0,2,IF($B32-VLOOKUP($AB32,药材与丹炉!$N:$P,2,0)=1,40,IF($B32-VLOOKUP($AB32,药材与丹炉!$N:$P,2,0)=2,80,"爆炸")))),"") -> 2 | AD32: =IFERROR($J32+IFERROR(IF($N32="",0,$N32),0)+IFERROR(IF($S32="",0,$S32),0)+IFERROR(IF($W32="",0,$W32),0)+IFERROR(IF($AA32="",0,$AA32),0),"") -> 5 | AE32: =IFERROR($J32*VLOOKUP($I32,药材与丹炉!$B:$K,10,0),0)+IFERROR($N32*VLOOKUP($M32,药材与丹炉!$B:$K,10,0),0)+IFERROR($S32*VLOOKUP($R32,药材与丹炉!$B:$K,10,0),0)+IFERROR($W32*VLOOKUP($V32,药材与丹炉!$B:$K,10,0),0)+IFERROR($AA32*VLOOKUP($Z32,药材与丹炉!$B:$K,10,0),0)+IFERROR($AC32*VLOOKUP($AB32,药材与丹炉!$N:$P,3,0)/100,0) -> 573 | AF32: 331 | AG32: =$AF32-$AE32 -> -242 | AH32: =$AF32*$AM$1*$AM$21 -> 662 | AI32: =$AH32-$AE32 -> 89 | AJ32: =IFERROR(IF($Y32/VLOOKUP($Y32,药材与丹炉!$T:$U,2,0)<=(VLOOKUP($AB32,药材与丹炉!$N:$O,2,0)+8)-($J32+IFERROR(IF($N32="",0,$N32),0)+IFERROR(IF($S32="",0,$S32),0)+IFERROR(IF($W32="",0,$W32),0)),1,2),1) -> 1 | AK32: =OR(NOT(IFERROR(OR($L32="",AND($L32<>"",$L32>0,VLOOKUP($AB32,药材与丹炉!$N:$O,2,0)=6)),0)),AND($L32<>"",$L32>0,OR(VLOOKUP($AB32,药材与丹炉!$N:$Q,4,0)-2<$N32,$N32="")),AND($U32<>"",$U32>0,OR(VLOOKUP($AB32,药材与丹炉!$N:$Q,4,0)-3<$W32,$W32="")),NOT(OR(AND($Q32<>"",$S32<>"",VLOOKUP($AB32,药材与丹炉!$N:$Q,4,0)-3>=$S32),$P32="")),NOT(OR(AND($H32<>"",$J32<>"",VLOOKUP($AB32,药材与丹炉!$N:$Q,4,0)-1>=$J32),$G32="")),NOT(OR($U32="",AND($U32<>"",$U32>0))),NOT(OR($Y32="",IF($Z32<>"",IFERROR(IF(VLOOKUP($Z32,药材与丹炉!$B:$D,3,0)=-1,$X32=1,IF(VLOOKUP($Z32,药材与丹炉!$B:$D,3,0)=1,$X32=2,$X32=0)),0),0))),$AC32="爆炸",(VLOOKUP($AB32,药材与丹炉!$N:$O,2,0)+8)<$AD32) -> FALSE
B33: 2 | C33: 二阶废丹 | D33: 999 | E33: 修为+539（需神秘贝壳）/丹毒+10 | F33: 6 | G33: 活血 | H33: 6 | I33: 银月花 | J33: =IFERROR(CEILING($H33/VLOOKUP($I33,药材与丹炉!$B:$H,COLUMN(药材与丹炉!$H33)-1,0),1),"") -> 6 | K33: 活血 | L33: =IFERROR(IF($F33-$H33=0,"",$F33-$H33),"") | N33: =IFERROR(CEILING($L33/VLOOKUP($M33,药材与丹炉!$B:$H,COLUMN(药材与丹炉!$H33)-1,0),1),"") | O33: 3 | P33: 固元 | Q33: 3 | R33: 银月花 | S33: =IFERROR(CEILING($Q33/VLOOKUP($R33,药材与丹炉!$B:$H,COLUMN(药材与丹炉!$H33)-1,0),1),"") -> 3 | T33: =P33 -> 固元 | U33: =IFERROR(IF($O33-$Q33=0,"",$O33-$Q33),"") | W33: =IFERROR(CEILING($U33/VLOOKUP($V33,药材与丹炉!$B:$H,COLUMN(药材与丹炉!$H33)-1,0),1),"") | X33: =IF(IFERROR(IF(AND($J33>0,$J33<>""),VLOOKUP($I33,药材与丹炉!$B:$D,3,0),0),0)+IFERROR(IF(AND($N33>0,$N33<>""),VLOOKUP($M33,药材与丹炉!$B:$D,3,0),0),0)+IFERROR(IF(AND($S33>0,$S33<>""),VLOOKUP($R33,药材与丹炉!$B:$D,3,0),0),0)+IFERROR(IF(AND($W33>0,$W33<>""),VLOOKUP($V33,药材与丹炉!$B:$D,3,0),0),0)>0,1,IF(IFERROR(IF(AND($J33>0,$J33<>""),VLOOKUP($I33,药材与丹炉!$B:$D,3,0),0),0)+IFERROR(IF(AND($N33>0,$N33<>""),VLOOKUP($M33,药材与丹炉!$B:$D,3,0),0),0)+IFERROR(IF(AND($S33>0,$S33<>""),VLOOKUP($R33,药材与丹炉!$B:$D,3,0),0),0)+IFERROR(IF(AND($W33>0,$W33<>""),VLOOKUP($V33,药材与丹炉!$B:$D,3,0),0),0)<0,2,0)) -> 2 | AA33: =IFERROR($Y33/VLOOKUP($Z33,药材与丹炉!$B:$H,COLUMN(药材与丹炉!$H33)-1,0),"") | AB33: 陨铁炉 | AC33: =IFERROR(IF($B33-VLOOKUP($AB33,药材与丹炉!$N:$P,2,0)<0,IF($AO$1="是",0,1),IF($B33-VLOOKUP($AB33,药材与丹炉!$N:$P,2,0)=0,2,IF($B33-VLOOKUP($AB33,药材与丹炉!$N:$P,2,0)=1,40,IF($B33-VLOOKUP($AB33,药材与丹炉!$N:$P,2,0)=2,80,"爆炸")))),"") -> 2 | AD33: =IFERROR($J33+IFERROR(IF($N33="",0,$N33),0)+IFERROR(IF($S33="",0,$S33),0)+IFERROR(IF($W33="",0,$W33),0)+IFERROR(IF($AA33="",0,$AA33),0),"") -> 9 | AE33: =IFERROR($J33*VLOOKUP($I33,药材与丹炉!$B:$K,10,0),0)+IFERROR($N33*VLOOKUP($M33,药材与丹炉!$B:$K,10,0),0)+IFERROR($S33*VLOOKUP($R33,药材与丹炉!$B:$K,10,0),0)+IFERROR($W33*VLOOKUP($V33,药材与丹炉!$B:$K,10,0),0)+IFERROR($AA33*VLOOKUP($Z33,药材与丹炉!$B:$K,10,0),0)+IFERROR($AC33*VLOOKUP($AB33,药材与丹炉!$N:$P,3,0)/100,0) -> 105 | AF33: 1 | AG33: =$AF33-$AE33 -> -104 | AH33: =$AF33*$AM$1*$AM$21 -> 2 | AI33: =$AH33-$AE33 -> -103 | AJ33: =IFERROR(IF($Y33/VLOOKUP($Y33,药材与丹炉!$T:$U,2,0)<=(VLOOKUP($AB33,药材与丹炉!$N:$O,2,0)+8)-($J33+IFERROR(IF($N33="",0,$N33),0)+IFERROR(IF($S33="",0,$S33),0)+IFERROR(IF($W33="",0,$W33),0)),1,2),1) -> 1 | AK33: =OR(NOT(IFERROR(OR($L33="",AND($L33<>"",$L33>0,VLOOKUP($AB33,药材与丹炉!$N:$O,2,0)=6)),0)),AND($L33<>"",$L33>0,OR(VLOOKUP($AB33,药材与丹炉!$N:$Q,4,0)-2<$N33,$N33="")),AND($U33<>"",$U33>0,OR(VLOOKUP($AB33,药材与丹炉!$N:$Q,4,0)-3<$W33,$W33="")),NOT(OR(AND($Q33<>"",$S33<>"",VLOOKUP($AB33,药材与丹炉!$N:$Q,4,0)-3>=$S33),$P33="")),NOT(OR(AND($H33<>"",$J33<>"",VLOOKUP($AB33,药材与丹炉!$N:$Q,4,0)-1>=$J33),$G33="")),NOT(OR($U33="",AND($U33<>"",$U33>0))),NOT(OR($Y33="",IF($Z33<>"",IFERROR(IF(VLOOKUP($Z33,药材与丹炉!$B:$D,3,0)=-1,$X33=1,IF(VLOOKUP($Z33,药材与丹炉!$B:$D,3,0)=1,$X33=2,$X33=0)),0),0))),$AC33="爆炸",(VLOOKUP($AB33,药材与丹炉!$N:$O,2,0)+8)<$AD33) -> FALSE
A34: 5201 | B34: 3 | C34: 回元丹 | D34: 999 | E34: 生命值+600/丹毒+1 | F34: 6 | G34: 活血 | H34: 6 | I34: 龙葵 | J34: =IFERROR(CEILING($H34/VLOOKUP($I34,药材与丹炉!$B:$H,COLUMN(药材与丹炉!$H34)-1,0),1),"") -> 2 | K34: 活血 | L34: =IFERROR(IF($F34-$H34=0,"",$F34-$H34),"") | N34: =IFERROR(CEILING($L34/VLOOKUP($M34,药材与丹炉!$B:$H,COLUMN(药材与丹炉!$H34)-1,0),1),"") | O34: 6 | P34: 固元 | Q34: 6 | R34: 银月花 | S34: =IFERROR(CEILING($Q34/VLOOKUP($R34,药材与丹炉!$B:$H,COLUMN(药材与丹炉!$H34)-1,0),1),"") -> 6 | T34: =P34 -> 固元 | U34: =IFERROR(IF($O34-$Q34=0,"",$O34-$Q34),"") | W34: =IFERROR(CEILING($U34/VLOOKUP($V34,药材与丹炉!$B:$H,COLUMN(药材与丹炉!$H34)-1,0),1),"") | X34: =IF(IFERROR(IF(AND($J34>0,$J34<>""),VLOOKUP($I34,药材与丹炉!$B:$D,3,0),0),0)+IFERROR(IF(AND($N34>0,$N34<>""),VLOOKUP($M34,药材与丹炉!$B:$D,3,0),0),0)+IFERROR(IF(AND($S34>0,$S34<>""),VLOOKUP($R34,药材与丹炉!$B:$D,3,0),0),0)+IFERROR(IF(AND($W34>0,$W34<>""),VLOOKUP($V34,药材与丹炉!$B:$D,3,0),0),0)>0,1,IF(IFERROR(IF(AND($J34>0,$J34<>""),VLOOKUP($I34,药材与丹炉!$B:$D,3,0),0),0)+IFERROR(IF(AND($N34>0,$N34<>""),VLOOKUP($M34,药材与丹炉!$B:$D,3,0),0),0)+IFERROR(IF(AND($S34>0,$S34<>""),VLOOKUP($R34,药材与丹炉!$B:$D,3,0),0),0)+IFERROR(IF(AND($W34>0,$W34<>""),VLOOKUP($V34,药材与丹炉!$B:$D,3,0),0),0)<0,2,0)) -> 2 | Y34: 3 | Z34: 天青花 | AA34: =IFERROR($Y34/VLOOKUP($Z34,药材与丹炉!$B:$H,COLUMN(药材与丹炉!$H34)-1,0),"") -> 3 | AB34: 雕花紫铜炉 | AC34: =IFERROR(IF($B34-VLOOKUP($AB34,药材与丹炉!$N:$P,2,0)<0,IF($AO$1="是",0,1),IF($B34-VLOOKUP($AB34,药材与丹炉!$N:$P,2,0)=0,2,IF($B34-VLOOKUP($AB34,药材与丹炉!$N:$P,2,0)=1,40,IF($B34-VLOOKUP($AB34,药材与丹炉!$N:$P,2,0)=2,80,"爆炸")))),"") -> 2 | AD34: =IFERROR($J34+IFERROR(IF($N34="",0,$N34),0)+IFERROR(IF($S34="",0,$S34),0)+IFERROR(IF($W34="",0,$W34),0)+IFERROR(IF($AA34="",0,$AA34),0),"") -> 11 | AE34: =IFERROR($J34*VLOOKUP($I34,药材与丹炉!$B:$K,10,0),0)+IFERROR($N34*VLOOKUP($M34,药材与丹炉!$B:$K,10,0),0)+IFERROR($S34*VLOOKUP($R34,药材与丹炉!$B:$K,10,0),0)+IFERROR($W34*VLOOKUP($V34,药材与丹炉!$B:$K,10,0),0)+IFERROR($AA34*VLOOKUP($Z34,药材与丹炉!$B:$K,10,0),0)+IFERROR($AC34*VLOOKUP($AB34,药材与丹炉!$N:$P,3,0)/100,0) -> 233 | AF34: 500 | AG34: =$AF34-$AE34 -> 267 | AH34: =$AF34*$AM$1*$AM$21 -> 1000 | AI34: =$AH34-$AE34 -> 767 | AJ34: =IFERROR(IF($Y34/VLOOKUP($Y34,药材与丹炉!$T:$U,2,0)<=(VLOOKUP($AB34,药材与丹炉!$N:$O,2,0)+8)-($J34+IFERROR(IF($N34="",0,$N34),0)+IFERROR(IF($S34="",0,$S34),0)+IFERROR(IF($W34="",0,$W34),0)),1,2),1) -> 1 | AK34: =OR(NOT(IFERROR(OR($L34="",AND($L34<>"",$L34>0,VLOOKUP($AB34,药材与丹炉!$N:$O,2,0)=6)),0)),AND($L34<>"",$L34>0,OR(VLOOKUP($AB34,药材与丹炉!$N:$Q,4,0)-2<$N34,$N34="")),AND($U34<>"",$U34>0,OR(VLOOKUP($AB34,药材与丹炉!$N:$Q,4,0)-3<$W34,$W34="")),NOT(OR(AND($Q34<>"",$S34<>"",VLOOKUP($AB34,药材与丹炉!$N:$Q,4,0)-3>=$S34),$P34="")),NOT(OR(AND($H34<>"",$J34<>"",VLOOKUP($AB34,药材与丹炉!$N:$Q,4,0)-1>=$J34),$G34="")),NOT(OR($U34="",AND($U34<>"",$U34>0))),NOT(OR($Y34="",IF($Z34<>"",IFERROR(IF(VLOOKUP($Z34,药材与丹炉!$B:$D,3,0)=-1,$X34=1,IF(VLOOKUP($Z34,药材与丹炉!$B:$D,3,0)=1,$X34=2,$X34=0)),0),0))),$AC34="爆炸",(VLOOKUP($AB34,药材与丹炉!$N:$O,2,0)+8)<$AD34) -> FALSE
A35: 5202 | B35: 3 | C35: 九转丹 | D35: 100 | E35: 修为+5940（境界不足筑基期时服用，丹毒+30） | F35: 36 | G35: 生息 | H35: 36 | I35: 枫香脂 | J35: =IFERROR(CEILING($H35/VLOOKUP($I35,药材与丹炉!$B:$H,COLUMN(药材与丹炉!$H35)-1,0),1),"") -> 4 | K35: 生息 | L35: =IFERROR(IF($F35-$H35=0,"",$F35-$H35),"") | N35: =IFERROR(CEILING($L35/VLOOKUP($M35,药材与丹炉!$B:$H,COLUMN(药材与丹炉!$H35)-1,0),1),"") | P35: 养气 | Q35: 45 | R35: 补天芝 | S35: =IFERROR(CEILING($Q35/VLOOKUP($R35,药材与丹炉!$B:$H,COLUMN(药材与丹炉!$H35)-1,0),1),"") -> 5 | T35: 炼气 | U35: 18 | V35: 菩提花 | W35: =IFERROR(CEILING($U35/VLOOKUP($V35,药材与丹炉!$B:$H,COLUMN(药材与丹炉!$H35)-1,0),1),"") -> 2 | X35: =IF(IFERROR(IF(AND($J35>0,$J35<>""),VLOOKUP($I35,药材与丹炉!$B:$D,3,0),0),0)+IFERROR(IF(AND($N35>0,$N35<>""),VLOOKUP($M35,药材与丹炉!$B:$D,3,0),0),0)+IFERROR(IF(AND($S35>0,$S35<>""),VLOOKUP($R35,药材与丹炉!$B:$D,3,0),0),0)+IFERROR(IF(AND($W35>0,$W35<>""),VLOOKUP($V35,药材与丹炉!$B:$D,3,0),0),0)>0,1,IF(IFERROR(IF(AND($J35>0,$J35<>""),VLOOKUP($I35,药材与丹炉!$B:$D,3,0),0),0)+IFERROR(IF(AND($N35>0,$N35<>""),VLOOKUP($M35,药材与丹炉!$B:$D,3,0),0),0)+IFERROR(IF(AND($S35>0,$S35<>""),VLOOKUP($R35,药材与丹炉!$B:$D,3,0),0),0)+IFERROR(IF(AND($W35>0,$W35<>""),VLOOKUP($V35,药材与丹炉!$B:$D,3,0),0),0)<0,2,0)) -> 0 | Y35: 9 | Z35: 菩提花 | AA35: =IFERROR($Y35/VLOOKUP($Z35,药材与丹炉!$B:$H,COLUMN(药材与丹炉!$H35)-1,0),"") -> 1 | AB35: 庚金龙纹炉 | AC35: =IFERROR(IF($B35-VLOOKUP($AB35,药材与丹炉!$N:$P,2,0)<0,IF($AO$1="是",0,1),IF($B35-VLOOKUP($AB35,药材与丹炉!$N:$P,2,0)=0,2,IF($B35-VLOOKUP($AB35,药材与丹炉!$N:$P,2,0)=1,40,IF($B35-VLOOKUP($AB35,药材与丹炉!$N:$P,2,0)=2,80,"爆炸")))),"") -> 1 | AD35: =IFERROR($J35+IFERROR(IF($N35="",0,$N35),0)+IFERROR(IF($S35="",0,$S35),0)+IFERROR(IF($W35="",0,$W35),0)+IFERROR(IF($AA35="",0,$AA35),0),"") -> 12 | AE35: =IFERROR($J35*VLOOKUP($I35,药材与丹炉!$B:$K,10,0),0)+IFERROR($N35*VLOOKUP($M35,药材与丹炉!$B:$K,10,0),0)+IFERROR($S35*VLOOKUP($R35,药材与丹炉!$B:$K,10,0),0)+IFERROR($W35*VLOOKUP($V35,药材与丹炉!$B:$K,10,0),0)+IFERROR($AA35*VLOOKUP($Z35,药材与丹炉!$B:$K,10,0),0)+IFERROR($AC35*VLOOKUP($AB35,药材与丹炉!$N:$P,3,0)/100,0) -> 4960 | AF35: 5940 | AG35: =$AF35-$AE35 -> 980 | AH35: =$AF35*$AM$1*$AM$21 -> 11880 | AI35: =$AH35-$AE35 -> 6920 | AJ35: =IFERROR(IF($Y35/VLOOKUP($Y35,药材与丹炉!$T:$U,2,0)<=(VLOOKUP($AB35,药材与丹炉!$N:$O,2,0)+8)-($J35+IFERROR(IF($N35="",0,$N35),0)+IFERROR(IF($S35="",0,$S35),0)+IFERROR(IF($W35="",0,$W35),0)),1,2),1) -> 2 | AK35: =OR(NOT(IFERROR(OR($L35="",AND($L35<>"",$L35>0,VLOOKUP($AB35,药材与丹炉!$N:$O,2,0)=6)),0)),AND($L35<>"",$L35>0,OR(VLOOKUP($AB35,药材与丹炉!$N:$Q,4,0)-2<$N35,$N35="")),AND($U35<>"",$U35>0,OR(VLOOKUP($AB35,药材与丹炉!$N:$Q,4,0)-3<$W35,$W35="")),NOT(OR(AND($Q35<>"",$S35<>"",VLOOKUP($AB35,药材与丹炉!$N:$Q,4,0)-3>=$S35),$P35="")),NOT(OR(AND($H35<>"",$J35<>"",VLOOKUP($AB35,药材与丹炉!$N:$Q,4,0)-1>=$J35),$G35="")),NOT(OR($U35="",AND($U35<>"",$U35>0))),NOT(OR($Y35="",IF($Z35<>"",IFERROR(IF(VLOOKUP($Z35,药材与丹炉!$B:$D,3,0)=-1,$X35=1,IF(VLOOKUP($Z35,药材与丹炉!$B:$D,3,0)=1,$X35=2,$X35=0)),0),0))),$AC35="爆炸",(VLOOKUP($AB35,药材与丹炉!$N:$O,2,0)+8)<$AD35) -> FALSE
A36: 5203 | B36: 3 | C36: 清蕴丹 | D36: 50 | E36: 下场战斗中免疫【中毒】（持续3回合）/丹毒+5 | F36: 18 | G36: 御气 | H36: 18 | I36: 地黄参 | J36: =IFERROR(CEILING($H36/VLOOKUP($I36,药材与丹炉!$B:$H,COLUMN(药材与丹炉!$H36)-1,0),1),"") -> 6 | K36: 御气 | L36: =IFERROR(IF($F36-$H36=0,"",$F36-$H36),"") | N36: =IFERROR(CEILING($L36/VLOOKUP($M36,药材与丹炉!$B:$H,COLUMN(药材与丹炉!$H36)-1,0),1),"") | O36: 9 | P36: 解毒 | Q36: 9 | R36: 龙葵 | S36: =IFERROR(CEILING($Q36/VLOOKUP($R36,药材与丹炉!$B:$H,COLUMN(药材与丹炉!$H36)-1,0),1),"") -> 3 | T36: =P36 -> 解毒 | U36: =IFERROR(IF($O36-$Q36=0,"",$O36-$Q36),"") | W36: =IFERROR(CEILING($U36/VLOOKUP($V36,药材与丹炉!$B:$H,COLUMN(药材与丹炉!$H36)-1,0),1),"") | X36: =IF(IFERROR(IF(AND($J36>0,$J36<>""),VLOOKUP($I36,药材与丹炉!$B:$D,3,0),0),0)+IFERROR(IF(AND($N36>0,$N36<>""),VLOOKUP($M36,药材与丹炉!$B:$D,3,0),0),0)+IFERROR(IF(AND($S36>0,$S36<>""),VLOOKUP($R36,药材与丹炉!$B:$D,3,0),0),0)+IFERROR(IF(AND($W36>0,$W36<>""),VLOOKUP($V36,药材与丹炉!$B:$D,3,0),0),0)>0,1,IF(IFERROR(IF(AND($J36>0,$J36<>""),VLOOKUP($I36,药材与丹炉!$B:$D,3,0),0),0)+IFERROR(IF(AND($N36>0,$N36<>""),VLOOKUP($M36,药材与丹炉!$B:$D,3,0),0),0)+IFERROR(IF(AND($S36>0,$S36<>""),VLOOKUP($R36,药材与丹炉!$B:$D,3,0),0),0)+IFERROR(IF(AND($W36>0,$W36<>""),VLOOKUP($V36,药材与丹炉!$B:$D,3,0),0),0)<0,2,0)) -> 0 | Y36: 9 | Z36: 红绫草 | AA36: =IFERROR($Y36/VLOOKUP($Z36,药材与丹炉!$B:$H,COLUMN(药材与丹炉!$H36)-1,0),"") -> 3 | AB36: 庚金龙纹炉 | AC36: =IFERROR(IF($B36-VLOOKUP($AB36,药材与丹炉!$N:$P,2,0)<0,IF($AO$1="是",0,1),IF($B36-VLOOKUP($AB36,药材与丹炉!$N:$P,2,0)=0,2,IF($B36-VLOOKUP($AB36,药材与丹炉!$N:$P,2,0)=1,40,IF($B36-VLOOKUP($AB36,药材与丹炉!$N:$P,2,0)=2,80,"爆炸")))),"") -> 1 | AD36: =IFERROR($J36+IFERROR(IF($N36="",0,$N36),0)+IFERROR(IF($S36="",0,$S36),0)+IFERROR(IF($W36="",0,$W36),0)+IFERROR(IF($AA36="",0,$AA36),0),"") -> 12 | AE36: =IFERROR($J36*VLOOKUP($I36,药材与丹炉!$B:$K,10,0),0)+IFERROR($N36*VLOOKUP($M36,药材与丹炉!$B:$K,10,0),0)+IFERROR($S36*VLOOKUP($R36,药材与丹炉!$B:$K,10,0),0)+IFERROR($W36*VLOOKUP($V36,药材与丹炉!$B:$K,10,0),0)+IFERROR($AA36*VLOOKUP($Z36,药材与丹炉!$B:$K,10,0),0)+IFERROR($AC36*VLOOKUP($AB36,药材与丹炉!$N:$P,3,0)/100,0) -> 532 | AF36: 800 | AG36: =$AF36-$AE36 -> 268 | AH36: =$AF36*$AM$1*$AM$21 -> 1600 | AI36: =$AH36-$AE36 -> 1068 | AJ36: =IFERROR(IF($Y36/VLOOKUP($Y36,药材与丹炉!$T:$U,2,0)<=(VLOOKUP($AB36,药材与丹炉!$N:$O,2,0)+8)-($J36+IFERROR(IF($N36="",0,$N36),0)+IFERROR(IF($S36="",0,$S36),0)+IFERROR(IF($W36="",0,$W36),0)),1,2),1) -> 1 | AK36: =OR(NOT(IFERROR(OR($L36="",AND($L36<>"",$L36>0,VLOOKUP($AB36,药材与丹炉!$N:$O,2,0)=6)),0)),AND($L36<>"",$L36>0,OR(VLOOKUP($AB36,药材与丹炉!$N:$Q,4,0)-2<$N36,$N36="")),AND($U36<>"",$U36>0,OR(VLOOKUP($AB36,药材与丹炉!$N:$Q,4,0)-3<$W36,$W36="")),NOT(OR(AND($Q36<>"",$S36<>"",VLOOKUP($AB36,药材与丹炉!$N:$Q,4,0)-3>=$S36),$P36="")),NOT(OR(AND($H36<>"",$J36<>"",VLOOKUP($AB36,药材与丹炉!$N:$Q,4,0)-1>=$J36),$G36="")),NOT(OR($U36="",AND($U36<>"",$U36>0))),NOT(OR($Y36="",IF($Z36<>"",IFERROR(IF(VLOOKUP($Z36,药材与丹炉!$B:$D,3,0)=-1,$X36=1,IF(VLOOKUP($Z36,药材与丹炉!$B:$D,3,0)=1,$X36=2,$X36=0)),0),0))),$AC36="爆炸",(VLOOKUP($AB36,药材与丹炉!$N:$O,2,0)+8)<$AD36) -> FALSE
A37: 5204 | B37: 3 | C37: 冰元丹 | D37: 50 | E37: 下场战斗中免疫【灼烧】（持续3回合）/丹毒+5 | F37: 18 | G37: 御气 | H37: 18 | I37: 地黄参 | J37: =IFERROR(CEILING($H37/VLOOKUP($I37,药材与丹炉!$B:$H,COLUMN(药材与丹炉!$H37)-1,0),1),"") -> 6 | K37: 御气 | L37: =IFERROR(IF($F37-$H37=0,"",$F37-$H37),"") | N37: =IFERROR(CEILING($L37/VLOOKUP($M37,药材与丹炉!$B:$H,COLUMN(药材与丹炉!$H37)-1,0),1),"") | O37: 9 | P37: 强水 | Q37: 9 | R37: 弗兰草 | S37: =IFERROR(CEILING($Q37/VLOOKUP($R37,药材与丹炉!$B:$H,COLUMN(药材与丹炉!$H37)-1,0),1),"") -> 3 | T37: =P37 -> 强水 | U37: =IFERROR(IF($O37-$Q37=0,"",$O37-$Q37),"") | W37: =IFERROR(CEILING($U37/VLOOKUP($V37,药材与丹炉!$B:$H,COLUMN(药材与丹炉!$H37)-1,0),1),"") | X37: =IF(IFERROR(IF(AND($J37>0,$J37<>""),VLOOKUP($I37,药材与丹炉!$B:$D,3,0),0),0)+IFERROR(IF(AND($N37>0,$N37<>""),VLOOKUP($M37,药材与丹炉!$B:$D,3,0),0),0)+IFERROR(IF(AND($S37>0,$S37<>""),VLOOKUP($R37,药材与丹炉!$B:$D,3,0),0),0)+IFERROR(IF(AND($W37>0,$W37<>""),VLOOKUP($V37,药材与丹炉!$B:$D,3,0),0),0)>0,1,IF(IFERROR(IF(AND($J37>0,$J37<>""),VLOOKUP($I37,药材与丹炉!$B:$D,3,0),0),0)+IFERROR(IF(AND($N37>0,$N37<>""),VLOOKUP($M37,药材与丹炉!$B:$D,3,0),0),0)+IFERROR(IF(AND($S37>0,$S37<>""),VLOOKUP($R37,药材与丹炉!$B:$D,3,0),0),0)+IFERROR(IF(AND($W37>0,$W37<>""),VLOOKUP($V37,药材与丹炉!$B:$D,3,0),0),0)<0,2,0)) -> 0 | Y37: 9 | Z37: 红绫草 | AA37: =IFERROR($Y37/VLOOKUP($Z37,药材与丹炉!$B:$H,COLUMN(药材与丹炉!$H37)-1,0),"") -> 3 | AB37: 庚金龙纹炉 | AC37: =IFERROR(IF($B37-VLOOKUP($AB37,药材与丹炉!$N:$P,2,0)<0,IF($AO$1="是",0,1),IF($B37-VLOOKUP($AB37,药材与丹炉!$N:$P,2,0)=0,2,IF($B37-VLOOKUP($AB37,药材与丹炉!$N:$P,2,0)=1,40,IF($B37-VLOOKUP($AB37,药材与丹炉!$N:$P,2,0)=2,80,"爆炸")))),"") -> 1 | AD37: =IFERROR($J37+IFERROR(IF($N37="",0,$N37),0)+IFERROR(IF($S37="",0,$S37),0)+IFERROR(IF($W37="",0,$W37),0)+IFERROR(IF($AA37="",0,$AA37),0),"") -> 12 | AE37: =IFERROR($J37*VLOOKUP($I37,药材与丹炉!$B:$K,10,0),0)+IFERROR($N37*VLOOKUP($M37,药材与丹炉!$B:$K,10,0),0)+IFERROR($S37*VLOOKUP($R37,药材与丹炉!$B:$K,10,0),0)+IFERROR($W37*VLOOKUP($V37,药材与丹炉!$B:$K,10,0),0)+IFERROR($AA37*VLOOKUP($Z37,药材与丹炉!$B:$K,10,0),0)+IFERROR($AC37*VLOOKUP($AB37,药材与丹炉!$N:$P,3,0)/100,0) -> 532 | AF37: 800 | AG37: =$AF37-$AE37 -> 268 | AH37: =$AF37*$AM$1*$AM$21 -> 1600 | AI37: =$AH37-$AE37 -> 1068 | AJ37: =IFERROR(IF($Y37/VLOOKUP($Y37,药材与丹炉!$T:$U,2,0)<=(VLOOKUP($AB37,药材与丹炉!$N:$O,2,0)+8)-($J37+IFERROR(IF($N37="",0,$N37),0)+IFERROR(IF($S37="",0,$S37),0)+IFERROR(IF($W37="",0,$W37),0)),1,2),1) -> 1 | AK37: =OR(NOT(IFERROR(OR($L37="",AND($L37<>"",$L37>0,VLOOKUP($AB37,药材与丹炉!$N:$O,2,0)=6)),0)),AND($L37<>"",$L37>0,OR(VLOOKUP($AB37,药材与丹炉!$N:$Q,4,0)-2<$N37,$N37="")),AND($U37<>"",$U37>0,OR(VLOOKUP($AB37,药材与丹炉!$N:$Q,4,0)-3<$W37,$W37="")),NOT(OR(AND($Q37<>"",$S37<>"",VLOOKUP($AB37,药材与丹炉!$N:$Q,4,0)-3>=$S37),$P37="")),NOT(OR(AND($H37<>"",$J37<>"",VLOOKUP($AB37,药材与丹炉!$N:$Q,4,0)-1>=$J37),$G37="")),NOT(OR($U37="",AND($U37<>"",$U37>0))),NOT(OR($Y37="",IF($Z37<>"",IFERROR(IF(VLOOKUP($Z37,药材与丹炉!$B:$D,3,0)=-1,$X37=1,IF(VLOOKUP($Z37,药材与丹炉!$B:$D,3,0)=1,$X37=2,$X37=0)),0),0))),$AC37="爆炸",(VLOOKUP($AB37,药材与丹炉!$N:$O,2,0)+8)<$AD37) -> FALSE
A38: 5205 | B38: 3 | C38: 筑基丹 | D38: 6 | E38: 筑基开始时，额外抽一张灵气牌。 | F38: 27 | G38: 振气 | H38: 27 | I38: 玄冰花 | J38: =IFERROR(CEILING($H38/VLOOKUP($I38,药材与丹炉!$B:$H,COLUMN(药材与丹炉!$H38)-1,0),1),"") -> 3 | K38: 振气 | L38: =IFERROR(IF($F38-$H38=0,"",$F38-$H38),"") | N38: =IFERROR(CEILING($L38/VLOOKUP($M38,药材与丹炉!$B:$H,COLUMN(药材与丹炉!$H38)-1,0),1),"") | P38: 定煞 | Q38: 9 | R38: 天灵果 | S38: =IFERROR(CEILING($Q38/VLOOKUP($R38,药材与丹炉!$B:$H,COLUMN(药材与丹炉!$H38)-1,0),1),"") -> 1 | T38: 调和 | U38: 9 | V38: 百草露 | W38: =IFERROR(CEILING($U38/VLOOKUP($V38,药材与丹炉!$B:$H,COLUMN(药材与丹炉!$H38)-1,0),1),"") -> 3 | X38: =IF(IFERROR(IF(AND($J38>0,$J38<>""),VLOOKUP($I38,药材与丹炉!$B:$D,3,0),0),0)+IFERROR(IF(AND($N38>0,$N38<>""),VLOOKUP($M38,药材与丹炉!$B:$D,3,0),0),0)+IFERROR(IF(AND($S38>0,$S38<>""),VLOOKUP($R38,药材与丹炉!$B:$D,3,0),0),0)+IFERROR(IF(AND($W38>0,$W38<>""),VLOOKUP($V38,药材与丹炉!$B:$D,3,0),0),0)>0,1,IF(IFERROR(IF(AND($J38>0,$J38<>""),VLOOKUP($I38,药材与丹炉!$B:$D,3,0),0),0)+IFERROR(IF(AND($N38>0,$N38<>""),VLOOKUP($M38,药材与丹炉!$B:$D,3,0),0),0)+IFERROR(IF(AND($S38>0,$S38<>""),VLOOKUP($R38,药材与丹炉!$B:$D,3,0),0),0)+IFERROR(IF(AND($W38>0,$W38<>""),VLOOKUP($V38,药材与丹炉!$B:$D,3,0),0),0)<0,2,0)) -> 0 | Y38: 9 | Z38: 风灵花 | AA38: =IFERROR($Y38/VLOOKUP($Z38,药材与丹炉!$B:$H,COLUMN(药材与丹炉!$H38)-1,0),"") -> 3 | AB38: 雕花紫铜炉 | AC38: =IFERROR(IF($B38-VLOOKUP($AB38,药材与丹炉!$N:$P,2,0)<0,IF($AO$1="是",0,1),IF($B38-VLOOKUP($AB38,药材与丹炉!$N:$P,2,0)=0,2,IF($B38-VLOOKUP($AB38,药材与丹炉!$N:$P,2,0)=1,40,IF($B38-VLOOKUP($AB38,药材与丹炉!$N:$P,2,0)=2,80,"爆炸")))),"") -> 2 | AD38: =IFERROR($J38+IFERROR(IF($N38="",0,$N38),0)+IFERROR(IF($S38="",0,$S38),0)+IFERROR(IF($W38="",0,$W38),0)+IFERROR(IF($AA38="",0,$AA38),0),"") -> 10 | AE38: =IFERROR($J38*VLOOKUP($I38,药材与丹炉!$B:$K,10,0),0)+IFERROR($N38*VLOOKUP($M38,药材与丹炉!$B:$K,10,0),0)+IFERROR($S38*VLOOKUP($R38,药材与丹炉!$B:$K,10,0),0)+IFERROR($W38*VLOOKUP($V38,药材与丹炉!$B:$K,10,0),0)+IFERROR($AA38*VLOOKUP($Z38,药材与丹炉!$B:$K,10,0),0)+IFERROR($AC38*VLOOKUP($AB38,药材与丹炉!$N:$P,3,0)/100,0) -> 1916 | AF38: 2500 | AG38: =$AF38-$AE38 -> 584 | AH38: =$AF38*$AM$1*$AM$21 -> 5000 | AI38: =$AH38-$AE38 -> 3084 | AJ38: =IFERROR(IF($Y38/VLOOKUP($Y38,药材与丹炉!$T:$U,2,0)<=(VLOOKUP($AB38,药材与丹炉!$N:$O,2,0)+8)-($J38+IFERROR(IF($N38="",0,$N38),0)+IFERROR(IF($S38="",0,$S38),0)+IFERROR(IF($W38="",0,$W38),0)),1,2),1) -> 1 | AK38: =OR(NOT(IFERROR(OR($L38="",AND($L38<>"",$L38>0,VLOOKUP($AB38,药材与丹炉!$N:$O,2,0)=6)),0)),AND($L38<>"",$L38>0,OR(VLOOKUP($AB38,药材与丹炉!$N:$Q,4,0)-2<$N38,$N38="")),AND($U38<>"",$U38>0,OR(VLOOKUP($AB38,药材与丹炉!$N:$Q,4,0)-3<$W38,$W38="")),NOT(OR(AND($Q38<>"",$S38<>"",VLOOKUP($AB38,药材与丹炉!$N:$Q,4,0)-3>=$S38),$P38="")),NOT(OR(AND($H38<>"",$J38<>"",VLOOKUP($AB38,药材与丹炉!$N:$Q,4,0)-1>=$J38),$G38="")),NOT(OR($U38="",AND($U38<>"",$U38>0))),NOT(OR($Y38="",IF($Z38<>"",IFERROR(IF(VLOOKUP($Z38,药材与丹炉!$B:$D,3,0)=-1,$X38=1,IF(VLOOKUP($Z38,药材与丹炉!$B:$D,3,0)=1,$X38=2,$X38=0)),0),0))),$AC38="爆炸",(VLOOKUP($AB38,药材与丹炉!$N:$O,2,0)+8)<$AD38) -> FALSE
A39: 5206 | B39: 3 | C39: 养魂丹 | D39: 3 | E39: 神识+1/丹毒+2 | F39: 18 | G39: 聚元 | H39: 18 | I39: 夜交藤 | J39: =IFERROR(CEILING($H39/VLOOKUP($I39,药材与丹炉!$B:$H,COLUMN(药材与丹炉!$H39)-1,0),1),"") -> 6 | K39: 聚元 | L39: =IFERROR(IF($F39-$H39=0,"",$F39-$H39),"") | N39: =IFERROR(CEILING($L39/VLOOKUP($M39,药材与丹炉!$B:$H,COLUMN(药材与丹炉!$H39)-1,0),1),"") | O39: 18 | P39: 养魂 | Q39: 18 | R39: 鬼臼草 | S39: =IFERROR(CEILING($Q39/VLOOKUP($R39,药材与丹炉!$B:$H,COLUMN(药材与丹炉!$H39)-1,0),1),"") -> 2 | T39: =P39 -> 养魂 | U39: =IFERROR(IF($O39-$Q39=0,"",$O39-$Q39),"") | W39: =IFERROR(CEILING($U39/VLOOKUP($V39,药材与丹炉!$B:$H,COLUMN(药材与丹炉!$H39)-1,0),1),"") | X39: =IF(IFERROR(IF(AND($J39>0,$J39<>""),VLOOKUP($I39,药材与丹炉!$B:$D,3,0),0),0)+IFERROR(IF(AND($N39>0,$N39<>""),VLOOKUP($M39,药材与丹炉!$B:$D,3,0),0),0)+IFERROR(IF(AND($S39>0,$S39<>""),VLOOKUP($R39,药材与丹炉!$B:$D,3,0),0),0)+IFERROR(IF(AND($W39>0,$W39<>""),VLOOKUP($V39,药材与丹炉!$B:$D,3,0),0),0)>0,1,IF(IFERROR(IF(AND($J39>0,$J39<>""),VLOOKUP($I39,药材与丹炉!$B:$D,3,0),0),0)+IFERROR(IF(AND($N39>0,$N39<>""),VLOOKUP($M39,药材与丹炉!$B:$D,3,0),0),0)+IFERROR(IF(AND($S39>0,$S39<>""),VLOOKUP($R39,药材与丹炉!$B:$D,3,0),0),0)+IFERROR(IF(AND($W39>0,$W39<>""),VLOOKUP($V39,药材与丹炉!$B:$D,3,0),0),0)<0,2,0)) -> 2 | Y39: 36 | Z39: 灯心草 | AA39: =IFERROR($Y39/VLOOKUP($Z39,药材与丹炉!$B:$H,COLUMN(药材与丹炉!$H39)-1,0),"") -> 4 | AB39: 庚金龙纹炉 | AC39: =IFERROR(IF($B39-VLOOKUP($AB39,药材与丹炉!$N:$P,2,0)<0,IF($AO$1="是",0,1),IF($B39-VLOOKUP($AB39,药材与丹炉!$N:$P,2,0)=0,2,IF($B39-VLOOKUP($AB39,药材与丹炉!$N:$P,2,0)=1,40,IF($B39-VLOOKUP($AB39,药材与丹炉!$N:$P,2,0)=2,80,"爆炸")))),"") -> 1 | AD39: =IFERROR($J39+IFERROR(IF($N39="",0,$N39),0)+IFERROR(IF($S39="",0,$S39),0)+IFERROR(IF($W39="",0,$W39),0)+IFERROR(IF($AA39="",0,$AA39),0),"") -> 12 | AE39: =IFERROR($J39*VLOOKUP($I39,药材与丹炉!$B:$K,10,0),0)+IFERROR($N39*VLOOKUP($M39,药材与丹炉!$B:$K,10,0),0)+IFERROR($S39*VLOOKUP($R39,药材与丹炉!$B:$K,10,0),0)+IFERROR($W39*VLOOKUP($V39,药材与丹炉!$B:$K,10,0),0)+IFERROR($AA39*VLOOKUP($Z39,药材与丹炉!$B:$K,10,0),0)+IFERROR($AC39*VLOOKUP($AB39,药材与丹炉!$N:$P,3,0)/100,0) -> 2746 | AF39: 4400 | AG39: =$AF39-$AE39 -> 1654 | AH39: =$AF39*$AM$1*$AM$21 -> 8800 | AI39: =$AH39-$AE39 -> 6054 | AJ39: =IFERROR(IF($Y39/VLOOKUP($Y39,药材与丹炉!$T:$U,2,0)<=(VLOOKUP($AB39,药材与丹炉!$N:$O,2,0)+8)-($J39+IFERROR(IF($N39="",0,$N39),0)+IFERROR(IF($S39="",0,$S39),0)+IFERROR(IF($W39="",0,$W39),0)),1,2),1) -> 1 | AK39: =OR(NOT(IFERROR(OR($L39="",AND($L39<>"",$L39>0,VLOOKUP($AB39,药材与丹炉!$N:$O,2,0)=6)),0)),AND($L39<>"",$L39>0,OR(VLOOKUP($AB39,药材与丹炉!$N:$Q,4,0)-2<$N39,$N39="")),AND($U39<>"",$U39>0,OR(VLOOKUP($AB39,药材与丹炉!$N:$Q,4,0)-3<$W39,$W39="")),NOT(OR(AND($Q39<>"",$S39<>"",VLOOKUP($AB39,药材与丹炉!$N:$Q,4,0)-3>=$S39),$P39="")),NOT(OR(AND($H39<>"",$J39<>"",VLOOKUP($AB39,药材与丹炉!$N:$Q,4,0)-1>=$J39),$G39="")),NOT(OR($U39="",AND($U39<>"",$U39>0))),NOT(OR($Y39="",IF($Z39<>"",IFERROR(IF(VLOOKUP($Z39,药材与丹炉!$B:$D,3,0)=-1,$X39=1,IF(VLOOKUP($Z39,药材与丹炉!$B:$D,3,0)=1,$X39=2,$X39=0)),0),0))),$AC39="爆炸",(VLOOKUP($AB39,药材与丹炉!$N:$O,2,0)+8)<$AD39) -> FALSE
A40: 5207 | B40: 3 | C40: 启灵丹 | D40: 3 | E40: 悟性+1/丹毒+2 | F40: 36 | G40: 聚元 | H40: 36 | I40: 天灵果 | J40: =IFERROR(CEILING($H40/VLOOKUP($I40,药材与丹炉!$B:$H,COLUMN(药材与丹炉!$H40)-1,0),1),"") -> 4 | K40: 聚元 | L40: =IFERROR(IF($F40-$H40=0,"",$F40-$H40),"") | N40: =IFERROR(CEILING($L40/VLOOKUP($M40,药材与丹炉!$B:$H,COLUMN(药材与丹炉!$H40)-1,0),1),"") | O40: 63 | P40: 开窍 | Q40: 36 | R40: 冰灵果 | S40: =IFERROR(CEILING($Q40/VLOOKUP($R40,药材与丹炉!$B:$H,COLUMN(药材与丹炉!$H40)-1,0),1),"") -> 4 | T40: =P40 -> 开窍 | U40: =IFERROR(IF(O40-Q40=0,"",O40-Q40),"") -> 27 | V40: 冰灵果 | W40: =IFERROR(CEILING($U40/VLOOKUP($V40,药材与丹炉!$B:$H,COLUMN(药材与丹炉!$H40)-1,0),1),"") -> 3 | X40: =IF(IFERROR(IF(AND($J40>0,$J40<>""),VLOOKUP($I40,药材与丹炉!$B:$D,3,0),0),0)+IFERROR(IF(AND($N40>0,$N40<>""),VLOOKUP($M40,药材与丹炉!$B:$D,3,0),0),0)+IFERROR(IF(AND($S40>0,$S40<>""),VLOOKUP($R40,药材与丹炉!$B:$D,3,0),0),0)+IFERROR(IF(AND($W40>0,$W40<>""),VLOOKUP($V40,药材与丹炉!$B:$D,3,0),0),0)>0,1,IF(IFERROR(IF(AND($J40>0,$J40<>""),VLOOKUP($I40,药材与丹炉!$B:$D,3,0),0),0)+IFERROR(IF(AND($N40>0,$N40<>""),VLOOKUP($M40,药材与丹炉!$B:$D,3,0),0),0)+IFERROR(IF(AND($S40>0,$S40<>""),VLOOKUP($R40,药材与丹炉!$B:$D,3,0),0),0)+IFERROR(IF(AND($W40>0,$W40<>""),VLOOKUP($V40,药材与丹炉!$B:$D,3,0),0),0)<0,2,0)) -> 2 | Y40: 9 | Z40: 天灵果 | AA40: =IFERROR($Y40/VLOOKUP($Z40,药材与丹炉!$B:$H,COLUMN(药材与丹炉!$H40)-1,0),"") -> 1 | AB40: 庚金龙纹炉 | AC40: =IFERROR(IF($B40-VLOOKUP($AB40,药材与丹炉!$N:$P,2,0)<0,IF($AO$1="是",0,1),IF($B40-VLOOKUP($AB40,药材与丹炉!$N:$P,2,0)=0,2,IF($B40-VLOOKUP($AB40,药材与丹炉!$N:$P,2,0)=1,40,IF($B40-VLOOKUP($AB40,药材与丹炉!$N:$P,2,0)=2,80,"爆炸")))),"") -> 1 | AD40: =IFERROR($J40+IFERROR(IF($N40="",0,$N40),0)+IFERROR(IF($S40="",0,$S40),0)+IFERROR(IF($W40="",0,$W40),0)+IFERROR(IF($AA40="",0,$AA40),0),"") -> 12 | AE40: =IFERROR($J40*VLOOKUP($I40,药材与丹炉!$B:$K,10,0),0)+IFERROR($N40*VLOOKUP($M40,药材与丹炉!$B:$K,10,0),0)+IFERROR($S40*VLOOKUP($R40,药材与丹炉!$B:$K,10,0),0)+IFERROR($W40*VLOOKUP($V40,药材与丹炉!$B:$K,10,0),0)+IFERROR($AA40*VLOOKUP($Z40,药材与丹炉!$B:$K,10,0),0)+IFERROR($AC40*VLOOKUP($AB40,药材与丹炉!$N:$P,3,0)/100,0) -> 4960 | AF40: 6250 | AG40: =$AF40-$AE40 -> 1290 | AH40: =$AF40*$AM$1*$AM$21 -> 12500 | AI40: =$AH40-$AE40 -> 7540 | AJ40: =IFERROR(IF($Y40/VLOOKUP($Y40,药材与丹炉!$T:$U,2,0)<=(VLOOKUP($AB40,药材与丹炉!$N:$O,2,0)+8)-($J40+IFERROR(IF($N40="",0,$N40),0)+IFERROR(IF($S40="",0,$S40),0)+IFERROR(IF($W40="",0,$W40),0)),1,2),1) -> 2 | AK40: =OR(NOT(IFERROR(OR($L40="",AND($L40<>"",$L40>0,VLOOKUP($AB40,药材与丹炉!$N:$O,2,0)=6)),0)),AND($L40<>"",$L40>0,OR(VLOOKUP($AB40,药材与丹炉!$N:$Q,4,0)-2<$N40,$N40="")),AND($U40<>"",$U40>0,OR(VLOOKUP($AB40,药材与丹炉!$N:$Q,4,0)-3<$W40,$W40="")),NOT(OR(AND($Q40<>"",$S40<>"",VLOOKUP($AB40,药材与丹炉!$N:$Q,4,0)-3>=$S40),$P40="")),NOT(OR(AND($H40<>"",$J40<>"",VLOOKUP($AB40,药材与丹炉!$N:$Q,4,0)-1>=$J40),$G40="")),NOT(OR($U40="",AND($U40<>"",$U40>0))),NOT(OR($Y40="",IF($Z40<>"",IFERROR(IF(VLOOKUP($Z40,药材与丹炉!$B:$D,3,0)=-1,$X40=1,IF(VLOOKUP($Z40,药材与丹炉!$B:$D,3,0)=1,$X40=2,$X40=0)),0),0))),$AC40="爆炸",(VLOOKUP($AB40,药材与丹炉!$N:$O,2,0)+8)<$AD40) -> FALSE
A41: 5208 | B41: 3 | C41: 草还丹 | D41: 3 | E41: 资质+1/丹毒+2 | F41: 36 | G41: 聚元 | H41: 36 | I41: 天灵果 | J41: =IFERROR(CEILING($H41/VLOOKUP($I41,药材与丹炉!$B:$H,COLUMN(药材与丹炉!$H41)-1,0),1),"") -> 4 | K41: 聚元 | L41: =IFERROR(IF($F41-$H41=0,"",$F41-$H41),"") | N41: =IFERROR(CEILING($L41/VLOOKUP($M41,药材与丹炉!$B:$H,COLUMN(药材与丹炉!$H41)-1,0),1),"") | O41: 54 | P41: 洗髓 | Q41: 36 | R41: 九叶芝 | S41: =IFERROR(CEILING($Q41/VLOOKUP($R41,药材与丹炉!$B:$H,COLUMN(药材与丹炉!$H41)-1,0),1),"") -> 4 | T41: =P41 -> 洗髓 | U41: =IFERROR(IF(O41-Q41=0,"",O41-Q41),"") -> 18 | V41: 九叶芝 | W41: =IFERROR(CEILING($U41/VLOOKUP($V41,药材与丹炉!$B:$H,COLUMN(药材与丹炉!$H41)-1,0),1),"") -> 2 | X41: =IF(IFERROR(IF(AND($J41>0,$J41<>""),VLOOKUP($I41,药材与丹炉!$B:$D,3,0),0),0)+IFERROR(IF(AND($N41>0,$N41<>""),VLOOKUP($M41,药材与丹炉!$B:$D,3,0),0),0)+IFERROR(IF(AND($S41>0,$S41<>""),VLOOKUP($R41,药材与丹炉!$B:$D,3,0),0),0)+IFERROR(IF(AND($W41>0,$W41<>""),VLOOKUP($V41,药材与丹炉!$B:$D,3,0),0),0)>0,1,IF(IFERROR(IF(AND($J41>0,$J41<>""),VLOOKUP($I41,药材与丹炉!$B:$D,3,0),0),0)+IFERROR(IF(AND($N41>0,$N41<>""),VLOOKUP($M41,药材与丹炉!$B:$D,3,0),0),0)+IFERROR(IF(AND($S41>0,$S41<>""),VLOOKUP($R41,药材与丹炉!$B:$D,3,0),0),0)+IFERROR(IF(AND($W41>0,$W41<>""),VLOOKUP($V41,药材与丹炉!$B:$D,3,0),0),0)<0,2,0)) -> 2 | Y41: 9 | Z41: 天灵果 | AA41: =IFERROR($Y41/VLOOKUP($Z41,药材与丹炉!$B:$H,COLUMN(药材与丹炉!$H41)-1,0),"") -> 1 | AB41: 雕花紫铜炉 | AC41: =IFERROR(IF($B41-VLOOKUP($AB41,药材与丹炉!$N:$P,2,0)<0,IF($AO$1="是",0,1),IF($B41-VLOOKUP($AB41,药材与丹炉!$N:$P,2,0)=0,2,IF($B41-VLOOKUP($AB41,药材与丹炉!$N:$P,2,0)=1,40,IF($B41-VLOOKUP($AB41,药材与丹炉!$N:$P,2,0)=2,80,"爆炸")))),"") -> 2 | AD41: =IFERROR($J41+IFERROR(IF($N41="",0,$N41),0)+IFERROR(IF($S41="",0,$S41),0)+IFERROR(IF($W41="",0,$W41),0)+IFERROR(IF($AA41="",0,$AA41),0),"") -> 11 | AE41: =IFERROR($J41*VLOOKUP($I41,药材与丹炉!$B:$K,10,0),0)+IFERROR($N41*VLOOKUP($M41,药材与丹炉!$B:$K,10,0),0)+IFERROR($S41*VLOOKUP($R41,药材与丹炉!$B:$K,10,0),0)+IFERROR($W41*VLOOKUP($V41,药材与丹炉!$B:$K,10,0),0)+IFERROR($AA41*VLOOKUP($Z41,药材与丹炉!$B:$K,10,0),0)+IFERROR($AC41*VLOOKUP($AB41,药材与丹炉!$N:$P,3,0)/100,0) -> 4535 | AF41: 5000 | AG41: =$AF41-$AE41 -> 465 | AH41: =$AF41*$AM$1*$AM$21 -> 10000 | AI41: =$AH41-$AE41 -> 5465 | AJ41: =IFERROR(IF($Y41/VLOOKUP($Y41,药材与丹炉!$T:$U,2,0)<=(VLOOKUP($AB41,药材与丹炉!$N:$O,2,0)+8)-($J41+IFERROR(IF($N41="",0,$N41),0)+IFERROR(IF($S41="",0,$S41),0)+IFERROR(IF($W41="",0,$W41),0)),1,2),1) -> 2 | AK41: =OR(NOT(IFERROR(OR($L41="",AND($L41<>"",$L41>0,VLOOKUP($AB41,药材与丹炉!$N:$O,2,0)=6)),0)),AND($L41<>"",$L41>0,OR(VLOOKUP($AB41,药材与丹炉!$N:$Q,4,0)-2<$N41,$N41="")),AND($U41<>"",$U41>0,OR(VLOOKUP($AB41,药材与丹炉!$N:$Q,4,0)-3<$W41,$W41="")),NOT(OR(AND($Q41<>"",$S41<>"",VLOOKUP($AB41,药材与丹炉!$N:$Q,4,0)-3>=$S41),$P41="")),NOT(OR(AND($H41<>"",$J41<>"",VLOOKUP($AB41,药材与丹炉!$N:$Q,4,0)-1>=$J41),$G41="")),NOT(OR($U41="",AND($U41<>"",$U41>0))),NOT(OR($Y41="",IF($Z41<>"",IFERROR(IF(VLOOKUP($Z41,药材与丹炉!$B:$D,3,0)=-1,$X41=1,IF(VLOOKUP($Z41,药材与丹炉!$B:$D,3,0)=1,$X41=2,$X41=0)),0),0))),$AC41="爆炸",(VLOOKUP($AB41,药材与丹炉!$N:$O,2,0)+8)<$AD41) -> FALSE
A42: 5209 | B42: 3 | C42: 煅体丹 | D42: 5 | E42: 生命值上限+3/丹毒+2 | F42: 27 | G42: 聚元 | H42: 27 | I42: 天灵果 | J42: =IFERROR(CEILING($H42/VLOOKUP($I42,药材与丹炉!$B:$H,COLUMN(药材与丹炉!$H42)-1,0),1),"") -> 3 | K42: 聚元 | L42: =IFERROR(IF($F42-$H42=0,"",$F42-$H42),"") | N42: =IFERROR(CEILING($L42/VLOOKUP($M42,药材与丹炉!$B:$H,COLUMN(药材与丹炉!$H42)-1,0),1),"") | O42: 27 | P42: 煅体 | Q42: 27 | R42: 龙鳞果 | S42: =IFERROR(CEILING($Q42/VLOOKUP($R42,药材与丹炉!$B:$H,COLUMN(药材与丹炉!$H42)-1,0),1),"") -> 3 | T42: =P42 -> 煅体 | U42: =IFERROR(IF($O42-$Q42=0,"",$O42-$Q42),"") | W42: =IFERROR(CEILING($U42/VLOOKUP($V42,药材与丹炉!$B:$H,COLUMN(药材与丹炉!$H42)-1,0),1),"") | X42: =IF(IFERROR(IF(AND($J42>0,$J42<>""),VLOOKUP($I42,药材与丹炉!$B:$D,3,0),0),0)+IFERROR(IF(AND($N42>0,$N42<>""),VLOOKUP($M42,药材与丹炉!$B:$D,3,0),0),0)+IFERROR(IF(AND($S42>0,$S42<>""),VLOOKUP($R42,药材与丹炉!$B:$D,3,0),0),0)+IFERROR(IF(AND($W42>0,$W42<>""),VLOOKUP($V42,药材与丹炉!$B:$D,3,0),0),0)>0,1,IF(IFERROR(IF(AND($J42>0,$J42<>""),VLOOKUP($I42,药材与丹炉!$B:$D,3,0),0),0)+IFERROR(IF(AND($N42>0,$N42<>""),VLOOKUP($M42,药材与丹炉!$B:$D,3,0),0),0)+IFERROR(IF(AND($S42>0,$S42<>""),VLOOKUP($R42,药材与丹炉!$B:$D,3,0),0),0)+IFERROR(IF(AND($W42>0,$W42<>""),VLOOKUP($V42,药材与丹炉!$B:$D,3,0),0),0)<0,2,0)) -> 1 | Y42: 9 | Z42: 轻灵草 | AA42: =IFERROR($Y42/VLOOKUP($Z42,药材与丹炉!$B:$H,COLUMN(药材与丹炉!$H42)-1,0),"") -> 3 | AB42: 雕花紫铜炉 | AC42: =IFERROR(IF($B42-VLOOKUP($AB42,药材与丹炉!$N:$P,2,0)<0,IF($AO$1="是",0,1),IF($B42-VLOOKUP($AB42,药材与丹炉!$N:$P,2,0)=0,2,IF($B42-VLOOKUP($AB42,药材与丹炉!$N:$P,2,0)=1,40,IF($B42-VLOOKUP($AB42,药材与丹炉!$N:$P,2,0)=2,80,"爆炸")))),"") -> 2 | AD42: =IFERROR($J42+IFERROR(IF($N42="",0,$N42),0)+IFERROR(IF($S42="",0,$S42),0)+IFERROR(IF($W42="",0,$W42),0)+IFERROR(IF($AA42="",0,$AA42),0),"") -> 9 | AE42: =IFERROR($J42*VLOOKUP($I42,药材与丹炉!$B:$K,10,0),0)+IFERROR($N42*VLOOKUP($M42,药材与丹炉!$B:$K,10,0),0)+IFERROR($S42*VLOOKUP($R42,药材与丹炉!$B:$K,10,0),0)+IFERROR($W42*VLOOKUP($V42,药材与丹炉!$B:$K,10,0),0)+IFERROR($AA42*VLOOKUP($Z42,药材与丹炉!$B:$K,10,0),0)+IFERROR($AC42*VLOOKUP($AB42,药材与丹炉!$N:$P,3,0)/100,0) -> 2618 | AF42: 2500 | AG42: =$AF42-$AE42 -> -118 | AH42: =$AF42*$AM$1*$AM$21 -> 5000 | AI42: =$AH42-$AE42 -> 2382 | AJ42: =IFERROR(IF($Y42/VLOOKUP($Y42,药材与丹炉!$T:$U,2,0)<=(VLOOKUP($AB42,药材与丹炉!$N:$O,2,0)+8)-($J42+IFERROR(IF($N42="",0,$N42),0)+IFERROR(IF($S42="",0,$S42),0)+IFERROR(IF($W42="",0,$W42),0)),1,2),1) -> 1 | AK42: =OR(NOT(IFERROR(OR($L42="",AND($L42<>"",$L42>0,VLOOKUP($AB42,药材与丹炉!$N:$O,2,0)=6)),0)),AND($L42<>"",$L42>0,OR(VLOOKUP($AB42,药材与丹炉!$N:$Q,4,0)-2<$N42,$N42="")),AND($U42<>"",$U42>0,OR(VLOOKUP($AB42,药材与丹炉!$N:$Q,4,0)-3<$W42,$W42="")),NOT(OR(AND($Q42<>"",$S42<>"",VLOOKUP($AB42,药材与丹炉!$N:$Q,4,0)-3>=$S42),$P42="")),NOT(OR(AND($H42<>"",$J42<>"",VLOOKUP($AB42,药材与丹炉!$N:$Q,4,0)-1>=$J42),$G42="")),NOT(OR($U42="",AND($U42<>"",$U42>0))),NOT(OR($Y42="",IF($Z42<>"",IFERROR(IF(VLOOKUP($Z42,药材与丹炉!$B:$D,3,0)=-1,$X42=1,IF(VLOOKUP($Z42,药材与丹炉!$B:$D,3,0)=1,$X42=2,$X42=0)),0),0))),$AC42="爆炸",(VLOOKUP($AB42,药材与丹炉!$N:$O,2,0)+8)<$AD42) -> FALSE
A43: 5210 | B43: 3 | C43: 御风丹 | D43: 5 | E43: 遁速+1/丹毒+2 | F43: 27 | G43: 聚元 | H43: 27 | I43: 天灵果 | J43: =IFERROR(CEILING($H43/VLOOKUP($I43,药材与丹炉!$B:$H,COLUMN(药材与丹炉!$H43)-1,0),1),"") -> 3 | K43: 聚元 | L43: =IFERROR(IF($F43-$H43=0,"",$F43-$H43),"") | N43: =IFERROR(CEILING($L43/VLOOKUP($M43,药材与丹炉!$B:$H,COLUMN(药材与丹炉!$H43)-1,0),1),"") | O43: 18 | P43: 神行 | Q43: 18 | R43: 夏枯草 | S43: =IFERROR(CEILING($Q43/VLOOKUP($R43,药材与丹炉!$B:$H,COLUMN(药材与丹炉!$H43)-1,0),1),"") -> 6 | T43: =P43 -> 神行 | U43: =IFERROR(IF($O43-$Q43=0,"",$O43-$Q43),"") | W43: =IFERROR(CEILING($U43/VLOOKUP($V43,药材与丹炉!$B:$H,COLUMN(药材与丹炉!$H43)-1,0),1),"") | X43: =IF(IFERROR(IF(AND($J43>0,$J43<>""),VLOOKUP($I43,药材与丹炉!$B:$D,3,0),0),0)+IFERROR(IF(AND($N43>0,$N43<>""),VLOOKUP($M43,药材与丹炉!$B:$D,3,0),0),0)+IFERROR(IF(AND($S43>0,$S43<>""),VLOOKUP($R43,药材与丹炉!$B:$D,3,0),0),0)+IFERROR(IF(AND($W43>0,$W43<>""),VLOOKUP($V43,药材与丹炉!$B:$D,3,0),0),0)>0,1,IF(IFERROR(IF(AND($J43>0,$J43<>""),VLOOKUP($I43,药材与丹炉!$B:$D,3,0),0),0)+IFERROR(IF(AND($N43>0,$N43<>""),VLOOKUP($M43,药材与丹炉!$B:$D,3,0),0),0)+IFERROR(IF(AND($S43>0,$S43<>""),VLOOKUP($R43,药材与丹炉!$B:$D,3,0),0),0)+IFERROR(IF(AND($W43>0,$W43<>""),VLOOKUP($V43,药材与丹炉!$B:$D,3,0),0),0)<0,2,0)) -> 1 | Y43: 3 | Z43: 轻灵草 | AA43: =IFERROR($Y43/VLOOKUP($Z43,药材与丹炉!$B:$H,COLUMN(药材与丹炉!$H43)-1,0),"") -> 1 | AB43: 雕花紫铜炉 | AC43: =IFERROR(IF($B43-VLOOKUP($AB43,药材与丹炉!$N:$P,2,0)<0,IF($AO$1="是",0,1),IF($B43-VLOOKUP($AB43,药材与丹炉!$N:$P,2,0)=0,2,IF($B43-VLOOKUP($AB43,药材与丹炉!$N:$P,2,0)=1,40,IF($B43-VLOOKUP($AB43,药材与丹炉!$N:$P,2,0)=2,80,"爆炸")))),"") -> 2 | AD43: =IFERROR($J43+IFERROR(IF($N43="",0,$N43),0)+IFERROR(IF($S43="",0,$S43),0)+IFERROR(IF($W43="",0,$W43),0)+IFERROR(IF($AA43="",0,$AA43),0),"") -> 10 | AE43: =IFERROR($J43*VLOOKUP($I43,药材与丹炉!$B:$K,10,0),0)+IFERROR($N43*VLOOKUP($M43,药材与丹炉!$B:$K,10,0),0)+IFERROR($S43*VLOOKUP($R43,药材与丹炉!$B:$K,10,0),0)+IFERROR($W43*VLOOKUP($V43,药材与丹炉!$B:$K,10,0),0)+IFERROR($AA43*VLOOKUP($Z43,药材与丹炉!$B:$K,10,0),0)+IFERROR($AC43*VLOOKUP($AB43,药材与丹炉!$N:$P,3,0)/100,0) -> 1547 | AF43: 1875 | AG43: =$AF43-$AE43 -> 328 | AH43: =$AF43*$AM$1*$AM$21 -> 3750 | AI43: =$AH43-$AE43 -> 2203 | AJ43: =IFERROR(IF($Y43/VLOOKUP($Y43,药材与丹炉!$T:$U,2,0)<=(VLOOKUP($AB43,药材与丹炉!$N:$O,2,0)+8)-($J43+IFERROR(IF($N43="",0,$N43),0)+IFERROR(IF($S43="",0,$S43),0)+IFERROR(IF($W43="",0,$W43),0)),1,2),1) -> 2 | AK43: =OR(NOT(IFERROR(OR($L43="",AND($L43<>"",$L43>0,VLOOKUP($AB43,药材与丹炉!$N:$O,2,0)=6)),0)),AND($L43<>"",$L43>0,OR(VLOOKUP($AB43,药材与丹炉!$N:$Q,4,0)-2<$N43,$N43="")),AND($U43<>"",$U43>0,OR(VLOOKUP($AB43,药材与丹炉!$N:$Q,4,0)-3<$W43,$W43="")),NOT(OR(AND($Q43<>"",$S43<>"",VLOOKUP($AB43,药材与丹炉!$N:$Q,4,0)-3>=$S43),$P43="")),NOT(OR(AND($H43<>"",$J43<>"",VLOOKUP($AB43,药材与丹炉!$N:$Q,4,0)-1>=$J43),$G43="")),NOT(OR($U43="",AND($U43<>"",$U43>0))),NOT(OR($Y43="",IF($Z43<>"",IFERROR(IF(VLOOKUP($Z43,药材与丹炉!$B:$D,3,0)=-1,$X43=1,IF(VLOOKUP($Z43,药材与丹炉!$B:$D,3,0)=1,$X43=2,$X43=0)),0),0))),$AC43="爆炸",(VLOOKUP($AB43,药材与丹炉!$N:$O,2,0)+8)<$AD43) -> FALSE
A44: 5211 | B44: 3 | C44: 延寿丹 | D44: 3 | E44: 寿元+10/丹毒+2 | F44: 54 | G44: 聚元 | H44: 54 | I44: 雪凝花 | J44: =IFERROR(CEILING($H44/VLOOKUP($I44,药材与丹炉!$B:$H,COLUMN(药材与丹炉!$H44)-1,0),1),"") -> 6 | K44: 聚元 | L44: =IFERROR(IF($F44-$H44=0,"",$F44-$H44),"") | N44: =IFERROR(CEILING($L44/VLOOKUP($M44,药材与丹炉!$B:$H,COLUMN(药材与丹炉!$H44)-1,0),1),"") | O44: 36 | P44: 益寿 | Q44: 36 | R44: 玉龙参 | S44: =IFERROR(CEILING($Q44/VLOOKUP($R44,药材与丹炉!$B:$H,COLUMN(药材与丹炉!$H44)-1,0),1),"") -> 4 | T44: =P44 -> 益寿 | U44: =IFERROR(IF($O44-$Q44=0,"",$O44-$Q44),"") | W44: =IFERROR(CEILING($U44/VLOOKUP($V44,药材与丹炉!$B:$H,COLUMN(药材与丹炉!$H44)-1,0),1),"") | X44: =IF(IFERROR(IF(AND($J44>0,$J44<>""),VLOOKUP($I44,药材与丹炉!$B:$D,3,0),0),0)+IFERROR(IF(AND($N44>0,$N44<>""),VLOOKUP($M44,药材与丹炉!$B:$D,3,0),0),0)+IFERROR(IF(AND($S44>0,$S44<>""),VLOOKUP($R44,药材与丹炉!$B:$D,3,0),0),0)+IFERROR(IF(AND($W44>0,$W44<>""),VLOOKUP($V44,药材与丹炉!$B:$D,3,0),0),0)>0,1,IF(IFERROR(IF(AND($J44>0,$J44<>""),VLOOKUP($I44,药材与丹炉!$B:$D,3,0),0),0)+IFERROR(IF(AND($N44>0,$N44<>""),VLOOKUP($M44,药材与丹炉!$B:$D,3,0),0),0)+IFERROR(IF(AND($S44>0,$S44<>""),VLOOKUP($R44,药材与丹炉!$B:$D,3,0),0),0)+IFERROR(IF(AND($W44>0,$W44<>""),VLOOKUP($V44,药材与丹炉!$B:$D,3,0),0),0)<0,2,0)) -> 2 | Y44: 3 | Z44: 蛇涎果 | AA44: =IFERROR($Y44/VLOOKUP($Z44,药材与丹炉!$B:$H,COLUMN(药材与丹炉!$H44)-1,0),"") -> 1 | AB44: 雕花紫铜炉 | AC44: =IFERROR(IF($B44-VLOOKUP($AB44,药材与丹炉!$N:$P,2,0)<0,IF($AO$1="是",0,1),IF($B44-VLOOKUP($AB44,药材与丹炉!$N:$P,2,0)=0,2,IF($B44-VLOOKUP($AB44,药材与丹炉!$N:$P,2,0)=1,40,IF($B44-VLOOKUP($AB44,药材与丹炉!$N:$P,2,0)=2,80,"爆炸")))),"") -> 2 | AD44: =IFERROR($J44+IFERROR(IF($N44="",0,$N44),0)+IFERROR(IF($S44="",0,$S44),0)+IFERROR(IF($W44="",0,$W44),0)+IFERROR(IF($AA44="",0,$AA44),0),"") -> 11 | AE44: =IFERROR($J44*VLOOKUP($I44,药材与丹炉!$B:$K,10,0),0)+IFERROR($N44*VLOOKUP($M44,药材与丹炉!$B:$K,10,0),0)+IFERROR($S44*VLOOKUP($R44,药材与丹炉!$B:$K,10,0),0)+IFERROR($W44*VLOOKUP($V44,药材与丹炉!$B:$K,10,0),0)+IFERROR($AA44*VLOOKUP($Z44,药材与丹炉!$B:$K,10,0),0)+IFERROR($AC44*VLOOKUP($AB44,药材与丹炉!$N:$P,3,0)/100,0) -> 4166 | AF44: 5000 | AG44: =$AF44-$AE44 -> 834 | AH44: =$AF44*$AM$1*$AM$21 -> 10000 | AI44: =$AH44-$AE44 -> 5834 | AJ44: =IFERROR(IF($Y44/VLOOKUP($Y44,药材与丹炉!$T:$U,2,0)<=(VLOOKUP($AB44,药材与丹炉!$N:$O,2,0)+8)-($J44+IFERROR(IF($N44="",0,$N44),0)+IFERROR(IF($S44="",0,$S44),0)+IFERROR(IF($W44="",0,$W44),0)),1,2),1) -> 2 | AK44: =OR(NOT(IFERROR(OR($L44="",AND($L44<>"",$L44>0,VLOOKUP($AB44,药材与丹炉!$N:$O,2,0)=6)),0)),AND($L44<>"",$L44>0,OR(VLOOKUP($AB44,药材与丹炉!$N:$Q,4,0)-2<$N44,$N44="")),AND($U44<>"",$U44>0,OR(VLOOKUP($AB44,药材与丹炉!$N:$Q,4,0)-3<$W44,$W44="")),NOT(OR(AND($Q44<>"",$S44<>"",VLOOKUP($AB44,药材与丹炉!$N:$Q,4,0)-3>=$S44),$P44="")),NOT(OR(AND($H44<>"",$J44<>"",VLOOKUP($AB44,药材与丹炉!$N:$Q,4,0)-1>=$J44),$G44="")),NOT(OR($U44="",AND($U44<>"",$U44>0))),NOT(OR($Y44="",IF($Z44<>"",IFERROR(IF(VLOOKUP($Z44,药材与丹炉!$B:$D,3,0)=-1,$X44=1,IF(VLOOKUP($Z44,药材与丹炉!$B:$D,3,0)=1,$X44=2,$X44=0)),0),0))),$AC44="爆炸",(VLOOKUP($AB44,药材与丹炉!$N:$O,2,0)+8)<$AD44) -> FALSE
A45: 5212 | B45: 3 | C45: 清脉丹 | D45: 10 | E45: 丹毒-10 | F45: 27 | G45: 净血 | H45: 27 | I45: 锦地罗 | J45: =IFERROR(CEILING($H45/VLOOKUP($I45,药材与丹炉!$B:$H,COLUMN(药材与丹炉!$H45)-1,0),1),"") -> 3 | K45: 净血 | L45: =IFERROR(IF($F45-$H45=0,"",$F45-$H45),"") | N45: =IFERROR(CEILING($L45/VLOOKUP($M45,药材与丹炉!$B:$H,COLUMN(药材与丹炉!$H45)-1,0),1),"") | O45: 21 | P45: 解毒 | Q45: 9 | R45: 龙葵 | S45: =IFERROR(CEILING($Q45/VLOOKUP($R45,药材与丹炉!$B:$H,COLUMN(药材与丹炉!$H45)-1,0),1),"") -> 3 | T45: =P45 -> 解毒 | U45: =IFERROR(IF($O45-$Q45=0,"",$O45-$Q45),"") -> 12 | V45: 龙葵 | W45: =IFERROR(CEILING($U45/VLOOKUP($V45,药材与丹炉!$B:$H,COLUMN(药材与丹炉!$H45)-1,0),1),"") -> 4 | X45: =IF(IFERROR(IF(AND($J45>0,$J45<>""),VLOOKUP($I45,药材与丹炉!$B:$D,3,0),0),0)+IFERROR(IF(AND($N45>0,$N45<>""),VLOOKUP($M45,药材与丹炉!$B:$D,3,0),0),0)+IFERROR(IF(AND($S45>0,$S45<>""),VLOOKUP($R45,药材与丹炉!$B:$D,3,0),0),0)+IFERROR(IF(AND($W45>0,$W45<>""),VLOOKUP($V45,药材与丹炉!$B:$D,3,0),0),0)>0,1,IF(IFERROR(IF(AND($J45>0,$J45<>""),VLOOKUP($I45,药材与丹炉!$B:$D,3,0),0),0)+IFERROR(IF(AND($N45>0,$N45<>""),VLOOKUP($M45,药材与丹炉!$B:$D,3,0),0),0)+IFERROR(IF(AND($S45>0,$S45<>""),VLOOKUP($R45,药材与丹炉!$B:$D,3,0),0),0)+IFERROR(IF(AND($W45>0,$W45<>""),VLOOKUP($V45,药材与丹炉!$B:$D,3,0),0),0)<0,2,0)) -> 2 | Y45: 3 | Z45: 地黄参 | AA45: =IFERROR($Y45/VLOOKUP($Z45,药材与丹炉!$B:$H,COLUMN(药材与丹炉!$H45)-1,0),"") -> 1 | AB45: 雕花紫铜炉 | AC45: =IFERROR(IF($B45-VLOOKUP($AB45,药材与丹炉!$N:$P,2,0)<0,IF($AO$1="是",0,1),IF($B45-VLOOKUP($AB45,药材与丹炉!$N:$P,2,0)=0,2,IF($B45-VLOOKUP($AB45,药材与丹炉!$N:$P,2,0)=1,40,IF($B45-VLOOKUP($AB45,药材与丹炉!$N:$P,2,0)=2,80,"爆炸")))),"") -> 2 | AD45: =IFERROR($J45+IFERROR(IF($N45="",0,$N45),0)+IFERROR(IF($S45="",0,$S45),0)+IFERROR(IF($W45="",0,$W45),0)+IFERROR(IF($AA45="",0,$AA45),0),"") -> 11 | AE45: =IFERROR($J45*VLOOKUP($I45,药材与丹炉!$B:$K,10,0),0)+IFERROR($N45*VLOOKUP($M45,药材与丹炉!$B:$K,10,0),0)+IFERROR($S45*VLOOKUP($R45,药材与丹炉!$B:$K,10,0),0)+IFERROR($W45*VLOOKUP($V45,药材与丹炉!$B:$K,10,0),0)+IFERROR($AA45*VLOOKUP($Z45,药材与丹炉!$B:$K,10,0),0)+IFERROR($AC45*VLOOKUP($AB45,药材与丹炉!$N:$P,3,0)/100,0) -> 1583 | AF45: 1500 | AG45: =$AF45-$AE45 -> -83 | AH45: =$AF45*$AM$1*$AM$21 -> 3000 | AI45: =$AH45-$AE45 -> 1417 | AJ45: =IFERROR(IF($Y45/VLOOKUP($Y45,药材与丹炉!$T:$U,2,0)<=(VLOOKUP($AB45,药材与丹炉!$N:$O,2,0)+8)-($J45+IFERROR(IF($N45="",0,$N45),0)+IFERROR(IF($S45="",0,$S45),0)+IFERROR(IF($W45="",0,$W45),0)),1,2),1) -> 2 | AK45: =OR(NOT(IFERROR(OR($L45="",AND($L45<>"",$L45>0,VLOOKUP($AB45,药材与丹炉!$N:$O,2,0)=6)),0)),AND($L45<>"",$L45>0,OR(VLOOKUP($AB45,药材与丹炉!$N:$Q,4,0)-2<$N45,$N45="")),AND($U45<>"",$U45>0,OR(VLOOKUP($AB45,药材与丹炉!$N:$Q,4,0)-3<$W45,$W45="")),NOT(OR(AND($Q45<>"",$S45<>"",VLOOKUP($AB45,药材与丹炉!$N:$Q,4,0)-3>=$S45),$P45="")),NOT(OR(AND($H45<>"",$J45<>"",VLOOKUP($AB45,药材与丹炉!$N:$Q,4,0)-1>=$J45),$G45="")),NOT(OR($U45="",AND($U45<>"",$U45>0))),NOT(OR($Y45="",IF($Z45<>"",IFERROR(IF(VLOOKUP($Z45,药材与丹炉!$B:$D,3,0)=-1,$X45=1,IF(VLOOKUP($Z45,药材与丹炉!$B:$D,3,0)=1,$X45=2,$X45=0)),0),0))),$AC45="爆炸",(VLOOKUP($AB45,药材与丹炉!$N:$O,2,0)+8)<$AD45) -> FALSE
A46: 5213 | B46: 3 | C46: 幻心玄丹 | D46: 50 | E46: 心境+6 | F46: 27 | G46: 聚元 | H46: 27 | I46: 天灵果 | J46: =IFERROR(CEILING($H46/VLOOKUP($I46,药材与丹炉!$B:$H,COLUMN(药材与丹炉!$H46)-1,0),1),"") -> 3 | K46: 聚元 | L46: =IFERROR(IF($F46-$H46=0,"",$F46-$H46),"") | N46: =IFERROR(CEILING($L46/VLOOKUP($M46,药材与丹炉!$B:$H,COLUMN(药材与丹炉!$H46)-1,0),1),"") | P46: 清心 | Q46: 9 | R46: 七星草 | S46: =IFERROR(CEILING($Q46/VLOOKUP($R46,药材与丹炉!$B:$H,COLUMN(药材与丹炉!$H46)-1,0),1),"") -> 3 | T46: 调和 | U46: 9 | V46: 百草露 | W46: =IFERROR(CEILING($U46/VLOOKUP($V46,药材与丹炉!$B:$H,COLUMN(药材与丹炉!$H46)-1,0),1),"") -> 3 | X46: =IF(IFERROR(IF(AND($J46>0,$J46<>""),VLOOKUP($I46,药材与丹炉!$B:$D,3,0),0),0)+IFERROR(IF(AND($N46>0,$N46<>""),VLOOKUP($M46,药材与丹炉!$B:$D,3,0),0),0)+IFERROR(IF(AND($S46>0,$S46<>""),VLOOKUP($R46,药材与丹炉!$B:$D,3,0),0),0)+IFERROR(IF(AND($W46>0,$W46<>""),VLOOKUP($V46,药材与丹炉!$B:$D,3,0),0),0)>0,1,IF(IFERROR(IF(AND($J46>0,$J46<>""),VLOOKUP($I46,药材与丹炉!$B:$D,3,0),0),0)+IFERROR(IF(AND($N46>0,$N46<>""),VLOOKUP($M46,药材与丹炉!$B:$D,3,0),0),0)+IFERROR(IF(AND($S46>0,$S46<>""),VLOOKUP($R46,药材与丹炉!$B:$D,3,0),0),0)+IFERROR(IF(AND($W46>0,$W46<>""),VLOOKUP($V46,药材与丹炉!$B:$D,3,0),0),0)<0,2,0)) -> 1 | Y46: 9 | Z46: 龙葵 | AA46: =IFERROR($Y46/VLOOKUP($Z46,药材与丹炉!$B:$H,COLUMN(药材与丹炉!$H46)-1,0),"") -> 3 | AB46: 庚金龙纹炉 | AC46: =IFERROR(IF($B46-VLOOKUP($AB46,药材与丹炉!$N:$P,2,0)<0,IF($AO$1="是",0,1),IF($B46-VLOOKUP($AB46,药材与丹炉!$N:$P,2,0)=0,2,IF($B46-VLOOKUP($AB46,药材与丹炉!$N:$P,2,0)=1,40,IF($B46-VLOOKUP($AB46,药材与丹炉!$N:$P,2,0)=2,80,"爆炸")))),"") -> 1 | AD46: =IFERROR($J46+IFERROR(IF($N46="",0,$N46),0)+IFERROR(IF($S46="",0,$S46),0)+IFERROR(IF($W46="",0,$W46),0)+IFERROR(IF($AA46="",0,$AA46),0),"") -> 12 | AE46: =IFERROR($J46*VLOOKUP($I46,药材与丹炉!$B:$K,10,0),0)+IFERROR($N46*VLOOKUP($M46,药材与丹炉!$B:$K,10,0),0)+IFERROR($S46*VLOOKUP($R46,药材与丹炉!$B:$K,10,0),0)+IFERROR($W46*VLOOKUP($V46,药材与丹炉!$B:$K,10,0),0)+IFERROR($AA46*VLOOKUP($Z46,药材与丹炉!$B:$K,10,0),0)+IFERROR($AC46*VLOOKUP($AB46,药材与丹炉!$N:$P,3,0)/100,0) -> 1639 | AF46: 1250 | AG46: =$AF46-$AE46 -> -389 | AH46: =$AF46*$AM$1*$AM$21 -> 2500 | AI46: =$AH46-$AE46 -> 861 | AJ46: =IFERROR(IF($Y46/VLOOKUP($Y46,药材与丹炉!$T:$U,2,0)<=(VLOOKUP($AB46,药材与丹炉!$N:$O,2,0)+8)-($J46+IFERROR(IF($N46="",0,$N46),0)+IFERROR(IF($S46="",0,$S46),0)+IFERROR(IF($W46="",0,$W46),0)),1,2),1) -> 1 | AK46: =OR(NOT(IFERROR(OR($L46="",AND($L46<>"",$L46>0,VLOOKUP($AB46,药材与丹炉!$N:$O,2,0)=6)),0)),AND($L46<>"",$L46>0,OR(VLOOKUP($AB46,药材与丹炉!$N:$Q,4,0)-2<$N46,$N46="")),AND($U46<>"",$U46>0,OR(VLOOKUP($AB46,药材与丹炉!$N:$Q,4,0)-3<$W46,$W46="")),NOT(OR(AND($Q46<>"",$S46<>"",VLOOKUP($AB46,药材与丹炉!$N:$Q,4,0)-3>=$S46),$P46="")),NOT(OR(AND($H46<>"",$J46<>"",VLOOKUP($AB46,药材与丹炉!$N:$Q,4,0)-1>=$J46),$G46="")),NOT(OR($U46="",AND($U46<>"",$U46>0))),NOT(OR($Y46="",IF($Z46<>"",IFERROR(IF(VLOOKUP($Z46,药材与丹炉!$B:$D,3,0)=-1,$X46=1,IF(VLOOKUP($Z46,药材与丹炉!$B:$D,3,0)=1,$X46=2,$X46=0)),0),0))),$AC46="爆炸",(VLOOKUP($AB46,药材与丹炉!$N:$O,2,0)+8)<$AD46) -> FALSE
A47: 5214 | B47: 3 | C47: 溯金丹 | D47: 50 | E47: 下场战斗开始时，金系灵根权重+30/丹毒+3 | F47: 9 | G47: 振气 | H47: 9 | I47: 夏枯草 | J47: =IFERROR(CEILING($H47/VLOOKUP($I47,药材与丹炉!$B:$H,COLUMN(药材与丹炉!$H47)-1,0),1),"") -> 3 | K47: 振气 | L47: =IFERROR(IF($F47-$H47=0,"",$F47-$H47),"") | N47: =IFERROR(CEILING($L47/VLOOKUP($M47,药材与丹炉!$B:$H,COLUMN(药材与丹炉!$H47)-1,0),1),"") | P47: 强金 | Q47: 9 | R47: 罗犀草 | S47: =IFERROR(CEILING($Q47/VLOOKUP($R47,药材与丹炉!$B:$H,COLUMN(药材与丹炉!$H47)-1,0),1),"") -> 3 | T47: 调和 | U47: 9 | V47: 百草露 | W47: =IFERROR(CEILING($U47/VLOOKUP($V47,药材与丹炉!$B:$H,COLUMN(药材与丹炉!$H47)-1,0),1),"") -> 3 | X47: =IF(IFERROR(IF(AND($J47>0,$J47<>""),VLOOKUP($I47,药材与丹炉!$B:$D,3,0),0),0)+IFERROR(IF(AND($N47>0,$N47<>""),VLOOKUP($M47,药材与丹炉!$B:$D,3,0),0),0)+IFERROR(IF(AND($S47>0,$S47<>""),VLOOKUP($R47,药材与丹炉!$B:$D,3,0),0),0)+IFERROR(IF(AND($W47>0,$W47<>""),VLOOKUP($V47,药材与丹炉!$B:$D,3,0),0),0)>0,1,IF(IFERROR(IF(AND($J47>0,$J47<>""),VLOOKUP($I47,药材与丹炉!$B:$D,3,0),0),0)+IFERROR(IF(AND($N47>0,$N47<>""),VLOOKUP($M47,药材与丹炉!$B:$D,3,0),0),0)+IFERROR(IF(AND($S47>0,$S47<>""),VLOOKUP($R47,药材与丹炉!$B:$D,3,0),0),0)+IFERROR(IF(AND($W47>0,$W47<>""),VLOOKUP($V47,药材与丹炉!$B:$D,3,0),0),0)<0,2,0)) -> 1 | Y47: 3 | Z47: 夜交藤 | AA47: =IFERROR($Y47/VLOOKUP($Z47,药材与丹炉!$B:$H,COLUMN(药材与丹炉!$H47)-1,0),"") -> 1 | AB47: 雕花紫铜炉 | AC47: =IFERROR(IF($B47-VLOOKUP($AB47,药材与丹炉!$N:$P,2,0)<0,IF($AO$1="是",0,1),IF($B47-VLOOKUP($AB47,药材与丹炉!$N:$P,2,0)=0,2,IF($B47-VLOOKUP($AB47,药材与丹炉!$N:$P,2,0)=1,40,IF($B47-VLOOKUP($AB47,药材与丹炉!$N:$P,2,0)=2,80,"爆炸")))),"") -> 2 | AD47: =IFERROR($J47+IFERROR(IF($N47="",0,$N47),0)+IFERROR(IF($S47="",0,$S47),0)+IFERROR(IF($W47="",0,$W47),0)+IFERROR(IF($AA47="",0,$AA47),0),"") -> 10 | AE47: =IFERROR($J47*VLOOKUP($I47,药材与丹炉!$B:$K,10,0),0)+IFERROR($N47*VLOOKUP($M47,药材与丹炉!$B:$K,10,0),0)+IFERROR($S47*VLOOKUP($R47,药材与丹炉!$B:$K,10,0),0)+IFERROR($W47*VLOOKUP($V47,药材与丹炉!$B:$K,10,0),0)+IFERROR($AA47*VLOOKUP($Z47,药材与丹炉!$B:$K,10,0),0)+IFERROR($AC47*VLOOKUP($AB47,药材与丹炉!$N:$P,3,0)/100,0) -> 440 | AF47: 1000 | AG47: =$AF47-$AE47 -> 560 | AH47: =$AF47*$AM$1*$AM$21 -> 2000 | AI47: =$AH47-$AE47 -> 1560 | AJ47: =IFERROR(IF($Y47/VLOOKUP($Y47,药材与丹炉!$T:$U,2,0)<=(VLOOKUP($AB47,药材与丹炉!$N:$O,2,0)+8)-($J47+IFERROR(IF($N47="",0,$N47),0)+IFERROR(IF($S47="",0,$S47),0)+IFERROR(IF($W47="",0,$W47),0)),1,2),1) -> 2 | AK47: =OR(NOT(IFERROR(OR($L47="",AND($L47<>"",$L47>0,VLOOKUP($AB47,药材与丹炉!$N:$O,2,0)=6)),0)),AND($L47<>"",$L47>0,OR(VLOOKUP($AB47,药材与丹炉!$N:$Q,4,0)-2<$N47,$N47="")),AND($U47<>"",$U47>0,OR(VLOOKUP($AB47,药材与丹炉!$N:$Q,4,0)-3<$W47,$W47="")),NOT(OR(AND($Q47<>"",$S47<>"",VLOOKUP($AB47,药材与丹炉!$N:$Q,4,0)-3>=$S47),$P47="")),NOT(OR(AND($H47<>"",$J47<>"",VLOOKUP($AB47,药材与丹炉!$N:$Q,4,0)-1>=$J47),$G47="")),NOT(OR($U47="",AND($U47<>"",$U47>0))),NOT(OR($Y47="",IF($Z47<>"",IFERROR(IF(VLOOKUP($Z47,药材与丹炉!$B:$D,3,0)=-1,$X47=1,IF(VLOOKUP($Z47,药材与丹炉!$B:$D,3,0)=1,$X47=2,$X47=0)),0),0))),$AC47="爆炸",(VLOOKUP($AB47,药材与丹炉!$N:$O,2,0)+8)<$AD47) -> FALSE
A48: 5215 | B48: 3 | C48: 万木丹 | D48: 50 | E48: 下场战斗开始时，木系灵根权重+30/丹毒+3 | F48: 9 | G48: 振气 | H48: 9 | I48: 夏枯草 | J48: =IFERROR(CEILING($H48/VLOOKUP($I48,药材与丹炉!$B:$H,COLUMN(药材与丹炉!$H48)-1,0),1),"") -> 3 | K48: 振气 | L48: =IFERROR(IF($F48-$H48=0,"",$F48-$H48),"") | N48: =IFERROR(CEILING($L48/VLOOKUP($M48,药材与丹炉!$B:$H,COLUMN(药材与丹炉!$H48)-1,0),1),"") | P48: 强木 | Q48: 9 | R48: 风灵花 | S48: =IFERROR(CEILING($Q48/VLOOKUP($R48,药材与丹炉!$B:$H,COLUMN(药材与丹炉!$H48)-1,0),1),"") -> 3 | T48: 调和 | U48: 9 | V48: 百草露 | W48: =IFERROR(CEILING($U48/VLOOKUP($V48,药材与丹炉!$B:$H,COLUMN(药材与丹炉!$H48)-1,0),1),"") -> 3 | X48: =IF(IFERROR(IF(AND($J48>0,$J48<>""),VLOOKUP($I48,药材与丹炉!$B:$D,3,0),0),0)+IFERROR(IF(AND($N48>0,$N48<>""),VLOOKUP($M48,药材与丹炉!$B:$D,3,0),0),0)+IFERROR(IF(AND($S48>0,$S48<>""),VLOOKUP($R48,药材与丹炉!$B:$D,3,0),0),0)+IFERROR(IF(AND($W48>0,$W48<>""),VLOOKUP($V48,药材与丹炉!$B:$D,3,0),0),0)>0,1,IF(IFERROR(IF(AND($J48>0,$J48<>""),VLOOKUP($I48,药材与丹炉!$B:$D,3,0),0),0)+IFERROR(IF(AND($N48>0,$N48<>""),VLOOKUP($M48,药材与丹炉!$B:$D,3,0),0),0)+IFERROR(IF(AND($S48>0,$S48<>""),VLOOKUP($R48,药材与丹炉!$B:$D,3,0),0),0)+IFERROR(IF(AND($W48>0,$W48<>""),VLOOKUP($V48,药材与丹炉!$B:$D,3,0),0),0)<0,2,0)) -> 1 | Y48: 3 | Z48: 夜交藤 | AA48: =IFERROR($Y48/VLOOKUP($Z48,药材与丹炉!$B:$H,COLUMN(药材与丹炉!$H48)-1,0),"") -> 1 | AB48: 雕花紫铜炉 | AC48: =IFERROR(IF($B48-VLOOKUP($AB48,药材与丹炉!$N:$P,2,0)<0,IF($AO$1="是",0,1),IF($B48-VLOOKUP($AB48,药材与丹炉!$N:$P,2,0)=0,2,IF($B48-VLOOKUP($AB48,药材与丹炉!$N:$P,2,0)=1,40,IF($B48-VLOOKUP($AB48,药材与丹炉!$N:$P,2,0)=2,80,"爆炸")))),"") -> 2 | AD48: =IFERROR($J48+IFERROR(IF($N48="",0,$N48),0)+IFERROR(IF($S48="",0,$S48),0)+IFERROR(IF($W48="",0,$W48),0)+IFERROR(IF($AA48="",0,$AA48),0),"") -> 10 | AE48: =IFERROR($J48*VLOOKUP($I48,药材与丹炉!$B:$K,10,0),0)+IFERROR($N48*VLOOKUP($M48,药材与丹炉!$B:$K,10,0),0)+IFERROR($S48*VLOOKUP($R48,药材与丹炉!$B:$K,10,0),0)+IFERROR($W48*VLOOKUP($V48,药材与丹炉!$B:$K,10,0),0)+IFERROR($AA48*VLOOKUP($Z48,药材与丹炉!$B:$K,10,0),0)+IFERROR($AC48*VLOOKUP($AB48,药材与丹炉!$N:$P,3,0)/100,0) -> 440 | AF48: 1000 | AG48: =$AF48-$AE48 -> 560 | AH48: =$AF48*$AM$1*$AM$21 -> 2000 | AI48: =$AH48-$AE48 -> 1560 | AJ48: =IFERROR(IF($Y48/VLOOKUP($Y48,药材与丹炉!$T:$U,2,0)<=(VLOOKUP($AB48,药材与丹炉!$N:$O,2,0)+8)-($J48+IFERROR(IF($N48="",0,$N48),0)+IFERROR(IF($S48="",0,$S48),0)+IFERROR(IF($W48="",0,$W48),0)),1,2),1) -> 2 | AK48: =OR(NOT(IFERROR(OR($L48="",AND($L48<>"",$L48>0,VLOOKUP($AB48,药材与丹炉!$N:$O,2,0)=6)),0)),AND($L48<>"",$L48>0,OR(VLOOKUP($AB48,药材与丹炉!$N:$Q,4,0)-2<$N48,$N48="")),AND($U48<>"",$U48>0,OR(VLOOKUP($AB48,药材与丹炉!$N:$Q,4,0)-3<$W48,$W48="")),NOT(OR(AND($Q48<>"",$S48<>"",VLOOKUP($AB48,药材与丹炉!$N:$Q,4,0)-3>=$S48),$P48="")),NOT(OR(AND($H48<>"",$J48<>"",VLOOKUP($AB48,药材与丹炉!$N:$Q,4,0)-1>=$J48),$G48="")),NOT(OR($U48="",AND($U48<>"",$U48>0))),NOT(OR($Y48="",IF($Z48<>"",IFERROR(IF(VLOOKUP($Z48,药材与丹炉!$B:$D,3,0)=-1,$X48=1,IF(VLOOKUP($Z48,药材与丹炉!$B:$D,3,0)=1,$X48=2,$X48=0)),0),0))),$AC48="爆炸",(VLOOKUP($AB48,药材与丹炉!$N:$O,2,0)+8)<$AD48) -> FALSE
A49: 5216 | B49: 3 | C49: 玄水丹 | D49: 50 | E49: 下场战斗开始时，水系灵根权重+30/丹毒+3 | F49: 9 | G49: 振气 | H49: 9 | I49: 夏枯草 | J49: =IFERROR(CEILING($H49/VLOOKUP($I49,药材与丹炉!$B:$H,COLUMN(药材与丹炉!$H49)-1,0),1),"") -> 3 | K49: 振气 | L49: =IFERROR(IF($F49-$H49=0,"",$F49-$H49),"") | N49: =IFERROR(CEILING($L49/VLOOKUP($M49,药材与丹炉!$B:$H,COLUMN(药材与丹炉!$H49)-1,0),1),"") | P49: 强水 | Q49: 9 | R49: 弗兰草 | S49: =IFERROR(CEILING($Q49/VLOOKUP($R49,药材与丹炉!$B:$H,COLUMN(药材与丹炉!$H49)-1,0),1),"") -> 3 | T49: 调和 | U49: 9 | V49: 百草露 | W49: =IFERROR(CEILING($U49/VLOOKUP($V49,药材与丹炉!$B:$H,COLUMN(药材与丹炉!$H49)-1,0),1),"") -> 3 | X49: =IF(IFERROR(IF(AND($J49>0,$J49<>""),VLOOKUP($I49,药材与丹炉!$B:$D,3,0),0),0)+IFERROR(IF(AND($N49>0,$N49<>""),VLOOKUP($M49,药材与丹炉!$B:$D,3,0),0),0)+IFERROR(IF(AND($S49>0,$S49<>""),VLOOKUP($R49,药材与丹炉!$B:$D,3,0),0),0)+IFERROR(IF(AND($W49>0,$W49<>""),VLOOKUP($V49,药材与丹炉!$B:$D,3,0),0),0)>0,1,IF(IFERROR(IF(AND($J49>0,$J49<>""),VLOOKUP($I49,药材与丹炉!$B:$D,3,0),0),0)+IFERROR(IF(AND($N49>0,$N49<>""),VLOOKUP($M49,药材与丹炉!$B:$D,3,0),0),0)+IFERROR(IF(AND($S49>0,$S49<>""),VLOOKUP($R49,药材与丹炉!$B:$D,3,0),0),0)+IFERROR(IF(AND($W49>0,$W49<>""),VLOOKUP($V49,药材与丹炉!$B:$D,3,0),0),0)<0,2,0)) -> 0 | Y49: 3 | Z49: 风灵花 | AA49: =IFERROR($Y49/VLOOKUP($Z49,药材与丹炉!$B:$H,COLUMN(药材与丹炉!$H49)-1,0),"") -> 1 | AB49: 雕花紫铜炉 | AC49: =IFERROR(IF($B49-VLOOKUP($AB49,药材与丹炉!$N:$P,2,0)<0,IF($AO$1="是",0,1),IF($B49-VLOOKUP($AB49,药材与丹炉!$N:$P,2,0)=0,2,IF($B49-VLOOKUP($AB49,药材与丹炉!$N:$P,2,0)=1,40,IF($B49-VLOOKUP($AB49,药材与丹炉!$N:$P,2,0)=2,80,"爆炸")))),"") -> 2 | AD49: =IFERROR($J49+IFERROR(IF($N49="",0,$N49),0)+IFERROR(IF($S49="",0,$S49),0)+IFERROR(IF($W49="",0,$W49),0)+IFERROR(IF($AA49="",0,$AA49),0),"") -> 10 | AE49: =IFERROR($J49*VLOOKUP($I49,药材与丹炉!$B:$K,10,0),0)+IFERROR($N49*VLOOKUP($M49,药材与丹炉!$B:$K,10,0),0)+IFERROR($S49*VLOOKUP($R49,药材与丹炉!$B:$K,10,0),0)+IFERROR($W49*VLOOKUP($V49,药材与丹炉!$B:$K,10,0),0)+IFERROR($AA49*VLOOKUP($Z49,药材与丹炉!$B:$K,10,0),0)+IFERROR($AC49*VLOOKUP($AB49,药材与丹炉!$N:$P,3,0)/100,0) -> 440 | AF49: 1000 | AG49: =$AF49-$AE49 -> 560 | AH49: =$AF49*$AM$1*$AM$21 -> 2000 | AI49: =$AH49-$AE49 -> 1560 | AJ49: =IFERROR(IF($Y49/VLOOKUP($Y49,药材与丹炉!$T:$U,2,0)<=(VLOOKUP($AB49,药材与丹炉!$N:$O,2,0)+8)-($J49+IFERROR(IF($N49="",0,$N49),0)+IFERROR(IF($S49="",0,$S49),0)+IFERROR(IF($W49="",0,$W49),0)),1,2),1) -> 2 | AK49: =OR(NOT(IFERROR(OR($L49="",AND($L49<>"",$L49>0,VLOOKUP($AB49,药材与丹炉!$N:$O,2,0)=6)),0)),AND($L49<>"",$L49>0,OR(VLOOKUP($AB49,药材与丹炉!$N:$Q,4,0)-2<$N49,$N49="")),AND($U49<>"",$U49>0,OR(VLOOKUP($AB49,药材与丹炉!$N:$Q,4,0)-3<$W49,$W49="")),NOT(OR(AND($Q49<>"",$S49<>"",VLOOKUP($AB49,药材与丹炉!$N:$Q,4,0)-3>=$S49),$P49="")),NOT(OR(AND($H49<>"",$J49<>"",VLOOKUP($AB49,药材与丹炉!$N:$Q,4,0)-1>=$J49),$G49="")),NOT(OR($U49="",AND($U49<>"",$U49>0))),NOT(OR($Y49="",IF($Z49<>"",IFERROR(IF(VLOOKUP($Z49,药材与丹炉!$B:$D,3,0)=-1,$X49=1,IF(VLOOKUP($Z49,药材与丹炉!$B:$D,3,0)=1,$X49=2,$X49=0)),0),0))),$AC49="爆炸",(VLOOKUP($AB49,药材与丹炉!$N:$O,2,0)+8)<$AD49) -> FALSE
A50: 5217 | B50: 3 | C50: 真阳丹 | D50: 50 | E50: 下场战斗开始时，火系灵根权重+30/丹毒+3 | F50: 9 | G50: 振气 | H50: 9 | I50: 夏枯草 | J50: =IFERROR(CEILING($H50/VLOOKUP($I50,药材与丹炉!$B:$H,COLUMN(药材与丹炉!$H50)-1,0),1),"") -> 3 | K50: 振气 | L50: =IFERROR(IF($F50-$H50=0,"",$F50-$H50),"") | N50: =IFERROR(CEILING($L50/VLOOKUP($M50,药材与丹炉!$B:$H,COLUMN(药材与丹炉!$H50)-1,0),1),"") | P50: 强火 | Q50: 9 | R50: 火精枣 | S50: =IFERROR(CEILING($Q50/VLOOKUP($R50,药材与丹炉!$B:$H,COLUMN(药材与丹炉!$H50)-1,0),1),"") -> 3 | T50: 调和 | U50: 9 | V50: 百草露 | W50: =IFERROR(CEILING($U50/VLOOKUP($V50,药材与丹炉!$B:$H,COLUMN(药材与丹炉!$H50)-1,0),1),"") -> 3 | X50: =IF(IFERROR(IF(AND($J50>0,$J50<>""),VLOOKUP($I50,药材与丹炉!$B:$D,3,0),0),0)+IFERROR(IF(AND($N50>0,$N50<>""),VLOOKUP($M50,药材与丹炉!$B:$D,3,0),0),0)+IFERROR(IF(AND($S50>0,$S50<>""),VLOOKUP($R50,药材与丹炉!$B:$D,3,0),0),0)+IFERROR(IF(AND($W50>0,$W50<>""),VLOOKUP($V50,药材与丹炉!$B:$D,3,0),0),0)>0,1,IF(IFERROR(IF(AND($J50>0,$J50<>""),VLOOKUP($I50,药材与丹炉!$B:$D,3,0),0),0)+IFERROR(IF(AND($N50>0,$N50<>""),VLOOKUP($M50,药材与丹炉!$B:$D,3,0),0),0)+IFERROR(IF(AND($S50>0,$S50<>""),VLOOKUP($R50,药材与丹炉!$B:$D,3,0),0),0)+IFERROR(IF(AND($W50>0,$W50<>""),VLOOKUP($V50,药材与丹炉!$B:$D,3,0),0),0)<0,2,0)) -> 1 | Y50: 3 | Z50: 夜交藤 | AA50: =IFERROR($Y50/VLOOKUP($Z50,药材与丹炉!$B:$H,COLUMN(药材与丹炉!$H50)-1,0),"") -> 1 | AB50: 雕花紫铜炉 | AC50: =IFERROR(IF($B50-VLOOKUP($AB50,药材与丹炉!$N:$P,2,0)<0,IF($AO$1="是",0,1),IF($B50-VLOOKUP($AB50,药材与丹炉!$N:$P,2,0)=0,2,IF($B50-VLOOKUP($AB50,药材与丹炉!$N:$P,2,0)=1,40,IF($B50-VLOOKUP($AB50,药材与丹炉!$N:$P,2,0)=2,80,"爆炸")))),"") -> 2 | AD50: =IFERROR($J50+IFERROR(IF($N50="",0,$N50),0)+IFERROR(IF($S50="",0,$S50),0)+IFERROR(IF($W50="",0,$W50),0)+IFERROR(IF($AA50="",0,$AA50),0),"") -> 10 | AE50: =IFERROR($J50*VLOOKUP($I50,药材与丹炉!$B:$K,10,0),0)+IFERROR($N50*VLOOKUP($M50,药材与丹炉!$B:$K,10,0),0)+IFERROR($S50*VLOOKUP($R50,药材与丹炉!$B:$K,10,0),0)+IFERROR($W50*VLOOKUP($V50,药材与丹炉!$B:$K,10,0),0)+IFERROR($AA50*VLOOKUP($Z50,药材与丹炉!$B:$K,10,0),0)+IFERROR($AC50*VLOOKUP($AB50,药材与丹炉!$N:$P,3,0)/100,0) -> 440 | AF50: 1000 | AG50: =$AF50-$AE50 -> 560 | AH50: =$AF50*$AM$1*$AM$21 -> 2000 | AI50: =$AH50-$AE50 -> 1560 | AJ50: =IFERROR(IF($Y50/VLOOKUP($Y50,药材与丹炉!$T:$U,2,0)<=(VLOOKUP($AB50,药材与丹炉!$N:$O,2,0)+8)-($J50+IFERROR(IF($N50="",0,$N50),0)+IFERROR(IF($S50="",0,$S50),0)+IFERROR(IF($W50="",0,$W50),0)),1,2),1) -> 2 | AK50: =OR(NOT(IFERROR(OR($L50="",AND($L50<>"",$L50>0,VLOOKUP($AB50,药材与丹炉!$N:$O,2,0)=6)),0)),AND($L50<>"",$L50>0,OR(VLOOKUP($AB50,药材与丹炉!$N:$Q,4,0)-2<$N50,$N50="")),AND($U50<>"",$U50>0,OR(VLOOKUP($AB50,药材与丹炉!$N:$Q,4,0)-3<$W50,$W50="")),NOT(OR(AND($Q50<>"",$S50<>"",VLOOKUP($AB50,药材与丹炉!$N:$Q,4,0)-3>=$S50),$P50="")),NOT(OR(AND($H50<>"",$J50<>"",VLOOKUP($AB50,药材与丹炉!$N:$Q,4,0)-1>=$J50),$G50="")),NOT(OR($U50="",AND($U50<>"",$U50>0))),NOT(OR($Y50="",IF($Z50<>"",IFERROR(IF(VLOOKUP($Z50,药材与丹炉!$B:$D,3,0)=-1,$X50=1,IF(VLOOKUP($Z50,药材与丹炉!$B:$D,3,0)=1,$X50=2,$X50=0)),0),0))),$AC50="爆炸",(VLOOKUP($AB50,药材与丹炉!$N:$O,2,0)+8)<$AD50) -> FALSE
A51: 5218 | B51: 3 | C51: 地元丹 | D51: 50 | E51: 下场战斗开始时，土系灵根权重+30/丹毒+3 | F51: 9 | G51: 振气 | H51: 9 | I51: 夏枯草 | J51: =IFERROR(CEILING($H51/VLOOKUP($I51,药材与丹炉!$B:$H,COLUMN(药材与丹炉!$H51)-1,0),1),"") -> 3 | K51: 振气 | L51: =IFERROR(IF($F51-$H51=0,"",$F51-$H51),"") | N51: =IFERROR(CEILING($L51/VLOOKUP($M51,药材与丹炉!$B:$H,COLUMN(药材与丹炉!$H51)-1,0),1),"") | P51: 强土 | Q51: 9 | R51: 地黄参 | S51: =IFERROR(CEILING($Q51/VLOOKUP($R51,药材与丹炉!$B:$H,COLUMN(药材与丹炉!$H51)-1,0),1),"") -> 3 | T51: 调和 | U51: 9 | V51: 百草露 | W51: =IFERROR(CEILING($U51/VLOOKUP($V51,药材与丹炉!$B:$H,COLUMN(药材与丹炉!$H51)-1,0),1),"") -> 3 | X51: =IF(IFERROR(IF(AND($J51>0,$J51<>""),VLOOKUP($I51,药材与丹炉!$B:$D,3,0),0),0)+IFERROR(IF(AND($N51>0,$N51<>""),VLOOKUP($M51,药材与丹炉!$B:$D,3,0),0),0)+IFERROR(IF(AND($S51>0,$S51<>""),VLOOKUP($R51,药材与丹炉!$B:$D,3,0),0),0)+IFERROR(IF(AND($W51>0,$W51<>""),VLOOKUP($V51,药材与丹炉!$B:$D,3,0),0),0)>0,1,IF(IFERROR(IF(AND($J51>0,$J51<>""),VLOOKUP($I51,药材与丹炉!$B:$D,3,0),0),0)+IFERROR(IF(AND($N51>0,$N51<>""),VLOOKUP($M51,药材与丹炉!$B:$D,3,0),0),0)+IFERROR(IF(AND($S51>0,$S51<>""),VLOOKUP($R51,药材与丹炉!$B:$D,3,0),0),0)+IFERROR(IF(AND($W51>0,$W51<>""),VLOOKUP($V51,药材与丹炉!$B:$D,3,0),0),0)<0,2,0)) -> 1 | Y51: 3 | Z51: 夜交藤 | AA51: =IFERROR($Y51/VLOOKUP($Z51,药材与丹炉!$B:$H,COLUMN(药材与丹炉!$H51)-1,0),"") -> 1 | AB51: 雕花紫铜炉 | AC51: =IFERROR(IF($B51-VLOOKUP($AB51,药材与丹炉!$N:$P,2,0)<0,IF($AO$1="是",0,1),IF($B51-VLOOKUP($AB51,药材与丹炉!$N:$P,2,0)=0,2,IF($B51-VLOOKUP($AB51,药材与丹炉!$N:$P,2,0)=1,40,IF($B51-VLOOKUP($AB51,药材与丹炉!$N:$P,2,0)=2,80,"爆炸")))),"") -> 2 | AD51: =IFERROR($J51+IFERROR(IF($N51="",0,$N51),0)+IFERROR(IF($S51="",0,$S51),0)+IFERROR(IF($W51="",0,$W51),0)+IFERROR(IF($AA51="",0,$AA51),0),"") -> 10 | AE51: =IFERROR($J51*VLOOKUP($I51,药材与丹炉!$B:$K,10,0),0)+IFERROR($N51*VLOOKUP($M51,药材与丹炉!$B:$K,10,0),0)+IFERROR($S51*VLOOKUP($R51,药材与丹炉!$B:$K,10,0),0)+IFERROR($W51*VLOOKUP($V51,药材与丹炉!$B:$K,10,0),0)+IFERROR($AA51*VLOOKUP($Z51,药材与丹炉!$B:$K,10,0),0)+IFERROR($AC51*VLOOKUP($AB51,药材与丹炉!$N:$P,3,0)/100,0) -> 440 | AF51: 1000 | AG51: =$AF51-$AE51 -> 560 | AH51: =$AF51*$AM$1*$AM$21 -> 2000 | AI51: =$AH51-$AE51 -> 1560 | AJ51: =IFERROR(IF($Y51/VLOOKUP($Y51,药材与丹炉!$T:$U,2,0)<=(VLOOKUP($AB51,药材与丹炉!$N:$O,2,0)+8)-($J51+IFERROR(IF($N51="",0,$N51),0)+IFERROR(IF($S51="",0,$S51),0)+IFERROR(IF($W51="",0,$W51),0)),1,2),1) -> 2 | AK51: =OR(NOT(IFERROR(OR($L51="",AND($L51<>"",$L51>0,VLOOKUP($AB51,药材与丹炉!$N:$O,2,0)=6)),0)),AND($L51<>"",$L51>0,OR(VLOOKUP($AB51,药材与丹炉!$N:$Q,4,0)-2<$N51,$N51="")),AND($U51<>"",$U51>0,OR(VLOOKUP($AB51,药材与丹炉!$N:$Q,4,0)-3<$W51,$W51="")),NOT(OR(AND($Q51<>"",$S51<>"",VLOOKUP($AB51,药材与丹炉!$N:$Q,4,0)-3>=$S51),$P51="")),NOT(OR(AND($H51<>"",$J51<>"",VLOOKUP($AB51,药材与丹炉!$N:$Q,4,0)-1>=$J51),$G51="")),NOT(OR($U51="",AND($U51<>"",$U51>0))),NOT(OR($Y51="",IF($Z51<>"",IFERROR(IF(VLOOKUP($Z51,药材与丹炉!$B:$D,3,0)=-1,$X51=1,IF(VLOOKUP($Z51,药材与丹炉!$B:$D,3,0)=1,$X51=2,$X51=0)),0),0))),$AC51="爆炸",(VLOOKUP($AB51,药材与丹炉!$N:$O,2,0)+8)<$AD51) -> FALSE
A52: 5219 | B52: 3 | C52: 奕剑丹 | D52: 50 | E52: 下场战斗开始时，获得【剑气】*5/丹毒+4 | F52: 12 | G52: 振气 | H52: 12 | I52: 夏枯草 | J52: =IFERROR(CEILING($H52/VLOOKUP($I52,药材与丹炉!$B:$H,COLUMN(药材与丹炉!$H52)-1,0),1),"") -> 4 | K52: 振气 | L52: =IFERROR(IF($F52-$H52=0,"",$F52-$H52),"") | N52: =IFERROR(CEILING($L52/VLOOKUP($M52,药材与丹炉!$B:$H,COLUMN(药材与丹炉!$H52)-1,0),1),"") | O52: 18 | P52: 剑意 | Q52: 9 | R52: 剑芦 | S52: =IFERROR(CEILING($Q52/VLOOKUP($R52,药材与丹炉!$B:$H,COLUMN(药材与丹炉!$H52)-1,0),1),"") -> 3 | T52: =P52 -> 剑意 | U52: =IFERROR(IF($O52-$Q52=0,"",$O52-$Q52),"") -> 9 | V52: 剑芦 | W52: =IFERROR(CEILING($U52/VLOOKUP($V52,药材与丹炉!$B:$H,COLUMN(药材与丹炉!$H52)-1,0),1),"") -> 3 | X52: =IF(IFERROR(IF(AND($J52>0,$J52<>""),VLOOKUP($I52,药材与丹炉!$B:$D,3,0),0),0)+IFERROR(IF(AND($N52>0,$N52<>""),VLOOKUP($M52,药材与丹炉!$B:$D,3,0),0),0)+IFERROR(IF(AND($S52>0,$S52<>""),VLOOKUP($R52,药材与丹炉!$B:$D,3,0),0),0)+IFERROR(IF(AND($W52>0,$W52<>""),VLOOKUP($V52,药材与丹炉!$B:$D,3,0),0),0)>0,1,IF(IFERROR(IF(AND($J52>0,$J52<>""),VLOOKUP($I52,药材与丹炉!$B:$D,3,0),0),0)+IFERROR(IF(AND($N52>0,$N52<>""),VLOOKUP($M52,药材与丹炉!$B:$D,3,0),0),0)+IFERROR(IF(AND($S52>0,$S52<>""),VLOOKUP($R52,药材与丹炉!$B:$D,3,0),0),0)+IFERROR(IF(AND($W52>0,$W52<>""),VLOOKUP($V52,药材与丹炉!$B:$D,3,0),0),0)<0,2,0)) -> 1 | Y52: 9 | Z52: 紫猴花 | AA52: =IFERROR($Y52/VLOOKUP($Z52,药材与丹炉!$B:$H,COLUMN(药材与丹炉!$H52)-1,0),"") -> 1 | AB52: 雕花紫铜炉 | AC52: =IFERROR(IF($B52-VLOOKUP($AB52,药材与丹炉!$N:$P,2,0)<0,IF($AO$1="是",0,1),IF($B52-VLOOKUP($AB52,药材与丹炉!$N:$P,2,0)=0,2,IF($B52-VLOOKUP($AB52,药材与丹炉!$N:$P,2,0)=1,40,IF($B52-VLOOKUP($AB52,药材与丹炉!$N:$P,2,0)=2,80,"爆炸")))),"") -> 2 | AD52: =IFERROR($J52+IFERROR(IF($N52="",0,$N52),0)+IFERROR(IF($S52="",0,$S52),0)+IFERROR(IF($W52="",0,$W52),0)+IFERROR(IF($AA52="",0,$AA52),0),"") -> 11 | AE52: =IFERROR($J52*VLOOKUP($I52,药材与丹炉!$B:$K,10,0),0)+IFERROR($N52*VLOOKUP($M52,药材与丹炉!$B:$K,10,0),0)+IFERROR($S52*VLOOKUP($R52,药材与丹炉!$B:$K,10,0),0)+IFERROR($W52*VLOOKUP($V52,药材与丹炉!$B:$K,10,0),0)+IFERROR($AA52*VLOOKUP($Z52,药材与丹炉!$B:$K,10,0),0)+IFERROR($AC52*VLOOKUP($AB52,药材与丹炉!$N:$P,3,0)/100,0) -> 845 | AF52: 1100 | AG52: =$AF52-$AE52 -> 255 | AH52: =$AF52*$AM$1*$AM$21 -> 2200 | AI52: =$AH52-$AE52 -> 1355 | AJ52: =IFERROR(IF($Y52/VLOOKUP($Y52,药材与丹炉!$T:$U,2,0)<=(VLOOKUP($AB52,药材与丹炉!$N:$O,2,0)+8)-($J52+IFERROR(IF($N52="",0,$N52),0)+IFERROR(IF($S52="",0,$S52),0)+IFERROR(IF($W52="",0,$W52),0)),1,2),1) -> 2 | AK52: =OR(NOT(IFERROR(OR($L52="",AND($L52<>"",$L52>0,VLOOKUP($AB52,药材与丹炉!$N:$O,2,0)=6)),0)),AND($L52<>"",$L52>0,OR(VLOOKUP($AB52,药材与丹炉!$N:$Q,4,0)-2<$N52,$N52="")),AND($U52<>"",$U52>0,OR(VLOOKUP($AB52,药材与丹炉!$N:$Q,4,0)-3<$W52,$W52="")),NOT(OR(AND($Q52<>"",$S52<>"",VLOOKUP($AB52,药材与丹炉!$N:$Q,4,0)-3>=$S52),$P52="")),NOT(OR(AND($H52<>"",$J52<>"",VLOOKUP($AB52,药材与丹炉!$N:$Q,4,0)-1>=$J52),$G52="")),NOT(OR($U52="",AND($U52<>"",$U52>0))),NOT(OR($Y52="",IF($Z52<>"",IFERROR(IF(VLOOKUP($Z52,药材与丹炉!$B:$D,3,0)=-1,$X52=1,IF(VLOOKUP($Z52,药材与丹炉!$B:$D,3,0)=1,$X52=2,$X52=0)),0),0))),$AC52="爆炸",(VLOOKUP($AB52,药材与丹炉!$N:$O,2,0)+8)<$AD52) -> FALSE
A53: 5220 | B53: 3 | C53: 凝金丹 | D53: 6 | E53: 在凝液成丹阶段，金系灵根权重+20/丹毒+3 | F53: 9 | G53: 振气 | H53: 9 | I53: 灯心草 | J53: =IFERROR(CEILING($H53/VLOOKUP($I53,药材与丹炉!$B:$H,COLUMN(药材与丹炉!$H53)-1,0),1),"") -> 1 | K53: 振气 | L53: =IFERROR(IF($F53-$H53=0,"",$F53-$H53),"") | N53: =IFERROR(CEILING($L53/VLOOKUP($M53,药材与丹炉!$B:$H,COLUMN(药材与丹炉!$H53)-1,0),1),"") | P53: 强金 | Q53: 18 | R53: 罗犀草 | S53: =IFERROR(CEILING($Q53/VLOOKUP($R53,药材与丹炉!$B:$H,COLUMN(药材与丹炉!$H53)-1,0),1),"") -> 6 | T53: 凝液 | U53: 9 | V53: 乌椆木 | W53: =IFERROR(CEILING($U53/VLOOKUP($V53,药材与丹炉!$B:$H,COLUMN(药材与丹炉!$H53)-1,0),1),"") -> 1 | X53: =IF(IFERROR(IF(AND($J53>0,$J53<>""),VLOOKUP($I53,药材与丹炉!$B:$D,3,0),0),0)+IFERROR(IF(AND($N53>0,$N53<>""),VLOOKUP($M53,药材与丹炉!$B:$D,3,0),0),0)+IFERROR(IF(AND($S53>0,$S53<>""),VLOOKUP($R53,药材与丹炉!$B:$D,3,0),0),0)+IFERROR(IF(AND($W53>0,$W53<>""),VLOOKUP($V53,药材与丹炉!$B:$D,3,0),0),0)>0,1,IF(IFERROR(IF(AND($J53>0,$J53<>""),VLOOKUP($I53,药材与丹炉!$B:$D,3,0),0),0)+IFERROR(IF(AND($N53>0,$N53<>""),VLOOKUP($M53,药材与丹炉!$B:$D,3,0),0),0)+IFERROR(IF(AND($S53>0,$S53<>""),VLOOKUP($R53,药材与丹炉!$B:$D,3,0),0),0)+IFERROR(IF(AND($W53>0,$W53<>""),VLOOKUP($V53,药材与丹炉!$B:$D,3,0),0),0)<0,2,0)) -> 0 | Y53: 9 | Z53: 红绫草 | AA53: =IFERROR($Y53/VLOOKUP($Z53,药材与丹炉!$B:$H,COLUMN(药材与丹炉!$H53)-1,0),"") -> 3 | AB53: 雕花紫铜炉 | AC53: =IFERROR(IF($B53-VLOOKUP($AB53,药材与丹炉!$N:$P,2,0)<0,IF($AO$1="是",0,1),IF($B53-VLOOKUP($AB53,药材与丹炉!$N:$P,2,0)=0,2,IF($B53-VLOOKUP($AB53,药材与丹炉!$N:$P,2,0)=1,40,IF($B53-VLOOKUP($AB53,药材与丹炉!$N:$P,2,0)=2,80,"爆炸")))),"") -> 2 | AD53: =IFERROR($J53+IFERROR(IF($N53="",0,$N53),0)+IFERROR(IF($S53="",0,$S53),0)+IFERROR(IF($W53="",0,$W53),0)+IFERROR(IF($AA53="",0,$AA53),0),"") -> 11 | AE53: =IFERROR($J53*VLOOKUP($I53,药材与丹炉!$B:$K,10,0),0)+IFERROR($N53*VLOOKUP($M53,药材与丹炉!$B:$K,10,0),0)+IFERROR($S53*VLOOKUP($R53,药材与丹炉!$B:$K,10,0),0)+IFERROR($W53*VLOOKUP($V53,药材与丹炉!$B:$K,10,0),0)+IFERROR($AA53*VLOOKUP($Z53,药材与丹炉!$B:$K,10,0),0)+IFERROR($AC53*VLOOKUP($AB53,药材与丹炉!$N:$P,3,0)/100,0) -> 1214 | AF53: 1450 | AG53: =$AF53-$AE53 -> 236 | AH53: =$AF53*$AM$1*$AM$21 -> 2900 | AI53: =$AH53-$AE53 -> 1686 | AJ53: =IFERROR(IF($Y53/VLOOKUP($Y53,药材与丹炉!$T:$U,2,0)<=(VLOOKUP($AB53,药材与丹炉!$N:$O,2,0)+8)-($J53+IFERROR(IF($N53="",0,$N53),0)+IFERROR(IF($S53="",0,$S53),0)+IFERROR(IF($W53="",0,$W53),0)),1,2),1) -> 1 | AK53: =OR(NOT(IFERROR(OR($L53="",AND($L53<>"",$L53>0,VLOOKUP($AB53,药材与丹炉!$N:$O,2,0)=6)),0)),AND($L53<>"",$L53>0,OR(VLOOKUP($AB53,药材与丹炉!$N:$Q,4,0)-2<$N53,$N53="")),AND($U53<>"",$U53>0,OR(VLOOKUP($AB53,药材与丹炉!$N:$Q,4,0)-3<$W53,$W53="")),NOT(OR(AND($Q53<>"",$S53<>"",VLOOKUP($AB53,药材与丹炉!$N:$Q,4,0)-3>=$S53),$P53="")),NOT(OR(AND($H53<>"",$J53<>"",VLOOKUP($AB53,药材与丹炉!$N:$Q,4,0)-1>=$J53),$G53="")),NOT(OR($U53="",AND($U53<>"",$U53>0))),NOT(OR($Y53="",IF($Z53<>"",IFERROR(IF(VLOOKUP($Z53,药材与丹炉!$B:$D,3,0)=-1,$X53=1,IF(VLOOKUP($Z53,药材与丹炉!$B:$D,3,0)=1,$X53=2,$X53=0)),0),0))),$AC53="爆炸",(VLOOKUP($AB53,药材与丹炉!$N:$O,2,0)+8)<$AD53) -> FALSE
A54: 5221 | B54: 3 | C54: 凝木丹 | D54: 6 | E54: 在凝液成丹阶段，木系灵根权重+20/丹毒+3 | F54: 9 | G54: 振气 | H54: 9 | I54: 灯心草 | J54: =IFERROR(CEILING($H54/VLOOKUP($I54,药材与丹炉!$B:$H,COLUMN(药材与丹炉!$H54)-1,0),1),"") -> 1 | K54: 振气 | L54: =IFERROR(IF($F54-$H54=0,"",$F54-$H54),"") | N54: =IFERROR(CEILING($L54/VLOOKUP($M54,药材与丹炉!$B:$H,COLUMN(药材与丹炉!$H54)-1,0),1),"") | P54: 强木 | Q54: 18 | R54: 风灵花 | S54: =IFERROR(CEILING($Q54/VLOOKUP($R54,药材与丹炉!$B:$H,COLUMN(药材与丹炉!$H54)-1,0),1),"") -> 6 | T54: 凝液 | U54: 9 | V54: 乌椆木 | W54: =IFERROR(CEILING($U54/VLOOKUP($V54,药材与丹炉!$B:$H,COLUMN(药材与丹炉!$H54)-1,0),1),"") -> 1 | X54: =IF(IFERROR(IF(AND($J54>0,$J54<>""),VLOOKUP($I54,药材与丹炉!$B:$D,3,0),0),0)+IFERROR(IF(AND($N54>0,$N54<>""),VLOOKUP($M54,药材与丹炉!$B:$D,3,0),0),0)+IFERROR(IF(AND($S54>0,$S54<>""),VLOOKUP($R54,药材与丹炉!$B:$D,3,0),0),0)+IFERROR(IF(AND($W54>0,$W54<>""),VLOOKUP($V54,药材与丹炉!$B:$D,3,0),0),0)>0,1,IF(IFERROR(IF(AND($J54>0,$J54<>""),VLOOKUP($I54,药材与丹炉!$B:$D,3,0),0),0)+IFERROR(IF(AND($N54>0,$N54<>""),VLOOKUP($M54,药材与丹炉!$B:$D,3,0),0),0)+IFERROR(IF(AND($S54>0,$S54<>""),VLOOKUP($R54,药材与丹炉!$B:$D,3,0),0),0)+IFERROR(IF(AND($W54>0,$W54<>""),VLOOKUP($V54,药材与丹炉!$B:$D,3,0),0),0)<0,2,0)) -> 0 | Y54: 9 | Z54: 红绫草 | AA54: =IFERROR($Y54/VLOOKUP($Z54,药材与丹炉!$B:$H,COLUMN(药材与丹炉!$H54)-1,0),"") -> 3 | AB54: 雕花紫铜炉 | AC54: =IFERROR(IF($B54-VLOOKUP($AB54,药材与丹炉!$N:$P,2,0)<0,IF($AO$1="是",0,1),IF($B54-VLOOKUP($AB54,药材与丹炉!$N:$P,2,0)=0,2,IF($B54-VLOOKUP($AB54,药材与丹炉!$N:$P,2,0)=1,40,IF($B54-VLOOKUP($AB54,药材与丹炉!$N:$P,2,0)=2,80,"爆炸")))),"") -> 2 | AD54: =IFERROR($J54+IFERROR(IF($N54="",0,$N54),0)+IFERROR(IF($S54="",0,$S54),0)+IFERROR(IF($W54="",0,$W54),0)+IFERROR(IF($AA54="",0,$AA54),0),"") -> 11 | AE54: =IFERROR($J54*VLOOKUP($I54,药材与丹炉!$B:$K,10,0),0)+IFERROR($N54*VLOOKUP($M54,药材与丹炉!$B:$K,10,0),0)+IFERROR($S54*VLOOKUP($R54,药材与丹炉!$B:$K,10,0),0)+IFERROR($W54*VLOOKUP($V54,药材与丹炉!$B:$K,10,0),0)+IFERROR($AA54*VLOOKUP($Z54,药材与丹炉!$B:$K,10,0),0)+IFERROR($AC54*VLOOKUP($AB54,药材与丹炉!$N:$P,3,0)/100,0) -> 1214 | AF54: 1450 | AG54: =$AF54-$AE54 -> 236 | AH54: =$AF54*$AM$1*$AM$21 -> 2900 | AI54: =$AH54-$AE54 -> 1686 | AJ54: =IFERROR(IF($Y54/VLOOKUP($Y54,药材与丹炉!$T:$U,2,0)<=(VLOOKUP($AB54,药材与丹炉!$N:$O,2,0)+8)-($J54+IFERROR(IF($N54="",0,$N54),0)+IFERROR(IF($S54="",0,$S54),0)+IFERROR(IF($W54="",0,$W54),0)),1,2),1) -> 1 | AK54: =OR(NOT(IFERROR(OR($L54="",AND($L54<>"",$L54>0,VLOOKUP($AB54,药材与丹炉!$N:$O,2,0)=6)),0)),AND($L54<>"",$L54>0,OR(VLOOKUP($AB54,药材与丹炉!$N:$Q,4,0)-2<$N54,$N54="")),AND($U54<>"",$U54>0,OR(VLOOKUP($AB54,药材与丹炉!$N:$Q,4,0)-3<$W54,$W54="")),NOT(OR(AND($Q54<>"",$S54<>"",VLOOKUP($AB54,药材与丹炉!$N:$Q,4,0)-3>=$S54),$P54="")),NOT(OR(AND($H54<>"",$J54<>"",VLOOKUP($AB54,药材与丹炉!$N:$Q,4,0)-1>=$J54),$G54="")),NOT(OR($U54="",AND($U54<>"",$U54>0))),NOT(OR($Y54="",IF($Z54<>"",IFERROR(IF(VLOOKUP($Z54,药材与丹炉!$B:$D,3,0)=-1,$X54=1,IF(VLOOKUP($Z54,药材与丹炉!$B:$D,3,0)=1,$X54=2,$X54=0)),0),0))),$AC54="爆炸",(VLOOKUP($AB54,药材与丹炉!$N:$O,2,0)+8)<$AD54) -> FALSE
A55: 5222 | B55: 3 | C55: 凝水丹 | D55: 6 | E55: 在凝液成丹阶段，水系灵根权重+20/丹毒+3 | F55: 9 | G55: 振气 | H55: 9 | I55: 灯心草 | J55: =IFERROR(CEILING($H55/VLOOKUP($I55,药材与丹炉!$B:$H,COLUMN(药材与丹炉!$H55)-1,0),1),"") -> 1 | K55: 振气 | L55: =IFERROR(IF($F55-$H55=0,"",$F55-$H55),"") | N55: =IFERROR(CEILING($L55/VLOOKUP($M55,药材与丹炉!$B:$H,COLUMN(药材与丹炉!$H55)-1,0),1),"") | P55: 强水 | Q55: 18 | R55: 弗兰草 | S55: =IFERROR(CEILING($Q55/VLOOKUP($R55,药材与丹炉!$B:$H,COLUMN(药材与丹炉!$H55)-1,0),1),"") -> 6 | T55: 凝液 | U55: 9 | V55: 乌椆木 | W55: =IFERROR(CEILING($U55/VLOOKUP($V55,药材与丹炉!$B:$H,COLUMN(药材与丹炉!$H55)-1,0),1),"") -> 1 | X55: =IF(IFERROR(IF(AND($J55>0,$J55<>""),VLOOKUP($I55,药材与丹炉!$B:$D,3,0),0),0)+IFERROR(IF(AND($N55>0,$N55<>""),VLOOKUP($M55,药材与丹炉!$B:$D,3,0),0),0)+IFERROR(IF(AND($S55>0,$S55<>""),VLOOKUP($R55,药材与丹炉!$B:$D,3,0),0),0)+IFERROR(IF(AND($W55>0,$W55<>""),VLOOKUP($V55,药材与丹炉!$B:$D,3,0),0),0)>0,1,IF(IFERROR(IF(AND($J55>0,$J55<>""),VLOOKUP($I55,药材与丹炉!$B:$D,3,0),0),0)+IFERROR(IF(AND($N55>0,$N55<>""),VLOOKUP($M55,药材与丹炉!$B:$D,3,0),0),0)+IFERROR(IF(AND($S55>0,$S55<>""),VLOOKUP($R55,药材与丹炉!$B:$D,3,0),0),0)+IFERROR(IF(AND($W55>0,$W55<>""),VLOOKUP($V55,药材与丹炉!$B:$D,3,0),0),0)<0,2,0)) -> 2 | Y55: 9 | Z55: 地黄参 | AA55: =IFERROR($Y55/VLOOKUP($Z55,药材与丹炉!$B:$H,COLUMN(药材与丹炉!$H55)-1,0),"") -> 3 | AB55: 雕花紫铜炉 | AC55: =IFERROR(IF($B55-VLOOKUP($AB55,药材与丹炉!$N:$P,2,0)<0,IF($AO$1="是",0,1),IF($B55-VLOOKUP($AB55,药材与丹炉!$N:$P,2,0)=0,2,IF($B55-VLOOKUP($AB55,药材与丹炉!$N:$P,2,0)=1,40,IF($B55-VLOOKUP($AB55,药材与丹炉!$N:$P,2,0)=2,80,"爆炸")))),"") -> 2 | AD55: =IFERROR($J55+IFERROR(IF($N55="",0,$N55),0)+IFERROR(IF($S55="",0,$S55),0)+IFERROR(IF($W55="",0,$W55),0)+IFERROR(IF($AA55="",0,$AA55),0),"") -> 11 | AE55: =IFERROR($J55*VLOOKUP($I55,药材与丹炉!$B:$K,10,0),0)+IFERROR($N55*VLOOKUP($M55,药材与丹炉!$B:$K,10,0),0)+IFERROR($S55*VLOOKUP($R55,药材与丹炉!$B:$K,10,0),0)+IFERROR($W55*VLOOKUP($V55,药材与丹炉!$B:$K,10,0),0)+IFERROR($AA55*VLOOKUP($Z55,药材与丹炉!$B:$K,10,0),0)+IFERROR($AC55*VLOOKUP($AB55,药材与丹炉!$N:$P,3,0)/100,0) -> 1214 | AF55: 1450 | AG55: =$AF55-$AE55 -> 236 | AH55: =$AF55*$AM$1*$AM$21 -> 2900 | AI55: =$AH55-$AE55 -> 1686 | AJ55: =IFERROR(IF($Y55/VLOOKUP($Y55,药材与丹炉!$T:$U,2,0)<=(VLOOKUP($AB55,药材与丹炉!$N:$O,2,0)+8)-($J55+IFERROR(IF($N55="",0,$N55),0)+IFERROR(IF($S55="",0,$S55),0)+IFERROR(IF($W55="",0,$W55),0)),1,2),1) -> 1 | AK55: =OR(NOT(IFERROR(OR($L55="",AND($L55<>"",$L55>0,VLOOKUP($AB55,药材与丹炉!$N:$O,2,0)=6)),0)),AND($L55<>"",$L55>0,OR(VLOOKUP($AB55,药材与丹炉!$N:$Q,4,0)-2<$N55,$N55="")),AND($U55<>"",$U55>0,OR(VLOOKUP($AB55,药材与丹炉!$N:$Q,4,0)-3<$W55,$W55="")),NOT(OR(AND($Q55<>"",$S55<>"",VLOOKUP($AB55,药材与丹炉!$N:$Q,4,0)-3>=$S55),$P55="")),NOT(OR(AND($H55<>"",$J55<>"",VLOOKUP($AB55,药材与丹炉!$N:$Q,4,0)-1>=$J55),$G55="")),NOT(OR($U55="",AND($U55<>"",$U55>0))),NOT(OR($Y55="",IF($Z55<>"",IFERROR(IF(VLOOKUP($Z55,药材与丹炉!$B:$D,3,0)=-1,$X55=1,IF(VLOOKUP($Z55,药材与丹炉!$B:$D,3,0)=1,$X55=2,$X55=0)),0),0))),$AC55="爆炸",(VLOOKUP($AB55,药材与丹炉!$N:$O,2,0)+8)<$AD55) -> FALSE
A56: 5223 | B56: 3 | C56: 凝火丹 | D56: 6 | E56: 在凝液成丹阶段，火系灵根权重+20/丹毒+3 | F56: 9 | G56: 振气 | H56: 9 | I56: 灯心草 | J56: =IFERROR(CEILING($H56/VLOOKUP($I56,药材与丹炉!$B:$H,COLUMN(药材与丹炉!$H56)-1,0),1),"") -> 1 | K56: 振气 | L56: =IFERROR(IF($F56-$H56=0,"",$F56-$H56),"") | N56: =IFERROR(CEILING($L56/VLOOKUP($M56,药材与丹炉!$B:$H,COLUMN(药材与丹炉!$H56)-1,0),1),"") | P56: 强火 | Q56: 18 | R56: 火精枣 | S56: =IFERROR(CEILING($Q56/VLOOKUP($R56,药材与丹炉!$B:$H,COLUMN(药材与丹炉!$H56)-1,0),1),"") -> 6 | T56: 凝液 | U56: 9 | V56: 乌椆木 | W56: =IFERROR(CEILING($U56/VLOOKUP($V56,药材与丹炉!$B:$H,COLUMN(药材与丹炉!$H56)-1,0),1),"") -> 1 | X56: =IF(IFERROR(IF(AND($J56>0,$J56<>""),VLOOKUP($I56,药材与丹炉!$B:$D,3,0),0),0)+IFERROR(IF(AND($N56>0,$N56<>""),VLOOKUP($M56,药材与丹炉!$B:$D,3,0),0),0)+IFERROR(IF(AND($S56>0,$S56<>""),VLOOKUP($R56,药材与丹炉!$B:$D,3,0),0),0)+IFERROR(IF(AND($W56>0,$W56<>""),VLOOKUP($V56,药材与丹炉!$B:$D,3,0),0),0)>0,1,IF(IFERROR(IF(AND($J56>0,$J56<>""),VLOOKUP($I56,药材与丹炉!$B:$D,3,0),0),0)+IFERROR(IF(AND($N56>0,$N56<>""),VLOOKUP($M56,药材与丹炉!$B:$D,3,0),0),0)+IFERROR(IF(AND($S56>0,$S56<>""),VLOOKUP($R56,药材与丹炉!$B:$D,3,0),0),0)+IFERROR(IF(AND($W56>0,$W56<>""),VLOOKUP($V56,药材与丹炉!$B:$D,3,0),0),0)<0,2,0)) -> 1 | Y56: 9 | Z56: 夜交藤 | AA56: =IFERROR($Y56/VLOOKUP($Z56,药材与丹炉!$B:$H,COLUMN(药材与丹炉!$H56)-1,0),"") -> 3 | AB56: 雕花紫铜炉 | AC56: =IFERROR(IF($B56-VLOOKUP($AB56,药材与丹炉!$N:$P,2,0)<0,IF($AO$1="是",0,1),IF($B56-VLOOKUP($AB56,药材与丹炉!$N:$P,2,0)=0,2,IF($B56-VLOOKUP($AB56,药材与丹炉!$N:$P,2,0)=1,40,IF($B56-VLOOKUP($AB56,药材与丹炉!$N:$P,2,0)=2,80,"爆炸")))),"") -> 2 | AD56: =IFERROR($J56+IFERROR(IF($N56="",0,$N56),0)+IFERROR(IF($S56="",0,$S56),0)+IFERROR(IF($W56="",0,$W56),0)+IFERROR(IF($AA56="",0,$AA56),0),"") -> 11 | AE56: =IFERROR($J56*VLOOKUP($I56,药材与丹炉!$B:$K,10,0),0)+IFERROR($N56*VLOOKUP($M56,药材与丹炉!$B:$K,10,0),0)+IFERROR($S56*VLOOKUP($R56,药材与丹炉!$B:$K,10,0),0)+IFERROR($W56*VLOOKUP($V56,药材与丹炉!$B:$K,10,0),0)+IFERROR($AA56*VLOOKUP($Z56,药材与丹炉!$B:$K,10,0),0)+IFERROR($AC56*VLOOKUP($AB56,药材与丹炉!$N:$P,3,0)/100,0) -> 1214 | AF56: 1450 | AG56: =$AF56-$AE56 -> 236 | AH56: =$AF56*$AM$1*$AM$21 -> 2900 | AI56: =$AH56-$AE56 -> 1686 | AJ56: =IFERROR(IF($Y56/VLOOKUP($Y56,药材与丹炉!$T:$U,2,0)<=(VLOOKUP($AB56,药材与丹炉!$N:$O,2,0)+8)-($J56+IFERROR(IF($N56="",0,$N56),0)+IFERROR(IF($S56="",0,$S56),0)+IFERROR(IF($W56="",0,$W56),0)),1,2),1) -> 1 | AK56: =OR(NOT(IFERROR(OR($L56="",AND($L56<>"",$L56>0,VLOOKUP($AB56,药材与丹炉!$N:$O,2,0)=6)),0)),AND($L56<>"",$L56>0,OR(VLOOKUP($AB56,药材与丹炉!$N:$Q,4,0)-2<$N56,$N56="")),AND($U56<>"",$U56>0,OR(VLOOKUP($AB56,药材与丹炉!$N:$Q,4,0)-3<$W56,$W56="")),NOT(OR(AND($Q56<>"",$S56<>"",VLOOKUP($AB56,药材与丹炉!$N:$Q,4,0)-3>=$S56),$P56="")),NOT(OR(AND($H56<>"",$J56<>"",VLOOKUP($AB56,药材与丹炉!$N:$Q,4,0)-1>=$J56),$G56="")),NOT(OR($U56="",AND($U56<>"",$U56>0))),NOT(OR($Y56="",IF($Z56<>"",IFERROR(IF(VLOOKUP($Z56,药材与丹炉!$B:$D,3,0)=-1,$X56=1,IF(VLOOKUP($Z56,药材与丹炉!$B:$D,3,0)=1,$X56=2,$X56=0)),0),0))),$AC56="爆炸",(VLOOKUP($AB56,药材与丹炉!$N:$O,2,0)+8)<$AD56) -> FALSE
A57: 5224 | B57: 3 | C57: 凝土丹 | D57: 6 | E57: 在凝液成丹阶段，土系灵根权重+20/丹毒+3 | F57: 9 | G57: 振气 | H57: 9 | I57: 灯心草 | J57: =IFERROR(CEILING($H57/VLOOKUP($I57,药材与丹炉!$B:$H,COLUMN(药材与丹炉!$H57)-1,0),1),"") -> 1 | K57: 振气 | L57: =IFERROR(IF($F57-$H57=0,"",$F57-$H57),"") | N57: =IFERROR(CEILING($L57/VLOOKUP($M57,药材与丹炉!$B:$H,COLUMN(药材与丹炉!$H57)-1,0),1),"") | P57: 强土 | Q57: 18 | R57: 地黄参 | S57: =IFERROR(CEILING($Q57/VLOOKUP($R57,药材与丹炉!$B:$H,COLUMN(药材与丹炉!$H57)-1,0),1),"") -> 6 | T57: 凝液 | U57: 9 | V57: 乌椆木 | W57: =IFERROR(CEILING($U57/VLOOKUP($V57,药材与丹炉!$B:$H,COLUMN(药材与丹炉!$H57)-1,0),1),"") -> 1 | X57: =IF(IFERROR(IF(AND($J57>0,$J57<>""),VLOOKUP($I57,药材与丹炉!$B:$D,3,0),0),0)+IFERROR(IF(AND($N57>0,$N57<>""),VLOOKUP($M57,药材与丹炉!$B:$D,3,0),0),0)+IFERROR(IF(AND($S57>0,$S57<>""),VLOOKUP($R57,药材与丹炉!$B:$D,3,0),0),0)+IFERROR(IF(AND($W57>0,$W57<>""),VLOOKUP($V57,药材与丹炉!$B:$D,3,0),0),0)>0,1,IF(IFERROR(IF(AND($J57>0,$J57<>""),VLOOKUP($I57,药材与丹炉!$B:$D,3,0),0),0)+IFERROR(IF(AND($N57>0,$N57<>""),VLOOKUP($M57,药材与丹炉!$B:$D,3,0),0),0)+IFERROR(IF(AND($S57>0,$S57<>""),VLOOKUP($R57,药材与丹炉!$B:$D,3,0),0),0)+IFERROR(IF(AND($W57>0,$W57<>""),VLOOKUP($V57,药材与丹炉!$B:$D,3,0),0),0)<0,2,0)) -> 1 | Y57: 9 | Z57: 夜交藤 | AA57: =IFERROR($Y57/VLOOKUP($Z57,药材与丹炉!$B:$H,COLUMN(药材与丹炉!$H57)-1,0),"") -> 3 | AB57: 雕花紫铜炉 | AC57: =IFERROR(IF($B57-VLOOKUP($AB57,药材与丹炉!$N:$P,2,0)<0,IF($AO$1="是",0,1),IF($B57-VLOOKUP($AB57,药材与丹炉!$N:$P,2,0)=0,2,IF($B57-VLOOKUP($AB57,药材与丹炉!$N:$P,2,0)=1,40,IF($B57-VLOOKUP($AB57,药材与丹炉!$N:$P,2,0)=2,80,"爆炸")))),"") -> 2 | AD57: =IFERROR($J57+IFERROR(IF($N57="",0,$N57),0)+IFERROR(IF($S57="",0,$S57),0)+IFERROR(IF($W57="",0,$W57),0)+IFERROR(IF($AA57="",0,$AA57),0),"") -> 11 | AE57: =IFERROR($J57*VLOOKUP($I57,药材与丹炉!$B:$K,10,0),0)+IFERROR($N57*VLOOKUP($M57,药材与丹炉!$B:$K,10,0),0)+IFERROR($S57*VLOOKUP($R57,药材与丹炉!$B:$K,10,0),0)+IFERROR($W57*VLOOKUP($V57,药材与丹炉!$B:$K,10,0),0)+IFERROR($AA57*VLOOKUP($Z57,药材与丹炉!$B:$K,10,0),0)+IFERROR($AC57*VLOOKUP($AB57,药材与丹炉!$N:$P,3,0)/100,0) -> 1214 | AF57: 1450 | AG57: =$AF57-$AE57 -> 236 | AH57: =$AF57*$AM$1*$AM$21 -> 2900 | AI57: =$AH57-$AE57 -> 1686 | AJ57: =IFERROR(IF($Y57/VLOOKUP($Y57,药材与丹炉!$T:$U,2,0)<=(VLOOKUP($AB57,药材与丹炉!$N:$O,2,0)+8)-($J57+IFERROR(IF($N57="",0,$N57),0)+IFERROR(IF($S57="",0,$S57),0)+IFERROR(IF($W57="",0,$W57),0)),1,2),1) -> 1 | AK57: =OR(NOT(IFERROR(OR($L57="",AND($L57<>"",$L57>0,VLOOKUP($AB57,药材与丹炉!$N:$O,2,0)=6)),0)),AND($L57<>"",$L57>0,OR(VLOOKUP($AB57,药材与丹炉!$N:$Q,4,0)-2<$N57,$N57="")),AND($U57<>"",$U57>0,OR(VLOOKUP($AB57,药材与丹炉!$N:$Q,4,0)-3<$W57,$W57="")),NOT(OR(AND($Q57<>"",$S57<>"",VLOOKUP($AB57,药材与丹炉!$N:$Q,4,0)-3>=$S57),$P57="")),NOT(OR(AND($H57<>"",$J57<>"",VLOOKUP($AB57,药材与丹炉!$N:$Q,4,0)-1>=$J57),$G57="")),NOT(OR($U57="",AND($U57<>"",$U57>0))),NOT(OR($Y57="",IF($Z57<>"",IFERROR(IF(VLOOKUP($Z57,药材与丹炉!$B:$D,3,0)=-1,$X57=1,IF(VLOOKUP($Z57,药材与丹炉!$B:$D,3,0)=1,$X57=2,$X57=0)),0),0))),$AC57="爆炸",(VLOOKUP($AB57,药材与丹炉!$N:$O,2,0)+8)<$AD57) -> FALSE
A58: 5225 | B58: 3 | C58: 玄武丹 | D58: 50 | E58: 下场战斗中受到的技能伤害-4/丹毒+5 | F58: 27 | G58: 御气 | H58: 27 | I58: 石龙芮 | J58: =IFERROR(CEILING($H58/VLOOKUP($I58,药材与丹炉!$B:$H,COLUMN(药材与丹炉!$H58)-1,0),1),"") -> 3 | K58: 御气 | L58: =IFERROR(IF($F58-$H58=0,"",$F58-$H58),"") | N58: =IFERROR(CEILING($L58/VLOOKUP($M58,药材与丹炉!$B:$H,COLUMN(药材与丹炉!$H58)-1,0),1),"") | O58: 12 | P58: 混元 | Q58: 9 | R58: 锦地罗 | S58: =IFERROR(CEILING($Q58/VLOOKUP($R58,药材与丹炉!$B:$H,COLUMN(药材与丹炉!$H58)-1,0),1),"") -> 1 | T58: =P58 -> 混元 | U58: =IFERROR(IF($O58-$Q58=0,"",$O58-$Q58),"") -> 3 | V58: 凝血草 | W58: =IFERROR(CEILING($U58/VLOOKUP($V58,药材与丹炉!$B:$H,COLUMN(药材与丹炉!$H58)-1,0),1),"") -> 3 | X58: =IF(IFERROR(IF(AND($J58>0,$J58<>""),VLOOKUP($I58,药材与丹炉!$B:$D,3,0),0),0)+IFERROR(IF(AND($N58>0,$N58<>""),VLOOKUP($M58,药材与丹炉!$B:$D,3,0),0),0)+IFERROR(IF(AND($S58>0,$S58<>""),VLOOKUP($R58,药材与丹炉!$B:$D,3,0),0),0)+IFERROR(IF(AND($W58>0,$W58<>""),VLOOKUP($V58,药材与丹炉!$B:$D,3,0),0),0)>0,1,IF(IFERROR(IF(AND($J58>0,$J58<>""),VLOOKUP($I58,药材与丹炉!$B:$D,3,0),0),0)+IFERROR(IF(AND($N58>0,$N58<>""),VLOOKUP($M58,药材与丹炉!$B:$D,3,0),0),0)+IFERROR(IF(AND($S58>0,$S58<>""),VLOOKUP($R58,药材与丹炉!$B:$D,3,0),0),0)+IFERROR(IF(AND($W58>0,$W58<>""),VLOOKUP($V58,药材与丹炉!$B:$D,3,0),0),0)<0,2,0)) -> 0 | Y58: 3 | Z58: 恒心草 | AA58: =IFERROR($Y58/VLOOKUP($Z58,药材与丹炉!$B:$H,COLUMN(药材与丹炉!$H58)-1,0),"") -> 3 | AB58: 雕花紫铜炉 | AC58: =IFERROR(IF($B58-VLOOKUP($AB58,药材与丹炉!$N:$P,2,0)<0,IF($AO$1="是",0,1),IF($B58-VLOOKUP($AB58,药材与丹炉!$N:$P,2,0)=0,2,IF($B58-VLOOKUP($AB58,药材与丹炉!$N:$P,2,0)=1,40,IF($B58-VLOOKUP($AB58,药材与丹炉!$N:$P,2,0)=2,80,"爆炸")))),"") -> 2 | AD58: =IFERROR($J58+IFERROR(IF($N58="",0,$N58),0)+IFERROR(IF($S58="",0,$S58),0)+IFERROR(IF($W58="",0,$W58),0)+IFERROR(IF($AA58="",0,$AA58),0),"") -> 10 | AE58: =IFERROR($J58*VLOOKUP($I58,药材与丹炉!$B:$K,10,0),0)+IFERROR($N58*VLOOKUP($M58,药材与丹炉!$B:$K,10,0),0)+IFERROR($S58*VLOOKUP($R58,药材与丹炉!$B:$K,10,0),0)+IFERROR($W58*VLOOKUP($V58,药材与丹炉!$B:$K,10,0),0)+IFERROR($AA58*VLOOKUP($Z58,药材与丹炉!$B:$K,10,0),0)+IFERROR($AC58*VLOOKUP($AB58,药材与丹炉!$N:$P,3,0)/100,0) -> 1754 | AF58: 1250 | AG58: =$AF58-$AE58 -> -504 | AH58: =$AF58*$AM$1*$AM$21 -> 2500 | AI58: =$AH58-$AE58 -> 746 | AJ58: =IFERROR(IF($Y58/VLOOKUP($Y58,药材与丹炉!$T:$U,2,0)<=(VLOOKUP($AB58,药材与丹炉!$N:$O,2,0)+8)-($J58+IFERROR(IF($N58="",0,$N58),0)+IFERROR(IF($S58="",0,$S58),0)+IFERROR(IF($W58="",0,$W58),0)),1,2),1) -> 1 | AK58: =OR(NOT(IFERROR(OR($L58="",AND($L58<>"",$L58>0,VLOOKUP($AB58,药材与丹炉!$N:$O,2,0)=6)),0)),AND($L58<>"",$L58>0,OR(VLOOKUP($AB58,药材与丹炉!$N:$Q,4,0)-2<$N58,$N58="")),AND($U58<>"",$U58>0,OR(VLOOKUP($AB58,药材与丹炉!$N:$Q,4,0)-3<$W58,$W58="")),NOT(OR(AND($Q58<>"",$S58<>"",VLOOKUP($AB58,药材与丹炉!$N:$Q,4,0)-3>=$S58),$P58="")),NOT(OR(AND($H58<>"",$J58<>"",VLOOKUP($AB58,药材与丹炉!$N:$Q,4,0)-1>=$J58),$G58="")),NOT(OR($U58="",AND($U58<>"",$U58>0))),NOT(OR($Y58="",IF($Z58<>"",IFERROR(IF(VLOOKUP($Z58,药材与丹炉!$B:$D,3,0)=-1,$X58=1,IF(VLOOKUP($Z58,药材与丹炉!$B:$D,3,0)=1,$X58=2,$X58=0)),0),0))),$AC58="爆炸",(VLOOKUP($AB58,药材与丹炉!$N:$O,2,0)+8)<$AD58) -> FALSE
A59: 5226 | B59: 3 | C59: 金元丹 | D59: 5 | E59: 永久提升金系灵根权重+2/丹毒+3 | F59: 36 | G59: 聚元 | H59: 36 | I59: 龙鳞果 | J59: =IFERROR(CEILING($H59/VLOOKUP($I59,药材与丹炉!$B:$H,COLUMN(药材与丹炉!$H59)-1,0),1),"") -> 4 | K59: 聚元 | L59: =IFERROR(IF($F59-$H59=0,"",$F59-$H59),"") | N59: =IFERROR(CEILING($L59/VLOOKUP($M59,药材与丹炉!$B:$H,COLUMN(药材与丹炉!$H59)-1,0),1),"") | O59: 36 | P59: 强金 | Q59: 36 | R59: 伏龙参 | S59: =IFERROR(CEILING($Q59/VLOOKUP($R59,药材与丹炉!$B:$H,COLUMN(药材与丹炉!$H59)-1,0),1),"") -> 4 | T59: 强金 | U59: =IFERROR(IF($O59-$Q59=0,"",$O59-$Q59),"") | W59: =IFERROR(CEILING($U59/VLOOKUP($V59,药材与丹炉!$B:$H,COLUMN(药材与丹炉!$H59)-1,0),1),"") | X59: =IF(IFERROR(IF(AND($J59>0,$J59<>""),VLOOKUP($I59,药材与丹炉!$B:$D,3,0),0),0)+IFERROR(IF(AND($N59>0,$N59<>""),VLOOKUP($M59,药材与丹炉!$B:$D,3,0),0),0)+IFERROR(IF(AND($S59>0,$S59<>""),VLOOKUP($R59,药材与丹炉!$B:$D,3,0),0),0)+IFERROR(IF(AND($W59>0,$W59<>""),VLOOKUP($V59,药材与丹炉!$B:$D,3,0),0),0)>0,1,IF(IFERROR(IF(AND($J59>0,$J59<>""),VLOOKUP($I59,药材与丹炉!$B:$D,3,0),0),0)+IFERROR(IF(AND($N59>0,$N59<>""),VLOOKUP($M59,药材与丹炉!$B:$D,3,0),0),0)+IFERROR(IF(AND($S59>0,$S59<>""),VLOOKUP($R59,药材与丹炉!$B:$D,3,0),0),0)+IFERROR(IF(AND($W59>0,$W59<>""),VLOOKUP($V59,药材与丹炉!$B:$D,3,0),0),0)<0,2,0)) -> 0 | Y59: 9 | Z59: 红绫草 | AA59: =IFERROR($Y59/VLOOKUP($Z59,药材与丹炉!$B:$H,COLUMN(药材与丹炉!$H59)-1,0),"") -> 3 | AB59: 雕花紫铜炉 | AC59: =IFERROR(IF($B59-VLOOKUP($AB59,药材与丹炉!$N:$P,2,0)<0,IF($AO$1="是",0,1),IF($B59-VLOOKUP($AB59,药材与丹炉!$N:$P,2,0)=0,2,IF($B59-VLOOKUP($AB59,药材与丹炉!$N:$P,2,0)=1,40,IF($B59-VLOOKUP($AB59,药材与丹炉!$N:$P,2,0)=2,80,"爆炸")))),"") -> 2 | AD59: =IFERROR($J59+IFERROR(IF($N59="",0,$N59),0)+IFERROR(IF($S59="",0,$S59),0)+IFERROR(IF($W59="",0,$W59),0)+IFERROR(IF($AA59="",0,$AA59),0),"") -> 11 | AE59: =IFERROR($J59*VLOOKUP($I59,药材与丹炉!$B:$K,10,0),0)+IFERROR($N59*VLOOKUP($M59,药材与丹炉!$B:$K,10,0),0)+IFERROR($S59*VLOOKUP($R59,药材与丹炉!$B:$K,10,0),0)+IFERROR($W59*VLOOKUP($V59,药材与丹炉!$B:$K,10,0),0)+IFERROR($AA59*VLOOKUP($Z59,药材与丹炉!$B:$K,10,0),0)+IFERROR($AC59*VLOOKUP($AB59,药材与丹炉!$N:$P,3,0)/100,0) -> 3428 | AF59: 3250 | AG59: =$AF59-$AE59 -> -178 | AH59: =$AF59*$AM$1*$AM$21 -> 6500 | AI59: =$AH59-$AE59 -> 3072 | AJ59: =IFERROR(IF($Y59/VLOOKUP($Y59,药材与丹炉!$T:$U,2,0)<=(VLOOKUP($AB59,药材与丹炉!$N:$O,2,0)+8)-($J59+IFERROR(IF($N59="",0,$N59),0)+IFERROR(IF($S59="",0,$S59),0)+IFERROR(IF($W59="",0,$W59),0)),1,2),1) -> 1 | AK59: =OR(NOT(IFERROR(OR($L59="",AND($L59<>"",$L59>0,VLOOKUP($AB59,药材与丹炉!$N:$O,2,0)=6)),0)),AND($L59<>"",$L59>0,OR(VLOOKUP($AB59,药材与丹炉!$N:$Q,4,0)-2<$N59,$N59="")),AND($U59<>"",$U59>0,OR(VLOOKUP($AB59,药材与丹炉!$N:$Q,4,0)-3<$W59,$W59="")),NOT(OR(AND($Q59<>"",$S59<>"",VLOOKUP($AB59,药材与丹炉!$N:$Q,4,0)-3>=$S59),$P59="")),NOT(OR(AND($H59<>"",$J59<>"",VLOOKUP($AB59,药材与丹炉!$N:$Q,4,0)-1>=$J59),$G59="")),NOT(OR($U59="",AND($U59<>"",$U59>0))),NOT(OR($Y59="",IF($Z59<>"",IFERROR(IF(VLOOKUP($Z59,药材与丹炉!$B:$D,3,0)=-1,$X59=1,IF(VLOOKUP($Z59,药材与丹炉!$B:$D,3,0)=1,$X59=2,$X59=0)),0),0))),$AC59="爆炸",(VLOOKUP($AB59,药材与丹炉!$N:$O,2,0)+8)<$AD59) -> FALSE
A60: 5227 | B60: 3 | C60: 木元丹 | D60: 5 | E60: 永久提升木系灵根权重+2/丹毒+3 | F60: 36 | G60: 聚元 | H60: 36 | I60: 雪凝花 | J60: =IFERROR(CEILING($H60/VLOOKUP($I60,药材与丹炉!$B:$H,COLUMN(药材与丹炉!$H60)-1,0),1),"") -> 4 | K60: 聚元 | L60: =IFERROR(IF($F60-$H60=0,"",$F60-$H60),"") | N60: =IFERROR(CEILING($L60/VLOOKUP($M60,药材与丹炉!$B:$H,COLUMN(药材与丹炉!$H60)-1,0),1),"") | O60: 36 | P60: 强木 | Q60: 36 | R60: 枫香脂 | S60: =IFERROR(CEILING($Q60/VLOOKUP($R60,药材与丹炉!$B:$H,COLUMN(药材与丹炉!$H60)-1,0),1),"") -> 4 | T60: 强木 | U60: =IFERROR(IF($O60-$Q60=0,"",$O60-$Q60),"") | W60: =IFERROR(CEILING($U60/VLOOKUP($V60,药材与丹炉!$B:$H,COLUMN(药材与丹炉!$H60)-1,0),1),"") | X60: =IF(IFERROR(IF(AND($J60>0,$J60<>""),VLOOKUP($I60,药材与丹炉!$B:$D,3,0),0),0)+IFERROR(IF(AND($N60>0,$N60<>""),VLOOKUP($M60,药材与丹炉!$B:$D,3,0),0),0)+IFERROR(IF(AND($S60>0,$S60<>""),VLOOKUP($R60,药材与丹炉!$B:$D,3,0),0),0)+IFERROR(IF(AND($W60>0,$W60<>""),VLOOKUP($V60,药材与丹炉!$B:$D,3,0),0),0)>0,1,IF(IFERROR(IF(AND($J60>0,$J60<>""),VLOOKUP($I60,药材与丹炉!$B:$D,3,0),0),0)+IFERROR(IF(AND($N60>0,$N60<>""),VLOOKUP($M60,药材与丹炉!$B:$D,3,0),0),0)+IFERROR(IF(AND($S60>0,$S60<>""),VLOOKUP($R60,药材与丹炉!$B:$D,3,0),0),0)+IFERROR(IF(AND($W60>0,$W60<>""),VLOOKUP($V60,药材与丹炉!$B:$D,3,0),0),0)<0,2,0)) -> 2 | Y60: 9 | Z60: 地黄参 | AA60: =IFERROR($Y60/VLOOKUP($Z60,药材与丹炉!$B:$H,COLUMN(药材与丹炉!$H60)-1,0),"") -> 3 | AB60: 雕花紫铜炉 | AC60: =IFERROR(IF($B60-VLOOKUP($AB60,药材与丹炉!$N:$P,2,0)<0,IF($AO$1="是",0,1),IF($B60-VLOOKUP($AB60,药材与丹炉!$N:$P,2,0)=0,2,IF($B60-VLOOKUP($AB60,药材与丹炉!$N:$P,2,0)=1,40,IF($B60-VLOOKUP($AB60,药材与丹炉!$N:$P,2,0)=2,80,"爆炸")))),"") -> 2 | AD60: =IFERROR($J60+IFERROR(IF($N60="",0,$N60),0)+IFERROR(IF($S60="",0,$S60),0)+IFERROR(IF($W60="",0,$W60),0)+IFERROR(IF($AA60="",0,$AA60),0),"") -> 11 | AE60: =IFERROR($J60*VLOOKUP($I60,药材与丹炉!$B:$K,10,0),0)+IFERROR($N60*VLOOKUP($M60,药材与丹炉!$B:$K,10,0),0)+IFERROR($S60*VLOOKUP($R60,药材与丹炉!$B:$K,10,0),0)+IFERROR($W60*VLOOKUP($V60,药材与丹炉!$B:$K,10,0),0)+IFERROR($AA60*VLOOKUP($Z60,药材与丹炉!$B:$K,10,0),0)+IFERROR($AC60*VLOOKUP($AB60,药材与丹炉!$N:$P,3,0)/100,0) -> 3428 | AF60: 3250 | AG60: =$AF60-$AE60 -> -178 | AH60: =$AF60*$AM$1*$AM$21 -> 6500 | AI60: =$AH60-$AE60 -> 3072 | AJ60: =IFERROR(IF($Y60/VLOOKUP($Y60,药材与丹炉!$T:$U,2,0)<=(VLOOKUP($AB60,药材与丹炉!$N:$O,2,0)+8)-($J60+IFERROR(IF($N60="",0,$N60),0)+IFERROR(IF($S60="",0,$S60),0)+IFERROR(IF($W60="",0,$W60),0)),1,2),1) -> 1 | AK60: =OR(NOT(IFERROR(OR($L60="",AND($L60<>"",$L60>0,VLOOKUP($AB60,药材与丹炉!$N:$O,2,0)=6)),0)),AND($L60<>"",$L60>0,OR(VLOOKUP($AB60,药材与丹炉!$N:$Q,4,0)-2<$N60,$N60="")),AND($U60<>"",$U60>0,OR(VLOOKUP($AB60,药材与丹炉!$N:$Q,4,0)-3<$W60,$W60="")),NOT(OR(AND($Q60<>"",$S60<>"",VLOOKUP($AB60,药材与丹炉!$N:$Q,4,0)-3>=$S60),$P60="")),NOT(OR(AND($H60<>"",$J60<>"",VLOOKUP($AB60,药材与丹炉!$N:$Q,4,0)-1>=$J60),$G60="")),NOT(OR($U60="",AND($U60<>"",$U60>0))),NOT(OR($Y60="",IF($Z60<>"",IFERROR(IF(VLOOKUP($Z60,药材与丹炉!$B:$D,3,0)=-1,$X60=1,IF(VLOOKUP($Z60,药材与丹炉!$B:$D,3,0)=1,$X60=2,$X60=0)),0),0))),$AC60="爆炸",(VLOOKUP($AB60,药材与丹炉!$N:$O,2,0)+8)<$AD60) -> FALSE
A61: 5228 | B61: 3 | C61: 水元丹 | D61: 5 | E61: 永久提升水系灵根权重+2/丹毒+3 | F61: 36 | G61: 聚元 | H61: 36 | I61: 龙鳞果 | J61: =IFERROR(CEILING($H61/VLOOKUP($I61,药材与丹炉!$B:$H,COLUMN(药材与丹炉!$H61)-1,0),1),"") -> 4 | K61: 聚元 | L61: =IFERROR(IF($F61-$H61=0,"",$F61-$H61),"") | N61: =IFERROR(CEILING($L61/VLOOKUP($M61,药材与丹炉!$B:$H,COLUMN(药材与丹炉!$H61)-1,0),1),"") | O61: 36 | P61: 强水 | Q61: 36 | R61: 雪凝花 | S61: =IFERROR(CEILING($Q61/VLOOKUP($R61,药材与丹炉!$B:$H,COLUMN(药材与丹炉!$H61)-1,0),1),"") -> 4 | T61: 强水 | U61: =IFERROR(IF($O61-$Q61=0,"",$O61-$Q61),"") | W61: =IFERROR(CEILING($U61/VLOOKUP($V61,药材与丹炉!$B:$H,COLUMN(药材与丹炉!$H61)-1,0),1),"") | X61: =IF(IFERROR(IF(AND($J61>0,$J61<>""),VLOOKUP($I61,药材与丹炉!$B:$D,3,0),0),0)+IFERROR(IF(AND($N61>0,$N61<>""),VLOOKUP($M61,药材与丹炉!$B:$D,3,0),0),0)+IFERROR(IF(AND($S61>0,$S61<>""),VLOOKUP($R61,药材与丹炉!$B:$D,3,0),0),0)+IFERROR(IF(AND($W61>0,$W61<>""),VLOOKUP($V61,药材与丹炉!$B:$D,3,0),0),0)>0,1,IF(IFERROR(IF(AND($J61>0,$J61<>""),VLOOKUP($I61,药材与丹炉!$B:$D,3,0),0),0)+IFERROR(IF(AND($N61>0,$N61<>""),VLOOKUP($M61,药材与丹炉!$B:$D,3,0),0),0)+IFERROR(IF(AND($S61>0,$S61<>""),VLOOKUP($R61,药材与丹炉!$B:$D,3,0),0),0)+IFERROR(IF(AND($W61>0,$W61<>""),VLOOKUP($V61,药材与丹炉!$B:$D,3,0),0),0)<0,2,0)) -> 2 | Y61: 9 | Z61: 地黄参 | AA61: =IFERROR($Y61/VLOOKUP($Z61,药材与丹炉!$B:$H,COLUMN(药材与丹炉!$H61)-1,0),"") -> 3 | AB61: 雕花紫铜炉 | AC61: =IFERROR(IF($B61-VLOOKUP($AB61,药材与丹炉!$N:$P,2,0)<0,IF($AO$1="是",0,1),IF($B61-VLOOKUP($AB61,药材与丹炉!$N:$P,2,0)=0,2,IF($B61-VLOOKUP($AB61,药材与丹炉!$N:$P,2,0)=1,40,IF($B61-VLOOKUP($AB61,药材与丹炉!$N:$P,2,0)=2,80,"爆炸")))),"") -> 2 | AD61: =IFERROR($J61+IFERROR(IF($N61="",0,$N61),0)+IFERROR(IF($S61="",0,$S61),0)+IFERROR(IF($W61="",0,$W61),0)+IFERROR(IF($AA61="",0,$AA61),0),"") -> 11 | AE61: =IFERROR($J61*VLOOKUP($I61,药材与丹炉!$B:$K,10,0),0)+IFERROR($N61*VLOOKUP($M61,药材与丹炉!$B:$K,10,0),0)+IFERROR($S61*VLOOKUP($R61,药材与丹炉!$B:$K,10,0),0)+IFERROR($W61*VLOOKUP($V61,药材与丹炉!$B:$K,10,0),0)+IFERROR($AA61*VLOOKUP($Z61,药材与丹炉!$B:$K,10,0),0)+IFERROR($AC61*VLOOKUP($AB61,药材与丹炉!$N:$P,3,0)/100,0) -> 3428 | AF61: 3250 | AG61: =$AF61-$AE61 -> -178 | AH61: =$AF61*$AM$1*$AM$21 -> 6500 | AI61: =$AH61-$AE61 -> 3072 | AJ61: =IFERROR(IF($Y61/VLOOKUP($Y61,药材与丹炉!$T:$U,2,0)<=(VLOOKUP($AB61,药材与丹炉!$N:$O,2,0)+8)-($J61+IFERROR(IF($N61="",0,$N61),0)+IFERROR(IF($S61="",0,$S61),0)+IFERROR(IF($W61="",0,$W61),0)),1,2),1) -> 1 | AK61: =OR(NOT(IFERROR(OR($L61="",AND($L61<>"",$L61>0,VLOOKUP($AB61,药材与丹炉!$N:$O,2,0)=6)),0)),AND($L61<>"",$L61>0,OR(VLOOKUP($AB61,药材与丹炉!$N:$Q,4,0)-2<$N61,$N61="")),AND($U61<>"",$U61>0,OR(VLOOKUP($AB61,药材与丹炉!$N:$Q,4,0)-3<$W61,$W61="")),NOT(OR(AND($Q61<>"",$S61<>"",VLOOKUP($AB61,药材与丹炉!$N:$Q,4,0)-3>=$S61),$P61="")),NOT(OR(AND($H61<>"",$J61<>"",VLOOKUP($AB61,药材与丹炉!$N:$Q,4,0)-1>=$J61),$G61="")),NOT(OR($U61="",AND($U61<>"",$U61>0))),NOT(OR($Y61="",IF($Z61<>"",IFERROR(IF(VLOOKUP($Z61,药材与丹炉!$B:$D,3,0)=-1,$X61=1,IF(VLOOKUP($Z61,药材与丹炉!$B:$D,3,0)=1,$X61=2,$X61=0)),0),0))),$AC61="爆炸",(VLOOKUP($AB61,药材与丹炉!$N:$O,2,0)+8)<$AD61) -> FALSE
A62: 5229 | B62: 3 | C62: 火元丹 | D62: 5 | E62: 永久提升火系灵根权重+2/丹毒+3 | F62: 36 | G62: 聚元 | H62: 36 | I62: 龙鳞果 | J62: =IFERROR(CEILING($H62/VLOOKUP($I62,药材与丹炉!$B:$H,COLUMN(药材与丹炉!$H62)-1,0),1),"") -> 4 | K62: 聚元 | L62: =IFERROR(IF($F62-$H62=0,"",$F62-$H62),"") | N62: =IFERROR(CEILING($L62/VLOOKUP($M62,药材与丹炉!$B:$H,COLUMN(药材与丹炉!$H62)-1,0),1),"") | O62: 36 | P62: 强火 | Q62: 36 | R62: 灯心草 | S62: =IFERROR(CEILING($Q62/VLOOKUP($R62,药材与丹炉!$B:$H,COLUMN(药材与丹炉!$H62)-1,0),1),"") -> 4 | T62: 强火 | U62: =IFERROR(IF($O62-$Q62=0,"",$O62-$Q62),"") | W62: =IFERROR(CEILING($U62/VLOOKUP($V62,药材与丹炉!$B:$H,COLUMN(药材与丹炉!$H62)-1,0),1),"") | X62: =IF(IFERROR(IF(AND($J62>0,$J62<>""),VLOOKUP($I62,药材与丹炉!$B:$D,3,0),0),0)+IFERROR(IF(AND($N62>0,$N62<>""),VLOOKUP($M62,药材与丹炉!$B:$D,3,0),0),0)+IFERROR(IF(AND($S62>0,$S62<>""),VLOOKUP($R62,药材与丹炉!$B:$D,3,0),0),0)+IFERROR(IF(AND($W62>0,$W62<>""),VLOOKUP($V62,药材与丹炉!$B:$D,3,0),0),0)>0,1,IF(IFERROR(IF(AND($J62>0,$J62<>""),VLOOKUP($I62,药材与丹炉!$B:$D,3,0),0),0)+IFERROR(IF(AND($N62>0,$N62<>""),VLOOKUP($M62,药材与丹炉!$B:$D,3,0),0),0)+IFERROR(IF(AND($S62>0,$S62<>""),VLOOKUP($R62,药材与丹炉!$B:$D,3,0),0),0)+IFERROR(IF(AND($W62>0,$W62<>""),VLOOKUP($V62,药材与丹炉!$B:$D,3,0),0),0)<0,2,0)) -> 1 | Y62: 9 | Z62: 夜交藤 | AA62: =IFERROR($Y62/VLOOKUP($Z62,药材与丹炉!$B:$H,COLUMN(药材与丹炉!$H62)-1,0),"") -> 3 | AB62: 雕花紫铜炉 | AC62: =IFERROR(IF($B62-VLOOKUP($AB62,药材与丹炉!$N:$P,2,0)<0,IF($AO$1="是",0,1),IF($B62-VLOOKUP($AB62,药材与丹炉!$N:$P,2,0)=0,2,IF($B62-VLOOKUP($AB62,药材与丹炉!$N:$P,2,0)=1,40,IF($B62-VLOOKUP($AB62,药材与丹炉!$N:$P,2,0)=2,80,"爆炸")))),"") -> 2 | AD62: =IFERROR($J62+IFERROR(IF($N62="",0,$N62),0)+IFERROR(IF($S62="",0,$S62),0)+IFERROR(IF($W62="",0,$W62),0)+IFERROR(IF($AA62="",0,$AA62),0),"") -> 11 | AE62: =IFERROR($J62*VLOOKUP($I62,药材与丹炉!$B:$K,10,0),0)+IFERROR($N62*VLOOKUP($M62,药材与丹炉!$B:$K,10,0),0)+IFERROR($S62*VLOOKUP($R62,药材与丹炉!$B:$K,10,0),0)+IFERROR($W62*VLOOKUP($V62,药材与丹炉!$B:$K,10,0),0)+IFERROR($AA62*VLOOKUP($Z62,药材与丹炉!$B:$K,10,0),0)+IFERROR($AC62*VLOOKUP($AB62,药材与丹炉!$N:$P,3,0)/100,0) -> 3428 | AF62: 3250 | AG62: =$AF62-$AE62 -> -178 | AH62: =$AF62*$AM$1*$AM$21 -> 6500 | AI62: =$AH62-$AE62 -> 3072 | AJ62: =IFERROR(IF($Y62/VLOOKUP($Y62,药材与丹炉!$T:$U,2,0)<=(VLOOKUP($AB62,药材与丹炉!$N:$O,2,0)+8)-($J62+IFERROR(IF($N62="",0,$N62),0)+IFERROR(IF($S62="",0,$S62),0)+IFERROR(IF($W62="",0,$W62),0)),1,2),1) -> 1 | AK62: =OR(NOT(IFERROR(OR($L62="",AND($L62<>"",$L62>0,VLOOKUP($AB62,药材与丹炉!$N:$O,2,0)=6)),0)),AND($L62<>"",$L62>0,OR(VLOOKUP($AB62,药材与丹炉!$N:$Q,4,0)-2<$N62,$N62="")),AND($U62<>"",$U62>0,OR(VLOOKUP($AB62,药材与丹炉!$N:$Q,4,0)-3<$W62,$W62="")),NOT(OR(AND($Q62<>"",$S62<>"",VLOOKUP($AB62,药材与丹炉!$N:$Q,4,0)-3>=$S62),$P62="")),NOT(OR(AND($H62<>"",$J62<>"",VLOOKUP($AB62,药材与丹炉!$N:$Q,4,0)-1>=$J62),$G62="")),NOT(OR($U62="",AND($U62<>"",$U62>0))),NOT(OR($Y62="",IF($Z62<>"",IFERROR(IF(VLOOKUP($Z62,药材与丹炉!$B:$D,3,0)=-1,$X62=1,IF(VLOOKUP($Z62,药材与丹炉!$B:$D,3,0)=1,$X62=2,$X62=0)),0),0))),$AC62="爆炸",(VLOOKUP($AB62,药材与丹炉!$N:$O,2,0)+8)<$AD62) -> FALSE
A63: 5230 | B63: 3 | C63: 土元丹 | D63: 5 | E63: 永久提升土系灵根权重+2/丹毒+3 | F63: 36 | G63: 聚元 | H63: 36 | I63: 龙鳞果 | J63: =IFERROR(CEILING($H63/VLOOKUP($I63,药材与丹炉!$B:$H,COLUMN(药材与丹炉!$H63)-1,0),1),"") -> 4 | K63: 聚元 | L63: =IFERROR(IF($F63-$H63=0,"",$F63-$H63),"") | N63: =IFERROR(CEILING($L63/VLOOKUP($M63,药材与丹炉!$B:$H,COLUMN(药材与丹炉!$H63)-1,0),1),"") | O63: 36 | P63: 强土 | Q63: 36 | R63: 石龙芮 | S63: =IFERROR(CEILING($Q63/VLOOKUP($R63,药材与丹炉!$B:$H,COLUMN(药材与丹炉!$H63)-1,0),1),"") -> 4 | T63: 强土 | U63: =IFERROR(IF($O63-$Q63=0,"",$O63-$Q63),"") | W63: =IFERROR(CEILING($U63/VLOOKUP($V63,药材与丹炉!$B:$H,COLUMN(药材与丹炉!$H63)-1,0),1),"") | X63: =IF(IFERROR(IF(AND($J63>0,$J63<>""),VLOOKUP($I63,药材与丹炉!$B:$D,3,0),0),0)+IFERROR(IF(AND($N63>0,$N63<>""),VLOOKUP($M63,药材与丹炉!$B:$D,3,0),0),0)+IFERROR(IF(AND($S63>0,$S63<>""),VLOOKUP($R63,药材与丹炉!$B:$D,3,0),0),0)+IFERROR(IF(AND($W63>0,$W63<>""),VLOOKUP($V63,药材与丹炉!$B:$D,3,0),0),0)>0,1,IF(IFERROR(IF(AND($J63>0,$J63<>""),VLOOKUP($I63,药材与丹炉!$B:$D,3,0),0),0)+IFERROR(IF(AND($N63>0,$N63<>""),VLOOKUP($M63,药材与丹炉!$B:$D,3,0),0),0)+IFERROR(IF(AND($S63>0,$S63<>""),VLOOKUP($R63,药材与丹炉!$B:$D,3,0),0),0)+IFERROR(IF(AND($W63>0,$W63<>""),VLOOKUP($V63,药材与丹炉!$B:$D,3,0),0),0)<0,2,0)) -> 2 | Y63: 9 | Z63: 地黄参 | AA63: =IFERROR($Y63/VLOOKUP($Z63,药材与丹炉!$B:$H,COLUMN(药材与丹炉!$H63)-1,0),"") -> 3 | AB63: 雕花紫铜炉 | AC63: =IFERROR(IF($B63-VLOOKUP($AB63,药材与丹炉!$N:$P,2,0)<0,IF($AO$1="是",0,1),IF($B63-VLOOKUP($AB63,药材与丹炉!$N:$P,2,0)=0,2,IF($B63-VLOOKUP($AB63,药材与丹炉!$N:$P,2,0)=1,40,IF($B63-VLOOKUP($AB63,药材与丹炉!$N:$P,2,0)=2,80,"爆炸")))),"") -> 2 | AD63: =IFERROR($J63+IFERROR(IF($N63="",0,$N63),0)+IFERROR(IF($S63="",0,$S63),0)+IFERROR(IF($W63="",0,$W63),0)+IFERROR(IF($AA63="",0,$AA63),0),"") -> 11 | AE63: =IFERROR($J63*VLOOKUP($I63,药材与丹炉!$B:$K,10,0),0)+IFERROR($N63*VLOOKUP($M63,药材与丹炉!$B:$K,10,0),0)+IFERROR($S63*VLOOKUP($R63,药材与丹炉!$B:$K,10,0),0)+IFERROR($W63*VLOOKUP($V63,药材与丹炉!$B:$K,10,0),0)+IFERROR($AA63*VLOOKUP($Z63,药材与丹炉!$B:$K,10,0),0)+IFERROR($AC63*VLOOKUP($AB63,药材与丹炉!$N:$P,3,0)/100,0) -> 3428 | AF63: 3250 | AG63: =$AF63-$AE63 -> -178 | AH63: =$AF63*$AM$1*$AM$21 -> 6500 | AI63: =$AH63-$AE63 -> 3072 | AJ63: =IFERROR(IF($Y63/VLOOKUP($Y63,药材与丹炉!$T:$U,2,0)<=(VLOOKUP($AB63,药材与丹炉!$N:$O,2,0)+8)-($J63+IFERROR(IF($N63="",0,$N63),0)+IFERROR(IF($S63="",0,$S63),0)+IFERROR(IF($W63="",0,$W63),0)),1,2),1) -> 1 | AK63: =OR(NOT(IFERROR(OR($L63="",AND($L63<>"",$L63>0,VLOOKUP($AB63,药材与丹炉!$N:$O,2,0)=6)),0)),AND($L63<>"",$L63>0,OR(VLOOKUP($AB63,药材与丹炉!$N:$Q,4,0)-2<$N63,$N63="")),AND($U63<>"",$U63>0,OR(VLOOKUP($AB63,药材与丹炉!$N:$Q,4,0)-3<$W63,$W63="")),NOT(OR(AND($Q63<>"",$S63<>"",VLOOKUP($AB63,药材与丹炉!$N:$Q,4,0)-3>=$S63),$P63="")),NOT(OR(AND($H63<>"",$J63<>"",VLOOKUP($AB63,药材与丹炉!$N:$Q,4,0)-1>=$J63),$G63="")),NOT(OR($U63="",AND($U63<>"",$U63>0))),NOT(OR($Y63="",IF($Z63<>"",IFERROR(IF(VLOOKUP($Z63,药材与丹炉!$B:$D,3,0)=-1,$X63=1,IF(VLOOKUP($Z63,药材与丹炉!$B:$D,3,0)=1,$X63=2,$X63=0)),0),0))),$AC63="爆炸",(VLOOKUP($AB63,药材与丹炉!$N:$O,2,0)+8)<$AD63) -> FALSE
